{
  "type": "Feature",
  "properties": {
    "gn:admin1_code":"46.0",
    "gn:asciiname":"Ch'ungwa",
    "gn:country_code":"ET",
    "gn:dem":2136,
    "gn:feature_class":"P",
    "gn:feature_code":"PPL",
    "gn:name":"Ch\u2019ungwa",
    "gn:population":0,
    "gn:timezone":"Africa/Addis_Ababa",
    "iso:country":"ET",
    "wof:name":"Ch'ungwa",
    "wof:placetype":"locality"
},
  "geometry": {"coordinates":[38.93333,11.13333],"type":"Point"}
}