{
  "type": "Feature",
  "properties": {
    "gn:admin1_code":"46",
    "gn:asciiname":"Masha",
    "gn:country_code":"ET",
    "gn:dem":2795,
    "gn:feature_class":"P",
    "gn:feature_code":"PPL",
    "gn:name":"Masha",
    "gn:population":0,
    "gn:timezone":"Africa/Addis_Ababa",
    "iso:country":"ET",
    "wof:name":"Masha",
    "wof:placetype":"locality"
},
  "geometry": {"coordinates":[39.06667,11.23333],"type":"Point"}
}