{
  "type": "Feature",
  "properties": {
    "gn:admin1_code":"46",
    "gn:asciiname":"Masha",
    "gn:country_code":"ET",
    "gn:dem":2795,
    "gn:feature_class":"P",
    "gn:feature_code":"PPL",
    "gn:name":"Masha",
    "gn:population":0,
    "gn:timezone":"Africa/Addis_Ababa",
    "iso:country":"ET",
    "name:deu_x_preferred":[
        "Mascha"
    ],
    "name:fra_x_preferred":[
        "Macha"
    ],
    "name:ltz_x_preferred":[
        "Mascha"
    ],
    "name:ron_x_preferred":[
        "Ma\u0219a"
    ],
    "name:srp_x_preferred":[
        "\u041c\u0430\u0448\u0430"
    ],
    "wof:name":"Masha",
    "wof:placetype":"locality"
},
  "geometry": {"coordinates":[39.06667,11.23333],"type":"Point"}
}