{
  "type": "Feature",
  "properties": {
    "gn:admin1_code":"51.0",
    "gn:asciiname":"Dengego",
    "gn:country_code":"ET",
    "gn:dem":2121,
    "gn:feature_class":"P",
    "gn:feature_code":"PPL",
    "gn:name":"Dengego",
    "gn:population":0,
    "gn:timezone":"Africa/Addis_Ababa",
    "iso:country":"ET",
    "name:und_x_variant":[
        "Dangag\u00f2",
        "Denengo",
        "Dengego-2",
        "Dengego"
    ],
    "wof:name":"Dengego",
    "wof:placetype":"locality"
},
  "geometry": {"coordinates":[41.91139,9.45694],"type":"Point"}
}