{
  "type": "Feature",
  "properties": {
    "gn:admin1_code":"53",
    "gn:asciiname":"May Omo",
    "gn:country_code":"ET",
    "gn:dem":2152,
    "gn:feature_class":"P",
    "gn:feature_code":"PPL",
    "gn:name":"May Omo",
    "gn:population":0,
    "gn:timezone":"Africa/Addis_Ababa",
    "iso:country":"ET",
    "wof:name":"May Omo",
    "wof:placetype":"locality"
},
  "geometry": {"coordinates":[39.19847,13.39343],"type":"Point"}
}