{
  "type": "Feature",
  "properties": {
    "gn:admin1_code":"46.0",
    "gn:asciiname":"Karra-Meger",
    "gn:country_code":"ET",
    "gn:dem":2107,
    "gn:feature_class":"P",
    "gn:feature_code":"PPL",
    "gn:name":"Karra-Meger",
    "gn:population":0,
    "gn:timezone":"Africa/Addis_Ababa",
    "iso:country":"ET",
    "wof:name":"Karra-Meger",
    "wof:placetype":"locality"
},
  "geometry": {"coordinates":[39.79045,9.48178],"type":"Point"}
}