{
  "type": "Feature",
  "properties": {
    "gn:admin1_code":"51",
    "gn:asciiname":"Doyo",
    "gn:country_code":"ET",
    "gn:dem":1426,
    "gn:feature_class":"P",
    "gn:feature_code":"PPL",
    "gn:name":"Doyo",
    "gn:population":0,
    "gn:timezone":"Africa/Addis_Ababa",
    "iso:country":"ET",
    "wof:name":"Doyo",
    "wof:placetype":"locality"
},
  "geometry": {"coordinates":[41.50194000000001,8.57222],"type":"Point"}
}