{
  "type": "Feature",
  "properties": {
    "gn:admin1_code":"26.0",
    "gn:asciiname":"Dembel",
    "gn:country_code":"ET",
    "gn:dem":1188,
    "gn:feature_class":"P",
    "gn:feature_code":"PPL",
    "gn:name":"Dembel",
    "gn:population":0,
    "gn:timezone":"Africa/Addis_Ababa",
    "iso:country":"ET",
    "wof:name":"Dembel",
    "wof:placetype":"locality"
},
  "geometry": {"coordinates":[42.7592,9.87689],"type":"Point"}
}