{
  "type": "Feature",
  "properties": {
    "gn:admin1_code":"46",
    "gn:asciiname":"Lego",
    "gn:country_code":"ET",
    "gn:dem":2575,
    "gn:feature_class":"P",
    "gn:feature_code":"PPL",
    "gn:name":"L\u0113go",
    "gn:population":0,
    "gn:timezone":"Africa/Addis_Ababa",
    "iso:country":"ET",
    "name:und_x_variant":[
        "Leghe Bobi",
        "L\u0113go"
    ],
    "wof:name":"Lego",
    "wof:placetype":"locality"
},
  "geometry": {"coordinates":[39.03165,9.71742],"type":"Point"}
}