{
  "type": "Feature",
  "properties": {
    "gn:admin1_code":"46",
    "gn:asciiname":"Lego",
    "gn:country_code":"ET",
    "gn:dem":2575,
    "gn:feature_class":"P",
    "gn:feature_code":"PPL",
    "gn:name":"L\u0113go",
    "gn:population":0,
    "gn:timezone":"Africa/Addis_Ababa",
    "iso:country":"ET",
    "name:ara_x_preferred":[
        "\u0644\u064a\u063a\u0648"
    ],
    "name:arz_x_preferred":[
        "\u0644\u064a\u062c\u0648"
    ],
    "name:bos_x_preferred":[
        "Lego"
    ],
    "name:bul_x_preferred":[
        "\u041b\u0435\u0433\u043e"
    ],
    "name:ces_x_preferred":[
        "Lego"
    ],
    "name:cym_x_preferred":[
        "Lego"
    ],
    "name:dan_x_preferred":[
        "Legoklods"
    ],
    "name:ell_x_preferred":[
        "Lego"
    ],
    "name:epo_x_preferred":[
        "Lego"
    ],
    "name:est_x_preferred":[
        "Lego"
    ],
    "name:fas_x_preferred":[
        "\u0644\u06af\u0648"
    ],
    "name:fin_x_preferred":[
        "Lego"
    ],
    "name:fra_x_preferred":[
        "Lego"
    ],
    "name:guj_x_preferred":[
        "\u0ab2\u0ac7\u0a97\u0acb"
    ],
    "name:heb_x_preferred":[
        "\u05dc\u05d2\u05d5"
    ],
    "name:hye_x_preferred":[
        "Lego"
    ],
    "name:hyw_x_preferred":[
        "Lego"
    ],
    "name:ind_x_preferred":[
        "Lego"
    ],
    "name:jav_x_preferred":[
        "Lego"
    ],
    "name:jbo_x_preferred":[
        "Lego"
    ],
    "name:lat_x_preferred":[
        "Lego"
    ],
    "name:lav_x_preferred":[
        "Lego"
    ],
    "name:lfn_x_preferred":[
        "Lego"
    ],
    "name:lit_x_preferred":[
        "Lego"
    ],
    "name:mal_x_preferred":[
        "\u0d32\u0d46\u0d17\u0d57"
    ],
    "name:msa_x_preferred":[
        "Lego"
    ],
    "name:por_x_preferred":[
        "Lego"
    ],
    "name:sco_x_preferred":[
        "Lego"
    ],
    "name:slk_x_preferred":[
        "Lego"
    ],
    "name:slv_x_preferred":[
        "Legokocke"
    ],
    "name:sqi_x_preferred":[
        "Lego"
    ],
    "name:srp_x_preferred":[
        "\u041b\u0435\u0433\u043e"
    ],
    "name:swa_x_preferred":[
        "Lego"
    ],
    "name:swe_x_preferred":[
        "Lego"
    ],
    "name:tam_x_preferred":[
        "\u0bb2\u0bc6\u0b95\u0bcb"
    ],
    "name:tgl_x_preferred":[
        "Lego"
    ],
    "name:tha_x_preferred":[
        "\u0e40\u0e25\u0e42\u0e01\u0e49"
    ],
    "name:tur_x_preferred":[
        "Lego"
    ],
    "name:und_x_variant":[
        "Leghe Bobi",
        "L\u0113go"
    ],
    "name:uzb_x_preferred":[
        "Lego"
    ],
    "name:vie_x_preferred":[
        "Lego"
    ],
    "name:war_x_preferred":[
        "Lego"
    ],
    "name:yid_x_preferred":[
        "\u05dc\u05e2\u05d2\u05d0"
    ],
    "wof:name":"Lego",
    "wof:placetype":"locality"
},
  "geometry": {"coordinates":[39.03165,9.71742],"type":"Point"}
}