{
  "type": "Feature",
  "properties": {
    "gn:admin1_code":"46",
    "gn:asciiname":"T'uk'ya",
    "gn:country_code":"ET",
    "gn:dem":2283,
    "gn:feature_class":"P",
    "gn:feature_code":"PPL",
    "gn:name":"T\u2019uk\u2019ya",
    "gn:population":0,
    "gn:timezone":"Africa/Addis_Ababa",
    "iso:country":"ET",
    "wof:name":"T'uk'ya",
    "wof:placetype":"locality"
},
  "geometry": {"coordinates":[38.96667,11.41667],"type":"Point"}
}