{
  "type": "Feature",
  "properties": {
    "gn:admin1_code":"52.0",
    "gn:asciiname":"Buro",
    "gn:country_code":"ET",
    "gn:dem":1227,
    "gn:feature_class":"P",
    "gn:feature_code":"PPL",
    "gn:name":"Buro",
    "gn:population":0,
    "gn:timezone":"Africa/Addis_Ababa",
    "iso:country":"ET",
    "name:ceb_x_preferred":[
        "Buro"
    ],
    "name:deu_x_preferred":[
        "Buro"
    ],
    "name:ita_x_preferred":[
        "Buro"
    ],
    "name:swe_x_preferred":[
        "Buro"
    ],
    "name:tgl_x_preferred":[
        "Buro"
    ],
    "wof:name":"Buro",
    "wof:placetype":"locality"
},
  "geometry": {"coordinates":[44.155,8.61222],"type":"Point"}
}