{
  "type": "Feature",
  "properties": {
    "gn:admin1_code":"52",
    "gn:asciiname":"Elan",
    "gn:country_code":"ET",
    "gn:dem":733,
    "gn:feature_class":"P",
    "gn:feature_code":"PPL",
    "gn:name":"Elan",
    "gn:population":0,
    "gn:timezone":"Africa/Addis_Ababa",
    "iso:country":"ET",
    "name:bre_x_preferred":[
        "Elan"
    ],
    "name:ceb_x_preferred":[
        "Elan"
    ],
    "name:ces_x_preferred":[
        "El\u00e1n"
    ],
    "name:deu_x_preferred":[
        "Elan"
    ],
    "name:ita_x_preferred":[
        "Elan"
    ],
    "name:nld_x_preferred":[
        "Elan"
    ],
    "name:pol_x_preferred":[
        "Elan"
    ],
    "name:rus_x_preferred":[
        "Elan"
    ],
    "name:slk_x_preferred":[
        "El\u00e1n"
    ],
    "name:spa_x_preferred":[
        "Elan"
    ],
    "name:swe_x_preferred":[
        "Elan"
    ],
    "name:ukr_x_preferred":[
        "\u0415\u043b\u0430\u043d"
    ],
    "wof:name":"Elan",
    "wof:placetype":"locality"
},
  "geometry": {"coordinates":[42.66667,10.71667],"type":"Point"}
}