{
  "type": "Feature",
  "properties": {
    "gn:admin1_code":"49.0",
    "gn:asciiname":"Bulimkun",
    "gn:country_code":"ET",
    "gn:dem":415,
    "gn:feature_class":"P",
    "gn:feature_code":"PPL",
    "gn:name":"Bulimkun",
    "gn:population":0,
    "gn:timezone":"Africa/Addis_Ababa",
    "iso:country":"ET",
    "wof:name":"Bulimkun",
    "wof:placetype":"locality"
},
  "geometry": {"coordinates":[33.89067,8.27197],"type":"Point"}
}