{
  "type": "Feature",
  "properties": {
    "gn:admin1_code":"51.0",
    "gn:asciiname":"Adeyle",
    "gn:country_code":"ET",
    "gn:dem":2110,
    "gn:feature_class":"P",
    "gn:feature_code":"PPL",
    "gn:name":"\u0100deyle",
    "gn:population":0,
    "gn:timezone":"Africa/Addis_Ababa",
    "iso:country":"ET",
    "name:und_x_variant":[
        "Sardo",
        "\u0100deyle (2)",
        "\u0100deyle"
    ],
    "wof:name":"Adeyle",
    "wof:placetype":"locality"
},
  "geometry": {"coordinates":[41.92667,9.42417],"type":"Point"}
}