{
  "type": "Feature",
  "properties": {
    "gn:admin1_code":"54",
    "gn:asciiname":"Meti Ciafi",
    "gn:country_code":"ET",
    "gn:dem":1314,
    "gn:feature_class":"P",
    "gn:feature_code":"PPL",
    "gn:name":"Meti Ciafi",
    "gn:population":0,
    "gn:timezone":"Africa/Addis_Ababa",
    "iso:country":"ET",
    "name:und_x_variant":[
        "Meti Chafi",
        "Meti Ciafi",
        "M\u0113t\u2019\u012b"
    ],
    "wof:name":"Meti Ciafi",
    "wof:placetype":"locality"
},
  "geometry": {"coordinates":[35.31667,7.23333],"type":"Point"}
}