{
  "type": "Feature",
  "properties": {
    "gn:admin1_code":"51",
    "gn:asciiname":"Lenia",
    "gn:country_code":"ET",
    "gn:dem":1180,
    "gn:feature_class":"P",
    "gn:feature_code":"PPL",
    "gn:name":"Lenia",
    "gn:population":0,
    "gn:timezone":"Africa/Addis_Ababa",
    "iso:country":"ET",
    "name:und_x_variant":[
        "Lengia",
        "Lenia"
    ],
    "wof:name":"Lenia",
    "wof:placetype":"locality"
},
  "geometry": {"coordinates":[37.28333,4.81667],"type":"Point"}
}