{
  "type": "Feature",
  "properties": {
    "gn:admin1_code":"52",
    "gn:asciiname":"Durwale",
    "gn:country_code":"ET",
    "gn:dem":1525,
    "gn:feature_class":"P",
    "gn:feature_code":"PPL",
    "gn:name":"Durwal\u0113",
    "gn:population":0,
    "gn:timezone":"Africa/Addis_Ababa",
    "iso:country":"ET",
    "name:und_x_variant":[
        "Guio Adda",
        "Durwal\u0113 (1)",
        "Goiu Ada",
        "Guiu Ada",
        "Duruole 1",
        "Durwal\u0113"
    ],
    "wof:name":"Durwale",
    "wof:placetype":"locality"
},
  "geometry": {"coordinates":[43.115,8.99],"type":"Point"}
}