{
  "type": "Feature",
  "properties": {
    "gn:admin1_code":"51.0",
    "gn:asciiname":"Meta",
    "gn:country_code":"ET",
    "gn:dem":1861,
    "gn:feature_class":"P",
    "gn:feature_code":"PPL",
    "gn:name":"Meta",
    "gn:population":0,
    "gn:timezone":"Africa/Addis_Ababa",
    "iso:country":"ET",
    "wof:name":"Meta",
    "wof:placetype":"locality"
},
  "geometry": {"coordinates":[42.02611,9.2925],"type":"Point"}
}