{
  "type": "Feature",
  "properties": {
    "gn:admin1_code":"46",
    "gn:asciiname":"Gedero",
    "gn:country_code":"ET",
    "gn:dem":2471,
    "gn:feature_class":"P",
    "gn:feature_code":"PPL",
    "gn:name":"Gedero",
    "gn:population":0,
    "gn:timezone":"Africa/Addis_Ababa",
    "iso:country":"ET",
    "wof:name":"Gedero",
    "wof:placetype":"locality"
},
  "geometry": {"coordinates":[39.81667,11.35],"type":"Point"}
}