{
  "type": "Feature",
  "properties": {
    "gn:admin1_code":"52",
    "gn:asciiname":"Hora Califo",
    "gn:country_code":"ET",
    "gn:dem":1336,
    "gn:feature_class":"P",
    "gn:feature_code":"PPL",
    "gn:name":"Hora Califo",
    "gn:population":0,
    "gn:timezone":"Africa/Addis_Ababa",
    "iso:country":"ET",
    "name:und_x_variant":[
        "Khora-Kalifo",
        "Hora Califo"
    ],
    "wof:name":"Hora Califo",
    "wof:placetype":"locality"
},
  "geometry": {"coordinates":[43.12556,8.835],"type":"Point"}
}