{
  "type": "Feature",
  "properties": {
    "gn:admin1_code":"54",
    "gn:asciiname":"Simini",
    "gn:country_code":"ET",
    "gn:dem":1752,
    "gn:feature_class":"P",
    "gn:feature_code":"PPL",
    "gn:name":"Simini",
    "gn:population":0,
    "gn:timezone":"Africa/Addis_Ababa",
    "iso:country":"ET",
    "wof:name":"Simini",
    "wof:placetype":"locality"
},
  "geometry": {"coordinates":[37.43333,7.93333],"type":"Point"}
}