{
  "type": "Feature",
  "properties": {
    "gn:admin1_code":"51",
    "gn:asciiname":"Haseliso",
    "gn:country_code":"ET",
    "gn:dem":2043,
    "gn:feature_class":"P",
    "gn:feature_code":"PPL",
    "gn:name":"H\u0101sel\u012bso",
    "gn:population":0,
    "gn:timezone":"Africa/Addis_Ababa",
    "iso:country":"ET",
    "name:und_x_variant":[
        "Khaseliso-1",
        "Khaseliso-2",
        "H\u0101sel\u012bso"
    ],
    "wof:name":"Haseliso",
    "wof:placetype":"locality"
},
  "geometry": {"coordinates":[41.77556,9.46056],"type":"Point"}
}