{
  "type": "Feature",
  "properties": {
    "gn:admin1_code":"52",
    "gn:asciiname":"K'emarmere",
    "gn:country_code":"ET",
    "gn:dem":331,
    "gn:feature_class":"P",
    "gn:feature_code":"PPL",
    "gn:name":"K\u2019emarmer\u0113",
    "gn:population":0,
    "gn:timezone":"Africa/Addis_Ababa",
    "iso:country":"ET",
    "name:und_x_variant":[
        "Camar Marie",
        "K\u2019emarmer\u0113"
    ],
    "wof:name":"K'emarmere",
    "wof:placetype":"locality"
},
  "geometry": {"coordinates":[42.78944,6.22],"type":"Point"}
}