{
  "type": "Feature",
  "properties": {
    "gn:admin1_code":"51",
    "gn:asciiname":"Gura",
    "gn:country_code":"ET",
    "gn:dem":2432,
    "gn:feature_class":"P",
    "gn:feature_code":"PPL",
    "gn:name":"Gura",
    "gn:population":0,
    "gn:timezone":"Africa/Addis_Ababa",
    "iso:country":"ET",
    "name:bel_x_preferred":[
        "\u0413\u0443\u0440\u0430"
    ],
    "name:ceb_x_preferred":[
        "Gura"
    ],
    "name:deu_x_preferred":[
        "Gura"
    ],
    "name:ita_x_preferred":[
        "Gura"
    ],
    "name:lit_x_preferred":[
        "Gura"
    ],
    "name:ron_x_preferred":[
        "Gura"
    ],
    "name:rus_x_preferred":[
        "\u0413\u0443\u0440\u0430"
    ],
    "name:swe_x_preferred":[
        "Gura"
    ],
    "name:szl_x_preferred":[
        "G\u016fra"
    ],
    "name:ukr_x_preferred":[
        "\u0413\u0443\u0440\u0430"
    ],
    "wof:name":"Gura",
    "wof:placetype":"locality"
},
  "geometry": {"coordinates":[37.76667,9.61667],"type":"Point"}
}