{
  "type": "Feature",
  "properties": {
    "gn:admin1_code":"54",
    "gn:asciiname":"Macheto",
    "gn:country_code":"ET",
    "gn:dem":1822,
    "gn:feature_class":"P",
    "gn:feature_code":"PPL",
    "gn:name":"Mach\u0113to",
    "gn:population":0,
    "gn:timezone":"Africa/Addis_Ababa",
    "iso:country":"ET",
    "wof:name":"Macheto",
    "wof:placetype":"locality"
},
  "geometry": {"coordinates":[36.01667,7.43333],"type":"Point"}
}