{
  "type": "Feature",
  "properties": {
    "gn:admin1_code":"46",
    "gn:asciiname":"Sera",
    "gn:country_code":"ET",
    "gn:dem":2966,
    "gn:feature_class":"P",
    "gn:feature_code":"PPL",
    "gn:name":"Sera",
    "gn:population":0,
    "gn:timezone":"Africa/Addis_Ababa",
    "iso:country":"ET",
    "name:bul_x_preferred":[
        "\u0421\u0435\u0440\u0430"
    ],
    "name:ceb_x_preferred":[
        "Sera"
    ],
    "name:deu_x_preferred":[
        "Sera"
    ],
    "name:fin_x_preferred":[
        "Sera"
    ],
    "name:fra_x_preferred":[
        "Sera"
    ],
    "name:ita_x_preferred":[
        "Sera"
    ],
    "name:nld_x_preferred":[
        "Sera"
    ],
    "name:rus_x_preferred":[
        "\u0421\u0435\u0440\u0430"
    ],
    "name:srp_x_preferred":[
        "\u0421\u0435\u0440\u0430"
    ],
    "name:swe_x_preferred":[
        "Sera"
    ],
    "name:ukr_x_preferred":[
        "\u0421\u0435\u0440\u0430"
    ],
    "wof:name":"Sera",
    "wof:placetype":"locality"
},
  "geometry": {"coordinates":[39.29784,10.7916],"type":"Point"}
}