{
  "type": "Feature",
  "properties": {
    "gn:admin1_code":"46",
    "gn:asciiname":"Sera",
    "gn:country_code":"ET",
    "gn:dem":2966,
    "gn:feature_class":"P",
    "gn:feature_code":"PPL",
    "gn:name":"Sera",
    "gn:population":0,
    "gn:timezone":"Africa/Addis_Ababa",
    "iso:country":"ET",
    "wof:name":"Sera",
    "wof:placetype":"locality"
},
  "geometry": {"coordinates":[39.29784,10.7916],"type":"Point"}
}