{
  "type": "Feature",
  "properties": {
    "gn:admin1_code":"51",
    "gn:asciiname":"Dukaye",
    "gn:country_code":"ET",
    "gn:dem":1775,
    "gn:feature_class":"P",
    "gn:feature_code":"PPL",
    "gn:name":"Dukay\u0113",
    "gn:population":0,
    "gn:timezone":"Africa/Addis_Ababa",
    "iso:country":"ET",
    "wof:name":"Dukaye",
    "wof:placetype":"locality"
},
  "geometry": {"coordinates":[40.75,8.65],"type":"Point"}
}