{
  "type": "Feature",
  "properties": {
    "gn:admin1_code":"53",
    "gn:asciiname":"Hafti Maryam",
    "gn:country_code":"ET",
    "gn:dem":1801,
    "gn:feature_class":"P",
    "gn:feature_code":"PPL",
    "gn:name":"H\u0101ft\u012b Maryam",
    "gn:population":0,
    "gn:timezone":"Africa/Addis_Ababa",
    "iso:country":"ET",
    "name:und_x_variant":[
        "Khafti Mar'yam",
        "H\u0101ft\u012b Maryam"
    ],
    "wof:name":"Hafti Maryam",
    "wof:placetype":"locality"
},
  "geometry": {"coordinates":[38.90039,14.40218],"type":"Point"}
}