{
  "type": "Feature",
  "properties": {
    "gn:admin1_code":"51",
    "gn:asciiname":"Sabaata",
    "gn:country_code":"ET",
    "gn:dem":1371,
    "gn:feature_class":"P",
    "gn:feature_code":"PPL",
    "gn:name":"Sabaata",
    "gn:population":0,
    "gn:timezone":"Africa/Addis_Ababa",
    "iso:country":"ET",
    "name:und_x_variant":[
        "Sabbata",
        "Sabaata"
    ],
    "wof:name":"Sabaata",
    "wof:placetype":"locality"
},
  "geometry": {"coordinates":[42.34389,9.67722],"type":"Point"}
}