{
  "type": "Feature",
  "properties": {
    "gn:admin1_code":"46.0",
    "gn:asciiname":"Alefa",
    "gn:country_code":"ET",
    "gn:dem":2133,
    "gn:feature_class":"P",
    "gn:feature_code":"PPL",
    "gn:name":"\u0100lefa",
    "gn:population":0,
    "gn:timezone":"Africa/Addis_Ababa",
    "iso:country":"ET",
    "name:und_x_variant":[
        "Alaf\u0101",
        "\u0100lefa"
    ],
    "wof:name":"Alefa",
    "wof:placetype":"locality"
},
  "geometry": {"coordinates":[36.86667,11.95],"type":"Point"}
}