{
  "type": "Feature",
  "properties": {
    "gn:admin1_code":"54",
    "gn:asciiname":"Uba",
    "gn:country_code":"ET",
    "gn:dem":1552,
    "gn:feature_class":"P",
    "gn:feature_code":"PPL",
    "gn:name":"Uba",
    "gn:population":0,
    "gn:timezone":"Africa/Addis_Ababa",
    "iso:country":"ET",
    "name:und_x_variant":[
        "Uba (2)",
        "Uba"
    ],
    "wof:name":"Uba",
    "wof:placetype":"locality"
},
  "geometry": {"coordinates":[36.88333,6.15],"type":"Point"}
}