{
  "type": "Feature",
  "properties": {
    "gn:admin1_code":"52",
    "gn:asciiname":"Schealutah",
    "gn:country_code":"ET",
    "gn:dem":762,
    "gn:feature_class":"P",
    "gn:feature_code":"PPL",
    "gn:name":"Schealutah",
    "gn:population":0,
    "gn:timezone":"Africa/Addis_Ababa",
    "iso:country":"ET",
    "wof:name":"Schealutah",
    "wof:placetype":"locality"
},
  "geometry": {"coordinates":[45.11667,7.86667],"type":"Point"}
}