{
  "type": "Feature",
  "properties": {
    "gn:admin1_code":"45.0",
    "gn:asciiname":"Bedda",
    "gn:country_code":"ET",
    "gn:dem":1356,
    "gn:feature_class":"P",
    "gn:feature_code":"PPL",
    "gn:name":"Bedda",
    "gn:population":0,
    "gn:timezone":"Africa/Addis_Ababa",
    "iso:country":"ET",
    "wof:name":"Bedda",
    "wof:placetype":"locality"
},
  "geometry": {"coordinates":[40.00869,12.9905],"type":"Point"}
}