{
  "type": "Feature",
  "properties": {
    "gn:admin1_code":"51",
    "gn:asciiname":"Dubi",
    "gn:country_code":"ET",
    "gn:dem":1600,
    "gn:feature_class":"P",
    "gn:feature_code":"PPL",
    "gn:name":"Dub\u012b",
    "gn:population":0,
    "gn:timezone":"Africa/Addis_Ababa",
    "iso:country":"ET",
    "name:und_x_variant":[
        "Dubbi",
        "Dub\u012b"
    ],
    "wof:name":"Dubi",
    "wof:placetype":"locality"
},
  "geometry": {"coordinates":[34.78333,8.96667],"type":"Point"}
}