{
  "type": "Feature",
  "properties": {
    "gn:admin1_code":"54",
    "gn:asciiname":"Sefato",
    "gn:country_code":"ET",
    "gn:dem":2599,
    "gn:feature_class":"P",
    "gn:feature_code":"PPL",
    "gn:name":"Sefato",
    "gn:population":0,
    "gn:timezone":"Africa/Addis_Ababa",
    "iso:country":"ET",
    "wof:name":"Sefato",
    "wof:placetype":"locality"
},
  "geometry": {"coordinates":[38.23333,8.31667],"type":"Point"}
}