{
  "type": "Feature",
  "properties": {
    "gn:admin1_code":"51.0",
    "gn:asciiname":"Afaflai",
    "gn:country_code":"ET",
    "gn:dem":1921,
    "gn:feature_class":"P",
    "gn:feature_code":"PPL",
    "gn:name":"Afaflai",
    "gn:population":0,
    "gn:timezone":"Africa/Addis_Ababa",
    "iso:country":"ET",
    "wof:name":"Afaflai",
    "wof:placetype":"locality"
},
  "geometry": {"coordinates":[38.95,5.98333],"type":"Point"}
}