{
  "type": "Feature",
  "properties": {
    "gn:admin1_code":"46.0",
    "gn:asciiname":"Bara",
    "gn:country_code":"ET",
    "gn:dem":2294,
    "gn:feature_class":"P",
    "gn:feature_code":"PPL",
    "gn:name":"Bara",
    "gn:population":0,
    "gn:timezone":"Africa/Addis_Ababa",
    "iso:country":"ET",
    "name:und_x_variant":[
        "Bara (2)",
        "Bara"
    ],
    "wof:name":"Bara",
    "wof:placetype":"locality"
},
  "geometry": {"coordinates":[38.98333,12.65],"type":"Point"}
}