{
  "type": "Feature",
  "properties": {
    "gn:admin1_code":"46",
    "gn:asciiname":"Semoy",
    "gn:country_code":"ET",
    "gn:dem":1908,
    "gn:feature_class":"P",
    "gn:feature_code":"PPL",
    "gn:name":"Semoy",
    "gn:population":0,
    "gn:timezone":"Africa/Addis_Ababa",
    "iso:country":"ET",
    "name:ceb_x_preferred":[
        "Semoy"
    ],
    "name:fra_x_preferred":[
        "Semoy"
    ],
    "name:nld_x_preferred":[
        "Semoy"
    ],
    "name:oci_x_preferred":[
        "Semoy"
    ],
    "name:swe_x_preferred":[
        "Semoy"
    ],
    "wof:name":"Semoy",
    "wof:placetype":"locality"
},
  "geometry": {"coordinates":[37.43333,10.81667],"type":"Point"}
}