{
  "type": "Feature",
  "properties": {
    "gn:admin1_code":"51",
    "gn:asciiname":"K'u'a",
    "gn:country_code":"ET",
    "gn:dem":1860,
    "gn:feature_class":"P",
    "gn:feature_code":"PPL",
    "gn:name":"K\u2019u\u2019\u0101",
    "gn:population":0,
    "gn:timezone":"Africa/Addis_Ababa",
    "iso:country":"ET",
    "wof:name":"K'u'a",
    "wof:placetype":"locality"
},
  "geometry": {"coordinates":[36.28333,8.65],"type":"Point"}
}