{
  "type": "Feature",
  "properties": {
    "gn:admin1_code":"53",
    "gn:asciiname":"Kerets'",
    "gn:country_code":"ET",
    "gn:dem":1805,
    "gn:feature_class":"P",
    "gn:feature_code":"PPL",
    "gn:name":"Kerets\u2019",
    "gn:population":0,
    "gn:timezone":"Africa/Addis_Ababa",
    "iso:country":"ET",
    "wof:name":"Kerets'",
    "wof:placetype":"locality"
},
  "geometry": {"coordinates":[39.1418,13.24178],"type":"Point"}
}