{
  "type": "Feature",
  "properties": {
    "gn:admin1_code":"53.0",
    "gn:asciiname":"Cheli",
    "gn:country_code":"ET",
    "gn:dem":1829,
    "gn:feature_class":"P",
    "gn:feature_code":"PPL",
    "gn:name":"Chel\u012b",
    "gn:population":0,
    "gn:timezone":"Africa/Addis_Ababa",
    "iso:country":"ET",
    "name:ast_x_preferred":[
        "Cheli"
    ],
    "name:fra_x_preferred":[
        "Cheli"
    ],
    "name:spa_x_preferred":[
        "Cheli"
    ],
    "wof:name":"Cheli",
    "wof:placetype":"locality"
},
  "geometry": {"coordinates":[39.1374,13.28985],"type":"Point"}
}