{
  "type": "Feature",
  "properties": {
    "gn:admin1_code":"51",
    "gn:asciiname":"K'ore",
    "gn:country_code":"ET",
    "gn:dem":2764,
    "gn:feature_class":"P",
    "gn:feature_code":"PPL",
    "gn:name":"K\u2019or\u0113",
    "gn:population":0,
    "gn:timezone":"Africa/Addis_Ababa",
    "iso:country":"ET",
    "name:und_x_variant":[
        "K\u2019or\u0113 (2)",
        "Core",
        "K\u2019or\u0113"
    ],
    "wof:name":"K'ore",
    "wof:placetype":"locality"
},
  "geometry": {"coordinates":[38.91667,7.21667],"type":"Point"}
}