{
  "type": "Feature",
  "properties": {
    "gn:admin1_code":"51.0",
    "gn:asciiname":"Agge",
    "gn:country_code":"ET",
    "gn:dem":2026,
    "gn:feature_class":"P",
    "gn:feature_code":"PPL",
    "gn:name":"Agge",
    "gn:population":0,
    "gn:timezone":"Africa/Addis_Ababa",
    "iso:country":"ET",
    "name:und_x_variant":[
        "\u0100j\u0113"
    ],
    "wof:name":"Agge",
    "wof:placetype":"locality"
},
  "geometry": {"coordinates":[38.35,7.28333],"type":"Point"}
}