{
  "type": "Feature",
  "properties": {
    "gn:admin1_code":"51",
    "gn:asciiname":"Tessama",
    "gn:country_code":"ET",
    "gn:dem":2118,
    "gn:feature_class":"P",
    "gn:feature_code":"PPL",
    "gn:name":"Tessama",
    "gn:population":0,
    "gn:timezone":"Africa/Addis_Ababa",
    "iso:country":"ET",
    "wof:name":"Tessama",
    "wof:placetype":"locality"
},
  "geometry": {"coordinates":[37.06667,8.66667],"type":"Point"}
}