{
  "type": "Feature",
  "properties": {
    "gn:admin1_code":"51",
    "gn:asciiname":"K'adi",
    "gn:country_code":"ET",
    "gn:dem":2561,
    "gn:feature_class":"P",
    "gn:feature_code":"PPL",
    "gn:name":"K\u2019ad\u012b",
    "gn:population":0,
    "gn:timezone":"Africa/Addis_Ababa",
    "iso:country":"ET",
    "wof:name":"K'adi",
    "wof:placetype":"locality"
},
  "geometry": {"coordinates":[38.33333,9.91667],"type":"Point"}
}