{
  "type": "Feature",
  "properties": {
    "gn:admin1_code":"49.0",
    "gn:asciiname":"Kochngol'ir",
    "gn:country_code":"ET",
    "gn:dem":413,
    "gn:feature_class":"P",
    "gn:feature_code":"PPL",
    "gn:name":"Kochngol\u2019ir",
    "gn:population":0,
    "gn:timezone":"Africa/Addis_Ababa",
    "iso:country":"ET",
    "wof:name":"Kochngol'ir",
    "wof:placetype":"locality"
},
  "geometry": {"coordinates":[33.77952,8.20591],"type":"Point"}
}