{
  "type": "Feature",
  "properties": {
    "gn:admin1_code":"54",
    "gn:asciiname":"Kuyle",
    "gn:country_code":"ET",
    "gn:dem":1947,
    "gn:feature_class":"P",
    "gn:feature_code":"PPL",
    "gn:name":"Kuyl\u0113",
    "gn:population":0,
    "gn:timezone":"Africa/Addis_Ababa",
    "iso:country":"ET",
    "wof:name":"Kuyle",
    "wof:placetype":"locality"
},
  "geometry": {"coordinates":[37.43333,6.13333],"type":"Point"}
}