{
  "type": "Feature",
  "properties": {
    "gn:admin1_code":"53.0",
    "gn:asciiname":"Adi Ademay",
    "gn:country_code":"ET",
    "gn:dem":1866,
    "gn:feature_class":"P",
    "gn:feature_code":"PPL",
    "gn:name":"\u0100d\u012b \u0100demay",
    "gn:population":0,
    "gn:timezone":"Africa/Addis_Ababa",
    "iso:country":"ET",
    "name:und_x_variant":[
        "Amba Georghis",
        "Amba Ghiorghis",
        "Amba Giyorgis",
        "Addi Ademay",
        "\u0100d\u012b \u0100demay"
    ],
    "wof:name":"Adi Ademay",
    "wof:placetype":"locality"
},
  "geometry": {"coordinates":[38.25246,14.12902],"type":"Point"}
}