{
  "type": "Feature",
  "properties": {
    "gn:admin1_code":"52",
    "gn:asciiname":"Idenki",
    "gn:country_code":"ET",
    "gn:dem":1659,
    "gn:feature_class":"P",
    "gn:feature_code":"PPL",
    "gn:name":"\u012adenk\u012b",
    "gn:population":0,
    "gn:timezone":"Africa/Addis_Ababa",
    "iso:country":"ET",
    "wof:name":"Idenki",
    "wof:placetype":"locality"
},
  "geometry": {"coordinates":[43.22722,9.70167],"type":"Point"}
}