{
  "type": "Feature",
  "properties": {
    "gn:admin1_code":"53",
    "gn:asciiname":"Nefag",
    "gn:country_code":"ET",
    "gn:dem":2068,
    "gn:feature_class":"P",
    "gn:feature_code":"PPL",
    "gn:name":"Nefag",
    "gn:population":0,
    "gn:timezone":"Africa/Addis_Ababa",
    "iso:country":"ET",
    "name:und_x_variant":[
        "Adi Nefas",
        "Nefas",
        "Nefag"
    ],
    "wof:name":"Nefag",
    "wof:placetype":"locality"
},
  "geometry": {"coordinates":[39.05,14.18333],"type":"Point"}
}