{
  "type": "Feature",
  "properties": {
    "gn:admin1_code":"53.0",
    "gn:asciiname":"`Aynu",
    "gn:country_code":"ET",
    "gn:dem":2631,
    "gn:feature_class":"P",
    "gn:feature_code":"PPL",
    "gn:name":"\u2018Aynu",
    "gn:population":0,
    "gn:timezone":"Africa/Addis_Ababa",
    "iso:country":"ET",
    "wof:name":"`Aynu",
    "wof:placetype":"locality"
},
  "geometry": {"coordinates":[39.15091,13.59598],"type":"Point"}
}