{
  "type": "Feature",
  "properties": {
    "gn:admin1_code":"46",
    "gn:asciiname":"Kok",
    "gn:country_code":"ET",
    "gn:dem":2461,
    "gn:feature_class":"P",
    "gn:feature_code":"PPL",
    "gn:name":"Kok",
    "gn:population":0,
    "gn:timezone":"Africa/Addis_Ababa",
    "iso:country":"ET",
    "name:ceb_x_preferred":[
        "Kok"
    ],
    "name:ces_x_preferred":[
        "Kok"
    ],
    "name:dan_x_preferred":[
        "Kok"
    ],
    "name:fin_x_preferred":[
        "Kok"
    ],
    "name:fry_x_preferred":[
        "Kok"
    ],
    "name:nld_x_preferred":[
        "Kok"
    ],
    "name:pol_x_preferred":[
        "Kok"
    ],
    "name:slk_x_preferred":[
        "Kok"
    ],
    "name:swe_x_preferred":[
        "Kok"
    ],
    "wof:name":"Kok",
    "wof:placetype":"locality"
},
  "geometry": {"coordinates":[38.63333,11.13333],"type":"Point"}
}