{
  "type": "Feature",
  "properties": {
    "gn:admin1_code":"46.0",
    "gn:asciiname":"Aznan",
    "gn:country_code":"ET",
    "gn:dem":2097,
    "gn:feature_class":"P",
    "gn:feature_code":"PPL",
    "gn:name":"\u0100znan",
    "gn:population":0,
    "gn:timezone":"Africa/Addis_Ababa",
    "iso:country":"ET",
    "name:und_x_variant":[
        "\u0100znan (2)",
        "\u0100znan"
    ],
    "wof:name":"Aznan",
    "wof:placetype":"locality"
},
  "geometry": {"coordinates":[38.68333,12.46667],"type":"Point"}
}