{
  "type": "Feature",
  "properties": {
    "gn:admin1_code":"54",
    "gn:asciiname":"Mejo",
    "gn:country_code":"ET",
    "gn:dem":2675,
    "gn:feature_class":"P",
    "gn:feature_code":"PPL",
    "gn:name":"Mejo",
    "gn:population":0,
    "gn:timezone":"Africa/Addis_Ababa",
    "iso:country":"ET",
    "wof:name":"Mejo",
    "wof:placetype":"locality"
},
  "geometry": {"coordinates":[38.95,6.45],"type":"Point"}
}