{
  "type": "Feature",
  "properties": {
    "gn:admin1_code":"52",
    "gn:asciiname":"Fantaweina",
    "gn:country_code":"ET",
    "gn:dem":708,
    "gn:feature_class":"P",
    "gn:feature_code":"PPL",
    "gn:name":"Fantaweina",
    "gn:population":0,
    "gn:timezone":"Africa/Addis_Ababa",
    "iso:country":"ET",
    "name:und_x_variant":[
        "Fantah Ueina",
        "Fantaueina",
        "Fantauena",
        "Fantaueyna",
        "Kurm\u012bs",
        "Fantaweina"
    ],
    "wof:name":"Fantaweina",
    "wof:placetype":"locality"
},
  "geometry": {"coordinates":[46.31583,8.025],"type":"Point"}
}