{
  "type": "Feature",
  "properties": {
    "gn:admin1_code":"53",
    "gn:asciiname":"Imbaza",
    "gn:country_code":"ET",
    "gn:dem":2051,
    "gn:feature_class":"P",
    "gn:feature_code":"PPL",
    "gn:name":"Imbaza",
    "gn:population":0,
    "gn:timezone":"Africa/Addis_Ababa",
    "iso:country":"ET",
    "wof:name":"Imbaza",
    "wof:placetype":"locality"
},
  "geometry": {"coordinates":[38.6205,14.01706],"type":"Point"}
}