{
  "type": "Feature",
  "properties": {
    "gn:admin1_code":"52.0",
    "gn:asciiname":"Cabenaua",
    "gn:country_code":"ET",
    "gn:dem":1197,
    "gn:feature_class":"P",
    "gn:feature_code":"PPL",
    "gn:name":"Cabenaua",
    "gn:population":0,
    "gn:timezone":"Africa/Addis_Ababa",
    "iso:country":"ET",
    "name:und_x_variant":[
        "Gabenaua",
        "Cabenaua"
    ],
    "wof:name":"Cabenaua",
    "wof:placetype":"locality"
},
  "geometry": {"coordinates":[42.36667,8.36667],"type":"Point"}
}