{
  "type": "Feature",
  "properties": {
    "gn:admin1_code":"51",
    "gn:asciiname":"Lola",
    "gn:country_code":"ET",
    "gn:dem":2252,
    "gn:feature_class":"P",
    "gn:feature_code":"PPL",
    "gn:name":"Lola",
    "gn:population":0,
    "gn:timezone":"Africa/Addis_Ababa",
    "iso:country":"ET",
    "wof:name":"Lola",
    "wof:placetype":"locality"
},
  "geometry": {"coordinates":[36.01667,7.86667],"type":"Point"}
}