{
  "type": "Feature",
  "properties": {
    "gn:admin1_code":"51",
    "gn:asciiname":"Gitilo",
    "gn:country_code":"ET",
    "gn:dem":2787,
    "gn:feature_class":"P",
    "gn:feature_code":"PPL",
    "gn:name":"G\u012bt\u012blo",
    "gn:population":0,
    "gn:timezone":"Africa/Addis_Ababa",
    "iso:country":"ET",
    "name:und_x_variant":[
        "G\u012bt\u012blo (1)",
        "G\u012bt\u012blo"
    ],
    "wof:name":"Gitilo",
    "wof:placetype":"locality"
},
  "geometry": {"coordinates":[37.05,9.55],"type":"Point"}
}