{
  "type": "Feature",
  "properties": {
    "gn:admin1_code":"53",
    "gn:asciiname":"Geyges",
    "gn:country_code":"ET",
    "gn:dem":2159,
    "gn:feature_class":"P",
    "gn:feature_code":"PPL",
    "gn:name":"G\u0113yg\u0113s",
    "gn:population":0,
    "gn:timezone":"Africa/Addis_Ababa",
    "iso:country":"ET",
    "wof:name":"Geyges",
    "wof:placetype":"locality"
},
  "geometry": {"coordinates":[39.35056,14.38806],"type":"Point"}
}