{
  "type": "Feature",
  "properties": {
    "gn:admin1_code":"51",
    "gn:asciiname":"Roca",
    "gn:country_code":"ET",
    "gn:dem":1251,
    "gn:feature_class":"P",
    "gn:feature_code":"PPL",
    "gn:name":"Roca",
    "gn:population":0,
    "gn:timezone":"Africa/Addis_Ababa",
    "iso:country":"ET",
    "name:bre_x_preferred":[
        "Roca"
    ],
    "name:cat_x_preferred":[
        "Roca"
    ],
    "name:ceb_x_preferred":[
        "Roca"
    ],
    "name:deu_x_preferred":[
        "Roca"
    ],
    "name:eus_x_preferred":[
        "Roca"
    ],
    "name:fra_x_preferred":[
        "Roca"
    ],
    "name:glg_x_preferred":[
        "Roca"
    ],
    "name:ita_x_preferred":[
        "Roca"
    ],
    "name:jpn_x_preferred":[
        "\u30ed\u30ab"
    ],
    "name:pol_x_preferred":[
        "Roca"
    ],
    "name:por_x_preferred":[
        "Roca"
    ],
    "name:spa_x_preferred":[
        "Roca"
    ],
    "name:swe_x_preferred":[
        "Roca"
    ],
    "wof:name":"Roca",
    "wof:placetype":"locality"
},
  "geometry": {"coordinates":[37.31667,5.15],"type":"Point"}
}