{
  "type": "Feature",
  "properties": {
    "gn:admin1_code":"51",
    "gn:asciiname":"Mole",
    "gn:country_code":"ET",
    "gn:dem":1828,
    "gn:feature_class":"P",
    "gn:feature_code":"PPL",
    "gn:name":"Mol\u0113",
    "gn:population":0,
    "gn:timezone":"Africa/Addis_Ababa",
    "iso:country":"ET",
    "name:ceb_x_preferred":[
        "Mole"
    ],
    "name:deu_x_preferred":[
        "Mole"
    ],
    "name:ell_x_preferred":[
        "Mole"
    ],
    "name:fin_x_preferred":[
        "Myyr\u00e4"
    ],
    "name:fra_x_preferred":[
        "Mole"
    ],
    "name:ita_x_preferred":[
        "Mole"
    ],
    "name:jpn_x_preferred":[
        "\u3082\u3050\u3089"
    ],
    "name:nld_x_preferred":[
        "Mole"
    ],
    "name:nor_x_preferred":[
        "Mole"
    ],
    "name:pol_x_preferred":[
        "Mole"
    ],
    "name:por_x_preferred":[
        "Mole"
    ],
    "name:spa_x_preferred":[
        "Mole"
    ],
    "name:swe_x_preferred":[
        "Mole"
    ],
    "name:und_x_variant":[
        "Teggio",
        "Teigio",
        "Mol\u0113"
    ],
    "wof:name":"Mole",
    "wof:placetype":"locality"
},
  "geometry": {"coordinates":[34.85,8.76667],"type":"Point"}
}