{
  "type": "Feature",
  "properties": {
    "gn:admin1_code":"51.0",
    "gn:asciiname":"Amida",
    "gn:country_code":"ET",
    "gn:dem":2309,
    "gn:feature_class":"P",
    "gn:feature_code":"PPL",
    "gn:name":"Amida",
    "gn:population":0,
    "gn:timezone":"Africa/Addis_Ababa",
    "iso:country":"ET",
    "name:cat_x_preferred":[
        "Amida"
    ],
    "name:ceb_x_preferred":[
        "Amida"
    ],
    "name:cym_x_preferred":[
        "Amida"
    ],
    "name:deu_x_preferred":[
        "Amida"
    ],
    "name:eus_x_preferred":[
        "Amida"
    ],
    "name:fra_x_preferred":[
        "Amida"
    ],
    "name:ita_x_preferred":[
        "Amida"
    ],
    "name:jpn_x_preferred":[
        "\u30a2\u30df\u30c0"
    ],
    "name:kor_x_preferred":[
        "\uc544\ubbf8\ub2e4"
    ],
    "name:nld_x_preferred":[
        "Amida"
    ],
    "name:pol_x_preferred":[
        "Amida"
    ],
    "name:por_x_preferred":[
        "Amida"
    ],
    "name:rus_x_preferred":[
        "\u0410\u043c\u0438\u0434\u0430"
    ],
    "name:swe_x_preferred":[
        "Amida"
    ],
    "wof:name":"Amida",
    "wof:placetype":"locality"
},
  "geometry": {"coordinates":[40.13333,7.21667],"type":"Point"}
}