{
  "type": "Feature",
  "properties": {
    "gn:admin1_code":"46",
    "gn:asciiname":"Washoch",
    "gn:country_code":"ET",
    "gn:dem":2064,
    "gn:feature_class":"P",
    "gn:feature_code":"PPL",
    "gn:name":"Washoch",
    "gn:population":0,
    "gn:timezone":"Africa/Addis_Ababa",
    "iso:country":"ET",
    "name:und_x_variant":[
        "Wasoch",
        "Washoch"
    ],
    "wof:name":"Washoch",
    "wof:placetype":"locality"
},
  "geometry": {"coordinates":[39.33333,11.26667],"type":"Point"}
}