{
  "type": "Feature",
  "properties": {
    "gn:admin1_code":"54.0",
    "gn:asciiname":"Birdiga",
    "gn:country_code":"ET",
    "gn:dem":973,
    "gn:feature_class":"P",
    "gn:feature_code":"PPL",
    "gn:name":"Birdiga",
    "gn:population":0,
    "gn:timezone":"Africa/Addis_Ababa",
    "iso:country":"ET",
    "wof:name":"Birdiga",
    "wof:placetype":"locality"
},
  "geometry": {"coordinates":[35.10758,5.8259],"type":"Point"}
}