{
  "type": "Feature",
  "properties": {
    "gn:admin1_code":"45.0",
    "gn:asciiname":"Aculle",
    "gn:country_code":"ET",
    "gn:dem":516,
    "gn:feature_class":"P",
    "gn:feature_code":"PPL",
    "gn:name":"Aculle",
    "gn:population":0,
    "gn:timezone":"Africa/Addis_Ababa",
    "iso:country":"ET",
    "name:und_x_variant":[
        "Akulle"
    ],
    "wof:name":"Aculle",
    "wof:placetype":"locality"
},
  "geometry": {"coordinates":[42.03178,12.57609],"type":"Point"}
}