{
  "type": "Feature",
  "properties": {
    "gn:admin1_code":"51",
    "gn:asciiname":"Teferi Birhan",
    "gn:country_code":"ET",
    "gn:dem":2241,
    "gn:feature_class":"P",
    "gn:feature_code":"PPL",
    "gn:name":"Tefer\u012b Birhan",
    "gn:population":0,
    "gn:timezone":"Africa/Addis_Ababa",
    "iso:country":"ET",
    "name:und_x_variant":[
        "Engheda",
        "Tefer\u012b Birhan"
    ],
    "wof:name":"Teferi Birhan",
    "wof:placetype":"locality"
},
  "geometry": {"coordinates":[40.03333,8.52472],"type":"Point"}
}