{
  "type": "Feature",
  "properties": {
    "gn:admin1_code":"51",
    "gn:asciiname":"Weter",
    "gn:country_code":"ET",
    "gn:dem":2054,
    "gn:feature_class":"P",
    "gn:feature_code":"PPL",
    "gn:name":"Weter",
    "gn:population":0,
    "gn:timezone":"Africa/Addis_Ababa",
    "iso:country":"ET",
    "name:und_x_variant":[
        "Weter (1)",
        "Uoter",
        "Weter"
    ],
    "wof:name":"Weter",
    "wof:placetype":"locality"
},
  "geometry": {"coordinates":[41.77083,9.3575],"type":"Point"}
}