{
  "type": "Feature",
  "properties": {
    "gn:admin1_code":"45",
    "gn:asciiname":"Shehet",
    "gn:country_code":"ET",
    "gn:dem":1464,
    "gn:feature_class":"P",
    "gn:feature_code":"PPL",
    "gn:name":"Sheh\u0113t",
    "gn:population":0,
    "gn:timezone":"Africa/Addis_Ababa",
    "iso:country":"ET",
    "name:und_x_variant":[
        "Secchet",
        "Sechet",
        "Shiket",
        "Sheh\u0113t"
    ],
    "wof:name":"Shehet",
    "wof:placetype":"locality"
},
  "geometry": {"coordinates":[39.75478,13.35531],"type":"Point"}
}