{
  "type": "Feature",
  "properties": {
    "gn:admin1_code":"46.0",
    "gn:asciiname":"Ashenga",
    "gn:country_code":"ET",
    "gn:dem":2857,
    "gn:feature_class":"P",
    "gn:feature_code":"PPL",
    "gn:name":"\u0100shenga",
    "gn:population":0,
    "gn:timezone":"Africa/Addis_Ababa",
    "iso:country":"ET",
    "name:und_x_variant":[
        "Melech Sanc\u00e0",
        "Malek Sank\u00e0",
        "Malek Sanca",
        "\u0100shenga"
    ],
    "wof:name":"Ashenga",
    "wof:placetype":"locality"
},
  "geometry": {"coordinates":[38.76667,11.03333],"type":"Point"}
}