{
  "type": "Feature",
  "properties": {
    "gn:admin1_code":"46",
    "gn:asciiname":"Werk'e Amba",
    "gn:country_code":"ET",
    "gn:dem":2386,
    "gn:feature_class":"P",
    "gn:feature_code":"PPL",
    "gn:name":"Werk\u2019\u0113 \u0100mba",
    "gn:population":0,
    "gn:timezone":"Africa/Addis_Ababa",
    "iso:country":"ET",
    "wof:name":"Werk'e Amba",
    "wof:placetype":"locality"
},
  "geometry": {"coordinates":[38.56667,10.65],"type":"Point"}
}