{
  "type": "Feature",
  "properties": {
    "gn:admin1_code":"51",
    "gn:asciiname":"Fesesa",
    "gn:country_code":"ET",
    "gn:dem":2375,
    "gn:feature_class":"P",
    "gn:feature_code":"PPL",
    "gn:name":"Fesesa",
    "gn:population":0,
    "gn:timezone":"Africa/Addis_Ababa",
    "iso:country":"ET",
    "wof:name":"Fesesa",
    "wof:placetype":"locality"
},
  "geometry": {"coordinates":[40.26667,7.28333],"type":"Point"}
}