{
  "type": "Feature",
  "properties": {
    "gn:admin1_code":"46",
    "gn:asciiname":"Fetek'a",
    "gn:country_code":"ET",
    "gn:dem":2191,
    "gn:feature_class":"P",
    "gn:feature_code":"PPL",
    "gn:name":"Fetek\u2019a",
    "gn:population":0,
    "gn:timezone":"Africa/Addis_Ababa",
    "iso:country":"ET",
    "wof:name":"Fetek'a",
    "wof:placetype":"locality"
},
  "geometry": {"coordinates":[39.85,11.23333],"type":"Point"}
}