{
  "type": "Feature",
  "properties": {
    "gn:admin1_code":"46",
    "gn:asciiname":"Madiji",
    "gn:country_code":"ET",
    "gn:dem":2890,
    "gn:feature_class":"P",
    "gn:feature_code":"PPL",
    "gn:name":"Mad\u012bj\u012b",
    "gn:population":0,
    "gn:timezone":"Africa/Addis_Ababa",
    "iso:country":"ET",
    "wof:name":"Madiji",
    "wof:placetype":"locality"
},
  "geometry": {"coordinates":[38.85,11.63333],"type":"Point"}
}