{
  "type": "Feature",
  "properties": {
    "gn:admin1_code":"46.0",
    "gn:asciiname":"Denk'ez",
    "gn:country_code":"ET",
    "gn:dem":2748,
    "gn:feature_class":"P",
    "gn:feature_code":"PPL",
    "gn:name":"Denk\u2019ez",
    "gn:population":0,
    "gn:timezone":"Africa/Addis_Ababa",
    "iso:country":"ET",
    "name:und_x_variant":[
        "Denk\u2019ez (2)",
        "Denk\u2019ez"
    ],
    "wof:name":"Denk'ez",
    "wof:placetype":"locality"
},
  "geometry": {"coordinates":[37.63333,12.48333],"type":"Point"}
}