{
  "type": "Feature",
  "properties": {
    "gn:admin1_code":"51",
    "gn:asciiname":"Lench'o",
    "gn:country_code":"ET",
    "gn:dem":2527,
    "gn:feature_class":"P",
    "gn:feature_code":"PPL",
    "gn:name":"L\u0113nch\u2019o",
    "gn:population":0,
    "gn:timezone":"Africa/Addis_Ababa",
    "iso:country":"ET",
    "wof:name":"Lench'o",
    "wof:placetype":"locality"
},
  "geometry": {"coordinates":[38.26667,10.01667],"type":"Point"}
}