{
  "type": "Feature",
  "properties": {
    "gn:admin1_code":"53.0",
    "gn:asciiname":"Anza",
    "gn:country_code":"ET",
    "gn:dem":2774,
    "gn:feature_class":"P",
    "gn:feature_code":"PPL",
    "gn:name":"\u0100nza",
    "gn:population":0,
    "gn:timezone":"Africa/Addis_Ababa",
    "iso:country":"ET",
    "wof:name":"Anza",
    "wof:placetype":"locality"
},
  "geometry": {"coordinates":[39.60919000000001,14.27002],"type":"Point"}
}