{
  "type": "Feature",
  "properties": {
    "gn:admin1_code":"52",
    "gn:asciiname":"San Dere",
    "gn:country_code":"ET",
    "gn:dem":476,
    "gn:feature_class":"P",
    "gn:feature_code":"PPL",
    "gn:name":"San Dere",
    "gn:population":0,
    "gn:timezone":"Africa/Addis_Ababa",
    "iso:country":"ET",
    "name:und_x_variant":[
        "Dara Duldul",
        "Santar",
        "San Dere"
    ],
    "wof:name":"San Dere",
    "wof:placetype":"locality"
},
  "geometry": {"coordinates":[43.01667,5.06667],"type":"Point"}
}