{
  "type": "Feature",
  "properties": {
    "gn:admin1_code":"51",
    "gn:asciiname":"Gefra Guda",
    "gn:country_code":"ET",
    "gn:dem":1741,
    "gn:feature_class":"P",
    "gn:feature_code":"PPL",
    "gn:name":"Gefra Guda",
    "gn:population":0,
    "gn:timezone":"Africa/Addis_Ababa",
    "iso:country":"ET",
    "wof:name":"Gefra Guda",
    "wof:placetype":"locality"
},
  "geometry": {"coordinates":[42.28361,9.39361],"type":"Point"}
}