{
  "type": "Feature",
  "properties": {
    "gn:admin1_code":"51",
    "gn:asciiname":"Doyo Gundi",
    "gn:country_code":"ET",
    "gn:dem":1733,
    "gn:feature_class":"P",
    "gn:feature_code":"PPL",
    "gn:name":"Doyo Gund\u012b",
    "gn:population":0,
    "gn:timezone":"Africa/Addis_Ababa",
    "iso:country":"ET",
    "wof:name":"Doyo Gundi",
    "wof:placetype":"locality"
},
  "geometry": {"coordinates":[35.36667,9.53333],"type":"Point"}
}