{
  "type": "Feature",
  "properties": {
    "iso:country":"ET",
    "name:dut_x_preferred":[
        "Waliso"
    ],
    "name:eng_x_preferred":[
        "Waliso"
    ],
    "name:fre_x_preferred":[
        "Waliso"
    ],
    "name:ita_x_preferred":[
        "Wolisso"
    ],
    "name:orm_x_preferred":[
        "Walisoo"
    ],
    "name:pol_x_preferred":[
        "Waliso"
    ],
    "name:rus_x_preferred":[
        "\u0413\u044b\u0439\u043e\u043d"
    ],
    "name:swe_x_preferred":[
        "Waliso"
    ],
    "name:unk_x_variant":[
        "Wolisso"
    ],
    "ne:ADM0CAP":0.0,
    "ne:ADM0NAME":"Ethiopia",
    "ne:ADM0_A3":"ETH",
    "ne:ADM1NAME":"Addis Ababa",
    "ne:ADMIN1_COD":44,
    "ne:CAPALT":0,
    "ne:CHANGED":0,
    "ne:CHECKME":0,
    "ne:COMPARE":0,
    "ne:DIFFASCII":0,
    "ne:ELEVATION":0.0,
    "ne:FEATURECLA":"Populated place",
    "ne:FEATURE_CL":"P",
    "ne:FEATURE_CO":"PPL",
    "ne:GEONAMEID":336372,
    "ne:GEONAMESNO":"Geonames ascii name + lat.d + long.d matching.",
    "ne:GN_ASCII":"Giyon",
    "ne:GN_POP":38394,
    "ne:GTOPO30":2049.0,
    "ne:ISO_A2":"ET",
    "ne:LABELRANK":3,
    "ne:LATITUDE":8.530421,
    "ne:LONGITUDE":37.970023,
    "ne:LS_MATCH":1,
    "ne:LS_NAME":"Giyon",
    "ne:MAX_AREAKM":204.0,
    "ne:MAX_AREAMI":79.0,
    "ne:MAX_BBXMAX":38.341667,
    "ne:MAX_BBXMIN":37.908333,
    "ne:MAX_BBYMAX":8.8,
    "ne:MAX_BBYMIN":8.416667,
    "ne:MAX_NATSCA":20.0,
    "ne:MAX_PERKM":205.0,
    "ne:MAX_PERMI":127.0,
    "ne:MAX_POP10":114534,
    "ne:MAX_POP20":114534,
    "ne:MAX_POP300":0,
    "ne:MAX_POP310":0,
    "ne:MAX_POP50":0,
    "ne:MEAN_BBXC":38.106108,
    "ne:MEAN_BBYC":8.61405,
    "ne:MEGACITY":0,
    "ne:MIN_AREAKM":204.0,
    "ne:MIN_AREAMI":79.0,
    "ne:MIN_BBXMAX":38.341667,
    "ne:MIN_BBXMIN":37.908333,
    "ne:MIN_BBYMAX":8.8,
    "ne:MIN_BBYMIN":8.416667,
    "ne:MIN_PERKM":205.0,
    "ne:MIN_PERMI":127.0,
    "ne:NAME":"Giyon",
    "ne:NAMEASCII":"Giyon",
    "ne:NAMEDIFF":0,
    "ne:NATSCALE":20,
    "ne:POP1950":0,
    "ne:POP1955":0,
    "ne:POP1960":0,
    "ne:POP1965":0,
    "ne:POP1970":0,
    "ne:POP1975":0,
    "ne:POP1980":0,
    "ne:POP1985":0,
    "ne:POP1990":0,
    "ne:POP1995":0,
    "ne:POP2000":0,
    "ne:POP2005":0,
    "ne:POP2010":0,
    "ne:POP2015":0,
    "ne:POP2020":0,
    "ne:POP2025":0,
    "ne:POP2050":0,
    "ne:POP_MAX":114534,
    "ne:POP_MIN":38394,
    "ne:POP_OTHER":464928,
    "ne:RANK_MAX":9,
    "ne:RANK_MIN":7,
    "ne:SCALERANK":7,
    "ne:SOV0NAME":"Ethiopia",
    "ne:SOV_A3":"ETH",
    "ne:TIMEZONE":"Africa/Addis_Ababa",
    "ne:UN_FID":0,
    "ne:UN_LAT":0.0,
    "ne:UN_LONG":0.0,
    "ne:WORLDCITY":0,
    "qs:gn_country":"ET",
    "qs:gn_fcode":"PPL",
    "qs:gn_pop":38394,
    "qs:name":"Giyon",
    "qs:name_adm0":"Ethiopia",
    "qs:name_adm1":"Oromia",
    "qs:photos":0,
    "qs:photos_1k":0,
    "qs:photos_9k":1,
    "qs:photos_9r":1,
    "qs:photos_all":1,
    "qs:photos_sr":0,
    "qs:placetype":"Town",
    "qs:pop_sr":"9",
    "qs:woe_adm0":23424808,
    "wof:name":"Giyon",
    "wof:placetype":"locality",
    "wof:population":38394
},
  "geometry": {"coordinates":[37.98333,8.53333],"type":"Point"}
}