{
  "type": "Feature",
  "properties": {
    "gn:admin1_code":"51",
    "gn:asciiname":"Ualla Kella",
    "gn:country_code":"ET",
    "gn:dem":1474,
    "gn:feature_class":"P",
    "gn:feature_code":"PPL",
    "gn:name":"Ualla Kella",
    "gn:population":0,
    "gn:timezone":"Africa/Addis_Ababa",
    "iso:country":"ET",
    "name:und_x_variant":[
        "Ualla",
        "Ualla Kella"
    ],
    "wof:name":"Ualla Kella",
    "wof:placetype":"locality"
},
  "geometry": {"coordinates":[36.46667,7.46667],"type":"Point"}
}