{
  "type": "Feature",
  "properties": {
    "gn:admin1_code":"51",
    "gn:asciiname":"Utulu",
    "gn:country_code":"ET",
    "gn:dem":1833,
    "gn:feature_class":"P",
    "gn:feature_code":"PPL",
    "gn:name":"Utulu",
    "gn:population":0,
    "gn:timezone":"Africa/Addis_Ababa",
    "iso:country":"ET",
    "wof:name":"Utulu",
    "wof:placetype":"locality"
},
  "geometry": {"coordinates":[41.96833,9.24583],"type":"Point"}
}