{
  "type": "Feature",
  "properties": {
    "gn:admin1_code":"46.0",
    "gn:asciiname":"Bit'oy",
    "gn:country_code":"ET",
    "gn:dem":2251,
    "gn:feature_class":"P",
    "gn:feature_code":"PPL",
    "gn:name":"Bit\u2019oy",
    "gn:population":0,
    "gn:timezone":"Africa/Addis_Ababa",
    "iso:country":"ET",
    "wof:name":"Bit'oy",
    "wof:placetype":"locality"
},
  "geometry": {"coordinates":[39.08333,11.88333],"type":"Point"}
}