{
  "type": "Feature",
  "properties": {
    "gn:admin1_code":"53.0",
    "gn:asciiname":"Adi Bidera",
    "gn:country_code":"ET",
    "gn:dem":1625,
    "gn:feature_class":"P",
    "gn:feature_code":"PPL",
    "gn:name":"\u0100d\u012b Bidera",
    "gn:population":0,
    "gn:timezone":"Africa/Addis_Ababa",
    "iso:country":"ET",
    "name:und_x_variant":[
        "Addi Abdera",
        "\u0100d\u012b Bidera (1)",
        "\u0100d\u012b Bidera"
    ],
    "wof:name":"Adi Bidera",
    "wof:placetype":"locality"
},
  "geometry": {"coordinates":[39.81667,12.76667],"type":"Point"}
}