{
  "type": "Feature",
  "properties": {
    "gn:admin1_code":"52",
    "gn:asciiname":"Durdere",
    "gn:country_code":"ET",
    "gn:dem":229,
    "gn:feature_class":"P",
    "gn:feature_code":"PPL",
    "gn:name":"Durd\u0113r\u0113",
    "gn:population":0,
    "gn:timezone":"Africa/Addis_Ababa",
    "iso:country":"ET",
    "wof:name":"Durdere",
    "wof:placetype":"locality"
},
  "geometry": {"coordinates":[44.46083,5.42361],"type":"Point"}
}