{
  "type": "Feature",
  "properties": {
    "gn:admin1_code":"53",
    "gn:asciiname":"Zekwa",
    "gn:country_code":"ET",
    "gn:dem":2085,
    "gn:feature_class":"P",
    "gn:feature_code":"PPL",
    "gn:name":"Zekwa",
    "gn:population":0,
    "gn:timezone":"Africa/Addis_Ababa",
    "iso:country":"ET",
    "name:und_x_variant":[
        "Zekua",
        "Zekwa"
    ],
    "wof:name":"Zekwa",
    "wof:placetype":"locality"
},
  "geometry": {"coordinates":[39.17537,13.43688],"type":"Point"}
}