{
  "type": "Feature",
  "properties": {
    "gn:admin1_code":"46.0",
    "gn:asciiname":"Amba Wiha",
    "gn:country_code":"ET",
    "gn:dem":1869,
    "gn:feature_class":"P",
    "gn:feature_code":"PPL",
    "gn:name":"\u0100mba Wiha",
    "gn:population":0,
    "gn:timezone":"Africa/Addis_Ababa",
    "iso:country":"ET",
    "wof:name":"Amba Wiha",
    "wof:placetype":"locality"
},
  "geometry": {"coordinates":[39.77956,10.61585],"type":"Point"}
}