{
  "type": "Feature",
  "properties": {
    "gn:admin1_code":"51",
    "gn:asciiname":"K'ere Loya",
    "gn:country_code":"ET",
    "gn:dem":2005,
    "gn:feature_class":"P",
    "gn:feature_code":"PPL",
    "gn:name":"K\u2019er\u0113 Loya",
    "gn:population":0,
    "gn:timezone":"Africa/Addis_Ababa",
    "iso:country":"ET",
    "wof:name":"K'ere Loya",
    "wof:placetype":"locality"
},
  "geometry": {"coordinates":[38.46667,9.98333],"type":"Point"}
}