{
  "type": "Feature",
  "properties": {
    "gn:admin1_code":"51",
    "gn:asciiname":"Sijo",
    "gn:country_code":"ET",
    "gn:dem":1838,
    "gn:feature_class":"P",
    "gn:feature_code":"PPL",
    "gn:name":"S\u012bjo",
    "gn:population":0,
    "gn:timezone":"Africa/Addis_Ababa",
    "iso:country":"ET",
    "name:ces_x_preferred":[
        "Sid\u017eo"
    ],
    "name:deu_x_preferred":[
        "Sijo"
    ],
    "name:fra_x_preferred":[
        "Sijo"
    ],
    "name:hun_x_preferred":[
        "Sidzso"
    ],
    "name:hye_x_preferred":[
        "\u054d\u056b\u057b\u0578"
    ],
    "name:ind_x_preferred":[
        "Sijo"
    ],
    "name:ita_x_preferred":[
        "Sijo"
    ],
    "name:jav_x_preferred":[
        "Sijo"
    ],
    "name:nep_x_preferred":[
        "\u0938\u093f\u091c\u094b"
    ],
    "name:rus_x_preferred":[
        "\u0421\u0438\u0434\u0436\u043e"
    ],
    "name:spa_x_preferred":[
        "Sijo"
    ],
    "name:ukr_x_preferred":[
        "\u0421\u0456\u0434\u0436\u043e"
    ],
    "name:und_x_variant":[
        "S\u012bjo (1)",
        "S\u012bjo"
    ],
    "name:vie_x_preferred":[
        "Sijo"
    ],
    "name:zho_x_preferred":[
        "\u6642\u8abf"
    ],
    "wof:name":"Sijo",
    "wof:placetype":"locality"
},
  "geometry": {"coordinates":[35.43333,9.56667],"type":"Point"}
}