{
  "type": "Feature",
  "properties": {
    "gn:admin1_code":"53.0",
    "gn:asciiname":"Adi Noguade",
    "gn:country_code":"ET",
    "gn:dem":2155,
    "gn:feature_class":"P",
    "gn:feature_code":"PPL",
    "gn:name":"Adi Noguade",
    "gn:population":0,
    "gn:timezone":"Africa/Addis_Ababa",
    "iso:country":"ET",
    "wof:name":"Adi Noguade",
    "wof:placetype":"locality"
},
  "geometry": {"coordinates":[39.40769,13.49108],"type":"Point"}
}