{
  "type": "Feature",
  "properties": {
    "gn:admin1_code":"52.0",
    "gn:asciiname":"Bubi",
    "gn:country_code":"ET",
    "gn:dem":509,
    "gn:feature_class":"P",
    "gn:feature_code":"PPL",
    "gn:name":"Bubi",
    "gn:population":0,
    "gn:timezone":"Africa/Addis_Ababa",
    "iso:country":"ET",
    "name:ceb_x_preferred":[
        "Bubi"
    ],
    "name:deu_x_preferred":[
        "Bubi"
    ],
    "name:fin_x_preferred":[
        "Bubi"
    ],
    "name:fra_x_preferred":[
        "Bubi"
    ],
    "name:hun_x_preferred":[
        "Bubi"
    ],
    "name:ita_x_preferred":[
        "Bubi"
    ],
    "name:nld_x_preferred":[
        "Bubi"
    ],
    "name:rus_x_preferred":[
        "\u0411\u0443\u0431\u0438"
    ],
    "name:swe_x_preferred":[
        "Bubi"
    ],
    "name:tat_x_preferred":[
        "\u0411\u0443\u0431\u0438"
    ],
    "wof:name":"Bubi",
    "wof:placetype":"locality"
},
  "geometry": {"coordinates":[44.62694000000001,6.66917],"type":"Point"}
}