{
  "type": "Feature",
  "properties": {
    "gn:admin1_code":"52.0",
    "gn:asciiname":"Bubi",
    "gn:country_code":"ET",
    "gn:dem":509,
    "gn:feature_class":"P",
    "gn:feature_code":"PPL",
    "gn:name":"Bubi",
    "gn:population":0,
    "gn:timezone":"Africa/Addis_Ababa",
    "iso:country":"ET",
    "wof:name":"Bubi",
    "wof:placetype":"locality"
},
  "geometry": {"coordinates":[44.62694000000001,6.66917],"type":"Point"}
}