{
  "type": "Feature",
  "properties": {
    "gn:admin1_code":"51",
    "gn:asciiname":"Sima",
    "gn:country_code":"ET",
    "gn:dem":2083,
    "gn:feature_class":"P",
    "gn:feature_code":"PPL",
    "gn:name":"S\u012bma",
    "gn:population":0,
    "gn:timezone":"Africa/Addis_Ababa",
    "iso:country":"ET",
    "name:ceb_x_preferred":[
        "Sima"
    ],
    "name:deu_x_preferred":[
        "Sima"
    ],
    "name:ell_x_preferred":[
        "\u03a3\u03ae\u03bc\u03b1"
    ],
    "name:est_x_preferred":[
        "Sima"
    ],
    "name:fin_x_preferred":[
        "Sima"
    ],
    "name:fra_x_preferred":[
        "Sima"
    ],
    "name:heb_x_preferred":[
        "\u05e1\u05d9\u05de\u05d4"
    ],
    "name:hye_x_preferred":[
        "\u054d\u056b\u0574\u0561"
    ],
    "name:ind_x_preferred":[
        "Sima"
    ],
    "name:ita_x_preferred":[
        "Sima"
    ],
    "name:jav_x_preferred":[
        "Sima"
    ],
    "name:kan_x_preferred":[
        "\u0cb8\u0cbf\u0cae\u0cbe"
    ],
    "name:new_x_preferred":[
        "\u0938\u093f\u092e\u093e \u0917\u093e\u0935\u093f\u0938"
    ],
    "name:nld_x_preferred":[
        "Sima"
    ],
    "name:pol_x_preferred":[
        "Sima"
    ],
    "name:ron_x_preferred":[
        "Sima"
    ],
    "name:rus_x_preferred":[
        "\u0421\u0438\u043c\u0430"
    ],
    "name:slk_x_preferred":[
        "Sima"
    ],
    "name:slv_x_preferred":[
        "Sima"
    ],
    "name:spa_x_preferred":[
        "Sima"
    ],
    "name:swe_x_preferred":[
        "Sima"
    ],
    "name:tgl_x_preferred":[
        "Sima"
    ],
    "name:ukr_x_preferred":[
        "\u0421\u0438\u043c\u0430"
    ],
    "wof:name":"Sima",
    "wof:placetype":"locality"
},
  "geometry": {"coordinates":[38.58333,8.88333],"type":"Point"}
}