{
  "type": "Feature",
  "properties": {
    "gn:admin1_code":"51",
    "gn:asciiname":"Gurbo",
    "gn:country_code":"ET",
    "gn:dem":1823,
    "gn:feature_class":"P",
    "gn:feature_code":"PPL",
    "gn:name":"Gurbo",
    "gn:population":0,
    "gn:timezone":"Africa/Addis_Ababa",
    "iso:country":"ET",
    "wof:name":"Gurbo",
    "wof:placetype":"locality"
},
  "geometry": {"coordinates":[36.93333,9.75],"type":"Point"}
}