{
  "type": "Feature",
  "properties": {
    "gn:admin1_code":"52.0",
    "gn:asciiname":"Gubedley",
    "gn:country_code":"ET",
    "gn:dem":188,
    "gn:feature_class":"P",
    "gn:feature_code":"PPL",
    "gn:name":"Gubedley",
    "gn:population":0,
    "gn:timezone":"Africa/Addis_Ababa",
    "iso:country":"ET",
    "wof:name":"Gubedley",
    "wof:placetype":"locality"
},
  "geometry": {"coordinates":[42.06639000000001,4.33028],"type":"Point"}
}