{
  "type": "Feature",
  "properties": {
    "gn:admin1_code":"53.0",
    "gn:asciiname":"Adi K'ebad",
    "gn:country_code":"ET",
    "gn:dem":1801,
    "gn:feature_class":"P",
    "gn:feature_code":"PPL",
    "gn:name":"\u0100d\u012b K\u2019ebad",
    "gn:population":0,
    "gn:timezone":"Africa/Addis_Ababa",
    "iso:country":"ET",
    "name:und_x_variant":[
        "Addi Kebad",
        "\u0100d\u012b K\u2019ebad"
    ],
    "wof:name":"Adi K'ebad",
    "wof:placetype":"locality"
},
  "geometry": {"coordinates":[38.50615,14.20879],"type":"Point"}
}