{
  "type": "Feature",
  "properties": {
    "gn:admin1_code":"52",
    "gn:asciiname":"Imei",
    "gn:country_code":"ET",
    "gn:dem":371,
    "gn:feature_class":"P",
    "gn:feature_code":"PPL",
    "gn:name":"Imei",
    "gn:population":0,
    "gn:timezone":"Africa/Addis_Ababa",
    "iso:country":"ET",
    "name:und_x_variant":[
        "Hinna",
        "Imei",
        "\u012am\u012b"
    ],
    "wof:name":"Imei",
    "wof:placetype":"locality"
},
  "geometry": {"coordinates":[42.17722,6.46667],"type":"Point"}
}