{
  "type": "Feature",
  "properties": {
    "gn:admin1_code":"52",
    "gn:asciiname":"El Fud",
    "gn:country_code":"ET",
    "gn:dem":872,
    "gn:feature_class":"P",
    "gn:feature_code":"PPL",
    "gn:name":"El Fud",
    "gn:population":0,
    "gn:timezone":"Africa/Addis_Ababa",
    "iso:country":"ET",
    "wof:name":"El Fud",
    "wof:placetype":"locality"
},
  "geometry": {"coordinates":[42.82258,7.24432],"type":"Point"}
}