{
  "type": "Feature",
  "properties": {
    "gn:admin1_code":"46",
    "gn:asciiname":"Sawdiba",
    "gn:country_code":"ET",
    "gn:dem":2046,
    "gn:feature_class":"P",
    "gn:feature_code":"PPL",
    "gn:name":"Sawdiba",
    "gn:population":0,
    "gn:timezone":"Africa/Addis_Ababa",
    "iso:country":"ET",
    "wof:name":"Sawdiba",
    "wof:placetype":"locality"
},
  "geometry": {"coordinates":[36.95,12.13333],"type":"Point"}
}