{
  "type": "Feature",
  "properties": {
    "gn:admin1_code":"54",
    "gn:asciiname":"Wisemo",
    "gn:country_code":"ET",
    "gn:dem":2038,
    "gn:feature_class":"P",
    "gn:feature_code":"PPL",
    "gn:name":"Wisemo",
    "gn:population":0,
    "gn:timezone":"Africa/Addis_Ababa",
    "iso:country":"ET",
    "wof:name":"Wisemo",
    "wof:placetype":"locality"
},
  "geometry": {"coordinates":[37.41667,6.11667],"type":"Point"}
}