{
  "type": "Feature",
  "properties": {
    "gn:admin1_code":"51",
    "gn:asciiname":"Lugoma",
    "gn:country_code":"ET",
    "gn:dem":2388,
    "gn:feature_class":"P",
    "gn:feature_code":"PPL",
    "gn:name":"Lugoma",
    "gn:population":0,
    "gn:timezone":"Africa/Addis_Ababa",
    "iso:country":"ET",
    "wof:name":"Lugoma",
    "wof:placetype":"locality"
},
  "geometry": {"coordinates":[38.43333,9.05],"type":"Point"}
}