{
  "type": "Feature",
  "properties": {
    "gn:admin1_code":"46",
    "gn:asciiname":"Liben",
    "gn:country_code":"ET",
    "gn:dem":1046,
    "gn:feature_class":"P",
    "gn:feature_code":"PPL",
    "gn:name":"L\u012bben",
    "gn:population":0,
    "gn:timezone":"Africa/Addis_Ababa",
    "iso:country":"ET",
    "name:ces_x_preferred":[
        "Libe\u0148"
    ],
    "name:deu_x_preferred":[
        "Libe\u0148"
    ],
    "name:fra_x_preferred":[
        "Liben"
    ],
    "wof:name":"Liben",
    "wof:placetype":"locality"
},
  "geometry": {"coordinates":[37.93333,9.96667],"type":"Point"}
}