{
  "type": "Feature",
  "properties": {
    "gn:admin1_code":"51.0",
    "gn:asciiname":"Darmu Dega",
    "gn:country_code":"ET",
    "gn:dem":2089,
    "gn:feature_class":"P",
    "gn:feature_code":"PPL",
    "gn:name":"Darmu D\u0113ga",
    "gn:population":0,
    "gn:timezone":"Africa/Addis_Ababa",
    "iso:country":"ET",
    "name:und_x_variant":[
        "Darma Dega",
        "Darmu D\u0113ga"
    ],
    "wof:name":"Darmu Dega",
    "wof:placetype":"locality"
},
  "geometry": {"coordinates":[36.05831,8.58968],"type":"Point"}
}