{
  "type": "Feature",
  "properties": {
    "gn:admin1_code":"46",
    "gn:asciiname":"Wok'olo",
    "gn:country_code":"ET",
    "gn:dem":2619,
    "gn:feature_class":"P",
    "gn:feature_code":"PPL",
    "gn:name":"Wok\u2019olo",
    "gn:population":0,
    "gn:timezone":"Africa/Addis_Ababa",
    "iso:country":"ET",
    "wof:name":"Wok'olo",
    "wof:placetype":"locality"
},
  "geometry": {"coordinates":[38.96667,9.78333],"type":"Point"}
}