{
  "type": "Feature",
  "properties": {
    "gn:admin1_code":"51",
    "gn:asciiname":"Waye",
    "gn:country_code":"ET",
    "gn:dem":2877,
    "gn:feature_class":"P",
    "gn:feature_code":"PPL",
    "gn:name":"Way\u0113",
    "gn:population":0,
    "gn:timezone":"Africa/Addis_Ababa",
    "iso:country":"ET",
    "wof:name":"Waye",
    "wof:placetype":"locality"
},
  "geometry": {"coordinates":[39.88333,8.25],"type":"Point"}
}