{
  "type": "Feature",
  "properties": {
    "gn:admin1_code":"51",
    "gn:asciiname":"Yeka",
    "gn:country_code":"ET",
    "gn:dem":2520,
    "gn:feature_class":"P",
    "gn:feature_code":"PPL",
    "gn:name":"Yeka",
    "gn:population":0,
    "gn:timezone":"Africa/Addis_Ababa",
    "iso:country":"ET",
    "wof:name":"Yeka",
    "wof:placetype":"locality"
},
  "geometry": {"coordinates":[38.73333,9.38333],"type":"Point"}
}