{
  "type": "Feature",
  "properties": {
    "gn:admin1_code":"53",
    "gn:asciiname":"Girame",
    "gn:country_code":"ET",
    "gn:dem":1739,
    "gn:feature_class":"P",
    "gn:feature_code":"PPL",
    "gn:name":"Girame",
    "gn:population":0,
    "gn:timezone":"Africa/Addis_Ababa",
    "iso:country":"ET",
    "name:und_x_variant":[
        "Gyrame",
        "Girame"
    ],
    "wof:name":"Girame",
    "wof:placetype":"locality"
},
  "geometry": {"coordinates":[39.1161,13.34715],"type":"Point"}
}