{
  "type": "Feature",
  "properties": {
    "gn:admin1_code":"51",
    "gn:asciiname":"Sire",
    "gn:country_code":"ET",
    "gn:dem":1828,
    "gn:feature_class":"P",
    "gn:feature_code":"PPL",
    "gn:name":"S\u012br\u0113",
    "gn:population":0,
    "gn:timezone":"Africa/Addis_Ababa",
    "iso:country":"ET",
    "name:deu_x_preferred":[
        "Sire"
    ],
    "name:ita_x_preferred":[
        "Sire"
    ],
    "name:nld_x_preferred":[
        "Sire"
    ],
    "name:rus_x_preferred":[
        "\u0421\u0438\u0440"
    ],
    "name:spa_x_preferred":[
        "Sire"
    ],
    "name:swe_x_preferred":[
        "Sire"
    ],
    "name:und_x_variant":[
        "S\u012br\u0113 (1)",
        "S\u012br\u0113"
    ],
    "wof:name":"Sire",
    "wof:placetype":"locality"
},
  "geometry": {"coordinates":[39.45,8.28333],"type":"Point"}
}