{
  "type": "Feature",
  "properties": {
    "gn:admin1_code":"46.0",
    "gn:asciiname":"Begide",
    "gn:country_code":"ET",
    "gn:dem":2634,
    "gn:feature_class":"P",
    "gn:feature_code":"PPL",
    "gn:name":"Begid\u0113",
    "gn:population":0,
    "gn:timezone":"Africa/Addis_Ababa",
    "iso:country":"ET",
    "wof:name":"Begide",
    "wof:placetype":"locality"
},
  "geometry": {"coordinates":[39.27213,10.51812],"type":"Point"}
}