{
  "type": "Feature",
  "properties": {
    "gn:admin1_code":"51",
    "gn:asciiname":"Guye",
    "gn:country_code":"ET",
    "gn:dem":2413,
    "gn:feature_class":"P",
    "gn:feature_code":"PPL",
    "gn:name":"Guy\u0113",
    "gn:population":0,
    "gn:timezone":"Africa/Addis_Ababa",
    "iso:country":"ET",
    "wof:name":"Guye",
    "wof:placetype":"locality"
},
  "geometry": {"coordinates":[38.56667,8.51667],"type":"Point"}
}