{
  "type": "Feature",
  "properties": {
    "gn:admin1_code":"51",
    "gn:asciiname":"K'ont'ola",
    "gn:country_code":"ET",
    "gn:dem":1650,
    "gn:feature_class":"P",
    "gn:feature_code":"PPL",
    "gn:name":"K\u2019ont\u2019ola",
    "gn:population":0,
    "gn:timezone":"Africa/Addis_Ababa",
    "iso:country":"ET",
    "wof:name":"K'ont'ola",
    "wof:placetype":"locality"
},
  "geometry": {"coordinates":[38.71667,7.98333],"type":"Point"}
}