{
  "type": "Feature",
  "properties": {
    "gn:admin1_code":"46",
    "gn:asciiname":"Negede",
    "gn:country_code":"ET",
    "gn:dem":2596,
    "gn:feature_class":"P",
    "gn:feature_code":"PPL",
    "gn:name":"Neged\u0113",
    "gn:population":0,
    "gn:timezone":"Africa/Addis_Ababa",
    "iso:country":"ET",
    "wof:name":"Negede",
    "wof:placetype":"locality"
},
  "geometry": {"coordinates":[37.53333,11.16667],"type":"Point"}
}