{
  "type": "Feature",
  "properties": {
    "gn:admin1_code":"51",
    "gn:asciiname":"Kora",
    "gn:country_code":"ET",
    "gn:dem":1513,
    "gn:feature_class":"P",
    "gn:feature_code":"PPL",
    "gn:name":"Kora",
    "gn:population":0,
    "gn:timezone":"Africa/Addis_Ababa",
    "iso:country":"ET",
    "wof:name":"Kora",
    "wof:placetype":"locality"
},
  "geometry": {"coordinates":[34.73333,9.36667],"type":"Point"}
}