{
  "type": "Feature",
  "properties": {
    "gn:admin1_code":"47",
    "gn:asciiname":"Koko",
    "gn:country_code":"ET",
    "gn:dem":1810,
    "gn:feature_class":"P",
    "gn:feature_code":"PPL",
    "gn:name":"Koko",
    "gn:population":0,
    "gn:timezone":"Africa/Addis_Ababa",
    "iso:country":"ET",
    "name:bul_x_preferred":[
        "\u041a\u043e\u043a\u043e"
    ],
    "name:ceb_x_preferred":[
        "Koko"
    ],
    "name:ces_x_preferred":[
        "Koko"
    ],
    "name:deu_x_preferred":[
        "Koko"
    ],
    "name:epo_x_preferred":[
        "Koko"
    ],
    "name:fin_x_preferred":[
        "Koko"
    ],
    "name:fra_x_preferred":[
        "Koko"
    ],
    "name:hun_x_preferred":[
        "Koko"
    ],
    "name:ind_x_preferred":[
        "Koko"
    ],
    "name:mya_x_preferred":[
        "\u1000\u102d\u102f\u1000\u102d\u102f"
    ],
    "name:nld_x_preferred":[
        "Koko"
    ],
    "name:pol_x_preferred":[
        "Koko"
    ],
    "name:por_x_preferred":[
        "Koko"
    ],
    "name:rus_x_preferred":[
        "\u041a\u043e\u043a\u043e"
    ],
    "name:srp_x_preferred":[
        "\u041a\u043e\u043a\u043e"
    ],
    "name:swe_x_preferred":[
        "Koko"
    ],
    "name:ukr_x_preferred":[
        "\u041a\u043e\u043a\u043e"
    ],
    "name:und_x_variant":[
        "Coco"
    ],
    "wof:name":"Koko",
    "wof:placetype":"locality"
},
  "geometry": {"coordinates":[36.11667,10.28333],"type":"Point"}
}