{
  "type": "Feature",
  "properties": {
    "gn:admin1_code":"47",
    "gn:asciiname":"Koko",
    "gn:country_code":"ET",
    "gn:dem":1810,
    "gn:feature_class":"P",
    "gn:feature_code":"PPL",
    "gn:name":"Koko",
    "gn:population":0,
    "gn:timezone":"Africa/Addis_Ababa",
    "iso:country":"ET",
    "name:und_x_variant":[
        "Coco",
        "Koko"
    ],
    "wof:name":"Koko",
    "wof:placetype":"locality"
},
  "geometry": {"coordinates":[36.11667,10.28333],"type":"Point"}
}