{
  "type": "Feature",
  "properties": {
    "gn:admin1_code":"52.0",
    "gn:asciiname":"Dibo",
    "gn:country_code":"ET",
    "gn:dem":506,
    "gn:feature_class":"P",
    "gn:feature_code":"PPL",
    "gn:name":"Dibo",
    "gn:population":0,
    "gn:timezone":"Africa/Addis_Ababa",
    "iso:country":"ET",
    "name:yor_x_preferred":[
        "Dibo"
    ],
    "wof:name":"Dibo",
    "wof:placetype":"locality"
},
  "geometry": {"coordinates":[41.83333,6.53333],"type":"Point"}
}