{
  "type": "Feature",
  "properties": {
    "gn:admin1_code":"51",
    "gn:asciiname":"Misrak'e",
    "gn:country_code":"ET",
    "gn:dem":2593,
    "gn:feature_class":"P",
    "gn:feature_code":"PPL",
    "gn:name":"Misrak\u2019\u0113",
    "gn:population":0,
    "gn:timezone":"Africa/Addis_Ababa",
    "iso:country":"ET",
    "wof:name":"Misrak'e",
    "wof:placetype":"locality"
},
  "geometry": {"coordinates":[38.86667,9.66667],"type":"Point"}
}