{
  "type": "Feature",
  "properties": {
    "gn:admin1_code":"52.0",
    "gn:asciiname":"El Jigle",
    "gn:country_code":"ET",
    "gn:dem":433,
    "gn:feature_class":"P",
    "gn:feature_code":"PPL",
    "gn:name":"El Jigle",
    "gn:population":0,
    "gn:timezone":"Africa/Addis_Ababa",
    "iso:country":"ET",
    "name:und_x_variant":[
        "El Dzhigle",
        "El Jigle"
    ],
    "wof:name":"El Jigle",
    "wof:placetype":"locality"
},
  "geometry": {"coordinates":[43.54361,5.02833],"type":"Point"}
}