{
  "type": "Feature",
  "properties": {
    "gn:admin1_code":"51.0",
    "gn:asciiname":"Berodo",
    "gn:country_code":"ET",
    "gn:dem":2239,
    "gn:feature_class":"P",
    "gn:feature_code":"PPL",
    "gn:name":"Berodo",
    "gn:population":0,
    "gn:timezone":"Africa/Addis_Ababa",
    "iso:country":"ET",
    "wof:name":"Berodo",
    "wof:placetype":"locality"
},
  "geometry": {"coordinates":[38.16667,9.03333],"type":"Point"}
}