{
  "type": "Feature",
  "properties": {
    "gn:admin1_code":"46",
    "gn:asciiname":"Indeher Giba",
    "gn:country_code":"ET",
    "gn:dem":1866,
    "gn:feature_class":"P",
    "gn:feature_code":"PPL",
    "gn:name":"Indeher Giba",
    "gn:population":0,
    "gn:timezone":"Africa/Addis_Ababa",
    "iso:country":"ET",
    "wof:name":"Indeher Giba",
    "wof:placetype":"locality"
},
  "geometry": {"coordinates":[39.18333,12.85],"type":"Point"}
}