{
  "type": "Feature",
  "properties": {
    "gn:admin1_code":"53.0",
    "gn:asciiname":"Adi Aba Jebano",
    "gn:country_code":"ET",
    "gn:dem":1724,
    "gn:feature_class":"P",
    "gn:feature_code":"PPL",
    "gn:name":"\u0100d\u012b \u0100ba Jebano",
    "gn:population":0,
    "gn:timezone":"Africa/Addis_Ababa",
    "iso:country":"ET",
    "wof:name":"Adi Aba Jebano",
    "wof:placetype":"locality"
},
  "geometry": {"coordinates":[39.76667,12.56667],"type":"Point"}
}