{
  "type": "Feature",
  "properties": {
    "gn:admin1_code":"51",
    "gn:asciiname":"Lalo",
    "gn:country_code":"ET",
    "gn:dem":2757,
    "gn:feature_class":"P",
    "gn:feature_code":"PPL",
    "gn:name":"Lalo",
    "gn:population":0,
    "gn:timezone":"Africa/Addis_Ababa",
    "iso:country":"ET",
    "name:ceb_x_preferred":[
        "Lalo"
    ],
    "name:deu_x_preferred":[
        "Lalo"
    ],
    "name:fra_x_preferred":[
        "Lalo"
    ],
    "name:nld_x_preferred":[
        "Lalo"
    ],
    "name:spa_x_preferred":[
        "Lalo"
    ],
    "name:swe_x_preferred":[
        "Lalo"
    ],
    "wof:name":"Lalo",
    "wof:placetype":"locality"
},
  "geometry": {"coordinates":[38.33333,9.13333],"type":"Point"}
}