{
  "type": "Feature",
  "properties": {
    "gn:admin1_code":"46",
    "gn:asciiname":"T'ik'ur Ch'inch'a",
    "gn:country_code":"ET",
    "gn:dem":3195,
    "gn:feature_class":"P",
    "gn:feature_code":"PPL",
    "gn:name":"T\u2019ik\u2019ur Ch\u2019inch\u2019a",
    "gn:population":0,
    "gn:timezone":"Africa/Addis_Ababa",
    "iso:country":"ET",
    "wof:name":"T'ik'ur Ch'inch'a",
    "wof:placetype":"locality"
},
  "geometry": {"coordinates":[39.26667,11.71667],"type":"Point"}
}