{
  "type": "Feature",
  "properties": {
    "gn:admin1_code":"51.0",
    "gn:asciiname":"Ch'anch'o",
    "gn:country_code":"ET",
    "gn:dem":3085,
    "gn:feature_class":"P",
    "gn:feature_code":"PPL",
    "gn:name":"Ch\u2019anch\u2019o",
    "gn:population":0,
    "gn:timezone":"Africa/Addis_Ababa",
    "iso:country":"ET",
    "wof:name":"Ch'anch'o",
    "wof:placetype":"locality"
},
  "geometry": {"coordinates":[38.63333,9.85],"type":"Point"}
}