{
  "type": "Feature",
  "properties": {
    "gn:admin1_code":"54.0",
    "gn:asciiname":"Abuli",
    "gn:country_code":"ET",
    "gn:dem":487,
    "gn:feature_class":"P",
    "gn:feature_code":"PPL",
    "gn:name":"Abuli",
    "gn:population":0,
    "gn:timezone":"Africa/Addis_Ababa",
    "iso:country":"ET",
    "wof:name":"Abuli",
    "wof:placetype":"locality"
},
  "geometry": {"coordinates":[34.52796,6.85727],"type":"Point"}
}