{
  "type": "Feature",
  "properties": {
    "gn:admin1_code":"45",
    "gn:asciiname":"Mengaga",
    "gn:country_code":"ET",
    "gn:dem":228,
    "gn:feature_class":"P",
    "gn:feature_code":"PPL",
    "gn:name":"Mengaga",
    "gn:population":0,
    "gn:timezone":"Africa/Addis_Ababa",
    "iso:country":"ET",
    "name:und_x_variant":[
        "Mangaga",
        "Menagaga",
        "Mengaga"
    ],
    "wof:name":"Mengaga",
    "wof:placetype":"locality"
},
  "geometry": {"coordinates":[41.27965,12.85625],"type":"Point"}
}