{
  "type": "Feature",
  "properties": {
    "gn:admin1_code":"51.0",
    "gn:asciiname":"Bedo",
    "gn:country_code":"ET",
    "gn:dem":2252,
    "gn:feature_class":"P",
    "gn:feature_code":"PPL",
    "gn:name":"Bedo",
    "gn:population":0,
    "gn:timezone":"Africa/Addis_Ababa",
    "iso:country":"ET",
    "wof:name":"Bedo",
    "wof:placetype":"locality"
},
  "geometry": {"coordinates":[37.13333,9.43333],"type":"Point"}
}