{
  "type": "Feature",
  "properties": {
    "gn:admin1_code":"53.0",
    "gn:asciiname":"Adi Hageray",
    "gn:country_code":"ET",
    "gn:dem":1372,
    "gn:feature_class":"P",
    "gn:feature_code":"PPL",
    "gn:name":"\u0100d\u012b Hageray",
    "gn:population":0,
    "gn:timezone":"Africa/Addis_Ababa",
    "iso:country":"ET",
    "name:und_x_variant":[
        "Adi Agghera",
        "Adi Agar\u00e0",
        "Addi Khageray",
        "\u0100d\u012b Hageray"
    ],
    "wof:name":"Adi Hageray",
    "wof:placetype":"locality"
},
  "geometry": {"coordinates":[38.05861,14.51556],"type":"Point"}
}