{
  "type": "Feature",
  "properties": {
    "gn:admin1_code":"46.0",
    "gn:asciiname":"Adami",
    "gn:country_code":"ET",
    "gn:dem":1990,
    "gn:feature_class":"P",
    "gn:feature_code":"PPL",
    "gn:name":"Adami",
    "gn:population":0,
    "gn:timezone":"Africa/Addis_Ababa",
    "iso:country":"ET",
    "name:ceb_x_preferred":[
        "Adami"
    ],
    "name:ces_x_preferred":[
        "Adami"
    ],
    "name:deu_x_preferred":[
        "Adami"
    ],
    "name:fra_x_preferred":[
        "Adami"
    ],
    "name:heb_x_preferred":[
        "\u05d0\u05d3\u05d0\u05de\u05d9"
    ],
    "name:ita_x_preferred":[
        "Adami"
    ],
    "name:kor_x_preferred":[
        "\uc544\ub2e4\ubbf8"
    ],
    "name:rus_x_preferred":[
        "\u0410\u0434\u0430\u043c\u0438"
    ],
    "name:slv_x_preferred":[
        "Adami"
    ],
    "name:spa_x_preferred":[
        "Adami"
    ],
    "name:swe_x_preferred":[
        "Adami"
    ],
    "name:ukr_x_preferred":[
        "\u0410\u0434\u0430\u043c\u0456"
    ],
    "name:und_x_variant":[
        "\u0100dam\u0113"
    ],
    "wof:name":"Adami",
    "wof:placetype":"locality"
},
  "geometry": {"coordinates":[39.82068,10.97809],"type":"Point"}
}