{
  "type": "Feature",
  "properties": {
    "gn:admin1_code":"46",
    "gn:asciiname":"Yigdu",
    "gn:country_code":"ET",
    "gn:dem":2160,
    "gn:feature_class":"P",
    "gn:feature_code":"PPL",
    "gn:name":"Yigdu",
    "gn:population":0,
    "gn:timezone":"Africa/Addis_Ababa",
    "iso:country":"ET",
    "wof:name":"Yigdu",
    "wof:placetype":"locality"
},
  "geometry": {"coordinates":[39.43528,10.16359],"type":"Point"}
}