{
  "type": "Feature",
  "properties": {
    "gn:admin1_code":"51",
    "gn:asciiname":"Gideya",
    "gn:country_code":"ET",
    "gn:dem":2152,
    "gn:feature_class":"P",
    "gn:feature_code":"PPL",
    "gn:name":"G\u012bdeya",
    "gn:population":0,
    "gn:timezone":"Africa/Addis_Ababa",
    "iso:country":"ET",
    "wof:name":"Gideya",
    "wof:placetype":"locality"
},
  "geometry": {"coordinates":[42.40583,9.48222],"type":"Point"}
}