{
  "type": "Feature",
  "properties": {
    "gn:admin1_code":"51",
    "gn:asciiname":"Rer Chihil",
    "gn:country_code":"ET",
    "gn:dem":1472,
    "gn:feature_class":"P",
    "gn:feature_code":"PPL",
    "gn:name":"Rer Chihil",
    "gn:population":0,
    "gn:timezone":"Africa/Addis_Ababa",
    "iso:country":"ET",
    "wof:name":"Rer Chihil",
    "wof:placetype":"locality"
},
  "geometry": {"coordinates":[42.46667,8.95],"type":"Point"}
}