{
  "type": "Feature",
  "properties": {
    "gn:admin1_code":"46.0",
    "gn:asciiname":"At'egeba",
    "gn:country_code":"ET",
    "gn:dem":3172,
    "gn:feature_class":"P",
    "gn:feature_code":"PPL",
    "gn:name":"\u0100t\u2019egeba",
    "gn:population":0,
    "gn:timezone":"Africa/Addis_Ababa",
    "iso:country":"ET",
    "wof:name":"At'egeba",
    "wof:placetype":"locality"
},
  "geometry": {"coordinates":[38.28333,13.26667],"type":"Point"}
}