{
  "type": "Feature",
  "properties": {
    "gn:admin1_code":"53.0",
    "gn:asciiname":"Adi Butzaat",
    "gn:country_code":"ET",
    "gn:dem":2000,
    "gn:feature_class":"P",
    "gn:feature_code":"PPL",
    "gn:name":"Adi Butzaat",
    "gn:population":0,
    "gn:timezone":"Africa/Addis_Ababa",
    "iso:country":"ET",
    "wof:name":"Adi Butzaat",
    "wof:placetype":"locality"
},
  "geometry": {"coordinates":[39.45,13.75],"type":"Point"}
}