{
  "type": "Feature",
  "properties": {
    "gn:admin1_code":"51",
    "gn:asciiname":"Gedo",
    "gn:country_code":"ET",
    "gn:dem":1482,
    "gn:feature_class":"P",
    "gn:feature_code":"PPL",
    "gn:name":"G\u0113do",
    "gn:population":0,
    "gn:timezone":"Africa/Addis_Ababa",
    "iso:country":"ET",
    "name:ara_x_preferred":[
        "\u062c\u062f\u0648"
    ],
    "name:bul_x_preferred":[
        "\u0413\u0435\u0434\u043e"
    ],
    "name:cat_x_preferred":[
        "Gedo"
    ],
    "name:ceb_x_preferred":[
        "Gobolka Gedo"
    ],
    "name:dan_x_preferred":[
        "Geedo"
    ],
    "name:deu_x_preferred":[
        "Gedo"
    ],
    "name:epo_x_preferred":[
        "Gedo"
    ],
    "name:eus_x_preferred":[
        "Gedo"
    ],
    "name:fin_x_preferred":[
        "Gedo"
    ],
    "name:fra_x_preferred":[
        "Gedo"
    ],
    "name:ita_x_preferred":[
        "Ghedo"
    ],
    "name:jav_x_preferred":[
        "Gedo"
    ],
    "name:jpn_x_preferred":[
        "\u30b2\u30c9\u5dde"
    ],
    "name:kat_x_preferred":[
        "\u10d2\u10d4\u10d3\u10dd\u10e1 \u10e0\u10d4\u10d2\u10d8\u10dd\u10dc\u10d8"
    ],
    "name:kor_x_preferred":[
        "\uac8c\ub3c4 \uc8fc"
    ],
    "name:nld_x_preferred":[
        "Gedo"
    ],
    "name:nor_x_preferred":[
        "Gedo"
    ],
    "name:pol_x_preferred":[
        "Gedo"
    ],
    "name:por_x_preferred":[
        "Gedo"
    ],
    "name:rus_x_preferred":[
        "\u0413\u0435\u0434\u043e"
    ],
    "name:som_x_preferred":[
        "Gedo"
    ],
    "name:swe_x_preferred":[
        "Gedo"
    ],
    "name:tha_x_preferred":[
        "\u0e40\u0e08\u0e42\u0e14"
    ],
    "name:tur_x_preferred":[
        "Gedo"
    ],
    "name:ukr_x_preferred":[
        "\u0413\u0435\u0434\u043e"
    ],
    "name:urd_x_preferred":[
        "\u062c\u062f\u0648"
    ],
    "name:zho_x_preferred":[
        "\u84cb\u591a\u5dde"
    ],
    "wof:name":"Gedo",
    "wof:placetype":"locality"
},
  "geometry": {"coordinates":[39.33333,8.56667],"type":"Point"}
}