{
  "type": "Feature",
  "properties": {
    "gn:admin1_code":"51",
    "gn:asciiname":"Gedo",
    "gn:country_code":"ET",
    "gn:dem":1482,
    "gn:feature_class":"P",
    "gn:feature_code":"PPL",
    "gn:name":"G\u0113do",
    "gn:population":0,
    "gn:timezone":"Africa/Addis_Ababa",
    "iso:country":"ET",
    "wof:name":"Gedo",
    "wof:placetype":"locality"
},
  "geometry": {"coordinates":[39.33333,8.56667],"type":"Point"}
}