{
  "type": "Feature",
  "properties": {
    "gn:admin1_code":"46",
    "gn:asciiname":"Welezi",
    "gn:country_code":"ET",
    "gn:dem":1890,
    "gn:feature_class":"P",
    "gn:feature_code":"PPL",
    "gn:name":"Welezi",
    "gn:population":0,
    "gn:timezone":"Africa/Addis_Ababa",
    "iso:country":"ET",
    "wof:name":"Welezi",
    "wof:placetype":"locality"
},
  "geometry": {"coordinates":[38.82,12.91278],"type":"Point"}
}