{
  "type": "Feature",
  "properties": {
    "gn:admin1_code":"51",
    "gn:asciiname":"Tulube",
    "gn:country_code":"ET",
    "gn:dem":1694,
    "gn:feature_class":"P",
    "gn:feature_code":"PPL",
    "gn:name":"Tulub\u0113",
    "gn:population":0,
    "gn:timezone":"Africa/Addis_Ababa",
    "iso:country":"ET",
    "wof:name":"Tulube",
    "wof:placetype":"locality"
},
  "geometry": {"coordinates":[35.53333,8.33333],"type":"Point"}
}