{
  "type": "Feature",
  "properties": {
    "gn:admin1_code":"49",
    "gn:asciiname":"Mangjang",
    "gn:country_code":"ET",
    "gn:dem":406,
    "gn:feature_class":"P",
    "gn:feature_code":"PPL",
    "gn:name":"Mangjang",
    "gn:population":0,
    "gn:timezone":"Africa/Addis_Ababa",
    "iso:country":"ET",
    "wof:name":"Mangjang",
    "wof:placetype":"locality"
},
  "geometry": {"coordinates":[33.17913,8.28936],"type":"Point"}
}