{
  "type": "Feature",
  "properties": {
    "gn:admin1_code":"54.0",
    "gn:asciiname":"Canta",
    "gn:country_code":"ET",
    "gn:dem":1464,
    "gn:feature_class":"P",
    "gn:feature_code":"PPL",
    "gn:name":"Canta",
    "gn:population":0,
    "gn:timezone":"Africa/Addis_Ababa",
    "iso:country":"ET",
    "name:aym_x_preferred":[
        "Kanta"
    ],
    "name:eng_x_preferred":[
        "Kanta"
    ],
    "name:nld_x_preferred":[
        "Canta"
    ],
    "name:por_x_preferred":[
        "Canta"
    ],
    "name:que_x_preferred":[
        "Kanta"
    ],
    "name:ron_x_preferred":[
        "Canta"
    ],
    "name:spa_x_preferred":[
        "Canta"
    ],
    "name:war_x_preferred":[
        "Canta"
    ],
    "wof:name":"Canta",
    "wof:placetype":"locality"
},
  "geometry": {"coordinates":[35.26847,6.04112],"type":"Point"}
}