{
  "type": "Feature",
  "properties": {
    "gn:admin1_code":"46.0",
    "gn:asciiname":"Ashenat",
    "gn:country_code":"ET",
    "gn:dem":2719,
    "gn:feature_class":"P",
    "gn:feature_code":"PPL",
    "gn:name":"\u0100shenat",
    "gn:population":0,
    "gn:timezone":"Africa/Addis_Ababa",
    "iso:country":"ET",
    "name:und_x_variant":[
        "\u0100shenat (2)",
        "\u0100shenat"
    ],
    "wof:name":"Ashenat",
    "wof:placetype":"locality"
},
  "geometry": {"coordinates":[38.93333,11.46667],"type":"Point"}
}