{
  "type": "Feature",
  "properties": {
    "gn:admin1_code":"53",
    "gn:asciiname":"Guldam",
    "gn:country_code":"ET",
    "gn:dem":2134,
    "gn:feature_class":"P",
    "gn:feature_code":"PPL",
    "gn:name":"Guldam",
    "gn:population":0,
    "gn:timezone":"Africa/Addis_Ababa",
    "iso:country":"ET",
    "wof:name":"Guldam",
    "wof:placetype":"locality"
},
  "geometry": {"coordinates":[39.0525,14.25222],"type":"Point"}
}