{
  "type": "Feature",
  "properties": {
    "gn:admin1_code":"49.0",
    "gn:asciiname":"Marial'",
    "gn:country_code":"ET",
    "gn:dem":414,
    "gn:feature_class":"P",
    "gn:feature_code":"PPL",
    "gn:name":"Marial\u2019",
    "gn:population":0,
    "gn:timezone":"Africa/Addis_Ababa",
    "iso:country":"ET",
    "wof:name":"Marial'",
    "wof:placetype":"locality"
},
  "geometry": {"coordinates":[33.69762,8.35796],"type":"Point"}
}