{
  "type": "Feature",
  "properties": {
    "gn:admin1_code":"51.0",
    "gn:asciiname":"Birbirsa",
    "gn:country_code":"ET",
    "gn:dem":1767,
    "gn:feature_class":"P",
    "gn:feature_code":"PPL",
    "gn:name":"B\u012brb\u012brsa",
    "gn:population":0,
    "gn:timezone":"Africa/Addis_Ababa",
    "iso:country":"ET",
    "wof:name":"Birbirsa",
    "wof:placetype":"locality"
},
  "geometry": {"coordinates":[42.18583,9.40889],"type":"Point"}
}