{
  "type": "Feature",
  "properties": {
    "gn:admin1_code":"54",
    "gn:asciiname":"Uatara",
    "gn:country_code":"ET",
    "gn:dem":2080,
    "gn:feature_class":"P",
    "gn:feature_code":"PPL",
    "gn:name":"Uatara",
    "gn:population":0,
    "gn:timezone":"Africa/Addis_Ababa",
    "iso:country":"ET",
    "wof:name":"Uatara",
    "wof:placetype":"locality"
},
  "geometry": {"coordinates":[37.88333,7.43333],"type":"Point"}
}