{
  "type": "Feature",
  "properties": {
    "gn:admin1_code":"52",
    "gn:asciiname":"Dube Dile",
    "gn:country_code":"ET",
    "gn:dem":1561,
    "gn:feature_class":"P",
    "gn:feature_code":"PPL",
    "gn:name":"Dube D\u012bl\u0113",
    "gn:population":0,
    "gn:timezone":"Africa/Addis_Ababa",
    "iso:country":"ET",
    "wof:name":"Dube Dile",
    "wof:placetype":"locality"
},
  "geometry": {"coordinates":[42.55806,9.36861],"type":"Point"}
}