{
  "type": "Feature",
  "properties": {
    "gn:admin1_code":"54",
    "gn:asciiname":"K'ilicha",
    "gn:country_code":"ET",
    "gn:dem":2203,
    "gn:feature_class":"P",
    "gn:feature_code":"PPL",
    "gn:name":"K\u2019il\u012bcha",
    "gn:population":0,
    "gn:timezone":"Africa/Addis_Ababa",
    "iso:country":"ET",
    "wof:name":"K'ilicha",
    "wof:placetype":"locality"
},
  "geometry": {"coordinates":[38.65,8.33333],"type":"Point"}
}