{
  "type": "Feature",
  "properties": {
    "gn:admin1_code":"52",
    "gn:asciiname":"Mula'ale",
    "gn:country_code":"ET",
    "gn:dem":1618,
    "gn:feature_class":"P",
    "gn:feature_code":"PPL",
    "gn:name":"Mula\u2019\u0101l\u0113",
    "gn:population":0,
    "gn:timezone":"Africa/Addis_Ababa",
    "iso:country":"ET",
    "wof:name":"Mula'ale",
    "wof:placetype":"locality"
},
  "geometry": {"coordinates":[42.91638,9.00355],"type":"Point"}
}