{
  "type": "Feature",
  "properties": {
    "gn:admin1_code":"46",
    "gn:asciiname":"K'urk'ura",
    "gn:country_code":"ET",
    "gn:dem":2038,
    "gn:feature_class":"P",
    "gn:feature_code":"PPL",
    "gn:name":"K\u2019urk\u2019ura",
    "gn:population":0,
    "gn:timezone":"Africa/Addis_Ababa",
    "iso:country":"ET",
    "wof:name":"K'urk'ura",
    "wof:placetype":"locality"
},
  "geometry": {"coordinates":[39.53333,12.16667],"type":"Point"}
}