{
  "type": "Feature",
  "properties": {
    "gn:admin1_code":"53.0",
    "gn:asciiname":"Adoduwa",
    "gn:country_code":"ET",
    "gn:dem":3096,
    "gn:feature_class":"P",
    "gn:feature_code":"PPL",
    "gn:name":"\u0100doduwa",
    "gn:population":0,
    "gn:timezone":"Africa/Addis_Ababa",
    "iso:country":"ET",
    "wof:name":"Adoduwa",
    "wof:placetype":"locality"
},
  "geometry": {"coordinates":[39.48333,12.88333],"type":"Point"}
}