{
  "type": "Feature",
  "properties": {
    "gn:admin1_code":"46",
    "gn:asciiname":"Gishenit",
    "gn:country_code":"ET",
    "gn:dem":2301,
    "gn:feature_class":"P",
    "gn:feature_code":"PPL",
    "gn:name":"Gishen\u012bt",
    "gn:population":0,
    "gn:timezone":"Africa/Addis_Ababa",
    "iso:country":"ET",
    "wof:name":"Gishenit",
    "wof:placetype":"locality"
},
  "geometry": {"coordinates":[39.23924,10.64708],"type":"Point"}
}