{
  "type": "Feature",
  "properties": {
    "gn:admin1_code":"52.0",
    "gn:asciiname":"Damerabob",
    "gn:country_code":"ET",
    "gn:dem":1481,
    "gn:feature_class":"P",
    "gn:feature_code":"PPL",
    "gn:name":"Damerabob",
    "gn:population":0,
    "gn:timezone":"Africa/Addis_Ababa",
    "iso:country":"ET",
    "name:und_x_variant":[
        "Domerab\u00f2b",
        "Dabera",
        "Damerabob"
    ],
    "wof:name":"Damerabob",
    "wof:placetype":"locality"
},
  "geometry": {"coordinates":[43.48333,9.41667],"type":"Point"}
}