{
  "type": "Feature",
  "properties": {
    "gn:admin1_code":"51",
    "gn:asciiname":"Lemi",
    "gn:country_code":"ET",
    "gn:dem":2706,
    "gn:feature_class":"P",
    "gn:feature_code":"PPL",
    "gn:name":"Lem\u012b",
    "gn:population":0,
    "gn:timezone":"Africa/Addis_Ababa",
    "iso:country":"ET",
    "name:ceb_x_preferred":[
        "Lemi"
    ],
    "name:deu_x_preferred":[
        "Lemi"
    ],
    "name:est_x_preferred":[
        "Lemi vald"
    ],
    "name:fin_x_preferred":[
        "Lemi"
    ],
    "name:fra_x_preferred":[
        "Lemi"
    ],
    "name:glg_x_preferred":[
        "Lemi"
    ],
    "name:ita_x_preferred":[
        "Lemi"
    ],
    "name:nld_x_preferred":[
        "Lemi"
    ],
    "name:nor_x_preferred":[
        "Lemi"
    ],
    "name:pol_x_preferred":[
        "Lemi"
    ],
    "name:por_x_preferred":[
        "Lemi"
    ],
    "name:ron_x_preferred":[
        "Lemi"
    ],
    "name:rus_x_preferred":[
        "\u041b\u0435\u043c\u0438"
    ],
    "name:sme_x_preferred":[
        "Lemi"
    ],
    "name:spa_x_preferred":[
        "Lemi"
    ],
    "name:sqi_x_preferred":[
        "Lemi"
    ],
    "name:swe_x_preferred":[
        "Klemis"
    ],
    "name:tur_x_preferred":[
        "Lemi"
    ],
    "name:zho_x_preferred":[
        "\u840a\u7c73"
    ],
    "wof:name":"Lemi",
    "wof:placetype":"locality"
},
  "geometry": {"coordinates":[38.68333,9.66667],"type":"Point"}
}