{
  "type": "Feature",
  "properties": {
    "gn:admin1_code":"46",
    "gn:asciiname":"Zeret",
    "gn:country_code":"ET",
    "gn:dem":2063,
    "gn:feature_class":"P",
    "gn:feature_code":"PPL",
    "gn:name":"Zeret",
    "gn:population":0,
    "gn:timezone":"Africa/Addis_Ababa",
    "iso:country":"ET",
    "wof:name":"Zeret",
    "wof:placetype":"locality"
},
  "geometry": {"coordinates":[39.26832,10.1359],"type":"Point"}
}