{
  "type": "Feature",
  "properties": {
    "gn:admin1_code":"46.0",
    "gn:asciiname":"Amed Guya",
    "gn:country_code":"ET",
    "gn:dem":2951,
    "gn:feature_class":"P",
    "gn:feature_code":"PPL",
    "gn:name":"\u0100med Guya",
    "gn:population":0,
    "gn:timezone":"Africa/Addis_Ababa",
    "iso:country":"ET",
    "wof:name":"Amed Guya",
    "wof:placetype":"locality"
},
  "geometry": {"coordinates":[39.56601,10.32833],"type":"Point"}
}