{
  "type": "Feature",
  "properties": {
    "gn:admin1_code":"51.0",
    "gn:asciiname":"Negeya",
    "gn:country_code":"ET",
    "gn:dem":1941,
    "gn:feature_class":"P",
    "gn:feature_code":"PPLL",
    "gn:name":"Negeya",
    "gn:population":0,
    "gn:timezone":"Africa/Addis_Ababa",
    "iso:country":"ET",
    "wof:name":"Negeya",
    "wof:placetype":"locality"
},
  "geometry": {"coordinates":[42.03605,9.31007],"type":"Point"}
}