{
  "type": "Feature",
  "properties": {
    "gn:admin1_code":"51",
    "gn:asciiname":"Soyema",
    "gn:country_code":"ET",
    "gn:dem":2096,
    "gn:feature_class":"P",
    "gn:feature_code":"PPL",
    "gn:name":"Soyema",
    "gn:population":0,
    "gn:timezone":"Africa/Addis_Ababa",
    "iso:country":"ET",
    "wof:name":"Soyema",
    "wof:placetype":"locality"
},
  "geometry": {"coordinates":[36.45,9.81667],"type":"Point"}
}