{
  "type": "Feature",
  "properties": {
    "gn:admin1_code":"51.0",
    "gn:asciiname":"Beke",
    "gn:country_code":"ET",
    "gn:dem":2512,
    "gn:feature_class":"P",
    "gn:feature_code":"PPL",
    "gn:name":"Bek\u0113",
    "gn:population":0,
    "gn:timezone":"Africa/Addis_Ababa",
    "iso:country":"ET",
    "name:bul_x_preferred":[
        "\u0411\u0435\u043a\u0435"
    ],
    "name:cat_x_preferred":[
        "Beke"
    ],
    "name:ceb_x_preferred":[
        "Beke"
    ],
    "name:deu_x_preferred":[
        "Beke"
    ],
    "name:fra_x_preferred":[
        "Beke"
    ],
    "name:nds_x_preferred":[
        "Beke"
    ],
    "name:rus_x_preferred":[
        "\u0411\u0435\u043a\u0435"
    ],
    "name:swe_x_preferred":[
        "Beke"
    ],
    "name:ukr_x_preferred":[
        "\u0411\u0435\u043a\u0435"
    ],
    "name:und_x_variant":[
        "Bek\u0113 (2)",
        "Bek\u0113"
    ],
    "wof:name":"Beke",
    "wof:placetype":"locality"
},
  "geometry": {"coordinates":[39.08551,9.0693],"type":"Point"}
}