{
  "type": "Feature",
  "properties": {
    "gn:admin1_code":"51",
    "gn:asciiname":"Haro Biftu",
    "gn:country_code":"ET",
    "gn:dem":2377,
    "gn:feature_class":"P",
    "gn:feature_code":"PPL",
    "gn:name":"Haro B\u012bftu",
    "gn:population":0,
    "gn:timezone":"Africa/Addis_Ababa",
    "iso:country":"ET",
    "wof:name":"Haro Biftu",
    "wof:placetype":"locality"
},
  "geometry": {"coordinates":[37.38333,9.61667],"type":"Point"}
}