{
  "type": "Feature",
  "properties": {
    "gn:admin1_code":"51",
    "gn:asciiname":"Maru",
    "gn:country_code":"ET",
    "gn:dem":1534,
    "gn:feature_class":"P",
    "gn:feature_code":"PPL",
    "gn:name":"Maru",
    "gn:population":0,
    "gn:timezone":"Africa/Addis_Ababa",
    "iso:country":"ET",
    "wof:name":"Maru",
    "wof:placetype":"locality"
},
  "geometry": {"coordinates":[42.30611,9.17111],"type":"Point"}
}