{
  "type": "Feature",
  "properties": {
    "gn:admin1_code":"51",
    "gn:asciiname":"Maru",
    "gn:country_code":"ET",
    "gn:dem":1534,
    "gn:feature_class":"P",
    "gn:feature_code":"PPL",
    "gn:name":"Maru",
    "gn:population":0,
    "gn:timezone":"Africa/Addis_Ababa",
    "iso:country":"ET",
    "name:ceb_x_preferred":[
        "Maru"
    ],
    "name:deu_x_preferred":[
        "Maru"
    ],
    "name:est_x_preferred":[
        "Maru"
    ],
    "name:fra_x_preferred":[
        "Maru"
    ],
    "name:rus_x_preferred":[
        "\u041c\u0430\u0440\u0443"
    ],
    "name:srp_x_preferred":[
        "\u041c\u0430\u0440\u0443"
    ],
    "name:swe_x_preferred":[
        "Maru"
    ],
    "name:ukr_x_preferred":[
        "\u041c\u0430\u0440\u0443"
    ],
    "name:zho_x_preferred":[
        "Maru"
    ],
    "wof:name":"Maru",
    "wof:placetype":"locality"
},
  "geometry": {"coordinates":[42.30611,9.17111],"type":"Point"}
}