{
  "type": "Feature",
  "properties": {
    "gn:admin1_code":"51",
    "gn:asciiname":"Gajo",
    "gn:country_code":"ET",
    "gn:dem":1903,
    "gn:feature_class":"P",
    "gn:feature_code":"PPL",
    "gn:name":"Gajo",
    "gn:population":0,
    "gn:timezone":"Africa/Addis_Ababa",
    "iso:country":"ET",
    "wof:name":"Gajo",
    "wof:placetype":"locality"
},
  "geometry": {"coordinates":[37.06667,9.18333],"type":"Point"}
}