{
  "type": "Feature",
  "properties": {
    "gn:admin1_code":"52",
    "gn:asciiname":"Waji",
    "gn:country_code":"ET",
    "gn:dem":1747,
    "gn:feature_class":"P",
    "gn:feature_code":"PPL",
    "gn:name":"Waj\u012b",
    "gn:population":0,
    "gn:timezone":"Africa/Addis_Ababa",
    "iso:country":"ET",
    "name:und_x_variant":[
        "Uadzhi",
        "Waj\u012b"
    ],
    "wof:name":"Waji",
    "wof:placetype":"locality"
},
  "geometry": {"coordinates":[42.69278,9.6975],"type":"Point"}
}