{
  "type": "Feature",
  "properties": {
    "gn:admin1_code":"51.0",
    "gn:asciiname":"Ch'alte",
    "gn:country_code":"ET",
    "gn:dem":2325,
    "gn:feature_class":"P",
    "gn:feature_code":"PPL",
    "gn:name":"Ch\u2019alt\u0113",
    "gn:population":0,
    "gn:timezone":"Africa/Addis_Ababa",
    "iso:country":"ET",
    "wof:name":"Ch'alte",
    "wof:placetype":"locality"
},
  "geometry": {"coordinates":[37.13333,9.55],"type":"Point"}
}