{
  "type": "Feature",
  "properties": {
    "gn:admin1_code":"51",
    "gn:asciiname":"Duncata",
    "gn:country_code":"ET",
    "gn:dem":1314,
    "gn:feature_class":"P",
    "gn:feature_code":"PPL",
    "gn:name":"Duncata",
    "gn:population":0,
    "gn:timezone":"Africa/Addis_Ababa",
    "iso:country":"ET",
    "name:und_x_variant":[
        "Dungata",
        "Duncata"
    ],
    "wof:name":"Duncata",
    "wof:placetype":"locality"
},
  "geometry": {"coordinates":[41.84568,8.28287],"type":"Point"}
}