{
  "type": "Feature",
  "properties": {
    "gn:admin1_code":"51",
    "gn:asciiname":"Roso",
    "gn:country_code":"ET",
    "gn:dem":3155,
    "gn:feature_class":"P",
    "gn:feature_code":"PPL",
    "gn:name":"Roso",
    "gn:population":0,
    "gn:timezone":"Africa/Addis_Ababa",
    "iso:country":"ET",
    "wof:name":"Roso",
    "wof:placetype":"locality"
},
  "geometry": {"coordinates":[38.61667,9.76667],"type":"Point"}
}