{
  "type": "Feature",
  "properties": {
    "gn:admin1_code":"49.0",
    "gn:asciiname":"Duyar",
    "gn:country_code":"ET",
    "gn:dem":412,
    "gn:feature_class":"P",
    "gn:feature_code":"PPL",
    "gn:name":"Duyar",
    "gn:population":0,
    "gn:timezone":"Africa/Addis_Ababa",
    "iso:country":"ET",
    "wof:name":"Duyar",
    "wof:placetype":"locality"
},
  "geometry": {"coordinates":[33.65954,8.42237],"type":"Point"}
}