{
  "type": "Feature",
  "properties": {
    "gn:admin1_code":"28.0",
    "gn:asciiname":"Shendi",
    "gn:country_code":"ET",
    "gn:dem":2105,
    "gn:elevation":"2063.0",
    "gn:feature_class":"P",
    "gn:feature_code":"PPLL",
    "gn:name":"Shendi",
    "gn:population":0,
    "gn:timezone":"Africa/Addis_Ababa",
    "iso:country":"ET",
    "wof:name":"Shendi",
    "wof:placetype":"locality"
},
  "geometry": {"coordinates":[36.94684,10.64061],"type":"Point"}
}