{
  "type": "Feature",
  "properties": {
    "gn:admin1_code":"28.0",
    "gn:asciiname":"Shendi",
    "gn:country_code":"ET",
    "gn:dem":2105,
    "gn:elevation":"2063.0",
    "gn:feature_class":"P",
    "gn:feature_code":"PPLL",
    "gn:name":"Shendi",
    "gn:population":0,
    "gn:timezone":"Africa/Addis_Ababa",
    "iso:country":"ET",
    "name:ara_x_preferred":[
        "\u0634\u0646\u062f\u064a"
    ],
    "name:azb_x_preferred":[
        "\u0634\u0646\u062f\u06cc"
    ],
    "name:cat_x_preferred":[
        "Xendi"
    ],
    "name:ceb_x_preferred":[
        "Shendi"
    ],
    "name:deu_x_preferred":[
        "Schandi"
    ],
    "name:fas_x_preferred":[
        "\u0634\u0646\u062f\u06cc"
    ],
    "name:fra_x_preferred":[
        "Chendi"
    ],
    "name:heb_x_preferred":[
        "\u05e9\u05e0\u05d3\u05d9"
    ],
    "name:hun_x_preferred":[
        "Shendi"
    ],
    "name:ita_x_preferred":[
        "Shendi"
    ],
    "name:pol_x_preferred":[
        "Szandi"
    ],
    "name:por_x_preferred":[
        "Xendi"
    ],
    "name:ron_x_preferred":[
        "Shandi"
    ],
    "name:rus_x_preferred":[
        "\u0428\u0435\u043d\u0434\u0438"
    ],
    "name:spa_x_preferred":[
        "Shendi"
    ],
    "name:swe_x_preferred":[
        "Shendi"
    ],
    "name:urd_x_preferred":[
        "\u0634\u0646\u062f\u06cc"
    ],
    "wof:name":"Shendi",
    "wof:placetype":"locality"
},
  "geometry": {"coordinates":[36.94684,10.64061],"type":"Point"}
}