{
  "type": "Feature",
  "properties": {
    "gn:admin1_code":"46",
    "gn:asciiname":"Meneyo",
    "gn:country_code":"ET",
    "gn:dem":1370,
    "gn:feature_class":"P",
    "gn:feature_code":"PPL",
    "gn:name":"Meneyo",
    "gn:population":0,
    "gn:timezone":"Africa/Addis_Ababa",
    "iso:country":"ET",
    "wof:name":"Meneyo",
    "wof:placetype":"locality"
},
  "geometry": {"coordinates":[39.83333,11.53333],"type":"Point"}
}