{
  "type": "Feature",
  "properties": {
    "gn:admin1_code":"51",
    "gn:asciiname":"Jemo",
    "gn:country_code":"ET",
    "gn:dem":2509,
    "gn:feature_class":"P",
    "gn:feature_code":"PPL",
    "gn:name":"Jemo",
    "gn:population":0,
    "gn:timezone":"Africa/Addis_Ababa",
    "iso:country":"ET",
    "wof:name":"Jemo",
    "wof:placetype":"locality"
},
  "geometry": {"coordinates":[38.25,9.96667],"type":"Point"}
}