{
  "type": "Feature",
  "properties": {
    "gn:admin1_code":"54",
    "gn:asciiname":"Marai",
    "gn:country_code":"ET",
    "gn:dem":1847,
    "gn:feature_class":"P",
    "gn:feature_code":"PPL",
    "gn:name":"Marai",
    "gn:population":0,
    "gn:timezone":"Africa/Addis_Ababa",
    "iso:country":"ET",
    "name:ceb_x_preferred":[
        "Marai"
    ],
    "name:deu_x_preferred":[
        "Marai"
    ],
    "name:swe_x_preferred":[
        "Marai"
    ],
    "wof:name":"Marai",
    "wof:placetype":"locality"
},
  "geometry": {"coordinates":[35.73333,7.13333],"type":"Point"}
}