{
  "type": "Feature",
  "properties": {
    "gn:admin1_code":"49.0",
    "gn:asciiname":"Rel' Bar",
    "gn:country_code":"ET",
    "gn:dem":407,
    "gn:feature_class":"P",
    "gn:feature_code":"PPL",
    "gn:name":"Rel\u2019 Bar",
    "gn:population":0,
    "gn:timezone":"Africa/Addis_Ababa",
    "iso:country":"ET",
    "wof:name":"Rel' Bar",
    "wof:placetype":"locality"
},
  "geometry": {"coordinates":[33.29762,8.44162],"type":"Point"}
}