{
  "type": "Feature",
  "properties": {
    "gn:admin1_code":"52",
    "gn:asciiname":"Gerrei",
    "gn:country_code":"ET",
    "gn:dem":256,
    "gn:feature_class":"P",
    "gn:feature_code":"PPL",
    "gn:name":"Gerrei",
    "gn:population":0,
    "gn:timezone":"Africa/Addis_Ababa",
    "iso:country":"ET",
    "name:und_x_variant":[
        "Dzherrey",
        "Jerrey",
        "Gerrei"
    ],
    "wof:name":"Gerrei",
    "wof:placetype":"locality"
},
  "geometry": {"coordinates":[43.89139,5.695],"type":"Point"}
}