{
  "type": "Feature",
  "properties": {
    "gn:admin1_code":"45",
    "gn:asciiname":"Galoch",
    "gn:country_code":"ET",
    "gn:dem":760,
    "gn:feature_class":"P",
    "gn:feature_code":"PPL",
    "gn:name":"Galoch",
    "gn:population":0,
    "gn:timezone":"Africa/Addis_Ababa",
    "iso:country":"ET",
    "wof:name":"Galoch",
    "wof:placetype":"locality"
},
  "geometry": {"coordinates":[40.05577,9.16297],"type":"Point"}
}