{
  "type": "Feature",
  "properties": {
    "gn:admin1_code":"51",
    "gn:asciiname":"Mucha Roba",
    "gn:country_code":"ET",
    "gn:dem":1466,
    "gn:feature_class":"P",
    "gn:feature_code":"PPL",
    "gn:name":"Mucha Roba",
    "gn:population":0,
    "gn:timezone":"Africa/Addis_Ababa",
    "iso:country":"ET",
    "wof:name":"Mucha Roba",
    "wof:placetype":"locality"
},
  "geometry": {"coordinates":[41.35354,8.87627],"type":"Point"}
}