{
  "type": "Feature",
  "properties": {
    "gn:admin1_code":"46.0",
    "gn:asciiname":"Azaye",
    "gn:country_code":"ET",
    "gn:dem":1964,
    "gn:feature_class":"P",
    "gn:feature_code":"PPL",
    "gn:name":"\u0100zay\u0113",
    "gn:population":0,
    "gn:timezone":"Africa/Addis_Ababa",
    "iso:country":"ET",
    "wof:name":"Azaye",
    "wof:placetype":"locality"
},
  "geometry": {"coordinates":[37.48333,12.48333],"type":"Point"}
}