{
  "type": "Feature",
  "properties": {
    "gn:admin1_code":"51",
    "gn:asciiname":"Seyo",
    "gn:country_code":"ET",
    "gn:dem":1684,
    "gn:feature_class":"P",
    "gn:feature_code":"PPL",
    "gn:name":"Seyo",
    "gn:population":0,
    "gn:timezone":"Africa/Addis_Ababa",
    "iso:country":"ET",
    "name:und_x_variant":[
        "Cello",
        "Seyo"
    ],
    "wof:name":"Seyo",
    "wof:placetype":"locality"
},
  "geometry": {"coordinates":[37.25,8.78333],"type":"Point"}
}