{
  "type": "Feature",
  "properties": {
    "gn:admin1_code":"53.0",
    "gn:asciiname":"Adi Minda",
    "gn:country_code":"ET",
    "gn:dem":2556,
    "gn:feature_class":"P",
    "gn:feature_code":"PPL",
    "gn:name":"\u0100d\u012b M\u012bnda",
    "gn:population":0,
    "gn:timezone":"Africa/Addis_Ababa",
    "iso:country":"ET",
    "wof:name":"Adi Minda",
    "wof:placetype":"locality"
},
  "geometry": {"coordinates":[39.48333,12.58333],"type":"Point"}
}