{
  "type": "Feature",
  "properties": {
    "gn:admin1_code":"46",
    "gn:asciiname":"Zibgaz",
    "gn:country_code":"ET",
    "gn:dem":2006,
    "gn:feature_class":"P",
    "gn:feature_code":"PPL",
    "gn:name":"Zibgaz",
    "gn:population":0,
    "gn:timezone":"Africa/Addis_Ababa",
    "iso:country":"ET",
    "wof:name":"Zibgaz",
    "wof:placetype":"locality"
},
  "geometry": {"coordinates":[38.85,12.03333],"type":"Point"}
}