{
  "type": "Feature",
  "properties": {
    "gn:admin1_code":"53",
    "gn:asciiname":"Edno",
    "gn:country_code":"ET",
    "gn:dem":2070,
    "gn:feature_class":"P",
    "gn:feature_code":"PPL",
    "gn:name":"Edno",
    "gn:population":0,
    "gn:timezone":"Africa/Addis_Ababa",
    "iso:country":"ET",
    "wof:name":"Edno",
    "wof:placetype":"locality"
},
  "geometry": {"coordinates":[39.28333,12.86667],"type":"Point"}
}