{
  "type": "Feature",
  "properties": {
    "gn:admin1_code":"53",
    "gn:asciiname":"Edno",
    "gn:country_code":"ET",
    "gn:dem":2070,
    "gn:feature_class":"P",
    "gn:feature_code":"PPL",
    "gn:name":"Edno",
    "gn:population":0,
    "gn:timezone":"Africa/Addis_Ababa",
    "iso:country":"ET",
    "name:azb_x_preferred":[
        "\u0627\u062f\u0646\u0648"
    ],
    "name:fas_x_preferred":[
        "\u0627\u062f\u0646\u0648"
    ],
    "name:fra_x_preferred":[
        "Edno"
    ],
    "name:ita_x_preferred":[
        "Edno"
    ],
    "name:jpn_x_preferred":[
        "\u30a8\u30b8\u30ce\u30fb\u30db\u30d9\u30eb\u30c8\u30fb\u30af\u30fc\u30cb\u30e3"
    ],
    "name:mlg_x_preferred":[
        "Edno"
    ],
    "name:pol_x_preferred":[
        "Edno"
    ],
    "name:por_x_preferred":[
        "Edno"
    ],
    "name:spa_x_preferred":[
        "Edno Cunha"
    ],
    "wof:name":"Edno",
    "wof:placetype":"locality"
},
  "geometry": {"coordinates":[39.28333,12.86667],"type":"Point"}
}