{
  "type": "Feature",
  "properties": {
    "gn:admin1_code":"53",
    "gn:asciiname":"Igre Hariba",
    "gn:country_code":"ET",
    "gn:dem":2357,
    "gn:feature_class":"P",
    "gn:feature_code":"PPL",
    "gn:name":"Igre Har\u012bba",
    "gn:population":0,
    "gn:timezone":"Africa/Addis_Ababa",
    "iso:country":"ET",
    "name:und_x_variant":[
        "Eghir Erive",
        "Igre Khariba",
        "Igre Har\u012bba"
    ],
    "wof:name":"Igre Hariba",
    "wof:placetype":"locality"
},
  "geometry": {"coordinates":[39.57203,13.47462],"type":"Point"}
}