{
  "type": "Feature",
  "properties": {
    "gn:admin1_code":"51",
    "gn:asciiname":"Golbo",
    "gn:country_code":"ET",
    "gn:dem":1522,
    "gn:feature_class":"P",
    "gn:feature_code":"PPL",
    "gn:name":"Golbo",
    "gn:population":0,
    "gn:timezone":"Africa/Addis_Ababa",
    "iso:country":"ET",
    "name:kir_x_preferred":[
        "\u0413\u043e\u043b\u0431\u043e"
    ],
    "name:rus_x_preferred":[
        "\u0413\u043e\u043b\u0431\u043e"
    ],
    "name:uzb_x_preferred":[
        "G\u02bbo\u02bblva"
    ],
    "wof:name":"Golbo",
    "wof:placetype":"locality"
},
  "geometry": {"coordinates":[40.65,8.03333],"type":"Point"}
}