{
  "type": "Feature",
  "properties": {
    "gn:admin1_code":"51.0",
    "gn:asciiname":"Berek",
    "gn:country_code":"ET",
    "gn:dem":2823,
    "gn:feature_class":"P",
    "gn:feature_code":"PPL",
    "gn:name":"Berek",
    "gn:population":0,
    "gn:timezone":"Africa/Addis_Ababa",
    "iso:country":"ET",
    "wof:name":"Berek",
    "wof:placetype":"locality"
},
  "geometry": {"coordinates":[38.96667,9.23333],"type":"Point"}
}