{
  "type": "Feature",
  "properties": {
    "gn:admin1_code":"52",
    "gn:asciiname":"Malca Dube",
    "gn:country_code":"ET",
    "gn:dem":413,
    "gn:feature_class":"P",
    "gn:feature_code":"PPL",
    "gn:name":"Malca Dube",
    "gn:population":0,
    "gn:timezone":"Africa/Addis_Ababa",
    "iso:country":"ET",
    "wof:name":"Malca Dube",
    "wof:placetype":"locality"
},
  "geometry": {"coordinates":[42.065,6.77972],"type":"Point"}
}