{
  "type": "Feature",
  "properties": {
    "gn:admin1_code":"49",
    "gn:asciiname":"Obwodi",
    "gn:country_code":"ET",
    "gn:dem":417,
    "gn:feature_class":"P",
    "gn:feature_code":"PPL",
    "gn:name":"Obwodi",
    "gn:population":0,
    "gn:timezone":"Africa/Addis_Ababa",
    "iso:country":"ET",
    "wof:name":"Obwodi",
    "wof:placetype":"locality"
},
  "geometry": {"coordinates":[33.61667,7.68333],"type":"Point"}
}