{
  "type": "Feature",
  "properties": {
    "gn:admin1_code":"51.0",
    "gn:asciiname":"Bot'olosi",
    "gn:country_code":"ET",
    "gn:dem":2333,
    "gn:feature_class":"P",
    "gn:feature_code":"PPL",
    "gn:name":"Bot\u2019olos\u012b",
    "gn:population":0,
    "gn:timezone":"Africa/Addis_Ababa",
    "iso:country":"ET",
    "wof:name":"Bot'olosi",
    "wof:placetype":"locality"
},
  "geometry": {"coordinates":[38.41667,9.85],"type":"Point"}
}