{
  "type": "Feature",
  "properties": {
    "gn:admin1_code":"52",
    "gn:asciiname":"Giadunlei",
    "gn:country_code":"ET",
    "gn:dem":275,
    "gn:feature_class":"P",
    "gn:feature_code":"PPL",
    "gn:name":"Giadunlei",
    "gn:population":0,
    "gn:timezone":"Africa/Addis_Ababa",
    "iso:country":"ET",
    "wof:name":"Giadunlei",
    "wof:placetype":"locality"
},
  "geometry": {"coordinates":[42.63333,4.25],"type":"Point"}
}