{
  "type": "Feature",
  "properties": {
    "gn:admin1_code":"51",
    "gn:asciiname":"Hak'o",
    "gn:country_code":"ET",
    "gn:dem":2470,
    "gn:feature_class":"P",
    "gn:feature_code":"PPL",
    "gn:name":"Hak\u2019o",
    "gn:population":0,
    "gn:timezone":"Africa/Addis_Ababa",
    "iso:country":"ET",
    "name:und_x_variant":[
        "Haco",
        "Hak\u2019o"
    ],
    "wof:name":"Hak'o",
    "wof:placetype":"locality"
},
  "geometry": {"coordinates":[39.53333,7.16667],"type":"Point"}
}