{
  "type": "Feature",
  "properties": {
    "gn:admin1_code":"46",
    "gn:asciiname":"Mida",
    "gn:country_code":"ET",
    "gn:dem":2539,
    "gn:feature_class":"P",
    "gn:feature_code":"PPL",
    "gn:name":"M\u012bda",
    "gn:population":0,
    "gn:timezone":"Africa/Addis_Ababa",
    "iso:country":"ET",
    "name:und_x_variant":[
        "Midda",
        "M\u012bda"
    ],
    "wof:name":"Mida",
    "wof:placetype":"locality"
},
  "geometry": {"coordinates":[39.15555,10.29134],"type":"Point"}
}