{
  "type": "Feature",
  "properties": {
    "gn:admin1_code":"51",
    "gn:asciiname":"Dugda Dera",
    "gn:country_code":"ET",
    "gn:dem":2479,
    "gn:feature_class":"P",
    "gn:feature_code":"PPL",
    "gn:name":"Dugda D\u0113ra",
    "gn:population":0,
    "gn:timezone":"Africa/Addis_Ababa",
    "iso:country":"ET",
    "wof:name":"Dugda Dera",
    "wof:placetype":"locality"
},
  "geometry": {"coordinates":[38.43333,9.38333],"type":"Point"}
}