{
  "type": "Feature",
  "properties": {
    "gn:admin1_code":"51",
    "gn:asciiname":"Genji",
    "gn:country_code":"ET",
    "gn:dem":1776,
    "gn:feature_class":"P",
    "gn:feature_code":"PPL",
    "gn:name":"Genj\u012b",
    "gn:population":0,
    "gn:timezone":"Africa/Addis_Ababa",
    "iso:country":"ET",
    "name:deu_x_preferred":[
        "Genji"
    ],
    "name:fra_x_preferred":[
        "Genji"
    ],
    "name:jpn_x_preferred":[
        "\u6e90\u6c0f"
    ],
    "name:rus_x_preferred":[
        "\u0413\u044d\u043d\u0434\u0437\u0438"
    ],
    "name:spa_x_preferred":[
        "Genji"
    ],
    "wof:name":"Genji",
    "wof:placetype":"locality"
},
  "geometry": {"coordinates":[37.81667,9.35],"type":"Point"}
}