{
  "type": "Feature",
  "properties": {
    "gn:admin1_code":"46",
    "gn:asciiname":"Yekoso",
    "gn:country_code":"ET",
    "gn:dem":3438,
    "gn:feature_class":"P",
    "gn:feature_code":"PPL",
    "gn:name":"Yekoso",
    "gn:population":0,
    "gn:timezone":"Africa/Addis_Ababa",
    "iso:country":"ET",
    "wof:name":"Yekoso",
    "wof:placetype":"locality"
},
  "geometry": {"coordinates":[39.35,11.95],"type":"Point"}
}