{
  "type": "Feature",
  "properties": {
    "gn:admin1_code":"51.0",
    "gn:asciiname":"Bek'ek'a",
    "gn:country_code":"ET",
    "gn:dem":1714,
    "gn:feature_class":"P",
    "gn:feature_code":"PPL",
    "gn:name":"Bek\u2019ek\u2019a",
    "gn:population":0,
    "gn:timezone":"Africa/Addis_Ababa",
    "iso:country":"ET",
    "wof:name":"Bek'ek'a",
    "wof:placetype":"locality"
},
  "geometry": {"coordinates":[38.71667,8.13333],"type":"Point"}
}