{
  "type": "Feature",
  "properties": {
    "gn:admin1_code":"45.0",
    "gn:asciiname":"Det Bahari",
    "gn:country_code":"ET",
    "gn:dem":359,
    "gn:feature_class":"P",
    "gn:feature_code":"PPL",
    "gn:name":"Det Bahar\u012b",
    "gn:population":0,
    "gn:timezone":"Africa/Addis_Ababa",
    "iso:country":"ET",
    "wof:name":"Det Bahari",
    "wof:placetype":"locality"
},
  "geometry": {"coordinates":[41.25843,11.57854],"type":"Point"}
}