{
  "type": "Feature",
  "properties": {
    "gn:admin1_code":"51.0",
    "gn:asciiname":"Abelti",
    "gn:country_code":"ET",
    "gn:dem":1633,
    "gn:feature_class":"P",
    "gn:feature_code":"PPL",
    "gn:name":"\u0100belt\u012b",
    "gn:population":0,
    "gn:timezone":"Africa/Addis_Ababa",
    "iso:country":"ET",
    "name:und_x_variant":[
        "Abalti",
        "Ablti",
        "\u0100belt\u012b"
    ],
    "wof:name":"Abelti",
    "wof:placetype":"locality"
},
  "geometry": {"coordinates":[37.56667,8.16667],"type":"Point"}
}