{
  "type": "Feature",
  "properties": {
    "gn:admin1_code":"46",
    "gn:asciiname":"Duba",
    "gn:country_code":"ET",
    "gn:dem":2629,
    "gn:feature_class":"P",
    "gn:feature_code":"PPL",
    "gn:name":"Duba",
    "gn:population":0,
    "gn:timezone":"Africa/Addis_Ababa",
    "iso:country":"ET",
    "wof:name":"Duba",
    "wof:placetype":"locality"
},
  "geometry": {"coordinates":[39.16874,10.15235],"type":"Point"}
}