{
  "type": "Feature",
  "properties": {
    "gn:admin1_code":"46",
    "gn:asciiname":"Walu",
    "gn:country_code":"ET",
    "gn:dem":1989,
    "gn:feature_class":"P",
    "gn:feature_code":"PPL",
    "gn:name":"Walu",
    "gn:population":0,
    "gn:timezone":"Africa/Addis_Ababa",
    "iso:country":"ET",
    "name:ceb_x_preferred":[
        "Walu"
    ],
    "name:swe_x_preferred":[
        "Walu"
    ],
    "name:und_x_variant":[
        "Walu (1)"
    ],
    "wof:name":"Walu",
    "wof:placetype":"locality"
},
  "geometry": {"coordinates":[38.58333,12.46667],"type":"Point"}
}