{
  "type": "Feature",
  "properties": {
    "gn:admin1_code":"54",
    "gn:asciiname":"Ela",
    "gn:country_code":"ET",
    "gn:dem":2142,
    "gn:feature_class":"P",
    "gn:feature_code":"PPL",
    "gn:name":"\u0112la",
    "gn:population":0,
    "gn:timezone":"Africa/Addis_Ababa",
    "iso:country":"ET",
    "name:und_x_variant":[
        "Iela",
        "\u0112la"
    ],
    "wof:name":"Ela",
    "wof:placetype":"locality"
},
  "geometry": {"coordinates":[36.71667,6.26667],"type":"Point"}
}