{
  "type": "Feature",
  "properties": {
    "gn:admin1_code":"52.0",
    "gn:asciiname":"Daua Ali",
    "gn:country_code":"ET",
    "gn:dem":661,
    "gn:feature_class":"P",
    "gn:feature_code":"PPL",
    "gn:name":"Daua Ali",
    "gn:population":0,
    "gn:timezone":"Africa/Addis_Ababa",
    "iso:country":"ET",
    "name:und_x_variant":[
        "Dau Ali",
        "Daua Ali"
    ],
    "wof:name":"Daua Ali",
    "wof:placetype":"locality"
},
  "geometry": {"coordinates":[46.25472,8.17278],"type":"Point"}
}