{
  "type": "Feature",
  "properties": {
    "gn:admin1_code":"47.0",
    "gn:asciiname":"Abba Ciotte",
    "gn:country_code":"ET",
    "gn:dem":1215,
    "gn:feature_class":"P",
    "gn:feature_code":"PPL",
    "gn:name":"Abba Ciotte",
    "gn:population":0,
    "gn:timezone":"Africa/Addis_Ababa",
    "iso:country":"ET",
    "name:und_x_variant":[
        "Aba Ciotte",
        "Abba Ciotte"
    ],
    "wof:name":"Abba Ciotte",
    "wof:placetype":"locality"
},
  "geometry": {"coordinates":[35.83333,9.55],"type":"Point"}
}