{
  "type": "Feature",
  "properties": {
    "gn:admin1_code":"53",
    "gn:asciiname":"Ts'ahafti",
    "gn:country_code":"ET",
    "gn:dem":2252,
    "gn:feature_class":"P",
    "gn:feature_code":"PPL",
    "gn:name":"Ts\u2019ahaft\u012b",
    "gn:population":0,
    "gn:timezone":"Africa/Addis_Ababa",
    "iso:country":"ET",
    "name:und_x_variant":[
        "Tsakhafti",
        "Ts\u2019ahaft\u012b"
    ],
    "wof:name":"Ts'ahafti",
    "wof:placetype":"locality"
},
  "geometry": {"coordinates":[39.66505,13.0154],"type":"Point"}
}