{
  "type": "Feature",
  "properties": {
    "gn:admin1_code":"51.0",
    "gn:asciiname":"Bara",
    "gn:country_code":"ET",
    "gn:dem":2777,
    "gn:feature_class":"P",
    "gn:feature_code":"PPL",
    "gn:name":"Bara",
    "gn:population":0,
    "gn:timezone":"Africa/Addis_Ababa",
    "iso:country":"ET",
    "name:bos_x_preferred":[
        "Bara"
    ],
    "name:bul_x_preferred":[
        "\u0411\u0430\u0440\u0430"
    ],
    "name:cat_x_preferred":[
        "Bara"
    ],
    "name:ceb_x_preferred":[
        "Bara"
    ],
    "name:ces_x_preferred":[
        "Bara"
    ],
    "name:deu_x_preferred":[
        "Bara"
    ],
    "name:epo_x_preferred":[
        "Bara"
    ],
    "name:eus_x_preferred":[
        "Bara"
    ],
    "name:fra_x_preferred":[
        "Bara"
    ],
    "name:hye_x_preferred":[
        "\u0532\u0561\u0580\u0561"
    ],
    "name:ita_x_preferred":[
        "Bara"
    ],
    "name:jpn_x_preferred":[
        "\u30d0\u30e9"
    ],
    "name:lav_x_preferred":[
        "Bara"
    ],
    "name:lit_x_preferred":[
        "Bara"
    ],
    "name:nds_x_preferred":[
        "Bara"
    ],
    "name:nld_x_preferred":[
        "Bara"
    ],
    "name:pol_x_preferred":[
        "Bara"
    ],
    "name:por_x_preferred":[
        "Bara"
    ],
    "name:rus_x_preferred":[
        "\u0411\u0430\u0440\u0430"
    ],
    "name:spa_x_preferred":[
        "Bara"
    ],
    "name:srp_x_preferred":[
        "\u0411\u0430\u0440\u0430"
    ],
    "name:swe_x_preferred":[
        "Bara"
    ],
    "name:tgl_x_preferred":[
        "Bara"
    ],
    "name:ukr_x_preferred":[
        "\u0411\u0430\u0440\u0430"
    ],
    "name:vie_x_preferred":[
        "Bara"
    ],
    "wof:name":"Bara",
    "wof:placetype":"locality"
},
  "geometry": {"coordinates":[38.33333,9.16667],"type":"Point"}
}