{
  "type": "Feature",
  "properties": {
    "gn:admin1_code":"45",
    "gn:asciiname":"Gorsaitou",
    "gn:country_code":"ET",
    "gn:dem":575,
    "gn:feature_class":"P",
    "gn:feature_code":"PPL",
    "gn:name":"Gorsaitou",
    "gn:population":0,
    "gn:timezone":"Africa/Addis_Ababa",
    "iso:country":"ET",
    "wof:name":"Gorsaitou",
    "wof:placetype":"locality"
},
  "geometry": {"coordinates":[40.66667,11.03333],"type":"Point"}
}