{
  "type": "Feature",
  "properties": {
    "gn:admin1_code":"54",
    "gn:asciiname":"Indibir",
    "gn:country_code":"ET",
    "gn:dem":2093,
    "gn:feature_class":"P",
    "gn:feature_code":"PPL",
    "gn:name":"Indibir",
    "gn:population":0,
    "gn:timezone":"Africa/Addis_Ababa",
    "iso:country":"ET",
    "name:und_x_variant":[
        "Endeber",
        "Imdibir",
        "Indibir"
    ],
    "wof:name":"Indibir",
    "wof:placetype":"locality"
},
  "geometry": {"coordinates":[37.93333,8.11667],"type":"Point"}
}