{
  "type": "Feature",
  "properties": {
    "gn:admin1_code":"46.0",
    "gn:asciiname":"Belesa",
    "gn:country_code":"ET",
    "gn:dem":3438,
    "gn:feature_class":"P",
    "gn:feature_code":"PPL",
    "gn:name":"Belesa",
    "gn:population":0,
    "gn:timezone":"Africa/Addis_Ababa",
    "iso:country":"ET",
    "wof:name":"Belesa",
    "wof:placetype":"locality"
},
  "geometry": {"coordinates":[38.14028,13.20972],"type":"Point"}
}