{
  "type": "Feature",
  "properties": {
    "gn:admin1_code":"52",
    "gn:asciiname":"Ferda",
    "gn:country_code":"ET",
    "gn:dem":1507,
    "gn:feature_class":"P",
    "gn:feature_code":"PPL",
    "gn:name":"Ferda",
    "gn:population":0,
    "gn:timezone":"Africa/Addis_Ababa",
    "iso:country":"ET",
    "wof:name":"Ferda",
    "wof:placetype":"locality"
},
  "geometry": {"coordinates":[43.03889,9.03972],"type":"Point"}
}