{
  "type": "Feature",
  "properties": {
    "gn:admin1_code":"51",
    "gn:asciiname":"Robele",
    "gn:country_code":"ET",
    "gn:dem":2770,
    "gn:feature_class":"P",
    "gn:feature_code":"PPL",
    "gn:name":"Robel\u0113",
    "gn:population":0,
    "gn:timezone":"Africa/Addis_Ababa",
    "iso:country":"ET",
    "wof:name":"Robele",
    "wof:placetype":"locality"
},
  "geometry": {"coordinates":[38.45,9.31667],"type":"Point"}
}