{
  "type": "Feature",
  "properties": {
    "gn:admin1_code":"53",
    "gn:asciiname":"May Hargets'",
    "gn:country_code":"ET",
    "gn:dem":926,
    "gn:feature_class":"P",
    "gn:feature_code":"PPL",
    "gn:name":"May Hargets\u2019",
    "gn:population":0,
    "gn:timezone":"Africa/Addis_Ababa",
    "iso:country":"ET",
    "wof:name":"May Hargets'",
    "wof:placetype":"locality"
},
  "geometry": {"coordinates":[37.76667,13.71667],"type":"Point"}
}