{
  "type": "Feature",
  "properties": {
    "gn:admin1_code":"51",
    "gn:asciiname":"Sek'e Gura",
    "gn:country_code":"ET",
    "gn:dem":2058,
    "gn:feature_class":"P",
    "gn:feature_code":"PPL",
    "gn:name":"Sek\u2019e Gura",
    "gn:population":0,
    "gn:timezone":"Africa/Addis_Ababa",
    "iso:country":"ET",
    "wof:name":"Sek'e Gura",
    "wof:placetype":"locality"
},
  "geometry": {"coordinates":[37.76667,9.53333],"type":"Point"}
}