{
  "type": "Feature",
  "properties": {
    "gn:admin1_code":"51",
    "gn:asciiname":"God",
    "gn:country_code":"ET",
    "gn:dem":2678,
    "gn:feature_class":"P",
    "gn:feature_code":"PPL",
    "gn:name":"God",
    "gn:population":0,
    "gn:timezone":"Africa/Addis_Ababa",
    "iso:country":"ET",
    "wof:name":"God",
    "wof:placetype":"locality"
},
  "geometry": {"coordinates":[39.38378,9.35855],"type":"Point"}
}