{
  "type": "Feature",
  "properties": {
    "gn:admin1_code":"46",
    "gn:asciiname":"Ligot",
    "gn:country_code":"ET",
    "gn:dem":2419,
    "gn:feature_class":"P",
    "gn:feature_code":"PPL",
    "gn:name":"Ligot",
    "gn:population":0,
    "gn:timezone":"Africa/Addis_Ababa",
    "iso:country":"ET",
    "name:und_x_variant":[
        "Lgot",
        "Ligot"
    ],
    "wof:name":"Ligot",
    "wof:placetype":"locality"
},
  "geometry": {"coordinates":[39.38333,11.31667],"type":"Point"}
}