{
  "type": "Feature",
  "properties": {
    "gn:admin1_code":"52",
    "gn:asciiname":"Guban",
    "gn:country_code":"ET",
    "gn:dem":756,
    "gn:feature_class":"P",
    "gn:feature_code":"PPL",
    "gn:name":"Guban",
    "gn:population":0,
    "gn:timezone":"Africa/Addis_Ababa",
    "iso:country":"ET",
    "name:deu_x_preferred":[
        "Guban"
    ],
    "name:som_x_preferred":[
        "Guban"
    ],
    "wof:name":"Guban",
    "wof:placetype":"locality"
},
  "geometry": {"coordinates":[42.64167,6.95333],"type":"Point"}
}