{
  "type": "Feature",
  "properties": {
    "gn:admin1_code":"46.0",
    "gn:asciiname":"Aba Bula",
    "gn:country_code":"ET",
    "gn:dem":3048,
    "gn:feature_class":"P",
    "gn:feature_code":"PPL",
    "gn:name":"\u0100ba Bula",
    "gn:population":0,
    "gn:timezone":"Africa/Addis_Ababa",
    "iso:country":"ET",
    "wof:name":"Aba Bula",
    "wof:placetype":"locality"
},
  "geometry": {"coordinates":[39.23333,11.15],"type":"Point"}
}