{
  "type": "Feature",
  "properties": {
    "gn:admin1_code":"52.0",
    "gn:asciiname":"Bur Hoos",
    "gn:country_code":"ET",
    "gn:dem":377,
    "gn:feature_class":"P",
    "gn:feature_code":"PPL",
    "gn:name":"Bur Hoos",
    "gn:population":0,
    "gn:timezone":"Africa/Addis_Ababa",
    "iso:country":"ET",
    "name:und_x_variant":[
        "Bur Khose",
        "Bur Hosc",
        "Bur Hose",
        "Bur Hoos"
    ],
    "wof:name":"Bur Hoos",
    "wof:placetype":"locality"
},
  "geometry": {"coordinates":[42.96863,4.63527],"type":"Point"}
}