{
  "type": "Feature",
  "properties": {
    "gn:admin1_code":"46",
    "gn:asciiname":"Tach Washa",
    "gn:country_code":"ET",
    "gn:dem":2201,
    "gn:feature_class":"P",
    "gn:feature_code":"PPL",
    "gn:name":"Tach Washa",
    "gn:population":0,
    "gn:timezone":"Africa/Addis_Ababa",
    "iso:country":"ET",
    "wof:name":"Tach Washa",
    "wof:placetype":"locality"
},
  "geometry": {"coordinates":[39.48961,9.83893],"type":"Point"}
}