{
  "type": "Feature",
  "properties": {
    "gn:admin1_code":"45.0",
    "gn:asciiname":"Gerekiby",
    "gn:country_code":"ET",
    "gn:dem":164,
    "gn:feature_class":"P",
    "gn:feature_code":"PPL",
    "gn:name":"Gerekiby",
    "gn:population":0,
    "gn:timezone":"Africa/Addis_Ababa",
    "iso:country":"ET",
    "wof:name":"Gerekiby",
    "wof:placetype":"locality"
},
  "geometry": {"coordinates":[40.68561,13.45165],"type":"Point"}
}