{
  "type": "Feature",
  "properties": {
    "gn:admin1_code":"51",
    "gn:asciiname":"Mine",
    "gn:country_code":"ET",
    "gn:dem":2446,
    "gn:feature_class":"P",
    "gn:feature_code":"PPL",
    "gn:name":"M\u012bn\u0113",
    "gn:population":0,
    "gn:timezone":"Africa/Addis_Ababa",
    "iso:country":"ET",
    "name:ceb_x_preferred":[
        "Mine"
    ],
    "name:ces_x_preferred":[
        "Mine"
    ],
    "name:dan_x_preferred":[
        "Mine"
    ],
    "name:deu_x_preferred":[
        "Mine"
    ],
    "name:epo_x_preferred":[
        "Mino"
    ],
    "name:fra_x_preferred":[
        "Mine"
    ],
    "name:hin_x_preferred":[
        "\u0916\u093e\u0928"
    ],
    "name:hun_x_preferred":[
        "Mine"
    ],
    "name:ita_x_preferred":[
        "Mine"
    ],
    "name:nld_x_preferred":[
        "Mine"
    ],
    "name:nno_x_preferred":[
        "Mine"
    ],
    "name:por_x_preferred":[
        "Mine"
    ],
    "name:rus_x_preferred":[
        "Mine"
    ],
    "name:swe_x_preferred":[
        "Mine"
    ],
    "name:tgl_x_preferred":[
        "Mine"
    ],
    "name:tha_x_preferred":[
        "\u0e44\u0e21\u0e19\u0e4c"
    ],
    "name:tur_x_preferred":[
        "Mine"
    ],
    "name:vie_x_preferred":[
        "Mine"
    ],
    "wof:name":"Mine",
    "wof:placetype":"locality"
},
  "geometry": {"coordinates":[37.76667,9.66667],"type":"Point"}
}