{
  "type": "Feature",
  "properties": {
    "gn:admin1_code":"53.0",
    "gn:asciiname":"Ch'e'ames Kebet",
    "gn:country_code":"ET",
    "gn:dem":1011,
    "gn:feature_class":"P",
    "gn:feature_code":"PPL",
    "gn:name":"Ch\u2019e\u2019\u0101mes Kebet",
    "gn:population":0,
    "gn:timezone":"Africa/Addis_Ababa",
    "iso:country":"ET",
    "wof:name":"Ch'e'ames Kebet",
    "wof:placetype":"locality"
},
  "geometry": {"coordinates":[37.77111,14.28583],"type":"Point"}
}