{
  "type": "Feature",
  "properties": {
    "gn:admin1_code":"47",
    "gn:asciiname":"Jima",
    "gn:country_code":"ET",
    "gn:dem":1280,
    "gn:feature_class":"P",
    "gn:feature_code":"PPL",
    "gn:name":"J\u012bma",
    "gn:population":0,
    "gn:timezone":"Africa/Addis_Ababa",
    "iso:country":"ET",
    "name:cat_x_preferred":[
        "Jima"
    ],
    "name:ceb_x_preferred":[
        "Jima"
    ],
    "name:deu_x_preferred":[
        "Jima"
    ],
    "name:fra_x_preferred":[
        "Jima"
    ],
    "name:spa_x_preferred":[
        "Jima"
    ],
    "name:swe_x_preferred":[
        "Jima"
    ],
    "name:und_x_variant":[
        "Gima",
        "J\u012bma"
    ],
    "wof:name":"Jima",
    "wof:placetype":"locality"
},
  "geometry": {"coordinates":[34.58333,10.36667],"type":"Point"}
}