{
  "type": "Feature",
  "properties": {
    "gn:admin1_code":"46",
    "gn:asciiname":"Weledi",
    "gn:country_code":"ET",
    "gn:dem":1507,
    "gn:feature_class":"P",
    "gn:feature_code":"PPL",
    "gn:name":"Weled\u012b",
    "gn:population":0,
    "gn:timezone":"Africa/Addis_Ababa",
    "iso:country":"ET",
    "wof:name":"Weledi",
    "wof:placetype":"locality"
},
  "geometry": {"coordinates":[39.81009,10.8342],"type":"Point"}
}