{
  "type": "Feature",
  "properties": {
    "gn:admin1_code":"46.0",
    "gn:asciiname":"Ach'ewa Bado",
    "gn:country_code":"ET",
    "gn:dem":2723,
    "gn:feature_class":"P",
    "gn:feature_code":"PPL",
    "gn:name":"\u0100ch\u2019ewa Bado",
    "gn:population":0,
    "gn:timezone":"Africa/Addis_Ababa",
    "iso:country":"ET",
    "wof:name":"Ach'ewa Bado",
    "wof:placetype":"locality"
},
  "geometry": {"coordinates":[38.03333,10.81667],"type":"Point"}
}