{
  "type": "Feature",
  "properties": {
    "gn:admin1_code":"46.0",
    "gn:asciiname":"Balchi",
    "gn:country_code":"ET",
    "gn:dem":1468,
    "gn:feature_class":"P",
    "gn:feature_code":"PPL",
    "gn:name":"Balchi",
    "gn:population":0,
    "gn:timezone":"Africa/Addis_Ababa",
    "iso:country":"ET",
    "wof:name":"Balchi",
    "wof:placetype":"locality"
},
  "geometry": {"coordinates":[39.96816,10.30023],"type":"Point"}
}