{
  "type": "Feature",
  "properties": {
    "gn:admin1_code":"51",
    "gn:asciiname":"Miaua",
    "gn:country_code":"ET",
    "gn:dem":1221,
    "gn:feature_class":"P",
    "gn:feature_code":"PPL",
    "gn:name":"Miaua",
    "gn:population":0,
    "gn:timezone":"Africa/Addis_Ababa",
    "iso:country":"ET",
    "wof:name":"Miaua",
    "wof:placetype":"locality"
},
  "geometry": {"coordinates":[41.32926,7.67139],"type":"Point"}
}