{
  "type": "Feature",
  "properties": {
    "gn:admin1_code":"51.0",
    "gn:asciiname":"Hula Jeneta",
    "gn:country_code":"ET",
    "gn:dem":1953,
    "gn:feature_class":"P",
    "gn:feature_code":"PPLL",
    "gn:name":"Hula Jeneta",
    "gn:population":0,
    "gn:timezone":"Africa/Addis_Ababa",
    "iso:country":"ET",
    "wof:name":"Hula Jeneta",
    "wof:placetype":"locality"
},
  "geometry": {"coordinates":[42.15536,9.39124],"type":"Point"}
}