{
  "type": "Feature",
  "properties": {
    "gn:admin1_code":"46.0",
    "gn:asciiname":"Biriti",
    "gn:country_code":"ET",
    "gn:dem":2212,
    "gn:feature_class":"P",
    "gn:feature_code":"PPL",
    "gn:name":"B\u012br\u012bt\u012b",
    "gn:population":0,
    "gn:timezone":"Africa/Addis_Ababa",
    "iso:country":"ET",
    "wof:name":"Biriti",
    "wof:placetype":"locality"
},
  "geometry": {"coordinates":[39.76667,11.26667],"type":"Point"}
}