{
  "type": "Feature",
  "properties": {
    "gn:admin1_code":"54",
    "gn:asciiname":"Tiacki",
    "gn:country_code":"ET",
    "gn:dem":1300,
    "gn:feature_class":"P",
    "gn:feature_code":"PPL",
    "gn:name":"Tiacki",
    "gn:population":0,
    "gn:timezone":"Africa/Addis_Ababa",
    "iso:country":"ET",
    "name:und_x_variant":[
        "Tiachi"
    ],
    "wof:name":"Tiacki",
    "wof:placetype":"locality"
},
  "geometry": {"coordinates":[35.50626,6.05541],"type":"Point"}
}