{
  "type": "Feature",
  "properties": {
    "gn:admin1_code":"46",
    "gn:asciiname":"Fenja",
    "gn:country_code":"ET",
    "gn:dem":1842,
    "gn:feature_class":"P",
    "gn:feature_code":"PPL",
    "gn:name":"Fenja",
    "gn:population":0,
    "gn:timezone":"Africa/Addis_Ababa",
    "iso:country":"ET",
    "name:dan_x_preferred":[
        "Fenja"
    ],
    "name:und_x_variant":[
        "Fangia",
        "Fenja"
    ],
    "wof:name":"Fenja",
    "wof:placetype":"locality"
},
  "geometry": {"coordinates":[37.28333,12.45],"type":"Point"}
}