{
  "type": "Feature",
  "properties": {
    "gn:admin1_code":"51",
    "gn:asciiname":"T'eno",
    "gn:country_code":"ET",
    "gn:dem":2761,
    "gn:feature_class":"P",
    "gn:feature_code":"PPL",
    "gn:name":"T\u2019\u0113no",
    "gn:population":0,
    "gn:timezone":"Africa/Addis_Ababa",
    "iso:country":"ET",
    "wof:name":"T'eno",
    "wof:placetype":"locality"
},
  "geometry": {"coordinates":[37.08333,9.53333],"type":"Point"}
}