{
  "type": "Feature",
  "properties": {
    "gn:admin1_code":"49.0",
    "gn:asciiname":"Birhane Selam",
    "gn:country_code":"ET",
    "gn:dem":419,
    "gn:feature_class":"P",
    "gn:feature_code":"PPL",
    "gn:name":"Birhane Selam",
    "gn:population":0,
    "gn:timezone":"Africa/Addis_Ababa",
    "iso:country":"ET",
    "wof:name":"Birhane Selam",
    "wof:placetype":"locality"
},
  "geometry": {"coordinates":[34.11667,8.21667],"type":"Point"}
}