{
  "type": "Feature",
  "properties": {
    "gn:admin1_code":"51",
    "gn:asciiname":"O'odesi",
    "gn:country_code":"ET",
    "gn:dem":1237,
    "gn:feature_class":"P",
    "gn:feature_code":"PPL",
    "gn:name":"O\u2019odes\u012b",
    "gn:population":0,
    "gn:timezone":"Africa/Addis_Ababa",
    "iso:country":"ET",
    "name:und_x_variant":[
        "Ooddessi",
        "O\u2019odes\u012b"
    ],
    "wof:name":"O'odesi",
    "wof:placetype":"locality"
},
  "geometry": {"coordinates":[38.86667,3.61667],"type":"Point"}
}