{
  "type": "Feature",
  "properties": {
    "gn:admin1_code":"54.0",
    "gn:asciiname":"Birbir",
    "gn:country_code":"ET",
    "gn:dem":1322,
    "gn:feature_class":"P",
    "gn:feature_code":"PPL",
    "gn:name":"Birbir",
    "gn:population":0,
    "gn:timezone":"Africa/Addis_Ababa",
    "iso:country":"ET",
    "wof:name":"Birbir",
    "wof:placetype":"locality"
},
  "geometry": {"coordinates":[37.73333,6.38333],"type":"Point"}
}