{
  "type": "Feature",
  "properties": {
    "gn:admin1_code":"46",
    "gn:asciiname":"Janora",
    "gn:country_code":"ET",
    "gn:dem":1896,
    "gn:feature_class":"P",
    "gn:feature_code":"PPL",
    "gn:name":"Janora",
    "gn:population":0,
    "gn:timezone":"Africa/Addis_Ababa",
    "iso:country":"ET",
    "wof:name":"Janora",
    "wof:placetype":"locality"
},
  "geometry": {"coordinates":[37.35,12.46667],"type":"Point"}
}