{
  "type": "Feature",
  "properties": {
    "gn:admin1_code":"52",
    "gn:asciiname":"Talla",
    "gn:country_code":"ET",
    "gn:dem":872,
    "gn:feature_class":"P",
    "gn:feature_code":"PPL",
    "gn:name":"Talla",
    "gn:population":0,
    "gn:timezone":"Africa/Addis_Ababa",
    "iso:country":"ET",
    "name:azb_x_preferred":[
        "\u062a\u0627\u0644\u0627"
    ],
    "name:bcl_x_preferred":[
        "Talla"
    ],
    "name:bel_x_preferred":[
        "\u0422\u0430\u043b\u0430"
    ],
    "name:bul_x_preferred":[
        "\u0422\u0430\u043b\u0430"
    ],
    "name:cat_x_preferred":[
        "Talla"
    ],
    "name:ceb_x_preferred":[
        "Talla"
    ],
    "name:deu_x_preferred":[
        "Talla"
    ],
    "name:epo_x_preferred":[
        "Talla"
    ],
    "name:eus_x_preferred":[
        "Talla"
    ],
    "name:fas_x_preferred":[
        "\u062a\u0627\u0644\u0627"
    ],
    "name:fra_x_preferred":[
        "Talla"
    ],
    "name:hun_x_preferred":[
        "Talla"
    ],
    "name:hye_x_preferred":[
        "\u054f\u0561\u056c\u056c\u0561"
    ],
    "name:ita_x_preferred":[
        "Talla"
    ],
    "name:jpn_x_preferred":[
        "\u30bf\u30c3\u30e9"
    ],
    "name:lat_x_preferred":[
        "Tallia"
    ],
    "name:lmo_x_preferred":[
        "Talla"
    ],
    "name:msa_x_preferred":[
        "Talla"
    ],
    "name:nap_x_preferred":[
        "Talla"
    ],
    "name:nld_x_preferred":[
        "Talla"
    ],
    "name:nor_x_preferred":[
        "Talla"
    ],
    "name:pms_x_preferred":[
        "Talla"
    ],
    "name:pol_x_preferred":[
        "Talla"
    ],
    "name:por_x_preferred":[
        "Talla"
    ],
    "name:ron_x_preferred":[
        "Talla"
    ],
    "name:rus_x_preferred":[
        "\u0422\u0430\u043b\u043b\u0430"
    ],
    "name:scn_x_preferred":[
        "Talla"
    ],
    "name:spa_x_preferred":[
        "Talla"
    ],
    "name:srp_x_preferred":[
        "\u0422\u0430\u043b\u0430"
    ],
    "name:tgl_x_preferred":[
        "Talla"
    ],
    "name:ukr_x_preferred":[
        "\u0422\u0430\u043b\u043b\u0430"
    ],
    "name:uzb_x_preferred":[
        "Talla"
    ],
    "name:vec_x_preferred":[
        "Ta\u0142a"
    ],
    "name:vol_x_preferred":[
        "Talla"
    ],
    "name:war_x_preferred":[
        "Talla"
    ],
    "wof:name":"Talla",
    "wof:placetype":"locality"
},
  "geometry": {"coordinates":[42.96667,7.48333],"type":"Point"}
}