{
  "type": "Feature",
  "properties": {
    "gn:admin1_code":"52",
    "gn:asciiname":"Talla",
    "gn:country_code":"ET",
    "gn:dem":872,
    "gn:feature_class":"P",
    "gn:feature_code":"PPL",
    "gn:name":"Talla",
    "gn:population":0,
    "gn:timezone":"Africa/Addis_Ababa",
    "iso:country":"ET",
    "wof:name":"Talla",
    "wof:placetype":"locality"
},
  "geometry": {"coordinates":[42.96667,7.48333],"type":"Point"}
}