{
  "type": "Feature",
  "properties": {
    "gn:admin1_code":"54",
    "gn:asciiname":"Zanga",
    "gn:country_code":"ET",
    "gn:dem":1317,
    "gn:feature_class":"P",
    "gn:feature_code":"PPL",
    "gn:name":"Zanga",
    "gn:population":0,
    "gn:timezone":"Africa/Addis_Ababa",
    "iso:country":"ET",
    "wof:name":"Zanga",
    "wof:placetype":"locality"
},
  "geometry": {"coordinates":[36.43333,6.35],"type":"Point"}
}