{
  "type": "Feature",
  "properties": {
    "gn:admin1_code":"51",
    "gn:asciiname":"Kurfa Ch'ele",
    "gn:country_code":"ET",
    "gn:dem":2221,
    "gn:feature_class":"P",
    "gn:feature_code":"PPL",
    "gn:name":"Kurfa Ch\u2019el\u0113",
    "gn:population":0,
    "gn:timezone":"Africa/Addis_Ababa",
    "iso:country":"ET",
    "wof:name":"Kurfa Ch'ele",
    "wof:placetype":"locality"
},
  "geometry": {"coordinates":[41.82306,9.23222],"type":"Point"}
}