{
  "type": "Feature",
  "properties": {
    "gn:admin1_code":"46",
    "gn:asciiname":"Magas",
    "gn:country_code":"ET",
    "gn:dem":2226,
    "gn:feature_class":"P",
    "gn:feature_code":"PPL",
    "gn:name":"Magas",
    "gn:population":0,
    "gn:timezone":"Africa/Addis_Ababa",
    "iso:country":"ET",
    "wof:name":"Magas",
    "wof:placetype":"locality"
},
  "geometry": {"coordinates":[39.08114000000001,10.08051],"type":"Point"}
}