{
  "type": "Feature",
  "properties": {
    "gn:admin1_code":"51",
    "gn:asciiname":"Gutey",
    "gn:country_code":"ET",
    "gn:dem":1640,
    "gn:feature_class":"P",
    "gn:feature_code":"PPL",
    "gn:name":"Gutey",
    "gn:population":0,
    "gn:timezone":"Africa/Addis_Ababa",
    "iso:country":"ET",
    "wof:name":"Gutey",
    "wof:placetype":"locality"
},
  "geometry": {"coordinates":[36.73333,9.01667],"type":"Point"}
}