{
  "type": "Feature",
  "properties": {
    "gn:admin1_code":"51",
    "gn:asciiname":"Kune",
    "gn:country_code":"ET",
    "gn:dem":2409,
    "gn:feature_class":"P",
    "gn:feature_code":"PPL",
    "gn:name":"Kun\u0113",
    "gn:population":0,
    "gn:timezone":"Africa/Addis_Ababa",
    "iso:country":"ET",
    "wof:name":"Kune",
    "wof:placetype":"locality"
},
  "geometry": {"coordinates":[39.08333,8.96667],"type":"Point"}
}