{
  "type": "Feature",
  "properties": {
    "gn:country":"ET",
    "gn:fcode":"PPLA",
    "gn:pop":833,
    "iso:country":"ET",
    "name:amh_x_preferred":[
        "Semera"
    ],
    "name:amh_x_variant":[
        "\u1230\u1218\u122b"
    ],
    "name:bul_x_preferred":[
        "\u0421\u0435\u043c\u0435\u0440\u0430"
    ],
    "name:ell_x_preferred":[
        "\u03a3\u03b5\u03bc\u03ad\u03c1\u03b1"
    ],
    "name:eng_x_preferred":[
        "Semera"
    ],
    "name:fra_x_preferred":[
        "Semera"
    ],
    "name:heb_x_preferred":[
        "\u05e1\u05d0\u05de\u05e8\u05d4"
    ],
    "name:jpn_x_preferred":[
        "\u30bb\u30e1\u30e9"
    ],
    "name:kat_x_preferred":[
        "\u10e1\u10d4\u10db\u10d4\u10e0\u10d0"
    ],
    "name:kor_x_preferred":[
        "\uc138\uba54\ub77c"
    ],
    "name:lit_x_preferred":[
        "Semera"
    ],
    "name:nld_x_preferred":[
        "Semera"
    ],
    "name:rus_x_preferred":[
        "\u0421\u0435\u043c\u0435\u0440\u0430"
    ],
    "name:swe_x_preferred":[
        "Semera"
    ],
    "name:urd_x_preferred":[
        "\u0633\u06cc\u0645\u06cc\u0631\u0627"
    ],
    "name:zho_x_preferred":[
        "\u585e\u6885\u62c9"
    ],
    "qs:name":"Semera",
    "qs:photos_9r":0,
    "qs:photos_sr":0,
    "qs:pop_sr":"5",
    "wd:wordcount":458,
    "wof:name":"Semera",
    "wof:placetype":"locality",
    "wof:population":833
},
  "geometry": {"coordinates":[41.20098,11.50099],"type":"Point"}
}