{
  "type": "Feature",
  "properties": {
    "gn:admin1_code":"52.0",
    "gn:asciiname":"Foka",
    "gn:country_code":"ET",
    "gn:dem":261,
    "gn:feature_class":"P",
    "gn:feature_code":"PPL",
    "gn:name":"Foka",
    "gn:population":0,
    "gn:timezone":"Africa/Addis_Ababa",
    "iso:country":"ET",
    "wof:name":"Foka",
    "wof:placetype":"locality"
},
  "geometry": {"coordinates":[42.11306,4.97139],"type":"Point"}
}