{
  "type": "Feature",
  "properties": {
    "gn:admin1_code":"52.0",
    "gn:asciiname":"Beit Ali",
    "gn:country_code":"ET",
    "gn:dem":640,
    "gn:feature_class":"P",
    "gn:feature_code":"PPL",
    "gn:name":"Beit Ali",
    "gn:population":0,
    "gn:timezone":"Africa/Addis_Ababa",
    "iso:country":"ET",
    "wof:name":"Beit Ali",
    "wof:placetype":"locality"
},
  "geometry": {"coordinates":[45.63333,7.73333],"type":"Point"}
}