{
  "type": "Feature",
  "properties": {
    "gn:admin1_code":"51",
    "gn:asciiname":"Rukeyti",
    "gn:country_code":"ET",
    "gn:dem":1628,
    "gn:feature_class":"P",
    "gn:feature_code":"PPL",
    "gn:name":"Ruk\u0113yti",
    "gn:population":0,
    "gn:timezone":"Africa/Addis_Ababa",
    "iso:country":"ET",
    "wof:name":"Rukeyti",
    "wof:placetype":"locality"
},
  "geometry": {"coordinates":[40.45,8.53333],"type":"Point"}
}