{
  "type": "Feature",
  "properties": {
    "gn:admin1_code":"46",
    "gn:asciiname":"Waho",
    "gn:country_code":"ET",
    "gn:dem":1597,
    "gn:feature_class":"P",
    "gn:feature_code":"PPL",
    "gn:name":"Waho",
    "gn:population":0,
    "gn:timezone":"Africa/Addis_Ababa",
    "iso:country":"ET",
    "name:und_x_variant":[
        "Waho (1)",
        "Waho"
    ],
    "wof:name":"Waho",
    "wof:placetype":"locality"
},
  "geometry": {"coordinates":[39.81667,11.56667],"type":"Point"}
}