{
  "type": "Feature",
  "properties": {
    "gn:admin1_code":"54",
    "gn:asciiname":"Gesha",
    "gn:country_code":"ET",
    "gn:dem":1801,
    "gn:feature_class":"P",
    "gn:feature_code":"PPL",
    "gn:name":"G\u0113sha",
    "gn:population":0,
    "gn:timezone":"Africa/Addis_Ababa",
    "iso:country":"ET",
    "name:ceb_x_preferred":[
        "G\u0113sha"
    ],
    "name:eng_x_preferred":[
        "Geisha"
    ],
    "name:fra_x_preferred":[
        "Gesha"
    ],
    "name:swe_x_preferred":[
        "G\u0113sha"
    ],
    "wof:name":"Gesha",
    "wof:placetype":"locality"
},
  "geometry": {"coordinates":[35.57729000000001,6.50615],"type":"Point"}
}