{
  "type": "Feature",
  "properties": {
    "gn:admin1_code":"46.0",
    "gn:asciiname":"Disim",
    "gn:country_code":"ET",
    "gn:dem":2914,
    "gn:feature_class":"P",
    "gn:feature_code":"PPL",
    "gn:name":"Disim",
    "gn:population":0,
    "gn:timezone":"Africa/Addis_Ababa",
    "iso:country":"ET",
    "wof:name":"Disim",
    "wof:placetype":"locality"
},
  "geometry": {"coordinates":[39.49795,10.80581],"type":"Point"}
}