{
  "type": "Feature",
  "properties": {
    "gn:admin1_code":"52",
    "gn:asciiname":"Guasasali",
    "gn:country_code":"ET",
    "gn:dem":472,
    "gn:feature_class":"P",
    "gn:feature_code":"PPL",
    "gn:name":"Guasasali",
    "gn:population":0,
    "gn:timezone":"Africa/Addis_Ababa",
    "iso:country":"ET",
    "wof:name":"Guasasali",
    "wof:placetype":"locality"
},
  "geometry": {"coordinates":[42.82667,6.57833],"type":"Point"}
}