{
  "type": "Feature",
  "properties": {
    "gn:admin1_code":"51.0",
    "gn:asciiname":"Wenodo Bido",
    "gn:country_code":"ET",
    "gn:dem":2949,
    "gn:feature_class":"P",
    "gn:feature_code":"PPL",
    "gn:name":"Wenodo Bido",
    "gn:population":0,
    "gn:timezone":"Africa/Addis_Ababa",
    "iso:country":"ET",
    "wof:name":"Wenodo Bido",
    "wof:placetype":"locality"
},
  "geometry": {"coordinates":[39.09904,9.28534],"type":"Point"}
}