{
  "type": "Feature",
  "properties": {
    "gn:admin1_code":"46",
    "gn:asciiname":"Lemi",
    "gn:country_code":"ET",
    "gn:dem":2630,
    "gn:feature_class":"P",
    "gn:feature_code":"PPL",
    "gn:name":"Lem\u012b",
    "gn:population":0,
    "gn:timezone":"Africa/Addis_Ababa",
    "iso:country":"ET",
    "wof:name":"Lemi",
    "wof:placetype":"locality"
},
  "geometry": {"coordinates":[38.88333,9.76667],"type":"Point"}
}