{
  "type": "Feature",
  "properties": {
    "gn:admin1_code":"45.0",
    "gn:asciiname":"Adaito Ela",
    "gn:country_code":"ET",
    "gn:dem":-11,
    "gn:feature_class":"P",
    "gn:feature_code":"PPL",
    "gn:name":"Adaito Ela",
    "gn:population":0,
    "gn:timezone":"Africa/Addis_Ababa",
    "iso:country":"ET",
    "name:und_x_variant":[
        "Adayto Elo",
        "Adaito Ela"
    ],
    "wof:name":"Adaito Ela",
    "wof:placetype":"locality"
},
  "geometry": {"coordinates":[40.83774,13.42718],"type":"Point"}
}