{
  "type": "Feature",
  "properties": {
    "gn:admin1_code":"51",
    "gn:asciiname":"Migiro",
    "gn:country_code":"ET",
    "gn:dem":2578,
    "gn:feature_class":"P",
    "gn:feature_code":"PPL",
    "gn:name":"M\u012bg\u012bro",
    "gn:population":0,
    "gn:timezone":"Africa/Addis_Ababa",
    "iso:country":"ET",
    "wof:name":"Migiro",
    "wof:placetype":"locality"
},
  "geometry": {"coordinates":[38.38333,9.85],"type":"Point"}
}