{
  "type": "Feature",
  "properties": {
    "gn:admin1_code":"37.0",
    "gn:asciiname":"Tahtay Koraro",
    "gn:country_code":"ET",
    "gn:dem":1895,
    "gn:feature_class":"P",
    "gn:feature_code":"PPL",
    "gn:name":"Tahtay Koraro",
    "gn:population":0,
    "gn:timezone":"Africa/Addis_Ababa",
    "iso:country":"ET",
    "name:fra_x_preferred":[
        "Tahtay Koraro"
    ],
    "wof:name":"Tahtay Koraro",
    "wof:placetype":"locality"
},
  "geometry": {"coordinates":[38.27211,14.08944],"type":"Point"}
}