{
  "type": "Feature",
  "properties": {
    "gn:admin1_code":"48",
    "gn:asciiname":"Oboshe",
    "gn:country_code":"ET",
    "gn:dem":1526,
    "gn:feature_class":"P",
    "gn:feature_code":"PPL",
    "gn:name":"Obosh\u0113",
    "gn:population":0,
    "gn:timezone":"Africa/Addis_Ababa",
    "iso:country":"ET",
    "wof:name":"Oboshe",
    "wof:placetype":"locality"
},
  "geometry": {"coordinates":[41.94306,9.60139],"type":"Point"}
}