{
  "type": "Feature",
  "properties": {
    "gn:admin1_code":"51",
    "gn:asciiname":"Seyo",
    "gn:country_code":"ET",
    "gn:dem":2629,
    "gn:feature_class":"P",
    "gn:feature_code":"PPL",
    "gn:name":"Seyo",
    "gn:population":0,
    "gn:timezone":"Africa/Addis_Ababa",
    "iso:country":"ET",
    "wof:name":"Seyo",
    "wof:placetype":"locality"
},
  "geometry": {"coordinates":[38.98333,9.56667],"type":"Point"}
}