{
  "type": "Feature",
  "properties": {
    "gn:admin1_code":"46",
    "gn:asciiname":"Zebekula",
    "gn:country_code":"ET",
    "gn:dem":2567,
    "gn:feature_class":"P",
    "gn:feature_code":"PPL",
    "gn:name":"Zebekula",
    "gn:population":0,
    "gn:timezone":"Africa/Addis_Ababa",
    "iso:country":"ET",
    "wof:name":"Zebekula",
    "wof:placetype":"locality"
},
  "geometry": {"coordinates":[39.31667,11.63333],"type":"Point"}
}