{
  "type": "Feature",
  "properties": {
    "gn:admin1_code":"49.0",
    "gn:asciiname":"Chuaylut",
    "gn:country_code":"ET",
    "gn:dem":408,
    "gn:feature_class":"P",
    "gn:feature_code":"PPL",
    "gn:name":"Chuaylut",
    "gn:population":0,
    "gn:timezone":"Africa/Addis_Ababa",
    "iso:country":"ET",
    "wof:name":"Chuaylut",
    "wof:placetype":"locality"
},
  "geometry": {"coordinates":[33.19313,8.15033],"type":"Point"}
}