{
  "type": "Feature",
  "properties": {
    "gn:admin1_code":"49.0",
    "gn:asciiname":"Apanauane",
    "gn:country_code":"ET",
    "gn:dem":492,
    "gn:feature_class":"P",
    "gn:feature_code":"PPL",
    "gn:name":"Apanauane",
    "gn:population":0,
    "gn:timezone":"Africa/Addis_Ababa",
    "iso:country":"ET",
    "name:und_x_variant":[
        "Apanango",
        "Apanauane"
    ],
    "wof:name":"Apanauane",
    "wof:placetype":"locality"
},
  "geometry": {"coordinates":[34.18333,7.18333],"type":"Point"}
}