{
  "type": "Feature",
  "properties": {
    "gn:admin1_code":"51.0",
    "gn:asciiname":"Ahmed Abdule",
    "gn:country_code":"ET",
    "gn:dem":2328,
    "gn:feature_class":"P",
    "gn:feature_code":"PPL",
    "gn:name":"\u0100hmed \u0100bdul\u0113",
    "gn:population":0,
    "gn:timezone":"Africa/Addis_Ababa",
    "iso:country":"ET",
    "wof:name":"Ahmed Abdule",
    "wof:placetype":"locality"
},
  "geometry": {"coordinates":[41.27715,9.17307],"type":"Point"}
}