{
  "type": "Feature",
  "properties": {
    "gn:admin1_code":"52.0",
    "gn:asciiname":"Dibili",
    "gn:country_code":"ET",
    "gn:dem":1603,
    "gn:feature_class":"P",
    "gn:feature_code":"PPL",
    "gn:name":"Dibili",
    "gn:population":0,
    "gn:timezone":"Africa/Addis_Ababa",
    "iso:country":"ET",
    "name:und_x_variant":[
        "Dibale",
        "Dibileh",
        "D\u012bb\u012bl\u0113"
    ],
    "wof:name":"Dibili",
    "wof:placetype":"locality"
},
  "geometry": {"coordinates":[43.49639000000001,9.16556],"type":"Point"}
}