{
  "type": "Feature",
  "properties": {
    "gn:admin1_code":"52",
    "gn:asciiname":"El Taulei",
    "gn:country_code":"ET",
    "gn:dem":717,
    "gn:feature_class":"P",
    "gn:feature_code":"PPL",
    "gn:name":"El Taulei",
    "gn:population":0,
    "gn:timezone":"Africa/Addis_Ababa",
    "iso:country":"ET",
    "wof:name":"El Taulei",
    "wof:placetype":"locality"
},
  "geometry": {"coordinates":[42.26667,5.75],"type":"Point"}
}