{
  "type": "Feature",
  "properties": {
    "gn:admin1_code":"51.0",
    "gn:asciiname":"Birbirsa Sek'ela",
    "gn:country_code":"ET",
    "gn:dem":2523,
    "gn:feature_class":"P",
    "gn:feature_code":"PPL",
    "gn:name":"Birbirsa Sek\u2019ela",
    "gn:population":0,
    "gn:timezone":"Africa/Addis_Ababa",
    "iso:country":"ET",
    "wof:name":"Birbirsa Sek'ela",
    "wof:placetype":"locality"
},
  "geometry": {"coordinates":[37.08333,9.66667],"type":"Point"}
}