{
  "type": "Feature",
  "properties": {
    "gn:admin1_code":"46.0",
    "gn:asciiname":"Aba Golja",
    "gn:country_code":"ET",
    "gn:dem":2135,
    "gn:feature_class":"P",
    "gn:feature_code":"PPL",
    "gn:name":"\u0100ba Golja",
    "gn:population":0,
    "gn:timezone":"Africa/Addis_Ababa",
    "iso:country":"ET",
    "wof:name":"Aba Golja",
    "wof:placetype":"locality"
},
  "geometry": {"coordinates":[37.02694,12.51806],"type":"Point"}
}