{
  "type": "Feature",
  "properties": {
    "gn:admin1_code":"51",
    "gn:asciiname":"Hara Seba",
    "gn:country_code":"ET",
    "gn:dem":2886,
    "gn:feature_class":"P",
    "gn:feature_code":"PPL",
    "gn:name":"H\u0101ra Seba",
    "gn:population":0,
    "gn:timezone":"Africa/Addis_Ababa",
    "iso:country":"ET",
    "wof:name":"Hara Seba",
    "wof:placetype":"locality"
},
  "geometry": {"coordinates":[37.06667,9.48333],"type":"Point"}
}