{
  "type": "Feature",
  "properties": {
    "gn:admin1_code":"51",
    "gn:asciiname":"Werebi",
    "gn:country_code":"ET",
    "gn:dem":2624,
    "gn:feature_class":"P",
    "gn:feature_code":"PPL",
    "gn:name":"Wereb\u012b",
    "gn:population":0,
    "gn:timezone":"Africa/Addis_Ababa",
    "iso:country":"ET",
    "wof:name":"Werebi",
    "wof:placetype":"locality"
},
  "geometry": {"coordinates":[39.01242,9.60561],"type":"Point"}
}