{
  "type": "Feature",
  "properties": {
    "gn:admin1_code":"53.0",
    "gn:asciiname":"Alak'ma",
    "gn:country_code":"ET",
    "gn:dem":2216,
    "gn:feature_class":"P",
    "gn:feature_code":"PPL",
    "gn:name":"\u0100lak\u2019ma",
    "gn:population":0,
    "gn:timezone":"Africa/Addis_Ababa",
    "iso:country":"ET",
    "wof:name":"Alak'ma",
    "wof:placetype":"locality"
},
  "geometry": {"coordinates":[39.37111,14.37778],"type":"Point"}
}