{
  "type": "Feature",
  "properties": {
    "gn:admin1_code":"51",
    "gn:asciiname":"Merere",
    "gn:country_code":"ET",
    "gn:dem":1867,
    "gn:feature_class":"P",
    "gn:feature_code":"PPL",
    "gn:name":"Merer\u0113",
    "gn:population":0,
    "gn:timezone":"Africa/Addis_Ababa",
    "iso:country":"ET",
    "wof:name":"Merere",
    "wof:placetype":"locality"
},
  "geometry": {"coordinates":[38.58333,9.51667],"type":"Point"}
}