{
  "type": "Feature",
  "properties": {
    "gn:gn_country":"ET",
    "gn:gn_fcode":"PPL",
    "gn:gn_pop":12442,
    "gn:population":12442,
    "iso:country":"ET",
    "name:bul_x_preferred":[
        "\u0425\u0443\u0440\u0443\u0442\u0430"
    ],
    "name:eng_x_preferred":[
        "Huruta"
    ],
    "name:fra_x_preferred":[
        "Huruta"
    ],
    "name:nld_x_preferred":[
        "Huruta"
    ],
    "name:swe_x_preferred":[
        "Huruta"
    ],
    "name:unk_x_variant":[
        "Uruta Mariam"
    ],
    "qs_pg:aaroncc":"ET",
    "qs_pg:gn_country":"ET",
    "qs_pg:gn_fcode":"PPL",
    "qs_pg:gn_pop":12442,
    "qs_pg:name":"Huruta",
    "qs_pg:photos_9r":0,
    "qs_pg:photos_sr":0,
    "qs_pg:pop_sr":6,
    "qs_pg:qs_pg_placetype":"locality",
    "wof:name":"Huruta",
    "wof:placetype":"locality",
    "wof:population":12442
},
  "geometry": {"coordinates":[39.35,8.15],"type":"Point"}
}