{
  "type": "Feature",
  "properties": {
    "gn:admin1_code":"52.0",
    "gn:asciiname":"Calega",
    "gn:country_code":"ET",
    "gn:dem":1665,
    "gn:feature_class":"P",
    "gn:feature_code":"PPL",
    "gn:name":"Calega",
    "gn:population":0,
    "gn:timezone":"Africa/Addis_Ababa",
    "iso:country":"ET",
    "wof:name":"Calega",
    "wof:placetype":"locality"
},
  "geometry": {"coordinates":[43.13333,9.11667],"type":"Point"}
}