{
  "type": "Feature",
  "properties": {
    "gn:admin1_code":"45.0",
    "gn:asciiname":"Cochebi Raja",
    "gn:country_code":"ET",
    "gn:dem":1128,
    "gn:feature_class":"P",
    "gn:feature_code":"PPL",
    "gn:name":"Cochebi Raja",
    "gn:population":0,
    "gn:timezone":"Africa/Addis_Ababa",
    "iso:country":"ET",
    "wof:name":"Cochebi Raja",
    "wof:placetype":"locality"
},
  "geometry": {"coordinates":[39.83333,12.13333],"type":"Point"}
}