{
  "type": "Feature",
  "properties": {
    "gn:admin1_code":"51",
    "gn:asciiname":"Ejere",
    "gn:country_code":"ET",
    "gn:dem":2345,
    "gn:feature_class":"P",
    "gn:feature_code":"PPL",
    "gn:name":"\u0112j\u0113r\u0113",
    "gn:population":0,
    "gn:timezone":"Africa/Addis_Ababa",
    "iso:country":"ET",
    "wof:name":"Ejere",
    "wof:placetype":"locality"
},
  "geometry": {"coordinates":[38.51667,9.91667],"type":"Point"}
}