{
  "type": "Feature",
  "properties": {
    "gn:admin1_code":"46",
    "gn:asciiname":"K'enso",
    "gn:country_code":"ET",
    "gn:dem":2521,
    "gn:feature_class":"P",
    "gn:feature_code":"PPL",
    "gn:name":"K\u2019enso",
    "gn:population":0,
    "gn:timezone":"Africa/Addis_Ababa",
    "iso:country":"ET",
    "wof:name":"K'enso",
    "wof:placetype":"locality"
},
  "geometry": {"coordinates":[39.06798,10.61646],"type":"Point"}
}