{
  "type": "Feature",
  "properties": {
    "gn:admin1_code":"45.0",
    "gn:asciiname":"Fillamake",
    "gn:country_code":"ET",
    "gn:dem":351,
    "gn:feature_class":"P",
    "gn:feature_code":"PPL",
    "gn:name":"Fillamake",
    "gn:population":0,
    "gn:timezone":"Africa/Addis_Ababa",
    "iso:country":"ET",
    "wof:name":"Fillamake",
    "wof:placetype":"locality"
},
  "geometry": {"coordinates":[41.51129,11.57874],"type":"Point"}
}