{
  "type": "Feature",
  "properties": {
    "gn:admin1_code":"46.0",
    "gn:asciiname":"Barat",
    "gn:country_code":"ET",
    "gn:dem":3034,
    "gn:feature_class":"P",
    "gn:feature_code":"PPL",
    "gn:name":"Barat",
    "gn:population":0,
    "gn:timezone":"Africa/Addis_Ababa",
    "iso:country":"ET",
    "name:bos_x_preferred":[
        "Barat"
    ],
    "name:ceb_x_preferred":[
        "Barat"
    ],
    "name:deu_x_preferred":[
        "Barat"
    ],
    "name:fra_x_preferred":[
        "Barat"
    ],
    "name:hrv_x_preferred":[
        "Barat"
    ],
    "name:hun_x_preferred":[
        "Barat"
    ],
    "name:ind_x_preferred":[
        "Barat"
    ],
    "name:nld_x_preferred":[
        "Barat"
    ],
    "name:slv_x_preferred":[
        "Barat"
    ],
    "name:srp_x_preferred":[
        "\u0411\u0430\u0440\u0430\u0442"
    ],
    "name:swe_x_preferred":[
        "Barat"
    ],
    "wof:name":"Barat",
    "wof:placetype":"locality"
},
  "geometry": {"coordinates":[38.98333,11.71667],"type":"Point"}
}