{
  "type": "Feature",
  "properties": {
    "gn:admin1_code":"53",
    "gn:asciiname":"Hilshe",
    "gn:country_code":"ET",
    "gn:dem":2492,
    "gn:feature_class":"P",
    "gn:feature_code":"PPL",
    "gn:name":"Hilshe",
    "gn:population":0,
    "gn:timezone":"Africa/Addis_Ababa",
    "iso:country":"ET",
    "name:und_x_variant":[
        "Khil'she"
    ],
    "wof:name":"Hilshe",
    "wof:placetype":"locality"
},
  "geometry": {"coordinates":[39.67462,13.53995],"type":"Point"}
}