{
  "type": "Feature",
  "properties": {
    "gn:admin1_code":"51",
    "gn:asciiname":"Meta",
    "gn:country_code":"ET",
    "gn:dem":2004,
    "gn:feature_class":"P",
    "gn:feature_code":"PPL",
    "gn:name":"M\u0113ta",
    "gn:population":0,
    "gn:timezone":"Africa/Addis_Ababa",
    "iso:country":"ET",
    "name:ara_x_preferred":[
        "\u0645\u064a\u062a\u0627"
    ],
    "name:bel_x_preferred":[
        "\u041c\u0435\u0442\u0430-"
    ],
    "name:dan_x_preferred":[
        "Meta"
    ],
    "name:est_x_preferred":[
        "Meta-"
    ],
    "name:fas_x_preferred":[
        "\u0645\u062a\u0627"
    ],
    "name:fin_x_preferred":[
        "Meta"
    ],
    "name:fra_x_preferred":[
        "M\u00e9ta"
    ],
    "name:heb_x_preferred":[
        "\u05de\u05d8\u05d0"
    ],
    "name:kat_x_preferred":[
        "\u10db\u10d4\u10e2\u10d0..."
    ],
    "name:kir_x_preferred":[
        "\u041c\u0435\u0442\u0430..."
    ],
    "name:nno_x_preferred":[
        "Meta"
    ],
    "name:nor_x_preferred":[
        "Meta"
    ],
    "name:rus_x_preferred":[
        "\u041c\u0435\u0442\u0430-"
    ],
    "name:spa_x_preferred":[
        "Meta"
    ],
    "name:swe_x_preferred":[
        "Meta-"
    ],
    "name:tha_x_preferred":[
        "\u0e40\u0e21\u0e17\u0e32"
    ],
    "wof:name":"Meta",
    "wof:placetype":"locality"
},
  "geometry": {"coordinates":[41.86778,9.335],"type":"Point"}
}