{
  "type": "Feature",
  "properties": {
    "gn:admin1_code":"51",
    "gn:asciiname":"Meta",
    "gn:country_code":"ET",
    "gn:dem":2004,
    "gn:feature_class":"P",
    "gn:feature_code":"PPL",
    "gn:name":"M\u0113ta",
    "gn:population":0,
    "gn:timezone":"Africa/Addis_Ababa",
    "iso:country":"ET",
    "wof:name":"Meta",
    "wof:placetype":"locality"
},
  "geometry": {"coordinates":[41.86778,9.335],"type":"Point"}
}