{
  "type": "Feature",
  "properties": {
    "gn:admin1_code":"53",
    "gn:asciiname":"Tembo",
    "gn:country_code":"ET",
    "gn:dem":1895,
    "gn:feature_class":"P",
    "gn:feature_code":"PPL",
    "gn:name":"Tembo",
    "gn:population":0,
    "gn:timezone":"Africa/Addis_Ababa",
    "iso:country":"ET",
    "name:fra_x_preferred":[
        "Tembo"
    ],
    "wof:name":"Tembo",
    "wof:placetype":"locality"
},
  "geometry": {"coordinates":[38.3209,14.22064],"type":"Point"}
}