{
  "type": "Feature",
  "properties": {
    "gn:admin1_code":"46.0",
    "gn:asciiname":"Dan'ye",
    "gn:country_code":"ET",
    "gn:dem":2321,
    "gn:feature_class":"P",
    "gn:feature_code":"PPL",
    "gn:name":"Dan\u2019ye",
    "gn:population":0,
    "gn:timezone":"Africa/Addis_Ababa",
    "iso:country":"ET",
    "wof:name":"Dan'ye",
    "wof:placetype":"locality"
},
  "geometry": {"coordinates":[39.62342,9.86979],"type":"Point"}
}