{
  "type": "Feature",
  "properties": {
    "gn:admin1_code":"51",
    "gn:asciiname":"Midega",
    "gn:country_code":"ET",
    "gn:dem":1548,
    "gn:feature_class":"P",
    "gn:feature_code":"PPL",
    "gn:name":"Midega",
    "gn:population":0,
    "gn:timezone":"Africa/Addis_Ababa",
    "iso:country":"ET",
    "name:und_x_variant":[
        "M\u012bdega Lola",
        "Midago",
        "Midagalola",
        "M\u012bdega",
        "Midega",
        "Midagal\u2019da"
    ],
    "wof:name":"Midega",
    "wof:placetype":"locality"
},
  "geometry": {"coordinates":[42.12326,8.86897],"type":"Point"}
}