{
  "type": "Feature",
  "properties": {
    "gn:admin1_code":"51.0",
    "gn:asciiname":"Aba Genda",
    "gn:country_code":"ET",
    "gn:dem":2581,
    "gn:feature_class":"P",
    "gn:feature_code":"PPL",
    "gn:name":"\u0100ba Genda",
    "gn:population":0,
    "gn:timezone":"Africa/Addis_Ababa",
    "iso:country":"ET",
    "wof:name":"Aba Genda",
    "wof:placetype":"locality"
},
  "geometry": {"coordinates":[39.61667,8.05],"type":"Point"}
}