{
  "type": "Feature",
  "properties": {
    "gn:admin1_code":"46",
    "gn:asciiname":"Wik'ma",
    "gn:country_code":"ET",
    "gn:dem":2155,
    "gn:feature_class":"P",
    "gn:feature_code":"PPL",
    "gn:name":"Wik\u2019ma",
    "gn:population":0,
    "gn:timezone":"Africa/Addis_Ababa",
    "iso:country":"ET",
    "wof:name":"Wik'ma",
    "wof:placetype":"locality"
},
  "geometry": {"coordinates":[38.26667,10.66667],"type":"Point"}
}