{
  "type": "Feature",
  "properties": {
    "gn:admin1_code":"46",
    "gn:asciiname":"Wahats'a",
    "gn:country_code":"ET",
    "gn:dem":2523,
    "gn:feature_class":"P",
    "gn:feature_code":"PPL",
    "gn:name":"Wahats\u2019a",
    "gn:population":0,
    "gn:timezone":"Africa/Addis_Ababa",
    "iso:country":"ET",
    "wof:name":"Wahats'a",
    "wof:placetype":"locality"
},
  "geometry": {"coordinates":[36.98333,10.88333],"type":"Point"}
}