{
  "type": "Feature",
  "properties": {
    "gn:admin1_code":"46",
    "gn:asciiname":"Fereshoch",
    "gn:country_code":"ET",
    "gn:dem":3145,
    "gn:feature_class":"P",
    "gn:feature_code":"PPL",
    "gn:name":"Fereshoch",
    "gn:population":0,
    "gn:timezone":"Africa/Addis_Ababa",
    "iso:country":"ET",
    "wof:name":"Fereshoch",
    "wof:placetype":"locality"
},
  "geometry": {"coordinates":[39.08333,11.68333],"type":"Point"}
}