{
  "type": "Feature",
  "properties": {
    "gn:admin1_code":"51",
    "gn:asciiname":"K'et'iba",
    "gn:country_code":"ET",
    "gn:dem":2054,
    "gn:feature_class":"P",
    "gn:feature_code":"PPL",
    "gn:name":"K\u2019et\u2019\u012bba",
    "gn:population":0,
    "gn:timezone":"Africa/Addis_Ababa",
    "iso:country":"ET",
    "wof:name":"K'et'iba",
    "wof:placetype":"locality"
},
  "geometry": {"coordinates":[40.53333,7.33333],"type":"Point"}
}