{
  "type": "Feature",
  "properties": {
    "gn:admin1_code":"51",
    "gn:asciiname":"Wach'u Dima",
    "gn:country_code":"ET",
    "gn:dem":1722,
    "gn:feature_class":"P",
    "gn:feature_code":"PPL",
    "gn:name":"Wach\u2019u D\u012bma",
    "gn:population":0,
    "gn:timezone":"Africa/Addis_Ababa",
    "iso:country":"ET",
    "name:und_x_variant":[
        "Uachu-Dima",
        "Wach\u2019u D\u012bma"
    ],
    "wof:name":"Wach'u Dima",
    "wof:placetype":"locality"
},
  "geometry": {"coordinates":[42.13972,9.03278],"type":"Point"}
}