{
  "type": "Feature",
  "properties": {
    "gn:admin1_code":"51.0",
    "gn:asciiname":"Dengi",
    "gn:country_code":"ET",
    "gn:dem":1838,
    "gn:feature_class":"P",
    "gn:feature_code":"PPL",
    "gn:name":"Deng\u012b",
    "gn:population":0,
    "gn:timezone":"Africa/Addis_Ababa",
    "iso:country":"ET",
    "wof:name":"Dengi",
    "wof:placetype":"locality"
},
  "geometry": {"coordinates":[35.33333,9.86667],"type":"Point"}
}