{
  "type": "Feature",
  "properties": {
    "gn:admin1_code":"51",
    "gn:asciiname":"K'ohiti",
    "gn:country_code":"ET",
    "gn:dem":2650,
    "gn:feature_class":"P",
    "gn:feature_code":"PPL",
    "gn:name":"K\u2019oh\u012bt\u012b",
    "gn:population":0,
    "gn:timezone":"Africa/Addis_Ababa",
    "iso:country":"ET",
    "wof:name":"K'ohiti",
    "wof:placetype":"locality"
},
  "geometry": {"coordinates":[38.95,9.56667],"type":"Point"}
}