{
  "type": "Feature",
  "properties": {
    "gn:admin1_code":"54",
    "gn:asciiname":"Murle",
    "gn:country_code":"ET",
    "gn:dem":443,
    "gn:feature_class":"P",
    "gn:feature_code":"PPL",
    "gn:name":"Murle",
    "gn:population":0,
    "gn:timezone":"Africa/Addis_Ababa",
    "iso:country":"ET",
    "wof:name":"Murle",
    "wof:placetype":"locality"
},
  "geometry": {"coordinates":[36.21667,5.15],"type":"Point"}
}