{
  "type": "Feature",
  "properties": {
    "gn:admin1_code":"54.0",
    "gn:asciiname":"Ba'ido",
    "gn:country_code":"ET",
    "gn:dem":1803,
    "gn:feature_class":"P",
    "gn:feature_code":"PPL",
    "gn:name":"Ba\u2019ido",
    "gn:population":0,
    "gn:timezone":"Africa/Addis_Ababa",
    "iso:country":"ET",
    "wof:name":"Ba'ido",
    "wof:placetype":"locality"
},
  "geometry": {"coordinates":[37.33333,5.56667],"type":"Point"}
}