{
  "type": "Feature",
  "properties": {
    "gn:admin1_code":"51.0",
    "gn:asciiname":"Albuna",
    "gn:country_code":"ET",
    "gn:dem":2560,
    "gn:feature_class":"P",
    "gn:feature_code":"PPL",
    "gn:name":"\u0100lbuna",
    "gn:population":0,
    "gn:timezone":"Africa/Addis_Ababa",
    "iso:country":"ET",
    "name:ceb_x_preferred":[
        "Albuna"
    ],
    "name:nld_x_preferred":[
        "Albuna"
    ],
    "name:swe_x_preferred":[
        "Albuna"
    ],
    "name:vie_x_preferred":[
        "Albuna"
    ],
    "name:war_x_preferred":[
        "Albuna"
    ],
    "wof:name":"Albuna",
    "wof:placetype":"locality"
},
  "geometry": {"coordinates":[38.66667,9.35],"type":"Point"}
}