{
  "type": "Feature",
  "properties": {
    "gn:admin1_code":"52.0",
    "gn:asciiname":"Ali Gedi",
    "gn:country_code":"ET",
    "gn:dem":850,
    "gn:feature_class":"P",
    "gn:feature_code":"PPL",
    "gn:name":"\u0100l\u012b Ged\u012b",
    "gn:population":0,
    "gn:timezone":"Africa/Addis_Ababa",
    "iso:country":"ET",
    "wof:name":"Ali Gedi",
    "wof:placetype":"locality"
},
  "geometry": {"coordinates":[42.33637,10.41837],"type":"Point"}
}