{
  "type": "Feature",
  "properties": {
    "gn:admin1_code":"53",
    "gn:asciiname":"Shiyaboni",
    "gn:country_code":"ET",
    "gn:dem":1564,
    "gn:feature_class":"P",
    "gn:feature_code":"PPL",
    "gn:name":"Sh\u012byabon\u012b",
    "gn:population":0,
    "gn:timezone":"Africa/Addis_Ababa",
    "iso:country":"ET",
    "name:und_x_variant":[
        "Beray",
        "Berai",
        "Sh\u012byabon\u012b"
    ],
    "wof:name":"Shiyaboni",
    "wof:placetype":"locality"
},
  "geometry": {"coordinates":[37.98611,14.52722],"type":"Point"}
}