{
  "type": "Feature",
  "properties": {
    "gn:admin1_code":"51.0",
    "gn:asciiname":"Dire Boch'ore",
    "gn:country_code":"ET",
    "gn:dem":2684,
    "gn:feature_class":"P",
    "gn:feature_code":"PPL",
    "gn:name":"Dir\u0113 Boch\u2019or\u0113",
    "gn:population":0,
    "gn:timezone":"Africa/Addis_Ababa",
    "iso:country":"ET",
    "wof:name":"Dire Boch'ore",
    "wof:placetype":"locality"
},
  "geometry": {"coordinates":[38.76667,9.73333],"type":"Point"}
}