{
  "type": "Feature",
  "properties": {
    "gn:admin1_code":"45.0",
    "gn:asciiname":"Bolotarmo",
    "gn:country_code":"ET",
    "gn:dem":653,
    "gn:feature_class":"P",
    "gn:feature_code":"PPL",
    "gn:name":"Bolotarmo",
    "gn:population":0,
    "gn:timezone":"Africa/Addis_Ababa",
    "iso:country":"ET",
    "name:und_x_variant":[
        "B\u00f2lotamo",
        "Bolotarmo"
    ],
    "wof:name":"Bolotarmo",
    "wof:placetype":"locality"
},
  "geometry": {"coordinates":[40.06986,14.39301],"type":"Point"}
}