{
  "type": "Feature",
  "properties": {
    "gn:admin1_code":"52",
    "gn:asciiname":"Dugacio",
    "gn:country_code":"ET",
    "gn:dem":304,
    "gn:feature_class":"P",
    "gn:feature_code":"PPL",
    "gn:name":"Dugacio",
    "gn:population":0,
    "gn:timezone":"Africa/Addis_Ababa",
    "iso:country":"ET",
    "wof:name":"Dugacio",
    "wof:placetype":"locality"
},
  "geometry": {"coordinates":[41.83333,5.03333],"type":"Point"}
}