{
  "type": "Feature",
  "properties": {
    "gn:admin1_code":"46.0",
    "gn:asciiname":"Abale",
    "gn:country_code":"ET",
    "gn:dem":1786,
    "gn:feature_class":"P",
    "gn:feature_code":"PPL",
    "gn:name":"\u0100bal\u0113",
    "gn:population":0,
    "gn:timezone":"Africa/Addis_Ababa",
    "iso:country":"ET",
    "name:und_x_variant":[
        "Ambara",
        "\u0100bal\u0113"
    ],
    "wof:name":"Abale",
    "wof:placetype":"locality"
},
  "geometry": {"coordinates":[37.45,12.28333],"type":"Point"}
}