{
  "type": "Feature",
  "properties": {
    "gn:admin1_code":"51",
    "gn:asciiname":"Giri",
    "gn:country_code":"ET",
    "gn:dem":1293,
    "gn:feature_class":"P",
    "gn:feature_code":"PPL",
    "gn:name":"G\u012br\u012b",
    "gn:population":0,
    "gn:timezone":"Africa/Addis_Ababa",
    "iso:country":"ET",
    "name:bel_x_preferred":[
        "\u0413\u0456\u0440\u044b"
    ],
    "name:ceb_x_preferred":[
        "Giri"
    ],
    "name:deu_x_preferred":[
        "Giri"
    ],
    "name:ind_x_preferred":[
        "Giri"
    ],
    "name:jav_x_preferred":[
        "Giri"
    ],
    "name:nld_x_preferred":[
        "Giri"
    ],
    "name:swe_x_preferred":[
        "Giri"
    ],
    "wof:name":"Giri",
    "wof:placetype":"locality"
},
  "geometry": {"coordinates":[42.535,9.06056],"type":"Point"}
}