{
  "type": "Feature",
  "properties": {
    "gn:admin1_code":"53",
    "gn:asciiname":"May Da'iro",
    "gn:country_code":"ET",
    "gn:dem":2249,
    "gn:feature_class":"P",
    "gn:feature_code":"PPL",
    "gn:name":"May Da\u2019iro",
    "gn:population":0,
    "gn:timezone":"Africa/Addis_Ababa",
    "iso:country":"ET",
    "name:und_x_variant":[
        "Da\u2019iro",
        "Dauro",
        "May Da\u2019iro"
    ],
    "wof:name":"May Da'iro",
    "wof:placetype":"locality"
},
  "geometry": {"coordinates":[39.46039,13.82597],"type":"Point"}
}