{
  "type": "Feature",
  "properties": {
    "gn:admin1_code":"51.0",
    "gn:asciiname":"Andode",
    "gn:country_code":"ET",
    "gn:dem":2052,
    "gn:feature_class":"P",
    "gn:feature_code":"PPL",
    "gn:name":"\u0100ndod\u0113",
    "gn:population":0,
    "gn:timezone":"Africa/Addis_Ababa",
    "iso:country":"ET",
    "name:und_x_variant":[
        "\u0100ndod\u0113 (1)",
        "\u0100ndod\u0113"
    ],
    "wof:name":"Andode",
    "wof:placetype":"locality"
},
  "geometry": {"coordinates":[38.73333,8.81667],"type":"Point"}
}