{
  "type": "Feature",
  "properties": {
    "gn:admin1_code":"53.0",
    "gn:asciiname":"Embeyto",
    "gn:country_code":"ET",
    "gn:dem":2205,
    "gn:feature_class":"P",
    "gn:feature_code":"PPL",
    "gn:name":"Embeyto",
    "gn:population":0,
    "gn:timezone":"Africa/Addis_Ababa",
    "iso:country":"ET",
    "wof:name":"Embeyto",
    "wof:placetype":"locality"
},
  "geometry": {"coordinates":[39.46655,14.42845],"type":"Point"}
}