{
  "type": "Feature",
  "properties": {
    "gn:admin1_code":"51.0",
    "gn:asciiname":"Buccio",
    "gn:country_code":"ET",
    "gn:dem":2479,
    "gn:feature_class":"P",
    "gn:feature_code":"PPL",
    "gn:name":"Buccio",
    "gn:population":0,
    "gn:timezone":"Africa/Addis_Ababa",
    "iso:country":"ET",
    "wof:name":"Buccio",
    "wof:placetype":"locality"
},
  "geometry": {"coordinates":[39.15,7.13333],"type":"Point"}
}