{
  "type": "Feature",
  "properties": {
    "gn:admin1_code":"47",
    "gn:asciiname":"Erring",
    "gn:country_code":"ET",
    "gn:dem":592,
    "gn:feature_class":"P",
    "gn:feature_code":"PPL",
    "gn:name":"Erring",
    "gn:population":0,
    "gn:timezone":"Africa/Addis_Ababa",
    "iso:country":"ET",
    "wof:name":"Erring",
    "wof:placetype":"locality"
},
  "geometry": {"coordinates":[35.28333,10.98333],"type":"Point"}
}