{
  "type": "Feature",
  "properties": {
    "gn:admin1_code":"46",
    "gn:asciiname":"Imbus Amba",
    "gn:country_code":"ET",
    "gn:dem":2065,
    "gn:feature_class":"P",
    "gn:feature_code":"PPL",
    "gn:name":"Imbus \u0100mba",
    "gn:population":0,
    "gn:timezone":"Africa/Addis_Ababa",
    "iso:country":"ET",
    "wof:name":"Imbus Amba",
    "wof:placetype":"locality"
},
  "geometry": {"coordinates":[39.22751,10.06347],"type":"Point"}
}