{
  "type": "Feature",
  "properties": {
    "gn:admin1_code":"54.0",
    "gn:asciiname":"Meskerem Fire",
    "gn:country_code":"ET",
    "gn:dem":1637,
    "gn:feature_class":"P",
    "gn:feature_code":"PPL",
    "gn:name":"Meskerem Fire",
    "gn:population":0,
    "gn:timezone":"Africa/Addis_Ababa",
    "iso:country":"ET",
    "wof:name":"Meskerem Fire",
    "wof:placetype":"locality"
},
  "geometry": {"coordinates":[35.65067,6.77513],"type":"Point"}
}