{
  "type": "Feature",
  "properties": {
    "gn:admin1_code":"46",
    "gn:asciiname":"Sacca",
    "gn:country_code":"ET",
    "gn:dem":1865,
    "gn:feature_class":"P",
    "gn:feature_code":"PPL",
    "gn:name":"Sacca",
    "gn:population":0,
    "gn:timezone":"Africa/Addis_Ababa",
    "iso:country":"ET",
    "name:nor_x_preferred":[
        "Sacca"
    ],
    "name:tha_x_preferred":[
        "\u0e2a\u0e31\u0e08\u0e08\u0e30"
    ],
    "name:und_x_variant":[
        "Saca"
    ],
    "name:zho_x_preferred":[
        "\u8ae6"
    ],
    "wof:name":"Sacca",
    "wof:placetype":"locality"
},
  "geometry": {"coordinates":[39.05,12.95],"type":"Point"}
}