{
  "type": "Feature",
  "properties": {
    "gn:admin1_code":"51.0",
    "gn:asciiname":"Dendema",
    "gn:country_code":"ET",
    "gn:dem":2240,
    "gn:feature_class":"P",
    "gn:feature_code":"PPLL",
    "gn:name":"Dendema",
    "gn:population":0,
    "gn:timezone":"Africa/Addis_Ababa",
    "iso:country":"ET",
    "name:und_x_variant":[
        "Dendema (1)",
        "Dendema"
    ],
    "wof:name":"Dendema",
    "wof:placetype":"locality"
},
  "geometry": {"coordinates":[42.06667,9.46667],"type":"Point"}
}