{
  "type": "Feature",
  "properties": {
    "gn:admin1_code":"54",
    "gn:asciiname":"Durame",
    "gn:country_code":"ET",
    "gn:dem":2014,
    "gn:feature_class":"P",
    "gn:feature_code":"PPL",
    "gn:name":"Duram\u0113",
    "gn:population":0,
    "gn:timezone":"Africa/Addis_Ababa",
    "iso:country":"ET",
    "name:fra_x_preferred":[
        "Durame"
    ],
    "name:pol_x_preferred":[
        "Durame"
    ],
    "name:und_x_variant":[
        "Duram\u0113"
    ],
    "name:zho_x_preferred":[
        "\u675c\u62c9\u59c6"
    ],
    "wof:name":"Durame",
    "wof:placetype":"locality"
},
  "geometry": {"coordinates":[37.88333,7.23333],"type":"Point"}
}