{
  "type": "Feature",
  "properties": {
    "gn:admin1_code":"46",
    "gn:asciiname":"Uotie",
    "gn:country_code":"ET",
    "gn:dem":2306,
    "gn:feature_class":"P",
    "gn:feature_code":"PPL",
    "gn:name":"Uotie",
    "gn:population":0,
    "gn:timezone":"Africa/Addis_Ababa",
    "iso:country":"ET",
    "name:und_x_variant":[
        "Cotti\u00e8",
        "Uotie"
    ],
    "wof:name":"Uotie",
    "wof:placetype":"locality"
},
  "geometry": {"coordinates":[39.66667,10.93333],"type":"Point"}
}