{
  "type": "Feature",
  "properties": {
    "gn:admin1_code":"52",
    "gn:asciiname":"Osbaleh",
    "gn:country_code":"ET",
    "gn:dem":747,
    "gn:feature_class":"P",
    "gn:feature_code":"PPL",
    "gn:name":"Osbaleh",
    "gn:population":0,
    "gn:timezone":"Africa/Addis_Ababa",
    "iso:country":"ET",
    "wof:name":"Osbaleh",
    "wof:placetype":"locality"
},
  "geometry": {"coordinates":[43.19799,7.17304],"type":"Point"}
}