{
  "type": "Feature",
  "properties": {
    "gn:admin1_code":"46",
    "gn:asciiname":"Gude Beret",
    "gn:country_code":"ET",
    "gn:dem":3070,
    "gn:feature_class":"P",
    "gn:feature_code":"PPL",
    "gn:name":"Gude Beret",
    "gn:population":0,
    "gn:timezone":"Africa/Addis_Ababa",
    "iso:country":"ET",
    "wof:name":"Gude Beret",
    "wof:placetype":"locality"
},
  "geometry": {"coordinates":[39.68116,9.79946],"type":"Point"}
}