{
  "type": "Feature",
  "properties": {
    "gn:admin1_code":"52.0",
    "gn:asciiname":"Kampsayt",
    "gn:country_code":"ET",
    "gn:dem":1624,
    "gn:feature_class":"P",
    "gn:feature_code":"PPL",
    "gn:name":"Kampsayt",
    "gn:population":0,
    "gn:timezone":"Africa/Addis_Ababa",
    "iso:country":"ET",
    "wof:name":"Kampsayt",
    "wof:placetype":"locality"
},
  "geometry": {"coordinates":[42.8225,9.09694],"type":"Point"}
}