{
  "type": "Feature",
  "properties": {
    "gn:admin1_code":"51",
    "gn:asciiname":"Funchaua",
    "gn:country_code":"ET",
    "gn:dem":1507,
    "gn:feature_class":"P",
    "gn:feature_code":"PPL",
    "gn:name":"Funchaua",
    "gn:population":0,
    "gn:timezone":"Africa/Addis_Ababa",
    "iso:country":"ET",
    "wof:name":"Funchaua",
    "wof:placetype":"locality"
},
  "geometry": {"coordinates":[38.35,4.63333],"type":"Point"}
}