{
  "type": "Feature",
  "properties": {
    "gn:admin1_code":"52.0",
    "gn:asciiname":"Coron",
    "gn:country_code":"ET",
    "gn:dem":942,
    "gn:feature_class":"P",
    "gn:feature_code":"PPL",
    "gn:name":"Coron",
    "gn:population":0,
    "gn:timezone":"Africa/Addis_Ababa",
    "iso:country":"ET",
    "name:ceb_x_preferred":[
        "Coron"
    ],
    "name:deu_x_preferred":[
        "Coron"
    ],
    "name:fra_x_preferred":[
        "Coron"
    ],
    "name:ita_x_preferred":[
        "Coron"
    ],
    "name:nld_x_preferred":[
        "Coron"
    ],
    "name:rus_x_preferred":[
        "\u041a\u043e\u0440\u043e\u043d"
    ],
    "name:spa_x_preferred":[
        "Coron"
    ],
    "name:ukr_x_preferred":[
        "\u041a\u043e\u0440\u043e\u043d"
    ],
    "name:war_x_preferred":[
        "Coron"
    ],
    "wof:name":"Coron",
    "wof:placetype":"locality"
},
  "geometry": {"coordinates":[44.61667,7.16667],"type":"Point"}
}