{
  "type": "Feature",
  "properties": {
    "gn:admin1_code":"54",
    "gn:asciiname":"Sofe",
    "gn:country_code":"ET",
    "gn:dem":1481,
    "gn:feature_class":"P",
    "gn:feature_code":"PPL",
    "gn:name":"Sofe",
    "gn:population":0,
    "gn:timezone":"Africa/Addis_Ababa",
    "iso:country":"ET",
    "wof:name":"Sofe",
    "wof:placetype":"locality"
},
  "geometry": {"coordinates":[37.66667,6.61667],"type":"Point"}
}