{
  "type": "Feature",
  "properties": {
    "gn:admin1_code":"46",
    "gn:asciiname":"Mesk'elo",
    "gn:country_code":"ET",
    "gn:dem":2341,
    "gn:feature_class":"P",
    "gn:feature_code":"PPL",
    "gn:name":"Mesk\u2019elo",
    "gn:population":0,
    "gn:timezone":"Africa/Addis_Ababa",
    "iso:country":"ET",
    "name:und_x_variant":[
        "Mascalo",
        "Mesk\u2019elo"
    ],
    "wof:name":"Mesk'elo",
    "wof:placetype":"locality"
},
  "geometry": {"coordinates":[38.95,12.48333],"type":"Point"}
}