{
  "type": "Feature",
  "properties": {
    "gn:admin1_code":"51",
    "gn:asciiname":"Doreni",
    "gn:country_code":"ET",
    "gn:dem":2549,
    "gn:feature_class":"P",
    "gn:feature_code":"PPL",
    "gn:name":"Doren\u012b",
    "gn:population":0,
    "gn:timezone":"Africa/Addis_Ababa",
    "iso:country":"ET",
    "wof:name":"Doreni",
    "wof:placetype":"locality"
},
  "geometry": {"coordinates":[38.85,9.68333],"type":"Point"}
}