{
  "type": "Feature",
  "properties": {
    "gn:admin1_code":"51",
    "gn:asciiname":"Shashemene",
    "gn:country_code":"ET",
    "gn:dem":2061,
    "gn:feature_class":"P",
    "gn:feature_code":"PPL",
    "gn:name":"Shashemen\u0113",
    "gn:population":0,
    "gn:timezone":"Africa/Addis_Ababa",
    "iso:country":"ET",
    "wof:name":"Shashemene",
    "wof:placetype":"locality"
},
  "geometry": {"coordinates":[38.71667,8.78333],"type":"Point"}
}