{
  "type": "Feature",
  "properties": {
    "gn:admin1_code":"52",
    "gn:asciiname":"Uergarti",
    "gn:country_code":"ET",
    "gn:dem":497,
    "gn:feature_class":"P",
    "gn:feature_code":"PPL",
    "gn:name":"Uergarti",
    "gn:population":0,
    "gn:timezone":"Africa/Addis_Ababa",
    "iso:country":"ET",
    "name:und_x_variant":[
        "Uelgarti",
        "Uergarti"
    ],
    "wof:name":"Uergarti",
    "wof:placetype":"locality"
},
  "geometry": {"coordinates":[44.33333,6.25],"type":"Point"}
}