{
  "type": "Feature",
  "properties": {
    "gn:admin1_code":"53",
    "gn:asciiname":"Hilsha",
    "gn:country_code":"ET",
    "gn:dem":2543,
    "gn:feature_class":"P",
    "gn:feature_code":"PPL",
    "gn:name":"Hilsha",
    "gn:population":0,
    "gn:timezone":"Africa/Addis_Ababa",
    "iso:country":"ET",
    "name:und_x_variant":[
        "Khilsha",
        "Hilsha"
    ],
    "wof:name":"Hilsha",
    "wof:placetype":"locality"
},
  "geometry": {"coordinates":[39.69954,13.48766],"type":"Point"}
}