{
  "type": "Feature",
  "properties": {
    "gn:admin1_code":"52.0",
    "gn:asciiname":"Dacub",
    "gn:country_code":"ET",
    "gn:dem":610,
    "gn:feature_class":"P",
    "gn:feature_code":"PPL",
    "gn:name":"Dacub",
    "gn:population":0,
    "gn:timezone":"Africa/Addis_Ababa",
    "iso:country":"ET",
    "wof:name":"Dacub",
    "wof:placetype":"locality"
},
  "geometry": {"coordinates":[46.33333,7.65],"type":"Point"}
}