{
  "type": "Feature",
  "properties": {
    "gn:admin1_code":"38.0",
    "gn:asciiname":"Sade or Dadee Faxee",
    "gn:country_code":"ET",
    "gn:dem":2009,
    "gn:feature_class":"P",
    "gn:feature_code":"PPL",
    "gn:name":"Sade or Dadee Faxee",
    "gn:population":0,
    "gn:timezone":"Africa/Addis_Ababa",
    "iso:country":"ET",
    "wof:name":"Sade or Dadee Faxee",
    "wof:placetype":"locality"
},
  "geometry": {"coordinates":[40.65825,7.22199],"type":"Point"}
}