{
  "type": "Feature",
  "properties": {
    "gn:admin1_code":"51",
    "gn:asciiname":"Sesi Mena",
    "gn:country_code":"ET",
    "gn:dem":2950,
    "gn:feature_class":"P",
    "gn:feature_code":"PPL",
    "gn:name":"Ses\u012b Mena",
    "gn:population":0,
    "gn:timezone":"Africa/Addis_Ababa",
    "iso:country":"ET",
    "wof:name":"Sesi Mena",
    "wof:placetype":"locality"
},
  "geometry": {"coordinates":[40.18333,6.95],"type":"Point"}
}