{
  "type": "Feature",
  "properties": {
    "gn:admin1_code":"51.0",
    "gn:asciiname":"Ch'eliya Yeka",
    "gn:country_code":"ET",
    "gn:dem":1545,
    "gn:feature_class":"P",
    "gn:feature_code":"PPL",
    "gn:name":"Ch\u2019el\u012bya Yeka",
    "gn:population":0,
    "gn:timezone":"Africa/Addis_Ababa",
    "iso:country":"ET",
    "wof:name":"Ch'eliya Yeka",
    "wof:placetype":"locality"
},
  "geometry": {"coordinates":[35.41667,9.21667],"type":"Point"}
}