{
  "type": "Feature",
  "properties": {
    "gn:admin1_code":"48.0",
    "gn:asciiname":"Belewa",
    "gn:country_code":"ET",
    "gn:dem":1677,
    "gn:feature_class":"P",
    "gn:feature_code":"PPL",
    "gn:name":"Belewa",
    "gn:population":0,
    "gn:timezone":"Africa/Addis_Ababa",
    "iso:country":"ET",
    "name:und_x_variant":[
        "Beloua",
        "Belewa"
    ],
    "wof:name":"Belewa",
    "wof:placetype":"locality"
},
  "geometry": {"coordinates":[42.13556,9.56889],"type":"Point"}
}