{
  "type": "Feature",
  "properties": {
    "gn:admin1_code":"53",
    "gn:asciiname":"Enda Mariam Tucul",
    "gn:country_code":"ET",
    "gn:dem":2094,
    "gn:feature_class":"P",
    "gn:feature_code":"PPL",
    "gn:name":"Enda Mariam Tucul",
    "gn:population":0,
    "gn:timezone":"Africa/Addis_Ababa",
    "iso:country":"ET",
    "name:und_x_variant":[
        "Enda Mariam Tukul'",
        "Enda Mariam Tucul"
    ],
    "wof:name":"Enda Mariam Tucul",
    "wof:placetype":"locality"
},
  "geometry": {"coordinates":[39.32776,13.65483],"type":"Point"}
}