{
  "type": "Feature",
  "properties": {
    "gn:admin1_code":"51.0",
    "gn:asciiname":"Beda",
    "gn:country_code":"ET",
    "gn:dem":2093,
    "gn:feature_class":"P",
    "gn:feature_code":"PPL",
    "gn:name":"Beda",
    "gn:population":0,
    "gn:timezone":"Africa/Addis_Ababa",
    "iso:country":"ET",
    "wof:name":"Beda",
    "wof:placetype":"locality"
},
  "geometry": {"coordinates":[42.04139,9.49556],"type":"Point"}
}