{
  "type": "Feature",
  "properties": {
    "gn:admin1_code":"52.0",
    "gn:asciiname":"Derwernache",
    "gn:country_code":"ET",
    "gn:dem":1426,
    "gn:feature_class":"P",
    "gn:feature_code":"PPL",
    "gn:name":"D\u0113rw\u0113rnach\u0113",
    "gn:population":0,
    "gn:timezone":"Africa/Addis_Ababa",
    "iso:country":"ET",
    "name:deu_x_preferred":[
        "Derwonaji"
    ],
    "name:fra_x_preferred":[
        "Derwonaji"
    ],
    "name:nld_x_preferred":[
        "Derwonaji"
    ],
    "name:und_x_variant":[
        "Douernache",
        "D\u0113rw\u0113rnach\u0113"
    ],
    "wof:name":"Derwernache",
    "wof:placetype":"locality"
},
  "geometry": {"coordinates":[43.04417,9.84],"type":"Point"}
}