{
  "type": "Feature",
  "properties": {
    "gn:admin1_code":"54",
    "gn:asciiname":"Kurit",
    "gn:country_code":"ET",
    "gn:dem":1096,
    "gn:feature_class":"P",
    "gn:feature_code":"PPL",
    "gn:name":"Kurit",
    "gn:population":0,
    "gn:timezone":"Africa/Addis_Ababa",
    "iso:country":"ET",
    "wof:name":"Kurit",
    "wof:placetype":"locality"
},
  "geometry": {"coordinates":[35.55,5.95],"type":"Point"}
}