{
  "type": "Feature",
  "properties": {
    "gn:admin1_code":"53",
    "gn:asciiname":"Ts'ahlo",
    "gn:country_code":"ET",
    "gn:dem":2038,
    "gn:feature_class":"P",
    "gn:feature_code":"PPL",
    "gn:name":"Ts\u2019ahlo",
    "gn:population":0,
    "gn:timezone":"Africa/Addis_Ababa",
    "iso:country":"ET",
    "name:und_x_variant":[
        "Tsakhlo",
        "Ts\u2019ahlo"
    ],
    "wof:name":"Ts'ahlo",
    "wof:placetype":"locality"
},
  "geometry": {"coordinates":[39.46709,13.63067],"type":"Point"}
}