{
  "type": "Feature",
  "properties": {
    "gn:admin1_code":"52",
    "gn:asciiname":"Hosale",
    "gn:country_code":"ET",
    "gn:dem":1824,
    "gn:feature_class":"P",
    "gn:feature_code":"PPL",
    "gn:name":"Hosal\u0113",
    "gn:population":0,
    "gn:timezone":"Africa/Addis_Ababa",
    "iso:country":"ET",
    "name:und_x_variant":[
        "Khosale",
        "Hosal\u0113"
    ],
    "wof:name":"Hosale",
    "wof:placetype":"locality"
},
  "geometry": {"coordinates":[42.73833,9.49944],"type":"Point"}
}