{
  "type": "Feature",
  "properties": {
    "gn:admin1_code":"46",
    "gn:asciiname":"Wenjet'a",
    "gn:country_code":"ET",
    "gn:dem":1810,
    "gn:feature_class":"P",
    "gn:feature_code":"PPL",
    "gn:name":"Wenj\u0113t\u2019a",
    "gn:population":0,
    "gn:timezone":"Africa/Addis_Ababa",
    "iso:country":"ET",
    "wof:name":"Wenjet'a",
    "wof:placetype":"locality"
},
  "geometry": {"coordinates":[37.28333,11.68333],"type":"Point"}
}