{
  "type": "Feature",
  "properties": {
    "gn:admin1_code":"53.0",
    "gn:asciiname":"Addi Gui",
    "gn:country_code":"ET",
    "gn:dem":2043,
    "gn:feature_class":"P",
    "gn:feature_code":"PPL",
    "gn:name":"Addi Gui",
    "gn:population":0,
    "gn:timezone":"Africa/Addis_Ababa",
    "iso:country":"ET",
    "name:und_x_variant":[
        "\u0100d\u012b Gu\u2019\u012b"
    ],
    "wof:name":"Addi Gui",
    "wof:placetype":"locality"
},
  "geometry": {"coordinates":[38.67861,14.0625],"type":"Point"}
}