{
  "type": "Feature",
  "properties": {
    "gn:admin1_code":"49.0",
    "gn:asciiname":"Madding",
    "gn:country_code":"ET",
    "gn:dem":417,
    "gn:feature_class":"P",
    "gn:feature_code":"PPL",
    "gn:name":"Madding",
    "gn:population":0,
    "gn:timezone":"Africa/Addis_Ababa",
    "iso:country":"ET",
    "name:und_x_variant":[
        "Mading",
        "Madding"
    ],
    "wof:name":"Madding",
    "wof:placetype":"locality"
},
  "geometry": {"coordinates":[33.82562,8.36],"type":"Point"}
}