{
  "type": "Feature",
  "properties": {
    "gn:admin1_code":"51",
    "gn:asciiname":"Menole",
    "gn:country_code":"ET",
    "gn:dem":2288,
    "gn:feature_class":"P",
    "gn:feature_code":"PPL",
    "gn:name":"Menol\u0113",
    "gn:population":0,
    "gn:timezone":"Africa/Addis_Ababa",
    "iso:country":"ET",
    "wof:name":"Menole",
    "wof:placetype":"locality"
},
  "geometry": {"coordinates":[38.88333,8.93333],"type":"Point"}
}