{
  "type": "Feature",
  "properties": {
    "gn:admin1_code":"54",
    "gn:asciiname":"Shenk'ola",
    "gn:country_code":"ET",
    "gn:dem":2156,
    "gn:feature_class":"P",
    "gn:feature_code":"PPL",
    "gn:name":"Shenk\u2019ola",
    "gn:population":0,
    "gn:timezone":"Africa/Addis_Ababa",
    "iso:country":"ET",
    "wof:name":"Shenk'ola",
    "wof:placetype":"locality"
},
  "geometry": {"coordinates":[37.76667,7.46667],"type":"Point"}
}