{
  "type": "Feature",
  "properties": {
    "gn:admin1_code":"53.0",
    "gn:asciiname":"Adi Ahiu",
    "gn:country_code":"ET",
    "gn:dem":1740,
    "gn:feature_class":"P",
    "gn:feature_code":"PPL",
    "gn:name":"Adi Ahiu",
    "gn:population":0,
    "gn:timezone":"Africa/Addis_Ababa",
    "iso:country":"ET",
    "wof:name":"Adi Ahiu",
    "wof:placetype":"locality"
},
  "geometry": {"coordinates":[39.08414000000001,13.96205],"type":"Point"}
}