{
  "type": "Feature",
  "properties": {
    "gn:admin1_code":"27.0",
    "gn:asciiname":"Merhabiete",
    "gn:country_code":"ET",
    "gn:dem":2215,
    "gn:feature_class":"P",
    "gn:feature_code":"PPL",
    "gn:name":"Merhabiete",
    "gn:population":0,
    "gn:timezone":"Africa/Addis_Ababa",
    "iso:country":"ET",
    "wof:name":"Merhabiete",
    "wof:placetype":"locality"
},
  "geometry": {"coordinates":[38.75,10.25],"type":"Point"}
}