{
  "type": "Feature",
  "properties": {
    "gn:admin1_code":"45.0",
    "gn:asciiname":"Daratakna",
    "gn:country_code":"ET",
    "gn:dem":632,
    "gn:feature_class":"P",
    "gn:feature_code":"PPL",
    "gn:name":"Daratakna",
    "gn:population":0,
    "gn:timezone":"Africa/Addis_Ababa",
    "iso:country":"ET",
    "wof:name":"Daratakna",
    "wof:placetype":"locality"
},
  "geometry": {"coordinates":[40.11199000000001,13.50622],"type":"Point"}
}