{
  "type": "Feature",
  "properties": {
    "gn:admin1_code":"46",
    "gn:asciiname":"K'want'any",
    "gn:country_code":"ET",
    "gn:dem":2801,
    "gn:feature_class":"P",
    "gn:feature_code":"PPL",
    "gn:name":"K\u2019want\u2019any",
    "gn:population":0,
    "gn:timezone":"Africa/Addis_Ababa",
    "iso:country":"ET",
    "wof:name":"K'want'any",
    "wof:placetype":"locality"
},
  "geometry": {"coordinates":[39.49755,10.39193],"type":"Point"}
}