{
  "type": "Feature",
  "properties": {
    "gn:admin1_code":"52",
    "gn:asciiname":"Duscia Milmil",
    "gn:country_code":"ET",
    "gn:dem":1277,
    "gn:feature_class":"P",
    "gn:feature_code":"PPL",
    "gn:name":"Duscia Milmil",
    "gn:population":0,
    "gn:timezone":"Africa/Addis_Ababa",
    "iso:country":"ET",
    "wof:name":"Duscia Milmil",
    "wof:placetype":"locality"
},
  "geometry": {"coordinates":[43.85639000000001,8.41972],"type":"Point"}
}