{
  "type": "Feature",
  "properties": {
    "gn:admin1_code":"54",
    "gn:asciiname":"Sciaco",
    "gn:country_code":"ET",
    "gn:dem":1067,
    "gn:feature_class":"P",
    "gn:feature_code":"PPL",
    "gn:name":"Sciaco",
    "gn:population":0,
    "gn:timezone":"Africa/Addis_Ababa",
    "iso:country":"ET",
    "wof:name":"Sciaco",
    "wof:placetype":"locality"
},
  "geometry": {"coordinates":[35.41667,7.05],"type":"Point"}
}