{
  "type": "Feature",
  "properties": {
    "gn:admin1_code":"51",
    "gn:asciiname":"Gubal",
    "gn:country_code":"ET",
    "gn:dem":1936,
    "gn:feature_class":"P",
    "gn:feature_code":"PPL",
    "gn:name":"Gubal",
    "gn:population":0,
    "gn:timezone":"Africa/Addis_Ababa",
    "iso:country":"ET",
    "name:deu_x_preferred":[
        "Gubal"
    ],
    "wof:name":"Gubal",
    "wof:placetype":"locality"
},
  "geometry": {"coordinates":[37.96667,4.28333],"type":"Point"}
}