{
  "type": "Feature",
  "properties": {
    "gn:admin1_code":"51.0",
    "gn:asciiname":"Abebe",
    "gn:country_code":"ET",
    "gn:dem":1880,
    "gn:feature_class":"P",
    "gn:feature_code":"PPL",
    "gn:name":"\u0100b\u0113b\u0113",
    "gn:population":0,
    "gn:timezone":"Africa/Addis_Ababa",
    "iso:country":"ET",
    "wof:name":"Abebe",
    "wof:placetype":"locality"
},
  "geometry": {"coordinates":[38.06667,9.41667],"type":"Point"}
}