{
  "type": "Feature",
  "properties": {
    "gn:admin1_code":"47",
    "gn:asciiname":"Ganeberri",
    "gn:country_code":"ET",
    "gn:dem":713,
    "gn:feature_class":"P",
    "gn:feature_code":"PPL",
    "gn:name":"Ganeberri",
    "gn:population":0,
    "gn:timezone":"Africa/Addis_Ababa",
    "iso:country":"ET",
    "name:und_x_variant":[
        "Ganaberri",
        "Ganeberri"
    ],
    "wof:name":"Ganeberri",
    "wof:placetype":"locality"
},
  "geometry": {"coordinates":[34.78333,10.73333],"type":"Point"}
}