{
  "type": "Feature",
  "properties": {
    "gn:admin1_code":"52.0",
    "gn:asciiname":"Adur",
    "gn:country_code":"ET",
    "gn:dem":551,
    "gn:feature_class":"P",
    "gn:feature_code":"PPL",
    "gn:name":"Adur",
    "gn:population":0,
    "gn:timezone":"Africa/Addis_Ababa",
    "iso:country":"ET",
    "wof:name":"Adur",
    "wof:placetype":"locality"
},
  "geometry": {"coordinates":[43.49778,5.5225],"type":"Point"}
}