{
  "type": "Feature",
  "properties": {
    "gn:admin1_code":"52.0",
    "gn:asciiname":"Adur",
    "gn:country_code":"ET",
    "gn:dem":551,
    "gn:feature_class":"P",
    "gn:feature_code":"PPL",
    "gn:name":"Adur",
    "gn:population":0,
    "gn:timezone":"Africa/Addis_Ababa",
    "iso:country":"ET",
    "name:cat_x_preferred":[
        "Adur"
    ],
    "name:ceb_x_preferred":[
        "Adur"
    ],
    "name:deu_x_preferred":[
        "Adur"
    ],
    "name:fra_x_preferred":[
        "Adur"
    ],
    "name:kat_x_preferred":[
        "\u10d0\u10d3\u10e3\u10e0\u10d8"
    ],
    "name:pol_x_preferred":[
        "Adur"
    ],
    "name:rus_x_preferred":[
        "\u0410\u0434\u0443\u0440"
    ],
    "name:spa_x_preferred":[
        "Adur"
    ],
    "name:swe_x_preferred":[
        "Adur"
    ],
    "wof:name":"Adur",
    "wof:placetype":"locality"
},
  "geometry": {"coordinates":[43.49778,5.5225],"type":"Point"}
}