{
  "type": "Feature",
  "properties": {
    "gn:admin1_code":"27.0",
    "gn:asciiname":"Lome",
    "gn:country_code":"ET",
    "gn:dem":1850,
    "gn:feature_class":"P",
    "gn:feature_code":"PPL",
    "gn:name":"Lome",
    "gn:population":0,
    "gn:timezone":"Africa/Addis_Ababa",
    "iso:country":"ET",
    "name:bos_x_preferred":[
        "Lome"
    ],
    "name:ceb_x_preferred":[
        "Lome"
    ],
    "name:sco_x_preferred":[
        "Lome"
    ],
    "name:swe_x_preferred":[
        "Lome"
    ],
    "wof:name":"Lome",
    "wof:placetype":"locality"
},
  "geometry": {"coordinates":[39.16667,8.58333],"type":"Point"}
}