{
  "type": "Feature",
  "properties": {
    "gn:admin1_code":"53",
    "gn:asciiname":"Mai Uaro",
    "gn:country_code":"ET",
    "gn:dem":2056,
    "gn:feature_class":"P",
    "gn:feature_code":"PPL",
    "gn:name":"Mai Uaro",
    "gn:population":0,
    "gn:timezone":"Africa/Addis_Ababa",
    "iso:country":"ET",
    "wof:name":"Mai Uaro",
    "wof:placetype":"locality"
},
  "geometry": {"coordinates":[38.86267,14.25925],"type":"Point"}
}