{
  "type": "Feature",
  "properties": {
    "gn:admin1_code":"46",
    "gn:asciiname":"Mek'enach'o",
    "gn:country_code":"ET",
    "gn:dem":2421,
    "gn:feature_class":"P",
    "gn:feature_code":"PPL",
    "gn:name":"Mek\u2019enach\u2019o",
    "gn:population":0,
    "gn:timezone":"Africa/Addis_Ababa",
    "iso:country":"ET",
    "wof:name":"Mek'enach'o",
    "wof:placetype":"locality"
},
  "geometry": {"coordinates":[39.52294000000001,9.97652],"type":"Point"}
}