{
  "type": "Feature",
  "properties": {
    "gn:admin1_code":"51",
    "gn:asciiname":"Dolo",
    "gn:country_code":"ET",
    "gn:dem":1905,
    "gn:feature_class":"P",
    "gn:feature_code":"PPL",
    "gn:name":"Dolo",
    "gn:population":0,
    "gn:timezone":"Africa/Addis_Ababa",
    "iso:country":"ET",
    "wof:name":"Dolo",
    "wof:placetype":"locality"
},
  "geometry": {"coordinates":[39.01667,8.66667],"type":"Point"}
}