{
  "type": "Feature",
  "properties": {
    "gn:admin1_code":"51",
    "gn:asciiname":"Dolo",
    "gn:country_code":"ET",
    "gn:dem":1905,
    "gn:feature_class":"P",
    "gn:feature_code":"PPL",
    "gn:name":"Dolo",
    "gn:population":0,
    "gn:timezone":"Africa/Addis_Ababa",
    "iso:country":"ET",
    "name:azb_x_preferred":[
        "\u062f\u0648\u0644\u0648"
    ],
    "name:bul_x_preferred":[
        "\u0414\u043e\u043b\u043e"
    ],
    "name:cat_x_preferred":[
        "Dolo"
    ],
    "name:ceb_x_preferred":[
        "Dolo"
    ],
    "name:ces_x_preferred":[
        "Dolo"
    ],
    "name:deu_x_preferred":[
        "Dolo"
    ],
    "name:epo_x_preferred":[
        "Dolo"
    ],
    "name:eus_x_preferred":[
        "Dolo"
    ],
    "name:fas_x_preferred":[
        "\u062f\u0648\u0644\u0648"
    ],
    "name:fra_x_preferred":[
        "Dolo"
    ],
    "name:glg_x_preferred":[
        "Dolo"
    ],
    "name:hun_x_preferred":[
        "Dolo"
    ],
    "name:hye_x_preferred":[
        "\u0534\u0578\u056c\u0578"
    ],
    "name:ind_x_preferred":[
        "Dolo"
    ],
    "name:ita_x_preferred":[
        "Dolo"
    ],
    "name:jpn_x_preferred":[
        "\u30c9\u30fc\u30ed"
    ],
    "name:kaz_x_preferred":[
        "\u0414\u043e\u043b\u043e"
    ],
    "name:lat_x_preferred":[
        "Daulum"
    ],
    "name:lmo_x_preferred":[
        "Dolo"
    ],
    "name:msa_x_preferred":[
        "Dolo"
    ],
    "name:nap_x_preferred":[
        "Dolo"
    ],
    "name:nld_x_preferred":[
        "Dolo"
    ],
    "name:pms_x_preferred":[
        "Dolo"
    ],
    "name:pol_x_preferred":[
        "Dolo"
    ],
    "name:por_x_preferred":[
        "Dolo"
    ],
    "name:ron_x_preferred":[
        "Dolo"
    ],
    "name:rus_x_preferred":[
        "\u0414\u043e\u043b\u043e"
    ],
    "name:scn_x_preferred":[
        "Dolo"
    ],
    "name:spa_x_preferred":[
        "Dolo"
    ],
    "name:srp_x_preferred":[
        "\u0414\u043e\u043b\u043e"
    ],
    "name:tgl_x_preferred":[
        "Dolo"
    ],
    "name:ukr_x_preferred":[
        "\u0414\u043e\u043b\u043e"
    ],
    "name:vec_x_preferred":[
        "El Do\u0142o"
    ],
    "name:vie_x_preferred":[
        "Dolo"
    ],
    "name:vol_x_preferred":[
        "Dolo"
    ],
    "name:war_x_preferred":[
        "Dolo"
    ],
    "wof:name":"Dolo",
    "wof:placetype":"locality"
},
  "geometry": {"coordinates":[39.01667,8.66667],"type":"Point"}
}