{
  "type": "Feature",
  "properties": {
    "gn:admin1_code":"51",
    "gn:asciiname":"Tulu Neboye",
    "gn:country_code":"ET",
    "gn:dem":2508,
    "gn:feature_class":"P",
    "gn:feature_code":"PPL",
    "gn:name":"Tulu Neboy\u0113",
    "gn:population":0,
    "gn:timezone":"Africa/Addis_Ababa",
    "iso:country":"ET",
    "name:und_x_variant":[
        "Tulu Naboy\u0113",
        "Tulu Neboy\u0113"
    ],
    "wof:name":"Tulu Neboye",
    "wof:placetype":"locality"
},
  "geometry": {"coordinates":[37.08333,9.63333],"type":"Point"}
}