{
  "type": "Feature",
  "properties": {
    "gn:admin1_code":"46",
    "gn:asciiname":"Gurbiya",
    "gn:country_code":"ET",
    "gn:dem":2796,
    "gn:feature_class":"P",
    "gn:feature_code":"PPL",
    "gn:name":"Gurb\u012bya",
    "gn:population":0,
    "gn:timezone":"Africa/Addis_Ababa",
    "iso:country":"ET",
    "wof:name":"Gurbiya",
    "wof:placetype":"locality"
},
  "geometry": {"coordinates":[39.21667,11.28333],"type":"Point"}
}