{
  "type": "Feature",
  "properties": {
    "gn:admin1_code":"46.0",
    "gn:asciiname":"Dinbar",
    "gn:country_code":"ET",
    "gn:dem":2875,
    "gn:feature_class":"P",
    "gn:feature_code":"PPL",
    "gn:name":"Dinbar",
    "gn:population":0,
    "gn:timezone":"Africa/Addis_Ababa",
    "iso:country":"ET",
    "name:und_x_variant":[
        "Dinbaro"
    ],
    "wof:name":"Dinbar",
    "wof:placetype":"locality"
},
  "geometry": {"coordinates":[39.63508,9.71214],"type":"Point"}
}