{
  "type": "Feature",
  "properties": {
    "gn:admin1_code":"53",
    "gn:asciiname":"Mai Uollel",
    "gn:country_code":"ET",
    "gn:dem":1860,
    "gn:feature_class":"P",
    "gn:feature_code":"PPL",
    "gn:name":"Mai Uollel",
    "gn:population":0,
    "gn:timezone":"Africa/Addis_Ababa",
    "iso:country":"ET",
    "wof:name":"Mai Uollel",
    "wof:placetype":"locality"
},
  "geometry": {"coordinates":[38.71667,14.21667],"type":"Point"}
}