{
  "type": "Feature",
  "properties": {
    "gn:admin1_code":"52",
    "gn:asciiname":"Gandaba",
    "gn:country_code":"ET",
    "gn:dem":1023,
    "gn:feature_class":"P",
    "gn:feature_code":"PPL",
    "gn:name":"Gandaba",
    "gn:population":0,
    "gn:timezone":"Africa/Addis_Ababa",
    "iso:country":"ET",
    "name:rus_x_preferred":[
        "\u0413\u0430\u043d\u0434\u0430\u0431\u0430"
    ],
    "name:und_x_variant":[
        "Gandabal",
        "Gundabella",
        "Gandaba"
    ],
    "wof:name":"Gandaba",
    "wof:placetype":"locality"
},
  "geometry": {"coordinates":[42.1846,7.82818],"type":"Point"}
}