{
  "type": "Feature",
  "properties": {
    "gn:admin1_code":"46",
    "gn:asciiname":"Zalma",
    "gn:country_code":"ET",
    "gn:dem":2020,
    "gn:feature_class":"P",
    "gn:feature_code":"PPL",
    "gn:name":"Zalma",
    "gn:population":0,
    "gn:timezone":"Africa/Addis_Ababa",
    "iso:country":"ET",
    "wof:name":"Zalma",
    "wof:placetype":"locality"
},
  "geometry": {"coordinates":[37.56667,11.66667],"type":"Point"}
}