{
  "type": "Feature",
  "properties": {
    "gn:admin1_code":"46.0",
    "gn:asciiname":"Adis Amba",
    "gn:country_code":"ET",
    "gn:dem":2656,
    "gn:feature_class":"P",
    "gn:feature_code":"PPL",
    "gn:name":"Adis Amba",
    "gn:population":0,
    "gn:timezone":"Africa/Addis_Ababa",
    "iso:country":"ET",
    "wof:name":"Adis Amba",
    "wof:placetype":"locality"
},
  "geometry": {"coordinates":[39.61879,9.527],"type":"Point"}
}