{
  "type": "Feature",
  "properties": {
    "gn:admin1_code":"51",
    "gn:asciiname":"Werenso",
    "gn:country_code":"ET",
    "gn:dem":1927,
    "gn:feature_class":"P",
    "gn:feature_code":"PPL",
    "gn:name":"Wer\u0113nso",
    "gn:population":0,
    "gn:timezone":"Africa/Addis_Ababa",
    "iso:country":"ET",
    "wof:name":"Werenso",
    "wof:placetype":"locality"
},
  "geometry": {"coordinates":[39.75,8.41667],"type":"Point"}
}