{
  "type": "Feature",
  "properties": {
    "gn:admin1_code":"51",
    "gn:asciiname":"Harbu Didibe",
    "gn:country_code":"ET",
    "gn:dem":2421,
    "gn:feature_class":"P",
    "gn:feature_code":"PPL",
    "gn:name":"Harbu D\u012bd\u012bb\u0113",
    "gn:population":0,
    "gn:timezone":"Africa/Addis_Ababa",
    "iso:country":"ET",
    "wof:name":"Harbu Didibe",
    "wof:placetype":"locality"
},
  "geometry": {"coordinates":[37.18333,9.91667],"type":"Point"}
}