{
  "type": "Feature",
  "properties": {
    "gn:admin1_code":"45.0",
    "gn:asciiname":"Berga",
    "gn:country_code":"ET",
    "gn:dem":350,
    "gn:feature_class":"P",
    "gn:feature_code":"PPL",
    "gn:name":"Berga",
    "gn:population":0,
    "gn:timezone":"Africa/Addis_Ababa",
    "iso:country":"ET",
    "wof:name":"Berga",
    "wof:placetype":"locality"
},
  "geometry": {"coordinates":[41.50105,11.51002],"type":"Point"}
}