{
  "type": "Feature",
  "properties": {
    "gn:admin1_code":"51",
    "gn:asciiname":"Kotu Gebeya",
    "gn:country_code":"ET",
    "gn:dem":2842,
    "gn:feature_class":"P",
    "gn:feature_code":"PPL",
    "gn:name":"Kotu Gebeya",
    "gn:population":0,
    "gn:timezone":"Africa/Addis_Ababa",
    "iso:country":"ET",
    "wof:name":"Kotu Gebeya",
    "wof:placetype":"locality"
},
  "geometry": {"coordinates":[39.39596,9.38692],"type":"Point"}
}