{
  "type": "Feature",
  "properties": {
    "gn:admin1_code":"51",
    "gn:asciiname":"Gimbas",
    "gn:country_code":"ET",
    "gn:dem":2136,
    "gn:feature_class":"P",
    "gn:feature_code":"PPL",
    "gn:name":"Gimbas",
    "gn:population":0,
    "gn:timezone":"Africa/Addis_Ababa",
    "iso:country":"ET",
    "wof:name":"Gimbas",
    "wof:placetype":"locality"
},
  "geometry": {"coordinates":[38.46667,9.46667],"type":"Point"}
}