{
  "type": "Feature",
  "properties": {
    "gn:admin1_code":"46",
    "gn:asciiname":"Laydanis",
    "gn:country_code":"ET",
    "gn:dem":2903,
    "gn:feature_class":"P",
    "gn:feature_code":"PPL",
    "gn:name":"Laydanis",
    "gn:population":0,
    "gn:timezone":"Africa/Addis_Ababa",
    "iso:country":"ET",
    "wof:name":"Laydanis",
    "wof:placetype":"locality"
},
  "geometry": {"coordinates":[39.53842,9.20746],"type":"Point"}
}