{
  "type": "Feature",
  "properties": {
    "gn:admin1_code":"46.0",
    "gn:asciiname":"Anchi Awgi",
    "gn:country_code":"ET",
    "gn:dem":2636,
    "gn:feature_class":"P",
    "gn:feature_code":"PPL",
    "gn:name":"\u0100nch\u012b \u0100wg\u012b",
    "gn:population":0,
    "gn:timezone":"Africa/Addis_Ababa",
    "iso:country":"ET",
    "wof:name":"Anchi Awgi",
    "wof:placetype":"locality"
},
  "geometry": {"coordinates":[39.37247,9.31452],"type":"Point"}
}