{
  "type": "Feature",
  "properties": {
    "gn:admin1_code":"51",
    "gn:asciiname":"Jilbo",
    "gn:country_code":"ET",
    "gn:dem":1417,
    "gn:feature_class":"P",
    "gn:feature_code":"PPL",
    "gn:name":"J\u012blbo",
    "gn:population":0,
    "gn:timezone":"Africa/Addis_Ababa",
    "iso:country":"ET",
    "name:und_x_variant":[
        "Sarcama",
        "J\u012blbo"
    ],
    "wof:name":"Jilbo",
    "wof:placetype":"locality"
},
  "geometry": {"coordinates":[41.62083,9.51833],"type":"Point"}
}