{
  "type": "Feature",
  "properties": {
    "gn:admin1_code":"54",
    "gn:asciiname":"Homi",
    "gn:country_code":"ET",
    "gn:dem":1699,
    "gn:feature_class":"P",
    "gn:feature_code":"PPL",
    "gn:name":"Homi",
    "gn:population":0,
    "gn:timezone":"Africa/Addis_Ababa",
    "iso:country":"ET",
    "wof:name":"Homi",
    "wof:placetype":"locality"
},
  "geometry": {"coordinates":[35.36667,7.48333],"type":"Point"}
}