{
  "type": "Feature",
  "properties": {
    "gn:admin1_code":"51",
    "gn:asciiname":"Megala",
    "gn:country_code":"ET",
    "gn:dem":1344,
    "gn:feature_class":"P",
    "gn:feature_code":"PPL",
    "gn:name":"Megala",
    "gn:population":0,
    "gn:timezone":"Africa/Addis_Ababa",
    "iso:country":"ET",
    "wof:name":"Megala",
    "wof:placetype":"locality"
},
  "geometry": {"coordinates":[41.20387,8.33737],"type":"Point"}
}