{
  "type": "Feature",
  "properties": {
    "gn:admin1_code":"46",
    "gn:asciiname":"Kore",
    "gn:country_code":"ET",
    "gn:dem":2713,
    "gn:feature_class":"P",
    "gn:feature_code":"PPL",
    "gn:name":"Kor\u0113",
    "gn:population":0,
    "gn:timezone":"Africa/Addis_Ababa",
    "iso:country":"ET",
    "name:bre_x_preferred":[
        "Kore"
    ],
    "name:cat_x_preferred":[
        "Kore"
    ],
    "name:ceb_x_preferred":[
        "Kore"
    ],
    "name:cym_x_preferred":[
        "Kore"
    ],
    "name:dan_x_preferred":[
        "Kore"
    ],
    "name:deu_x_preferred":[
        "Kore"
    ],
    "name:ell_x_preferred":[
        "\u039a\u03cc\u03c1\u03b7"
    ],
    "name:est_x_preferred":[
        "Kore"
    ],
    "name:fin_x_preferred":[
        "Kore"
    ],
    "name:fra_x_preferred":[
        "Kore"
    ],
    "name:ita_x_preferred":[
        "Kore"
    ],
    "name:kur_x_preferred":[
        "Kore"
    ],
    "name:nld_x_preferred":[
        "Kore"
    ],
    "name:nor_x_preferred":[
        "Kore"
    ],
    "name:rus_x_preferred":[
        "\u041a\u043e\u0440\u0435"
    ],
    "name:swe_x_preferred":[
        "Kore"
    ],
    "name:tur_x_preferred":[
        "Kore"
    ],
    "wof:name":"Kore",
    "wof:placetype":"locality"
},
  "geometry": {"coordinates":[39.14868,10.74852],"type":"Point"}
}