{
  "type": "Feature",
  "properties": {
    "gn:admin1_code":"51.0",
    "gn:asciiname":"Alga",
    "gn:country_code":"ET",
    "gn:dem":1661,
    "gn:feature_class":"P",
    "gn:feature_code":"PPL",
    "gn:name":"\u0100lga",
    "gn:population":0,
    "gn:timezone":"Africa/Addis_Ababa",
    "iso:country":"ET",
    "wof:name":"Alga",
    "wof:placetype":"locality"
},
  "geometry": {"coordinates":[35.43333,8.55],"type":"Point"}
}