{
  "type": "Feature",
  "properties": {
    "gn:admin1_code":"53",
    "gn:asciiname":"Gunya",
    "gn:country_code":"ET",
    "gn:dem":2300,
    "gn:feature_class":"P",
    "gn:feature_code":"PPL",
    "gn:name":"Gunya",
    "gn:population":0,
    "gn:timezone":"Africa/Addis_Ababa",
    "iso:country":"ET",
    "wof:name":"Gunya",
    "wof:placetype":"locality"
},
  "geometry": {"coordinates":[39.2308,14.22007],"type":"Point"}
}