{
  "type": "Feature",
  "properties": {
    "gn:admin1_code":"53",
    "gn:asciiname":"Geregidi",
    "gn:country_code":"ET",
    "gn:dem":1837,
    "gn:feature_class":"P",
    "gn:feature_code":"PPL",
    "gn:name":"Geregid\u012b",
    "gn:population":0,
    "gn:timezone":"Africa/Addis_Ababa",
    "iso:country":"ET",
    "wof:name":"Geregidi",
    "wof:placetype":"locality"
},
  "geometry": {"coordinates":[39.31396,13.44486],"type":"Point"}
}