{
  "type": "Feature",
  "properties": {
    "gn:admin1_code":"46",
    "gn:asciiname":"K'ach'ur",
    "gn:country_code":"ET",
    "gn:dem":1430,
    "gn:feature_class":"P",
    "gn:feature_code":"PPL",
    "gn:name":"K\u2019ach\u2019ur",
    "gn:population":0,
    "gn:timezone":"Africa/Addis_Ababa",
    "iso:country":"ET",
    "wof:name":"K'ach'ur",
    "wof:placetype":"locality"
},
  "geometry": {"coordinates":[39.84198,10.72529],"type":"Point"}
}