{
  "type": "Feature",
  "properties": {
    "gn:admin1_code":"52.0",
    "gn:asciiname":"Beley",
    "gn:country_code":"ET",
    "gn:dem":1841,
    "gn:feature_class":"P",
    "gn:feature_code":"PPL",
    "gn:name":"Bel\u0113y",
    "gn:population":0,
    "gn:timezone":"Africa/Addis_Ababa",
    "iso:country":"ET",
    "wof:name":"Beley",
    "wof:placetype":"locality"
},
  "geometry": {"coordinates":[42.93194,9.56194],"type":"Point"}
}