{
  "type": "Feature",
  "properties": {
    "gn:admin1_code":"51",
    "gn:asciiname":"Sefane",
    "gn:country_code":"ET",
    "gn:dem":2709,
    "gn:feature_class":"P",
    "gn:feature_code":"PPL",
    "gn:name":"Sefan\u0113",
    "gn:population":0,
    "gn:timezone":"Africa/Addis_Ababa",
    "iso:country":"ET",
    "wof:name":"Sefane",
    "wof:placetype":"locality"
},
  "geometry": {"coordinates":[38.76667,9.75],"type":"Point"}
}