{
  "type": "Feature",
  "properties": {
    "gn:admin1_code":"51.0",
    "gn:asciiname":"Dar Dabat",
    "gn:country_code":"ET",
    "gn:dem":1205,
    "gn:feature_class":"P",
    "gn:feature_code":"PPL",
    "gn:name":"Dar Dabat",
    "gn:population":0,
    "gn:timezone":"Africa/Addis_Ababa",
    "iso:country":"ET",
    "wof:name":"Dar Dabat",
    "wof:placetype":"locality"
},
  "geometry": {"coordinates":[39.91667,4.65],"type":"Point"}
}