{
  "type": "Feature",
  "properties": {
    "gn:admin1_code":"51",
    "gn:asciiname":"K'et'k'et'o",
    "gn:country_code":"ET",
    "gn:dem":2545,
    "gn:feature_class":"P",
    "gn:feature_code":"PPL",
    "gn:name":"K\u2019et\u2019k\u2019et\u2019o",
    "gn:population":0,
    "gn:timezone":"Africa/Addis_Ababa",
    "iso:country":"ET",
    "wof:name":"K'et'k'et'o",
    "wof:placetype":"locality"
},
  "geometry": {"coordinates":[38.21667,9.38333],"type":"Point"}
}