{
  "type": "Feature",
  "properties": {
    "gn:admin1_code":"51",
    "gn:asciiname":"Hena",
    "gn:country_code":"ET",
    "gn:dem":1931,
    "gn:feature_class":"P",
    "gn:feature_code":"PPL",
    "gn:name":"H\u0113na",
    "gn:population":0,
    "gn:timezone":"Africa/Addis_Ababa",
    "iso:country":"ET",
    "name:deu_x_preferred":[
        "Hena"
    ],
    "wof:name":"Hena",
    "wof:placetype":"locality"
},
  "geometry": {"coordinates":[36.95,9.31667],"type":"Point"}
}