{
  "type": "Feature",
  "properties": {
    "gn:admin1_code":"53",
    "gn:asciiname":"Era",
    "gn:country_code":"ET",
    "gn:dem":2206,
    "gn:feature_class":"P",
    "gn:feature_code":"PPL",
    "gn:name":"\u0112ra",
    "gn:population":0,
    "gn:timezone":"Africa/Addis_Ababa",
    "iso:country":"ET",
    "wof:name":"Era",
    "wof:placetype":"locality"
},
  "geometry": {"coordinates":[39.73333,13.76667],"type":"Point"}
}