{
  "type": "Feature",
  "properties": {
    "gn:admin1_code":"53",
    "gn:asciiname":"Era",
    "gn:country_code":"ET",
    "gn:dem":2206,
    "gn:feature_class":"P",
    "gn:feature_code":"PPL",
    "gn:name":"\u0112ra",
    "gn:population":0,
    "gn:timezone":"Africa/Addis_Ababa",
    "iso:country":"ET",
    "name:aze_x_preferred":[
        "Era"
    ],
    "name:bul_x_preferred":[
        "\u0415\u0440\u0430"
    ],
    "name:cat_x_preferred":[
        "Era"
    ],
    "name:deu_x_preferred":[
        "\u00c4ra"
    ],
    "name:epo_x_preferred":[
        "Erao"
    ],
    "name:est_x_preferred":[
        "Ajastu"
    ],
    "name:fas_x_preferred":[
        "\u062f\u0648\u0631\u0627\u0646"
    ],
    "name:hrv_x_preferred":[
        "Era"
    ],
    "name:isl_x_preferred":[
        "T\u00edmabil"
    ],
    "name:ita_x_preferred":[
        "Era"
    ],
    "name:kan_x_preferred":[
        "\u0caf\u0cc1\u0c97"
    ],
    "name:kaz_x_preferred":[
        "\u0417\u0430\u043c\u0430\u043d"
    ],
    "name:kir_x_preferred":[
        "\u042d\u0440\u0430"
    ],
    "name:mhr_x_preferred":[
        "\u042d\u0440\u0430"
    ],
    "name:mkd_x_preferred":[
        "\u0415\u0440\u0430"
    ],
    "name:nld_x_preferred":[
        "Tijdperk"
    ],
    "name:nor_x_preferred":[
        "\u00c6ra"
    ],
    "name:rus_x_preferred":[
        "\u042d\u0440\u0430"
    ],
    "name:spa_x_preferred":[
        "Era"
    ],
    "name:sqi_x_preferred":[
        "Era"
    ],
    "name:tel_x_preferred":[
        "\u0c36\u0c15\u0c02"
    ],
    "name:tgk_x_preferred":[
        "\u0414\u0430\u0432\u0440\u043e\u043d"
    ],
    "name:tha_x_preferred":[
        "\u0e28\u0e31\u0e01\u0e23\u0e32\u0e0a"
    ],
    "name:urd_x_preferred":[
        "\u0639\u06c1\u062f"
    ],
    "name:uzb_x_preferred":[
        "Era"
    ],
    "wof:name":"Era",
    "wof:placetype":"locality"
},
  "geometry": {"coordinates":[39.73333,13.76667],"type":"Point"}
}