{
  "type": "Feature",
  "properties": {
    "gn:admin1_code":"51",
    "gn:asciiname":"Melke",
    "gn:country_code":"ET",
    "gn:dem":1888,
    "gn:feature_class":"P",
    "gn:feature_code":"PPL",
    "gn:name":"Melk\u0113",
    "gn:population":0,
    "gn:timezone":"Africa/Addis_Ababa",
    "iso:country":"ET",
    "wof:name":"Melke",
    "wof:placetype":"locality"
},
  "geometry": {"coordinates":[38.66667,9.56667],"type":"Point"}
}