{
  "type": "Feature",
  "properties": {
    "gn:admin1_code":"46",
    "gn:asciiname":"Uadi Mena",
    "gn:country_code":"ET",
    "gn:dem":1030,
    "gn:feature_class":"P",
    "gn:feature_code":"PPL",
    "gn:name":"Uadi Mena",
    "gn:population":0,
    "gn:timezone":"Africa/Addis_Ababa",
    "iso:country":"ET",
    "wof:name":"Uadi Mena",
    "wof:placetype":"locality"
},
  "geometry": {"coordinates":[36.51667,12.58333],"type":"Point"}
}