{
  "type": "Feature",
  "properties": {
    "gn:admin1_code":"46.0",
    "gn:asciiname":"Abo Arka",
    "gn:country_code":"ET",
    "gn:dem":1805,
    "gn:feature_class":"P",
    "gn:feature_code":"PPL",
    "gn:name":"\u0100bo \u0100rka",
    "gn:population":0,
    "gn:timezone":"Africa/Addis_Ababa",
    "iso:country":"ET",
    "wof:name":"Abo Arka",
    "wof:placetype":"locality"
},
  "geometry": {"coordinates":[37.61667,12.16667],"type":"Point"}
}