{
  "type": "Feature",
  "properties": {
    "gn:admin1_code":"52.0",
    "gn:asciiname":"Killelu",
    "gn:country_code":"ET",
    "gn:dem":558,
    "gn:feature_class":"P",
    "gn:feature_code":"PPL",
    "gn:name":"Killelu",
    "gn:population":0,
    "gn:timezone":"Africa/Addis_Ababa",
    "iso:country":"ET",
    "name:und_x_variant":[
        "Chillelu"
    ],
    "wof:name":"Killelu",
    "wof:placetype":"locality"
},
  "geometry": {"coordinates":[41.47311,10.59394],"type":"Point"}
}