{
  "type": "Feature",
  "properties": {
    "gn:admin1_code":"54",
    "gn:asciiname":"Gofere",
    "gn:country_code":"ET",
    "gn:dem":1920,
    "gn:feature_class":"P",
    "gn:feature_code":"PPL",
    "gn:name":"Gofer\u0113",
    "gn:population":0,
    "gn:timezone":"Africa/Addis_Ababa",
    "iso:country":"ET",
    "wof:name":"Gofere",
    "wof:placetype":"locality"
},
  "geometry": {"coordinates":[38.16667,7.68333],"type":"Point"}
}