{
  "type": "Feature",
  "properties": {
    "gn:admin1_code":"53",
    "gn:asciiname":"Hulaga",
    "gn:country_code":"ET",
    "gn:dem":1733,
    "gn:feature_class":"P",
    "gn:feature_code":"PPL",
    "gn:name":"Hulaga",
    "gn:population":0,
    "gn:timezone":"Africa/Addis_Ababa",
    "iso:country":"ET",
    "wof:name":"Hulaga",
    "wof:placetype":"locality"
},
  "geometry": {"coordinates":[39.78333,12.46667],"type":"Point"}
}