{
  "type": "Feature",
  "properties": {
    "gn:admin1_code":"46",
    "gn:asciiname":"Zenbar",
    "gn:country_code":"ET",
    "gn:dem":2536,
    "gn:feature_class":"P",
    "gn:feature_code":"PPL",
    "gn:name":"Zenbar",
    "gn:population":0,
    "gn:timezone":"Africa/Addis_Ababa",
    "iso:country":"ET",
    "wof:name":"Zenbar",
    "wof:placetype":"locality"
},
  "geometry": {"coordinates":[39.55668,9.45423],"type":"Point"}
}