{
  "type": "Feature",
  "properties": {
    "gn:admin1_code":"46.0",
    "gn:asciiname":"Arga",
    "gn:country_code":"ET",
    "gn:dem":3451,
    "gn:feature_class":"P",
    "gn:feature_code":"PPL",
    "gn:name":"\u0100rga",
    "gn:population":0,
    "gn:timezone":"Africa/Addis_Ababa",
    "iso:country":"ET",
    "name:deu_x_preferred":[
        "Arga"
    ],
    "name:por_x_preferred":[
        "Arga"
    ],
    "wof:name":"Arga",
    "wof:placetype":"locality"
},
  "geometry": {"coordinates":[38.23333,11.76667],"type":"Point"}
}