{
  "type": "Feature",
  "properties": {
    "gn:admin1_code":"46",
    "gn:asciiname":"Gala K'ibe",
    "gn:country_code":"ET",
    "gn:dem":1842,
    "gn:feature_class":"P",
    "gn:feature_code":"PPL",
    "gn:name":"Gala K\u2019ib\u0113",
    "gn:population":0,
    "gn:timezone":"Africa/Addis_Ababa",
    "iso:country":"ET",
    "wof:name":"Gala K'ibe",
    "wof:placetype":"locality"
},
  "geometry": {"coordinates":[37.71667,11.83333],"type":"Point"}
}