{
  "type": "Feature",
  "properties": {
    "gn:admin1_code":"52",
    "gn:asciiname":"Shaki",
    "gn:country_code":"ET",
    "gn:dem":390,
    "gn:feature_class":"P",
    "gn:feature_code":"PPL",
    "gn:name":"Shaki",
    "gn:population":0,
    "gn:timezone":"Africa/Addis_Ababa",
    "iso:country":"ET",
    "name:und_x_variant":[
        "Sciachissa",
        "Shaki"
    ],
    "wof:name":"Shaki",
    "wof:placetype":"locality"
},
  "geometry": {"coordinates":[41.83333,5.71667],"type":"Point"}
}