{
  "type": "Feature",
  "properties": {
    "gn:admin1_code":"52.0",
    "gn:asciiname":"Burcai",
    "gn:country_code":"ET",
    "gn:dem":1039,
    "gn:feature_class":"P",
    "gn:feature_code":"PPL",
    "gn:name":"Burcai",
    "gn:population":0,
    "gn:timezone":"Africa/Addis_Ababa",
    "iso:country":"ET",
    "name:und_x_variant":[
        "Burkai",
        "Burcai"
    ],
    "wof:name":"Burcai",
    "wof:placetype":"locality"
},
  "geometry": {"coordinates":[41.01667,6.01667],"type":"Point"}
}