{
  "type": "Feature",
  "properties": {
    "gn:admin1_code":"53.0",
    "gn:asciiname":"Bahira",
    "gn:country_code":"ET",
    "gn:dem":2203,
    "gn:feature_class":"P",
    "gn:feature_code":"PPL",
    "gn:name":"Bahira",
    "gn:population":0,
    "gn:timezone":"Africa/Addis_Ababa",
    "iso:country":"ET",
    "name:und_x_variant":[
        "Bakhira"
    ],
    "wof:name":"Bahira",
    "wof:placetype":"locality"
},
  "geometry": {"coordinates":[39.65173,13.91134],"type":"Point"}
}