{
  "type": "Feature",
  "properties": {
    "gn:admin1_code":"53.0",
    "gn:asciiname":"Bahira",
    "gn:country_code":"ET",
    "gn:dem":2203,
    "gn:feature_class":"P",
    "gn:feature_code":"PPL",
    "gn:name":"Bahira",
    "gn:population":0,
    "gn:timezone":"Africa/Addis_Ababa",
    "iso:country":"ET",
    "name:ara_x_preferred":[
        "\u0628\u062d\u064a\u0631\u0649"
    ],
    "name:arz_x_preferred":[
        "\u0628\u062d\u064a\u0631\u0649 \u0627\u0644\u0631\u0627\u0647\u0628"
    ],
    "name:che_x_preferred":[
        "\u0411\u0430\u0445\u044c\u0438\u0440\u0430"
    ],
    "name:deu_x_preferred":[
        "Bah\u012br\u0101"
    ],
    "name:fas_x_preferred":[
        "\u0628\u062d\u06cc\u0631\u0627"
    ],
    "name:fra_x_preferred":[
        "Bahira"
    ],
    "name:hin_x_preferred":[
        "\u092c\u0939\u093f\u0930\u093e"
    ],
    "name:ind_x_preferred":[
        "Buhaira"
    ],
    "name:ita_x_preferred":[
        "Bahira"
    ],
    "name:kaz_x_preferred":[
        "\u0411\u0430\u0445\u0438\u0440\u0430"
    ],
    "name:kor_x_preferred":[
        "\ubc14\ud788\ub77c"
    ],
    "name:msa_x_preferred":[
        "Buhaira"
    ],
    "name:nld_x_preferred":[
        "Bahira-legende"
    ],
    "name:pol_x_preferred":[
        "Bahira"
    ],
    "name:ron_x_preferred":[
        "Bahira"
    ],
    "name:rus_x_preferred":[
        "\u0411\u0430\u0445\u0438\u0440\u0430"
    ],
    "name:spa_x_preferred":[
        "Bahira"
    ],
    "name:sun_x_preferred":[
        "Buhaero"
    ],
    "name:swe_x_preferred":[
        "Bahira"
    ],
    "name:tur_x_preferred":[
        "Bahira"
    ],
    "name:und_x_variant":[
        "Bakhira"
    ],
    "name:urd_x_preferred":[
        "\u0628\u062d\u06cc\u0631\u0627 \u0631\u0627\u06c1\u0628"
    ],
    "wof:name":"Bahira",
    "wof:placetype":"locality"
},
  "geometry": {"coordinates":[39.65173,13.91134],"type":"Point"}
}