{
  "type": "Feature",
  "properties": {
    "gn:admin1_code":"53",
    "gn:asciiname":"Mik'imat' Ariwa",
    "gn:country_code":"ET",
    "gn:dem":2055,
    "gn:feature_class":"P",
    "gn:feature_code":"PPL",
    "gn:name":"Mik\u2019imat\u2019 \u0100riwa",
    "gn:population":0,
    "gn:timezone":"Africa/Addis_Ababa",
    "iso:country":"ET",
    "name:und_x_variant":[
        "Mikimat Ariuo",
        "Mik\u2019imat\u2019 \u0100riwa"
    ],
    "wof:name":"Mik'imat' Ariwa",
    "wof:placetype":"locality"
},
  "geometry": {"coordinates":[39.39544,13.66741],"type":"Point"}
}