{
  "type": "Feature",
  "properties": {
    "gn:admin1_code":"52",
    "gn:asciiname":"Elahmar",
    "gn:country_code":"ET",
    "gn:dem":1812,
    "gn:feature_class":"P",
    "gn:feature_code":"PPL",
    "gn:name":"\u0112lahmar",
    "gn:population":0,
    "gn:timezone":"Africa/Addis_Ababa",
    "iso:country":"ET",
    "name:und_x_variant":[
        "Elakhmar",
        "\u0112lahmar"
    ],
    "wof:name":"Elahmar",
    "wof:placetype":"locality"
},
  "geometry": {"coordinates":[42.85778,9.51667],"type":"Point"}
}