{
  "type": "Feature",
  "properties": {
    "gn:admin1_code":"46.0",
    "gn:asciiname":"Bitilta Zebraro",
    "gn:country_code":"ET",
    "gn:dem":2105,
    "gn:feature_class":"P",
    "gn:feature_code":"PPL",
    "gn:name":"Bitilta Zebraro",
    "gn:population":0,
    "gn:timezone":"Africa/Addis_Ababa",
    "iso:country":"ET",
    "wof:name":"Bitilta Zebraro",
    "wof:placetype":"locality"
},
  "geometry": {"coordinates":[36.78333,10.76667],"type":"Point"}
}