{
  "type": "Feature",
  "properties": {
    "gn:admin1_code":"53.0",
    "gn:asciiname":"Zarmra",
    "gn:country_code":"ET",
    "gn:dem":1415,
    "gn:feature_class":"P",
    "gn:feature_code":"PPL",
    "gn:name":"Zarmra",
    "gn:population":0,
    "gn:timezone":"Africa/Addis_Ababa",
    "iso:country":"ET",
    "wof:name":"Zarmra",
    "wof:placetype":"locality"
},
  "geometry": {"coordinates":[39.0669,13.05855],"type":"Point"}
}