{
  "type": "Feature",
  "properties": {
    "gn:admin1_code":"51",
    "gn:asciiname":"Taleta",
    "gn:country_code":"ET",
    "gn:dem":1655,
    "gn:feature_class":"P",
    "gn:feature_code":"PPL",
    "gn:name":"Taleta",
    "gn:population":0,
    "gn:timezone":"Africa/Addis_Ababa",
    "iso:country":"ET",
    "wof:name":"Taleta",
    "wof:placetype":"locality"
},
  "geometry": {"coordinates":[40.16667,8.71667],"type":"Point"}
}