{
  "type": "Feature",
  "properties": {
    "gn:admin1_code":"46.0",
    "gn:asciiname":"Antagussa",
    "gn:country_code":"ET",
    "gn:dem":1786,
    "gn:feature_class":"P",
    "gn:feature_code":"PPL",
    "gn:name":"Antagussa",
    "gn:population":0,
    "gn:timezone":"Africa/Addis_Ababa",
    "iso:country":"ET",
    "name:und_x_variant":[
        "Atangus\u00e0",
        "Antagussa"
    ],
    "wof:name":"Antagussa",
    "wof:placetype":"locality"
},
  "geometry": {"coordinates":[37.33333,11.66667],"type":"Point"}
}