{
  "type": "Feature",
  "properties": {
    "gn:admin1_code":"51.0",
    "gn:asciiname":"Colba",
    "gn:country_code":"ET",
    "gn:dem":1237,
    "gn:feature_class":"P",
    "gn:feature_code":"PPL",
    "gn:name":"Colba",
    "gn:population":0,
    "gn:timezone":"Africa/Addis_Ababa",
    "iso:country":"ET",
    "wof:name":"Colba",
    "wof:placetype":"locality"
},
  "geometry": {"coordinates":[37.41667,4.83333],"type":"Point"}
}