{
  "type": "Feature",
  "properties": {
    "gn:admin1_code":"51",
    "gn:asciiname":"Ido Dire",
    "gn:country_code":"ET",
    "gn:dem":1808,
    "gn:feature_class":"P",
    "gn:feature_code":"PPL",
    "gn:name":"\u012ado Dir\u0113",
    "gn:population":0,
    "gn:timezone":"Africa/Addis_Ababa",
    "iso:country":"ET",
    "name:und_x_variant":[
        "Ido-Dyre",
        "\u012ado Dir\u0113"
    ],
    "wof:name":"Ido Dire",
    "wof:placetype":"locality"
},
  "geometry": {"coordinates":[41.99806,9.25556],"type":"Point"}
}