{
  "type": "Feature",
  "properties": {
    "gn:admin1_code":"46",
    "gn:asciiname":"Shafi",
    "gn:country_code":"ET",
    "gn:dem":2513,
    "gn:feature_class":"P",
    "gn:feature_code":"PPL",
    "gn:name":"Shaf\u012b",
    "gn:population":0,
    "gn:timezone":"Africa/Addis_Ababa",
    "iso:country":"ET",
    "wof:name":"Shafi",
    "wof:placetype":"locality"
},
  "geometry": {"coordinates":[39.07193,10.53697],"type":"Point"}
}