{
  "type": "Feature",
  "properties": {
    "gn:admin1_code":"46.0",
    "gn:asciiname":"Dibir",
    "gn:country_code":"ET",
    "gn:dem":2272,
    "gn:feature_class":"P",
    "gn:feature_code":"PPL",
    "gn:name":"Dibir",
    "gn:population":0,
    "gn:timezone":"Africa/Addis_Ababa",
    "iso:country":"ET",
    "wof:name":"Dibir",
    "wof:placetype":"locality"
},
  "geometry": {"coordinates":[38.81667,11.73333],"type":"Point"}
}