{
  "type": "Feature",
  "properties": {
    "gn:admin1_code":"51",
    "gn:asciiname":"Gombi",
    "gn:country_code":"ET",
    "gn:dem":1626,
    "gn:feature_class":"P",
    "gn:feature_code":"PPL",
    "gn:name":"Gomb\u012b",
    "gn:population":0,
    "gn:timezone":"Africa/Addis_Ababa",
    "iso:country":"ET",
    "name:ceb_x_preferred":[
        "Gombi"
    ],
    "name:fra_x_preferred":[
        "Gombi"
    ],
    "name:hau_x_preferred":[
        "Gombi"
    ],
    "name:ita_x_preferred":[
        "Gombi"
    ],
    "name:spa_x_preferred":[
        "Gombi"
    ],
    "wof:name":"Gombi",
    "wof:placetype":"locality"
},
  "geometry": {"coordinates":[35.11667,9.88333],"type":"Point"}
}