{
  "type": "Feature",
  "properties": {
    "gn:admin1_code":"46",
    "gn:asciiname":"Jewaha",
    "gn:country_code":"ET",
    "gn:dem":1154,
    "gn:feature_class":"P",
    "gn:feature_code":"PPL",
    "gn:name":"Jewaha",
    "gn:population":0,
    "gn:timezone":"Africa/Addis_Ababa",
    "iso:country":"ET",
    "name:und_x_variant":[
        "Jebuha"
    ],
    "wof:name":"Jewaha",
    "wof:placetype":"locality"
},
  "geometry": {"coordinates":[39.97301,10.10669],"type":"Point"}
}