{
  "type": "Feature",
  "properties": {
    "gn:admin1_code":"52",
    "gn:asciiname":"Elejela",
    "gn:country_code":"ET",
    "gn:dem":1014,
    "gn:feature_class":"P",
    "gn:feature_code":"PPL",
    "gn:name":"\u0112lejela",
    "gn:population":0,
    "gn:timezone":"Africa/Addis_Ababa",
    "iso:country":"ET",
    "wof:name":"Elejela",
    "wof:placetype":"locality"
},
  "geometry": {"coordinates":[41.57917,9.66917],"type":"Point"}
}