{
  "type": "Feature",
  "properties": {
    "gn:admin1_code":"52.0",
    "gn:asciiname":"Daballac",
    "gn:country_code":"ET",
    "gn:dem":802,
    "gn:feature_class":"P",
    "gn:feature_code":"PPL",
    "gn:name":"Daballac",
    "gn:population":0,
    "gn:timezone":"Africa/Addis_Ababa",
    "iso:country":"ET",
    "wof:name":"Daballac",
    "wof:placetype":"locality"
},
  "geometry": {"coordinates":[43.31549,7.21486],"type":"Point"}
}