{
  "type": "Feature",
  "properties": {
    "gn:admin1_code":"51.0",
    "gn:asciiname":"Bedada Tola",
    "gn:country_code":"ET",
    "gn:dem":2880,
    "gn:feature_class":"P",
    "gn:feature_code":"PPL",
    "gn:name":"Bedada Tola",
    "gn:population":0,
    "gn:timezone":"Africa/Addis_Ababa",
    "iso:country":"ET",
    "name:und_x_variant":[
        "Bedoda Tola",
        "Bedada Tola"
    ],
    "wof:name":"Bedada Tola",
    "wof:placetype":"locality"
},
  "geometry": {"coordinates":[38.06667,8.85],"type":"Point"}
}