{
  "type": "Feature",
  "properties": {
    "gn:admin1_code":"46",
    "gn:asciiname":"Godeburk'a",
    "gn:country_code":"ET",
    "gn:dem":1357,
    "gn:feature_class":"P",
    "gn:feature_code":"PPL",
    "gn:name":"Godeburk\u2019a",
    "gn:population":0,
    "gn:timezone":"Africa/Addis_Ababa",
    "iso:country":"ET",
    "name:und_x_variant":[
        "Gwodaburka",
        "Gadaburq\u0101",
        "Godaburka",
        "Godoburka",
        "Godeburk\u2019a"
    ],
    "wof:name":"Godeburk'a",
    "wof:placetype":"locality"
},
  "geometry": {"coordinates":[39.58333,8.91667],"type":"Point"}
}