{
  "type": "Feature",
  "properties": {
    "gn:admin1_code":"46.0",
    "gn:asciiname":"Ch'ibas",
    "gn:country_code":"ET",
    "gn:dem":3031,
    "gn:feature_class":"P",
    "gn:feature_code":"PPL",
    "gn:name":"Ch\u2019ibas",
    "gn:population":0,
    "gn:timezone":"Africa/Addis_Ababa",
    "iso:country":"ET",
    "name:und_x_variant":[
        "Curie",
        "Ch\u2019ibas"
    ],
    "wof:name":"Ch'ibas",
    "wof:placetype":"locality"
},
  "geometry": {"coordinates":[39.59802,10.3544],"type":"Point"}
}