{
  "type": "Feature",
  "properties": {
    "gn:admin1_code":"54.0",
    "gn:asciiname":"Angach'a",
    "gn:country_code":"ET",
    "gn:dem":2321,
    "gn:feature_class":"P",
    "gn:feature_code":"PPL",
    "gn:name":"\u0100ngach\u2019a",
    "gn:population":0,
    "gn:timezone":"Africa/Addis_Ababa",
    "iso:country":"ET",
    "name:und_x_variant":[
        "Agaccia",
        "Angaccia",
        "\u0100ngech\u2019a",
        "Angech\u2019a (1)",
        "\u0100ngach\u2019a"
    ],
    "wof:name":"Angach'a",
    "wof:placetype":"locality"
},
  "geometry": {"coordinates":[37.85,7.33333],"type":"Point"}
}