{
  "type": "Feature",
  "properties": {
    "gn:admin1_code":"53.0",
    "gn:asciiname":"Adi K'elk'el",
    "gn:country_code":"ET",
    "gn:dem":2002,
    "gn:feature_class":"P",
    "gn:feature_code":"PPL",
    "gn:name":"\u0100d\u012b K\u2019elk\u2019el",
    "gn:population":0,
    "gn:timezone":"Africa/Addis_Ababa",
    "iso:country":"ET",
    "name:und_x_variant":[
        "Ad\u012b K\u2019elk\u2019el (2)",
        "Addi Kel'kel' 2",
        "\u0100d\u012b K\u2019elk\u2019el"
    ],
    "wof:name":"Adi K'elk'el",
    "wof:placetype":"locality"
},
  "geometry": {"coordinates":[39.10028,14.36667],"type":"Point"}
}