{
  "type": "Feature",
  "properties": {
    "gn:admin1_code":"51",
    "gn:asciiname":"Gebugela",
    "gn:country_code":"ET",
    "gn:dem":1510,
    "gn:feature_class":"P",
    "gn:feature_code":"PPL",
    "gn:name":"Gebugela",
    "gn:population":0,
    "gn:timezone":"Africa/Addis_Ababa",
    "iso:country":"ET",
    "wof:name":"Gebugela",
    "wof:placetype":"locality"
},
  "geometry": {"coordinates":[38.45,4.65],"type":"Point"}
}