{
  "type": "Feature",
  "properties": {
    "gn:admin1_code":"51",
    "gn:asciiname":"Korma",
    "gn:country_code":"ET",
    "gn:dem":1567,
    "gn:feature_class":"P",
    "gn:feature_code":"PPL",
    "gn:name":"Korma",
    "gn:population":0,
    "gn:timezone":"Africa/Addis_Ababa",
    "iso:country":"ET",
    "name:ara_x_preferred":[
        "\u0642\u0648\u0631\u0645\u0629"
    ],
    "name:ben_x_preferred":[
        "\u0995\u09cb\u09b0\u09cd\u09ae\u09be"
    ],
    "name:bul_x_preferred":[
        "\u041a\u0430\u0432\u044a\u0440\u043c\u0430"
    ],
    "name:cat_x_preferred":[
        "Kavurma"
    ],
    "name:ceb_x_preferred":[
        "Korm\u0101"
    ],
    "name:deu_x_preferred":[
        "Korma"
    ],
    "name:fra_x_preferred":[
        "Korma"
    ],
    "name:ind_x_preferred":[
        "Korma"
    ],
    "name:jpn_x_preferred":[
        "\u30b3\u30eb\u30de"
    ],
    "name:kor_x_preferred":[
        "\ucf54\ub974\ub9c8"
    ],
    "name:kur_x_preferred":[
        "Qel\u00ee"
    ],
    "name:mai_x_preferred":[
        "\u091a\u093f\u0915\u0928 \u0915\u094b\u0930\u092e\u093e"
    ],
    "name:mal_x_preferred":[
        "\u0d15\u0d41\u0d31\u0d41\u0d2e"
    ],
    "name:msa_x_preferred":[
        "Korma"
    ],
    "name:pol_x_preferred":[
        "Korma"
    ],
    "name:por_x_preferred":[
        "Korma"
    ],
    "name:rus_x_preferred":[
        "\u041a\u043e\u0440\u043c\u0430"
    ],
    "name:spa_x_preferred":[
        "Korma"
    ],
    "name:srp_x_preferred":[
        "\u041a\u0430\u0432\u0443\u0440\u043c\u0430"
    ],
    "name:tam_x_preferred":[
        "\u0b95\u0bc1\u0bb0\u0bcd\u0bae\u0bbe"
    ],
    "name:tgl_x_preferred":[
        "Korma"
    ],
    "name:tha_x_preferred":[
        "\u0e41\u0e01\u0e07\u0e01\u0e38\u0e23\u0e38\u0e2b\u0e21\u0e48\u0e32"
    ],
    "wof:name":"Korma",
    "wof:placetype":"locality"
},
  "geometry": {"coordinates":[35.13333,9.63333],"type":"Point"}
}