{
  "type": "Feature",
  "properties": {
    "iso:country":"ET",
    "name:amh_x_preferred":[
        "\u12f0\u1265\u1228 \u12c8\u122d\u1245"
    ],
    "name:eng_x_preferred":[
        "Debre Work"
    ],
    "name:fra_x_preferred":[
        "Debre Werq"
    ],
    "name:nld_x_preferred":[
        "Debre Werq"
    ],
    "name:unk_x_variant":[
        "Dabra-Warq"
    ],
    "qs:gn_country":"ET",
    "qs:gn_fcode":"PPL",
    "qs:gn_pop":10579,
    "qs:name":"Debre Werk'",
    "qs:name_adm0":"Ethiopia",
    "qs:name_adm1":"Amhara",
    "qs:photos":0,
    "qs:photos_1k":0,
    "qs:photos_9k":0,
    "qs:photos_9r":0,
    "qs:photos_all":0,
    "qs:photos_sr":0,
    "qs:placetype":"Town",
    "qs:pop_sr":"6",
    "qs:woe_adm0":23424808,
    "wd:wordcount":381,
    "wof:name":"Debre Werk'",
    "wof:placetype":"locality",
    "wof:population":10579
},
  "geometry": {"coordinates":[38.16667,10.66667],"type":"Point"}
}