{
  "type": "Feature",
  "properties": {
    "gn:admin1_code":"52",
    "gn:asciiname":"Garasleh",
    "gn:country_code":"ET",
    "gn:dem":913,
    "gn:feature_class":"P",
    "gn:feature_code":"PPL",
    "gn:name":"Garasleh",
    "gn:population":0,
    "gn:timezone":"Africa/Addis_Ababa",
    "iso:country":"ET",
    "name:und_x_variant":[
        "Garasl\u00e9",
        "Garasleh"
    ],
    "wof:name":"Garasleh",
    "wof:placetype":"locality"
},
  "geometry": {"coordinates":[42.13306,9.83417],"type":"Point"}
}