{
  "type": "Feature",
  "properties": {
    "gn:admin1_code":"54",
    "gn:asciiname":"Gesuba",
    "gn:country_code":"ET",
    "gn:dem":1545,
    "gn:feature_class":"P",
    "gn:feature_code":"PPL",
    "gn:name":"Gesuba",
    "gn:population":0,
    "gn:timezone":"Africa/Addis_Ababa",
    "iso:country":"ET",
    "name:und_x_variant":[
        "Murie",
        "Mure",
        "Gesuba"
    ],
    "wof:name":"Gesuba",
    "wof:placetype":"locality"
},
  "geometry": {"coordinates":[37.56667,6.71667],"type":"Point"}
}