{
  "type": "Feature",
  "properties": {
    "gn:admin1_code":"46.0",
    "gn:asciiname":"Dil Amba",
    "gn:country_code":"ET",
    "gn:dem":2650,
    "gn:feature_class":"P",
    "gn:feature_code":"PPL",
    "gn:name":"Dil \u0100mba",
    "gn:population":0,
    "gn:timezone":"Africa/Addis_Ababa",
    "iso:country":"ET",
    "wof:name":"Dil Amba",
    "wof:placetype":"locality"
},
  "geometry": {"coordinates":[39.22208,9.70738],"type":"Point"}
}