{
  "type": "Feature",
  "properties": {
    "gn:admin1_code":"53.0",
    "gn:asciiname":"Adi Amshashi",
    "gn:country_code":"ET",
    "gn:dem":2250,
    "gn:feature_class":"P",
    "gn:feature_code":"PPL",
    "gn:name":"\u0100d\u012b \u0100mshash\u012b",
    "gn:population":0,
    "gn:timezone":"Africa/Addis_Ababa",
    "iso:country":"ET",
    "wof:name":"Adi Amshashi",
    "wof:placetype":"locality"
},
  "geometry": {"coordinates":[39.55,12.73333],"type":"Point"}
}