{
  "type": "Feature",
  "properties": {
    "gn:admin1_code":"51.0",
    "gn:asciiname":"Awashi",
    "gn:country_code":"ET",
    "gn:dem":2107,
    "gn:feature_class":"P",
    "gn:feature_code":"PPL",
    "gn:name":"\u0100wash\u012b",
    "gn:population":0,
    "gn:timezone":"Africa/Addis_Ababa",
    "iso:country":"ET",
    "wof:name":"Awashi",
    "wof:placetype":"locality"
},
  "geometry": {"coordinates":[35.46667,9.66667],"type":"Point"}
}