{
  "type": "Feature",
  "properties": {
    "gn:admin1_code":"52.0",
    "gn:asciiname":"Abeselli",
    "gn:country_code":"ET",
    "gn:dem":978,
    "gn:feature_class":"P",
    "gn:feature_code":"PPL",
    "gn:name":"Abeselli",
    "gn:population":0,
    "gn:timezone":"Africa/Addis_Ababa",
    "iso:country":"ET",
    "name:und_x_variant":[
        "Abeselh",
        "Abeselli"
    ],
    "wof:name":"Abeselli",
    "wof:placetype":"locality"
},
  "geometry": {"coordinates":[43.60694,7.35056],"type":"Point"}
}