{
  "type": "Feature",
  "properties": {
    "gn:admin1_code":"46",
    "gn:asciiname":"Kumer",
    "gn:country_code":"ET",
    "gn:dem":748,
    "gn:feature_class":"P",
    "gn:feature_code":"PPL",
    "gn:name":"Kumer",
    "gn:population":0,
    "gn:timezone":"Africa/Addis_Ababa",
    "iso:country":"ET",
    "name:und_x_variant":[
        "Comar",
        "Kumer"
    ],
    "wof:name":"Kumer",
    "wof:placetype":"locality"
},
  "geometry": {"coordinates":[36.25,12.83333],"type":"Point"}
}