{
  "type": "Feature",
  "properties": {
    "gn:admin1_code":"51.0",
    "gn:asciiname":"Diksis",
    "gn:country_code":"ET",
    "gn:dem":2800,
    "gn:feature_class":"P",
    "gn:feature_code":"PPL",
    "gn:name":"D\u012bks\u012bs",
    "gn:population":0,
    "gn:timezone":"Africa/Addis_Ababa",
    "iso:country":"ET",
    "name:und_x_variant":[
        "H\u0101mda D\u012bks\u012bs",
        "D\u012bks\u012bs"
    ],
    "wof:name":"Diksis",
    "wof:placetype":"locality"
},
  "geometry": {"coordinates":[39.55,8.05],"type":"Point"}
}