{
  "type": "Feature",
  "properties": {
    "gn:admin1_code":"51.0",
    "gn:asciiname":"Dire",
    "gn:country_code":"ET",
    "gn:dem":1625,
    "gn:feature_class":"P",
    "gn:feature_code":"PPL",
    "gn:name":"D\u012br\u0113",
    "gn:population":0,
    "gn:timezone":"Africa/Addis_Ababa",
    "iso:country":"ET",
    "name:ceb_x_preferred":[
        "Dire"
    ],
    "name:fra_x_preferred":[
        "Dire"
    ],
    "name:ita_x_preferred":[
        "Dire"
    ],
    "name:rus_x_preferred":[
        "\u0414\u0438\u0440\u0435"
    ],
    "name:swe_x_preferred":[
        "Dire"
    ],
    "wof:name":"Dire",
    "wof:placetype":"locality"
},
  "geometry": {"coordinates":[37.06667,8.35],"type":"Point"}
}