{
  "type": "Feature",
  "properties": {
    "gn:admin1_code":"53",
    "gn:asciiname":"Inda Silase",
    "gn:country_code":"ET",
    "gn:dem":1969,
    "gn:feature_class":"P",
    "gn:feature_code":"PPL",
    "gn:name":"Inda Silas\u0113",
    "gn:population":0,
    "gn:timezone":"Africa/Addis_Ababa",
    "iso:country":"ET",
    "name:und_x_variant":[
        "Andin",
        "Ynda Syllase",
        "Inda Silas\u0113"
    ],
    "wof:name":"Inda Silase",
    "wof:placetype":"locality"
},
  "geometry": {"coordinates":[39.18825,13.50799],"type":"Point"}
}