{
  "type": "Feature",
  "properties": {
    "gn:admin1_code":"51",
    "gn:asciiname":"Inch'ini",
    "gn:country_code":"ET",
    "gn:dem":2547,
    "gn:feature_class":"P",
    "gn:feature_code":"PPL",
    "gn:name":"Inch\u2019in\u012b",
    "gn:population":0,
    "gn:timezone":"Africa/Addis_Ababa",
    "iso:country":"ET",
    "wof:name":"Inch'ini",
    "wof:placetype":"locality"
},
  "geometry": {"coordinates":[38.51667,9.86667],"type":"Point"}
}