{
  "type": "Feature",
  "properties": {
    "gn:admin1_code":"53",
    "gn:asciiname":"Inda Aba Ts'ahma",
    "gn:country_code":"ET",
    "gn:dem":1999,
    "gn:feature_class":"P",
    "gn:feature_code":"PPL",
    "gn:name":"Inda \u0100ba Ts\u2019ahma",
    "gn:population":0,
    "gn:timezone":"Africa/Addis_Ababa",
    "iso:country":"ET",
    "name:und_x_variant":[
        "Enda Abbamas",
        "Indaba Ts\u2019ahma (1)",
        "Inda Aba Tsahama",
        "Inda \u0100ba Ts\u2019ahma"
    ],
    "wof:name":"Inda Aba Ts'ahma",
    "wof:placetype":"locality"
},
  "geometry": {"coordinates":[39.07117,14.03827],"type":"Point"}
}