{
  "type": "Feature",
  "properties": {
    "gn:admin1_code":"54.0",
    "gn:asciiname":"Arghi",
    "gn:country_code":"ET",
    "gn:dem":617,
    "gn:feature_class":"P",
    "gn:feature_code":"PPL",
    "gn:name":"Arghi",
    "gn:population":0,
    "gn:timezone":"Africa/Addis_Ababa",
    "iso:country":"ET",
    "wof:name":"Arghi",
    "wof:placetype":"locality"
},
  "geometry": {"coordinates":[36.16667,6.25],"type":"Point"}
}