{
  "type": "Feature",
  "properties": {
    "gn:admin1_code":"53.0",
    "gn:asciiname":"Adi Washo",
    "gn:country_code":"ET",
    "gn:dem":2708,
    "gn:feature_class":"P",
    "gn:feature_code":"PPL",
    "gn:name":"\u0100d\u012b Washo",
    "gn:population":0,
    "gn:timezone":"Africa/Addis_Ababa",
    "iso:country":"ET",
    "name:und_x_variant":[
        "\u0100d\u012b Washo (1)",
        "\u0100d\u012b Washo"
    ],
    "wof:name":"Adi Washo",
    "wof:placetype":"locality"
},
  "geometry": {"coordinates":[39.43333,12.53333],"type":"Point"}
}