{
  "type": "Feature",
  "properties": {
    "gn:admin1_code":"51",
    "gn:asciiname":"K'orench'ati",
    "gn:country_code":"ET",
    "gn:dem":1343,
    "gn:feature_class":"P",
    "gn:feature_code":"PPL",
    "gn:name":"K\u2019orench\u2019at\u012b",
    "gn:population":0,
    "gn:timezone":"Africa/Addis_Ababa",
    "iso:country":"ET",
    "wof:name":"K'orench'ati",
    "wof:placetype":"locality"
},
  "geometry": {"coordinates":[41.73333,9.53333],"type":"Point"}
}