{
  "type": "Feature",
  "properties": {
    "gn:admin1_code":"53.0",
    "gn:asciiname":"Adi Mendi",
    "gn:country_code":"ET",
    "gn:dem":1720,
    "gn:feature_class":"P",
    "gn:feature_code":"PPL",
    "gn:name":"\u0100d\u012b Mend\u012b",
    "gn:population":0,
    "gn:timezone":"Africa/Addis_Ababa",
    "iso:country":"ET",
    "name:und_x_variant":[
        "Me\u2019asak\u0113",
        "Adi Mandi",
        "\u0100d\u012b Mend\u012b"
    ],
    "wof:name":"Adi Mendi",
    "wof:placetype":"locality"
},
  "geometry": {"coordinates":[38.494,14.37624],"type":"Point"}
}