{
  "type": "Feature",
  "properties": {
    "gn:admin1_code":"51",
    "gn:asciiname":"Hayu",
    "gn:country_code":"ET",
    "gn:dem":1676,
    "gn:feature_class":"P",
    "gn:feature_code":"PPL",
    "gn:name":"H\u0101yu",
    "gn:population":0,
    "gn:timezone":"Africa/Addis_Ababa",
    "iso:country":"ET",
    "name:nep_x_preferred":[
        "\u0939\u093e\u092f\u0942 \u091c\u093e\u0924\u093f"
    ],
    "name:new_x_preferred":[
        "\u0939\u093e\u092f\u0942"
    ],
    "wof:name":"Hayu",
    "wof:placetype":"locality"
},
  "geometry": {"coordinates":[40.55,8.98333],"type":"Point"}
}