{
  "type": "Feature",
  "properties": {
    "gn:admin1_code":"52",
    "gn:asciiname":"Kololo",
    "gn:country_code":"ET",
    "gn:dem":819,
    "gn:feature_class":"P",
    "gn:feature_code":"PPL",
    "gn:name":"Kololo",
    "gn:population":0,
    "gn:timezone":"Africa/Addis_Ababa",
    "iso:country":"ET",
    "name:und_x_variant":[
        "Cololo",
        "Kololo",
        "Nololo"
    ],
    "wof:name":"Kololo",
    "wof:placetype":"locality"
},
  "geometry": {"coordinates":[41.98072,7.39991],"type":"Point"}
}