{
  "type": "Feature",
  "properties": {
    "gn:admin1_code":"52",
    "gn:asciiname":"Ionnis",
    "gn:country_code":"ET",
    "gn:dem":972,
    "gn:feature_class":"P",
    "gn:feature_code":"PPL",
    "gn:name":"Ionnis",
    "gn:population":0,
    "gn:timezone":"Africa/Addis_Ababa",
    "iso:country":"ET",
    "name:und_x_variant":[
        "Yonnis",
        "Ionnis"
    ],
    "wof:name":"Ionnis",
    "wof:placetype":"locality"
},
  "geometry": {"coordinates":[41.86667,9.76667],"type":"Point"}
}