{
  "type": "Feature",
  "properties": {
    "gn:admin1_code":"46",
    "gn:asciiname":"Jara",
    "gn:country_code":"ET",
    "gn:dem":3249,
    "gn:feature_class":"P",
    "gn:feature_code":"PPL",
    "gn:name":"Jara",
    "gn:population":0,
    "gn:timezone":"Africa/Addis_Ababa",
    "iso:country":"ET",
    "wof:name":"Jara",
    "wof:placetype":"locality"
},
  "geometry": {"coordinates":[39.34981,10.96294],"type":"Point"}
}