{
  "type": "Feature",
  "properties": {
    "gn:admin1_code":"46",
    "gn:asciiname":"Gosh Meda",
    "gn:country_code":"ET",
    "gn:dem":2241,
    "gn:feature_class":"P",
    "gn:feature_code":"PPL",
    "gn:name":"Gosh M\u0113da",
    "gn:population":0,
    "gn:timezone":"Africa/Addis_Ababa",
    "iso:country":"ET",
    "wof:name":"Gosh Meda",
    "wof:placetype":"locality"
},
  "geometry": {"coordinates":[39.25,11.53333],"type":"Point"}
}