{
  "type": "Feature",
  "properties": {
    "gn:admin1_code":"46.0",
    "gn:asciiname":"Ch'ibach'ibasa",
    "gn:country_code":"ET",
    "gn:dem":2122,
    "gn:feature_class":"P",
    "gn:feature_code":"PPL",
    "gn:name":"Ch\u2019ibach\u2019ibasa",
    "gn:population":0,
    "gn:timezone":"Africa/Addis_Ababa",
    "iso:country":"ET",
    "wof:name":"Ch'ibach'ibasa",
    "wof:placetype":"locality"
},
  "geometry": {"coordinates":[36.86667,10.76667],"type":"Point"}
}