{
  "type": "Feature",
  "properties": {
    "gn:admin1_code":"46",
    "gn:asciiname":"Yesor",
    "gn:country_code":"ET",
    "gn:dem":2403,
    "gn:feature_class":"P",
    "gn:feature_code":"PPL",
    "gn:name":"Yesor",
    "gn:population":0,
    "gn:timezone":"Africa/Addis_Ababa",
    "iso:country":"ET",
    "wof:name":"Yesor",
    "wof:placetype":"locality"
},
  "geometry": {"coordinates":[38.78333,11.33333],"type":"Point"}
}