{
  "type": "Feature",
  "properties": {
    "gn:admin1_code":"53.0",
    "gn:asciiname":"Bizet",
    "gn:country_code":"ET",
    "gn:dem":2044,
    "gn:feature_class":"P",
    "gn:feature_code":"PPL",
    "gn:name":"Bizet",
    "gn:population":0,
    "gn:timezone":"Africa/Addis_Ababa",
    "iso:country":"ET",
    "name:und_x_variant":[
        "Tebeka"
    ],
    "wof:name":"Bizet",
    "wof:placetype":"locality"
},
  "geometry": {"coordinates":[39.2902,14.28164],"type":"Point"}
}