{
  "type": "Feature",
  "properties": {
    "gn:admin1_code":"53.0",
    "gn:asciiname":"Debek'",
    "gn:country_code":"ET",
    "gn:dem":1565,
    "gn:feature_class":"P",
    "gn:feature_code":"PPL",
    "gn:name":"Debek\u2019",
    "gn:population":0,
    "gn:timezone":"Africa/Addis_Ababa",
    "iso:country":"ET",
    "wof:name":"Debek'",
    "wof:placetype":"locality"
},
  "geometry": {"coordinates":[38.61196,14.32773],"type":"Point"}
}