{
  "type": "Feature",
  "properties": {
    "gn:admin1_code":"46",
    "gn:asciiname":"Nini",
    "gn:country_code":"ET",
    "gn:dem":1602,
    "gn:feature_class":"P",
    "gn:feature_code":"PPL",
    "gn:name":"N\u012bn\u012b",
    "gn:population":0,
    "gn:timezone":"Africa/Addis_Ababa",
    "iso:country":"ET",
    "name:und_x_variant":[
        "N\u012bn\u012b (1)",
        "N\u012bn\u012b"
    ],
    "wof:name":"Nini",
    "wof:placetype":"locality"
},
  "geometry": {"coordinates":[39.68333,11.61667],"type":"Point"}
}