{
  "type": "Feature",
  "properties": {
    "gn:admin1_code":"53",
    "gn:asciiname":"Gudguda Laham",
    "gn:country_code":"ET",
    "gn:dem":1961,
    "gn:feature_class":"P",
    "gn:feature_code":"PPL",
    "gn:name":"Gudguda Laham",
    "gn:population":0,
    "gn:timezone":"Africa/Addis_Ababa",
    "iso:country":"ET",
    "name:und_x_variant":[
        "Gudguda Lakham",
        "Gudguda Laham"
    ],
    "wof:name":"Gudguda Laham",
    "wof:placetype":"locality"
},
  "geometry": {"coordinates":[38.4441,14.02905],"type":"Point"}
}