{
  "type": "Feature",
  "properties": {
    "gn:admin1_code":"52.0",
    "gn:asciiname":"Awubere",
    "gn:country_code":"ET",
    "gn:dem":1606,
    "gn:feature_class":"P",
    "gn:feature_code":"PPL",
    "gn:name":"\u0100wuber\u0113",
    "gn:population":0,
    "gn:timezone":"Africa/Addis_Ababa",
    "iso:country":"ET",
    "name:und_x_variant":[
        "Avubere",
        "\u0100wuber\u0113"
    ],
    "wof:name":"Awubere",
    "wof:placetype":"locality"
},
  "geometry": {"coordinates":[43.24444,9.63444],"type":"Point"}
}