{
  "type": "Feature",
  "properties": {
    "gn:admin1_code":"47.0",
    "gn:asciiname":"Assamadun",
    "gn:country_code":"ET",
    "gn:dem":356,
    "gn:feature_class":"P",
    "gn:feature_code":"PPL",
    "gn:name":"Assamadun",
    "gn:population":0,
    "gn:timezone":"Africa/Addis_Ababa",
    "iso:country":"ET",
    "wof:name":"Assamadun",
    "wof:placetype":"locality"
},
  "geometry": {"coordinates":[41.40466,11.61404],"type":"Point"}
}