{
  "type": "Feature",
  "properties": {
    "gn:admin1_code":"51.0",
    "gn:asciiname":"Berbade",
    "gn:country_code":"ET",
    "gn:dem":491,
    "gn:feature_class":"P",
    "gn:feature_code":"PPL",
    "gn:name":"Berbade",
    "gn:population":0,
    "gn:timezone":"Africa/Addis_Ababa",
    "iso:country":"ET",
    "wof:name":"Berbade",
    "wof:placetype":"locality"
},
  "geometry": {"coordinates":[42.15,7.33333],"type":"Point"}
}