{
  "type": "Feature",
  "properties": {
    "gn:admin1_code":"53.0",
    "gn:asciiname":"Lama",
    "gn:country_code":"ET",
    "gn:dem":1062,
    "gn:feature_class":"P",
    "gn:feature_code":"PPL",
    "gn:name":"Lama",
    "gn:population":0,
    "gn:timezone":"Africa/Addis_Ababa",
    "iso:country":"ET",
    "wof:name":"Lama",
    "wof:placetype":"locality"
},
  "geometry": {"coordinates":[37.82,14.66806],"type":"Point"}
}