{
  "type": "Feature",
  "properties": {
    "gn:admin1_code":"52.0",
    "gn:asciiname":"Barriye",
    "gn:country_code":"ET",
    "gn:dem":783,
    "gn:feature_class":"P",
    "gn:feature_code":"PPL",
    "gn:name":"Barriye",
    "gn:population":0,
    "gn:timezone":"Africa/Addis_Ababa",
    "iso:country":"ET",
    "wof:name":"Barriye",
    "wof:placetype":"locality"
},
  "geometry": {"coordinates":[44.89333,7.03083],"type":"Point"}
}