{
  "type": "Feature",
  "properties": {
    "gn:admin1_code":"51",
    "gn:asciiname":"Galata",
    "gn:country_code":"ET",
    "gn:dem":1850,
    "gn:feature_class":"P",
    "gn:feature_code":"PPL",
    "gn:name":"Galata",
    "gn:population":0,
    "gn:timezone":"Africa/Addis_Ababa",
    "iso:country":"ET",
    "wof:name":"Galata",
    "wof:placetype":"locality"
},
  "geometry": {"coordinates":[39.43333,8.25],"type":"Point"}
}