{
  "type": "Feature",
  "properties": {
    "gn:admin1_code":"51",
    "gn:asciiname":"Galata",
    "gn:country_code":"ET",
    "gn:dem":1850,
    "gn:feature_class":"P",
    "gn:feature_code":"PPL",
    "gn:name":"Galata",
    "gn:population":0,
    "gn:timezone":"Africa/Addis_Ababa",
    "iso:country":"ET",
    "name:ara_x_preferred":[
        "\u063a\u0644\u0637\u0629"
    ],
    "name:bel_x_preferred":[
        "\u0413\u0430\u043b\u0430\u0442\u0430"
    ],
    "name:bul_x_preferred":[
        "\u0413\u0430\u043b\u0430\u0442\u0430"
    ],
    "name:cat_x_preferred":[
        "Galata"
    ],
    "name:ces_x_preferred":[
        "Galata"
    ],
    "name:deu_x_preferred":[
        "Galata"
    ],
    "name:diq_x_preferred":[
        "Galata"
    ],
    "name:ell_x_preferred":[
        "\u0393\u03b1\u03bb\u03b1\u03c4\u03ac\u03c2"
    ],
    "name:fas_x_preferred":[
        "\u06af\u0627\u0644\u0627\u062a\u0627"
    ],
    "name:heb_x_preferred":[
        "\u05d2\u05dc\u05d0\u05d8\u05d4"
    ],
    "name:hye_x_preferred":[
        "\u0533\u0561\u056c\u0561\u0569\u0561"
    ],
    "name:ind_x_preferred":[
        "Galata"
    ],
    "name:ita_x_preferred":[
        "Galata"
    ],
    "name:jpn_x_preferred":[
        "\u30ac\u30e9\u30bf"
    ],
    "name:kor_x_preferred":[
        "\uac08\ub77c\ud0c0"
    ],
    "name:lad_x_preferred":[
        "Galata"
    ],
    "name:lav_x_preferred":[
        "Galata"
    ],
    "name:mkd_x_preferred":[
        "\u0413\u0430\u043b\u0430\u0442\u0430"
    ],
    "name:nld_x_preferred":[
        "Galata"
    ],
    "name:nor_x_preferred":[
        "Galata"
    ],
    "name:pol_x_preferred":[
        "Galata"
    ],
    "name:por_x_preferred":[
        "G\u00e1lata"
    ],
    "name:ron_x_preferred":[
        "Galata"
    ],
    "name:rus_x_preferred":[
        "\u0413\u0430\u043b\u0430\u0442\u0430"
    ],
    "name:srp_x_preferred":[
        "\u0413\u0430\u043b\u0430\u0442\u0430"
    ],
    "name:swe_x_preferred":[
        "Galata"
    ],
    "name:tur_x_preferred":[
        "Galata"
    ],
    "name:ukr_x_preferred":[
        "\u0413\u0430\u043b\u0430\u0442\u0430"
    ],
    "name:urd_x_preferred":[
        "\u063a\u0644\u0637\u06c1"
    ],
    "name:zho_x_preferred":[
        "\u52a0\u62c9\u5854"
    ],
    "wof:name":"Galata",
    "wof:placetype":"locality"
},
  "geometry": {"coordinates":[39.43333,8.25],"type":"Point"}
}