{
  "type": "Feature",
  "properties": {
    "gn:admin1_code":"46",
    "gn:asciiname":"Mene Ona",
    "gn:country_code":"ET",
    "gn:dem":2614,
    "gn:feature_class":"P",
    "gn:feature_code":"PPL",
    "gn:name":"Mene Ona",
    "gn:population":0,
    "gn:timezone":"Africa/Addis_Ababa",
    "iso:country":"ET",
    "wof:name":"Mene Ona",
    "wof:placetype":"locality"
},
  "geometry": {"coordinates":[38.93333,9.78333],"type":"Point"}
}