{
  "type": "Feature",
  "properties": {
    "gn:admin1_code":"46.0",
    "gn:asciiname":"Baych'a",
    "gn:country_code":"ET",
    "gn:dem":2410,
    "gn:feature_class":"P",
    "gn:feature_code":"PPL",
    "gn:name":"Baych\u2019a",
    "gn:population":0,
    "gn:timezone":"Africa/Addis_Ababa",
    "iso:country":"ET",
    "wof:name":"Baych'a",
    "wof:placetype":"locality"
},
  "geometry": {"coordinates":[38.61667,12.46667],"type":"Point"}
}