{
  "type": "Feature",
  "properties": {
    "gn:admin1_code":"51",
    "gn:asciiname":"Kembolcha",
    "gn:country_code":"ET",
    "gn:dem":1904,
    "gn:feature_class":"P",
    "gn:feature_code":"PPL",
    "gn:name":"Kembolcha",
    "gn:population":0,
    "gn:timezone":"Africa/Addis_Ababa",
    "iso:country":"ET",
    "wof:name":"Kembolcha",
    "wof:placetype":"locality"
},
  "geometry": {"coordinates":[36.06667,8.36667],"type":"Point"}
}