{
  "type": "Feature",
  "properties": {
    "gn:admin1_code":"51",
    "gn:asciiname":"Iteya",
    "gn:country_code":"ET",
    "gn:dem":2379,
    "gn:feature_class":"P",
    "gn:feature_code":"PPL",
    "gn:name":"\u012ateya",
    "gn:population":0,
    "gn:timezone":"Africa/Addis_Ababa",
    "iso:country":"ET",
    "name:fra_x_preferred":[
        "Iteya"
    ],
    "name:zho_x_preferred":[
        "\u4f0a\u7279\u4e9e"
    ],
    "wof:name":"Iteya",
    "wof:placetype":"locality"
},
  "geometry": {"coordinates":[39.25,8.05],"type":"Point"}
}