{
  "type": "Feature",
  "properties": {
    "gn:admin1_code":"53.0",
    "gn:asciiname":"Gereb Didik",
    "gn:country_code":"ET",
    "gn:dem":2100,
    "gn:feature_class":"P",
    "gn:feature_code":"PPL",
    "gn:name":"Gereb Didik",
    "gn:population":0,
    "gn:timezone":"Africa/Addis_Ababa",
    "iso:country":"ET",
    "wof:name":"Gereb Didik",
    "wof:placetype":"locality"
},
  "geometry": {"coordinates":[39.51447,13.10491],"type":"Point"}
}