{
  "type": "Feature",
  "properties": {
    "gn:admin1_code":"46.0",
    "gn:asciiname":"Hadere",
    "gn:country_code":"ET",
    "gn:dem":1433,
    "gn:feature_class":"P",
    "gn:feature_code":"PPL",
    "gn:name":"Hadere",
    "gn:population":0,
    "gn:timezone":"Africa/Addis_Ababa",
    "iso:country":"ET",
    "wof:name":"Hadere",
    "wof:placetype":"locality"
},
  "geometry": {"coordinates":[39.95932,10.29582],"type":"Point"}
}