{
  "type": "Feature",
  "properties": {
    "gn:admin1_code":"52",
    "gn:asciiname":"Duyer Ali",
    "gn:country_code":"ET",
    "gn:dem":538,
    "gn:feature_class":"P",
    "gn:feature_code":"PPL",
    "gn:name":"Duyer Ali",
    "gn:population":0,
    "gn:timezone":"Africa/Addis_Ababa",
    "iso:country":"ET",
    "name:und_x_variant":[
        "Duierali",
        "Duyerali",
        "Duerali",
        "Duyer Ali"
    ],
    "wof:name":"Duyer Ali",
    "wof:placetype":"locality"
},
  "geometry": {"coordinates":[46.72278,7.50167],"type":"Point"}
}