{
  "type": "Feature",
  "properties": {
    "gn:admin1_code":"50",
    "gn:asciiname":"Mek'ora",
    "gn:country_code":"ET",
    "gn:dem":1980,
    "gn:feature_class":"P",
    "gn:feature_code":"PPL",
    "gn:name":"Mek\u2019ora",
    "gn:population":0,
    "gn:timezone":"Africa/Addis_Ababa",
    "iso:country":"ET",
    "wof:name":"Mek'ora",
    "wof:placetype":"locality"
},
  "geometry": {"coordinates":[42.11278,9.33528],"type":"Point"}
}