{
  "type": "Feature",
  "properties": {
    "gn:admin1_code":"46",
    "gn:asciiname":"Gucere",
    "gn:country_code":"ET",
    "gn:dem":1774,
    "gn:feature_class":"P",
    "gn:feature_code":"PPL",
    "gn:name":"Gucere",
    "gn:population":0,
    "gn:timezone":"Africa/Addis_Ababa",
    "iso:country":"ET",
    "wof:name":"Gucere",
    "wof:placetype":"locality"
},
  "geometry": {"coordinates":[37.68333,13.08333],"type":"Point"}
}