{
  "type": "Feature",
  "properties": {
    "gn:admin1_code":"53.0",
    "gn:asciiname":"Adi Scimti",
    "gn:country_code":"ET",
    "gn:dem":1649,
    "gn:feature_class":"P",
    "gn:feature_code":"PPL",
    "gn:name":"Adi Scimti",
    "gn:population":0,
    "gn:timezone":"Africa/Addis_Ababa",
    "iso:country":"ET",
    "name:und_x_variant":[
        "Addi Scimti",
        "Adi Scimti"
    ],
    "wof:name":"Adi Scimti",
    "wof:placetype":"locality"
},
  "geometry": {"coordinates":[39.63333,12.61667],"type":"Point"}
}