{
  "type": "Feature",
  "properties": {
    "gn:admin1_code":"53",
    "gn:asciiname":"Mark'os",
    "gn:country_code":"ET",
    "gn:dem":1815,
    "gn:feature_class":"P",
    "gn:feature_code":"PPL",
    "gn:name":"Mark\u2019os",
    "gn:population":0,
    "gn:timezone":"Africa/Addis_Ababa",
    "iso:country":"ET",
    "name:und_x_variant":[
        "Adi Decal",
        "Addi Decal",
        "Mark\u2019os"
    ],
    "wof:name":"Mark'os",
    "wof:placetype":"locality"
},
  "geometry": {"coordinates":[38.1974,14.02997],"type":"Point"}
}