{
  "type": "Feature",
  "properties": {
    "gn:admin1_code":"46.0",
    "gn:asciiname":"Birgida",
    "gn:country_code":"ET",
    "gn:dem":1816,
    "gn:feature_class":"P",
    "gn:feature_code":"PPL",
    "gn:name":"Birg\u012bda",
    "gn:population":0,
    "gn:timezone":"Africa/Addis_Ababa",
    "iso:country":"ET",
    "wof:name":"Birgida",
    "wof:placetype":"locality"
},
  "geometry": {"coordinates":[37.28333,12.21667],"type":"Point"}
}