{
  "type": "Feature",
  "properties": {
    "gn:admin1_code":"53.0",
    "gn:asciiname":"Enda Mariam Bahafeyti",
    "gn:country_code":"ET",
    "gn:dem":2719,
    "gn:feature_class":"P",
    "gn:feature_code":"PPL",
    "gn:name":"Enda Mariam Bahafeyti",
    "gn:population":0,
    "gn:timezone":"Africa/Addis_Ababa",
    "iso:country":"ET",
    "wof:name":"Enda Mariam Bahafeyti",
    "wof:placetype":"locality"
},
  "geometry": {"coordinates":[39.72183,13.93779],"type":"Point"}
}