{
  "type": "Feature",
  "properties": {
    "gn:admin1_code":"46",
    "gn:asciiname":"K'ola Diba",
    "gn:country_code":"ET",
    "gn:dem":1830,
    "gn:feature_class":"P",
    "gn:feature_code":"PPL",
    "gn:name":"K\u2019ola Diba",
    "gn:population":0,
    "gn:timezone":"Africa/Addis_Ababa",
    "iso:country":"ET",
    "name:und_x_variant":[
        "Sarua",
        "Kolla Debba",
        "K\u2019ola Diba"
    ],
    "wof:name":"K'ola Diba",
    "wof:placetype":"locality"
},
  "geometry": {"coordinates":[37.325,12.42417],"type":"Point"}
}