{
  "type": "Feature",
  "properties": {
    "gn:admin1_code":"51",
    "gn:asciiname":"Molliccia",
    "gn:country_code":"ET",
    "gn:dem":2032,
    "gn:feature_class":"P",
    "gn:feature_code":"PPL",
    "gn:name":"Molliccia",
    "gn:population":0,
    "gn:timezone":"Africa/Addis_Ababa",
    "iso:country":"ET",
    "wof:name":"Molliccia",
    "wof:placetype":"locality"
},
  "geometry": {"coordinates":[39.26667,6.25],"type":"Point"}
}