{
  "type": "Feature",
  "properties": {
    "gn:admin1_code":"51",
    "gn:asciiname":"Doyo",
    "gn:country_code":"ET",
    "gn:dem":2768,
    "gn:feature_class":"P",
    "gn:feature_code":"PPL",
    "gn:name":"Doyo",
    "gn:population":0,
    "gn:timezone":"Africa/Addis_Ababa",
    "iso:country":"ET",
    "wof:name":"Doyo",
    "wof:placetype":"locality"
},
  "geometry": {"coordinates":[38.93333,9.35],"type":"Point"}
}