{
  "type": "Feature",
  "properties": {
    "gn:admin1_code":"51",
    "gn:asciiname":"Mojo",
    "gn:country_code":"ET",
    "gn:dem":1749,
    "gn:feature_class":"P",
    "gn:feature_code":"PPL",
    "gn:name":"Mojo",
    "gn:population":0,
    "gn:timezone":"Africa/Addis_Ababa",
    "iso:country":"ET",
    "name:und_x_variant":[
        "Amule",
        "Mojo"
    ],
    "wof:name":"Mojo",
    "wof:placetype":"locality"
},
  "geometry": {"coordinates":[34.93333,8.61667],"type":"Point"}
}