{
  "type": "Feature",
  "properties": {
    "gn:admin1_code":"51",
    "gn:asciiname":"Mojo",
    "gn:country_code":"ET",
    "gn:dem":1749,
    "gn:feature_class":"P",
    "gn:feature_code":"PPL",
    "gn:name":"Mojo",
    "gn:population":0,
    "gn:timezone":"Africa/Addis_Ababa",
    "iso:country":"ET",
    "name:ceb_x_preferred":[
        "Mojo"
    ],
    "name:ces_x_preferred":[
        "Mojo"
    ],
    "name:deu_x_preferred":[
        "Mojo"
    ],
    "name:fra_x_preferred":[
        "Mojo"
    ],
    "name:hun_x_preferred":[
        "Mojo"
    ],
    "name:ind_x_preferred":[
        "Mojo"
    ],
    "name:ita_x_preferred":[
        "Mojo"
    ],
    "name:jpn_x_preferred":[
        "\u30e2\u30b8\u30e7"
    ],
    "name:msa_x_preferred":[
        "Mojo"
    ],
    "name:nld_x_preferred":[
        "Mojo"
    ],
    "name:pol_x_preferred":[
        "Mojo"
    ],
    "name:por_x_preferred":[
        "Mojo"
    ],
    "name:rus_x_preferred":[
        "Mojo"
    ],
    "name:spa_x_preferred":[
        "Mojo"
    ],
    "name:swe_x_preferred":[
        "Mojo"
    ],
    "name:und_x_variant":[
        "Amule",
        "Mojo"
    ],
    "wof:name":"Mojo",
    "wof:placetype":"locality"
},
  "geometry": {"coordinates":[34.93333,8.61667],"type":"Point"}
}