{
  "type": "Feature",
  "properties": {
    "gn:admin1_code":"53.0",
    "gn:asciiname":"De'are",
    "gn:country_code":"ET",
    "gn:dem":2301,
    "gn:feature_class":"P",
    "gn:feature_code":"PPL",
    "gn:name":"De\u2019\u0101re",
    "gn:population":0,
    "gn:timezone":"Africa/Addis_Ababa",
    "iso:country":"ET",
    "wof:name":"De'are",
    "wof:placetype":"locality"
},
  "geometry": {"coordinates":[39.17088,13.58909],"type":"Point"}
}