{
  "type": "Feature",
  "properties": {
    "gn:admin1_code":"51",
    "gn:asciiname":"Gedeb",
    "gn:country_code":"ET",
    "gn:dem":2774,
    "gn:feature_class":"P",
    "gn:feature_code":"PPL",
    "gn:name":"Gedeb",
    "gn:population":0,
    "gn:timezone":"Africa/Addis_Ababa",
    "iso:country":"ET",
    "name:ceb_x_preferred":[
        "Gedeb"
    ],
    "name:swe_x_preferred":[
        "Gedeb"
    ],
    "wof:name":"Gedeb",
    "wof:placetype":"locality"
},
  "geometry": {"coordinates":[39.28333,7.31667],"type":"Point"}
}