{
  "type": "Feature",
  "properties": {
    "gn:admin1_code":"46",
    "gn:asciiname":"K'ulf Amba",
    "gn:country_code":"ET",
    "gn:dem":3484,
    "gn:feature_class":"P",
    "gn:feature_code":"PPL",
    "gn:name":"K\u2019ulf \u0100mba",
    "gn:population":0,
    "gn:timezone":"Africa/Addis_Ababa",
    "iso:country":"ET",
    "name:und_x_variant":[
        "K\u2019ulf \u0100mba (2)",
        "K\u2019ulf \u0100mba"
    ],
    "wof:name":"K'ulf Amba",
    "wof:placetype":"locality"
},
  "geometry": {"coordinates":[39.38333,11.86667],"type":"Point"}
}