{
  "type": "Feature",
  "properties": {
    "gn:admin1_code":"51",
    "gn:asciiname":"Geresu",
    "gn:country_code":"ET",
    "gn:dem":2285,
    "gn:feature_class":"P",
    "gn:feature_code":"PPL",
    "gn:name":"Geresu",
    "gn:population":0,
    "gn:timezone":"Africa/Addis_Ababa",
    "iso:country":"ET",
    "wof:name":"Geresu",
    "wof:placetype":"locality"
},
  "geometry": {"coordinates":[38.51667,8.98333],"type":"Point"}
}