{
  "type": "Feature",
  "properties": {
    "gn:admin1_code":"53.0",
    "gn:asciiname":"Adi Alecti",
    "gn:country_code":"ET",
    "gn:dem":1826,
    "gn:feature_class":"P",
    "gn:feature_code":"PPL",
    "gn:name":"Adi Alecti",
    "gn:population":0,
    "gn:timezone":"Africa/Addis_Ababa",
    "iso:country":"ET",
    "wof:name":"Adi Alecti",
    "wof:placetype":"locality"
},
  "geometry": {"coordinates":[37.38333,13.71667],"type":"Point"}
}