{
  "type": "Feature",
  "properties": {
    "gn:admin1_code":"51",
    "gn:asciiname":"Serdo",
    "gn:country_code":"ET",
    "gn:dem":1663,
    "gn:feature_class":"P",
    "gn:feature_code":"PPL",
    "gn:name":"S\u0113rdo",
    "gn:population":0,
    "gn:timezone":"Africa/Addis_Ababa",
    "iso:country":"ET",
    "wof:name":"Serdo",
    "wof:placetype":"locality"
},
  "geometry": {"coordinates":[37.75,9.16667],"type":"Point"}
}