{
  "type": "Feature",
  "properties": {
    "gn:admin1_code":"51",
    "gn:asciiname":"Mitayi",
    "gn:country_code":"ET",
    "gn:dem":2677,
    "gn:feature_class":"P",
    "gn:feature_code":"PPL",
    "gn:name":"M\u012btay\u012b",
    "gn:population":0,
    "gn:timezone":"Africa/Addis_Ababa",
    "iso:country":"ET",
    "wof:name":"Mitayi",
    "wof:placetype":"locality"
},
  "geometry": {"coordinates":[39.05818,9.36464],"type":"Point"}
}