{
  "type": "Feature",
  "properties": {
    "gn:admin1_code":"51",
    "gn:asciiname":"Madde Maiu",
    "gn:country_code":"ET",
    "gn:dem":1279,
    "gn:feature_class":"P",
    "gn:feature_code":"PPL",
    "gn:name":"Madde Maiu",
    "gn:population":0,
    "gn:timezone":"Africa/Addis_Ababa",
    "iso:country":"ET",
    "name:und_x_variant":[
        "Madde Mayu",
        "Madde Maiu"
    ],
    "wof:name":"Madde Maiu",
    "wof:placetype":"locality"
},
  "geometry": {"coordinates":[41.8782,8.45155],"type":"Point"}
}