{
  "type": "Feature",
  "properties": {
    "gn:admin1_code":"53.0",
    "gn:asciiname":"Alah",
    "gn:country_code":"ET",
    "gn:dem":2287,
    "gn:feature_class":"P",
    "gn:feature_code":"PPL",
    "gn:name":"\u0100lah",
    "gn:population":0,
    "gn:timezone":"Africa/Addis_Ababa",
    "iso:country":"ET",
    "name:und_x_variant":[
        "Alakh",
        "\u0100lah"
    ],
    "wof:name":"Alah",
    "wof:placetype":"locality"
},
  "geometry": {"coordinates":[39.24213,13.66146],"type":"Point"}
}