{
  "type": "Feature",
  "properties": {
    "gn:admin1_code":"46",
    "gn:asciiname":"Gol",
    "gn:country_code":"ET",
    "gn:dem":3245,
    "gn:feature_class":"P",
    "gn:feature_code":"PPL",
    "gn:name":"Gol",
    "gn:population":0,
    "gn:timezone":"Africa/Addis_Ababa",
    "iso:country":"ET",
    "name:aze_x_preferred":[
        "Qol"
    ],
    "name:bpy_x_preferred":[
        "\u0997\u09cb\u09b2"
    ],
    "name:bul_x_preferred":[
        "\u0413\u043e\u043b"
    ],
    "name:ceb_x_preferred":[
        "Gol"
    ],
    "name:ckb_x_preferred":[
        "\u06af\u06c6\u0644"
    ],
    "name:deu_x_preferred":[
        "Gol"
    ],
    "name:fra_x_preferred":[
        "Gol"
    ],
    "name:glg_x_preferred":[
        "Gol"
    ],
    "name:ind_x_preferred":[
        "Gol"
    ],
    "name:kur_x_preferred":[
        "Gol"
    ],
    "name:msa_x_preferred":[
        "Gol"
    ],
    "name:nds_x_preferred":[
        "Gol"
    ],
    "name:nld_x_preferred":[
        "Gol"
    ],
    "name:pol_x_preferred":[
        "Gol"
    ],
    "name:por_x_preferred":[
        "Gol"
    ],
    "name:ron_x_preferred":[
        "Gol"
    ],
    "name:rus_x_preferred":[
        "\u0413\u043e\u043b"
    ],
    "name:slv_x_preferred":[
        "Gol"
    ],
    "name:spa_x_preferred":[
        "Gol"
    ],
    "name:tur_x_preferred":[
        "Gol"
    ],
    "name:ukr_x_preferred":[
        "\u0413\u043e\u043b"
    ],
    "wof:name":"Gol",
    "wof:placetype":"locality"
},
  "geometry": {"coordinates":[39.30266,10.91349],"type":"Point"}
}