{
  "type": "Feature",
  "properties": {
    "gn:admin1_code":"46",
    "gn:asciiname":"Gol",
    "gn:country_code":"ET",
    "gn:dem":3245,
    "gn:feature_class":"P",
    "gn:feature_code":"PPL",
    "gn:name":"Gol",
    "gn:population":0,
    "gn:timezone":"Africa/Addis_Ababa",
    "iso:country":"ET",
    "wof:name":"Gol",
    "wof:placetype":"locality"
},
  "geometry": {"coordinates":[39.30266,10.91349],"type":"Point"}
}