{
  "type": "Feature",
  "properties": {
    "gn:admin1_code":"53",
    "gn:asciiname":"Gergember",
    "gn:country_code":"ET",
    "gn:dem":2264,
    "gn:feature_class":"P",
    "gn:feature_code":"PPL",
    "gn:name":"Gergember",
    "gn:population":0,
    "gn:timezone":"Africa/Addis_Ababa",
    "iso:country":"ET",
    "name:und_x_variant":[
        "Gruamber",
        "Gergember"
    ],
    "wof:name":"Gergember",
    "wof:placetype":"locality"
},
  "geometry": {"coordinates":[39.51361,13.47047],"type":"Point"}
}