{
  "type": "Feature",
  "properties": {
    "gn:admin1_code":"46",
    "gn:asciiname":"Gedam",
    "gn:country_code":"ET",
    "gn:dem":2472,
    "gn:feature_class":"P",
    "gn:feature_code":"PPL",
    "gn:name":"Gedam",
    "gn:population":0,
    "gn:timezone":"Africa/Addis_Ababa",
    "iso:country":"ET",
    "wof:name":"Gedam",
    "wof:placetype":"locality"
},
  "geometry": {"coordinates":[39.66099000000001,9.98467],"type":"Point"}
}