{
  "type": "Feature",
  "properties": {
    "gn:admin1_code":"51.0",
    "gn:asciiname":"Buk'ata",
    "gn:country_code":"ET",
    "gn:dem":1760,
    "gn:feature_class":"P",
    "gn:feature_code":"PPL",
    "gn:name":"Buk\u2019ata",
    "gn:population":0,
    "gn:timezone":"Africa/Addis_Ababa",
    "iso:country":"ET",
    "wof:name":"Buk'ata",
    "wof:placetype":"locality"
},
  "geometry": {"coordinates":[37.76667,8.38333],"type":"Point"}
}