{
  "type": "Feature",
  "properties": {
    "gn:admin1_code":"51",
    "gn:asciiname":"Haro Gorontu",
    "gn:country_code":"ET",
    "gn:dem":1502,
    "gn:feature_class":"P",
    "gn:feature_code":"PPL",
    "gn:name":"Haro Gorontu",
    "gn:population":0,
    "gn:timezone":"Africa/Addis_Ababa",
    "iso:country":"ET",
    "wof:name":"Haro Gorontu",
    "wof:placetype":"locality"
},
  "geometry": {"coordinates":[41.03734,7.75656],"type":"Point"}
}