{
  "type": "Feature",
  "properties": {
    "gn:admin1_code":"46.0",
    "gn:asciiname":"Arka",
    "gn:country_code":"ET",
    "gn:dem":2593,
    "gn:feature_class":"P",
    "gn:feature_code":"PPL",
    "gn:name":"\u0100rka",
    "gn:population":0,
    "gn:timezone":"Africa/Addis_Ababa",
    "iso:country":"ET",
    "name:ceb_x_preferred":[
        "Arka"
    ],
    "name:deu_x_preferred":[
        "Arka"
    ],
    "name:nld_x_preferred":[
        "Arka"
    ],
    "name:pol_x_preferred":[
        "Arka"
    ],
    "name:und_x_variant":[
        "\u0100rka (1)",
        "\u0100rka"
    ],
    "wof:name":"Arka",
    "wof:placetype":"locality"
},
  "geometry": {"coordinates":[39.16667,12.25],"type":"Point"}
}