{
  "type": "Feature",
  "properties": {
    "gn:admin1_code":"46.0",
    "gn:asciiname":"Dibo",
    "gn:country_code":"ET",
    "gn:dem":2455,
    "gn:feature_class":"P",
    "gn:feature_code":"PPL",
    "gn:name":"Dibo",
    "gn:population":0,
    "gn:timezone":"Africa/Addis_Ababa",
    "iso:country":"ET",
    "wof:name":"Dibo",
    "wof:placetype":"locality"
},
  "geometry": {"coordinates":[38.31667,10.85],"type":"Point"}
}