{
  "type": "Feature",
  "properties": {
    "gn:admin1_code":"51",
    "gn:asciiname":"Kombolcha",
    "gn:country_code":"ET",
    "gn:dem":2118,
    "gn:feature_class":"P",
    "gn:feature_code":"PPL",
    "gn:name":"Kombolcha",
    "gn:population":0,
    "gn:timezone":"Africa/Addis_Ababa",
    "iso:country":"ET",
    "name:rus_x_preferred":[
        "\u041a\u043e\u043c\u0431\u043e\u043b\u044c\u0447\u0430"
    ],
    "name:und_x_variant":[
        "Melkarafu",
        "Kembolcha",
        "Combulcia",
        "Kambolch\u0101",
        "Combolcia",
        "Kombalcha",
        "Cambolcia",
        "Kombalsha",
        "Kombolcha"
    ],
    "wof:name":"Kombolcha",
    "wof:placetype":"locality"
},
  "geometry": {"coordinates":[42.12131,9.4385],"type":"Point"}
}