{
  "type": "Feature",
  "properties": {
    "gn:admin1_code":"46.0",
    "gn:asciiname":"Debre Zebit",
    "gn:country_code":"ET",
    "gn:dem":2886,
    "gn:feature_class":"P",
    "gn:feature_code":"PPL",
    "gn:name":"Debre Zeb\u012bt",
    "gn:population":0,
    "gn:timezone":"Africa/Addis_Ababa",
    "iso:country":"ET",
    "name:fra_x_preferred":[
        "Debre Zebit"
    ],
    "name:und_x_variant":[
        "Zebit",
        "Debra Zebit",
        "Dabrazabat",
        "Debre Zeb\u012bt"
    ],
    "wof:name":"Debre Zebit",
    "wof:placetype":"locality"
},
  "geometry": {"coordinates":[38.58333,11.81667],"type":"Point"}
}