{
  "type": "Feature",
  "properties": {
    "gn:admin1_code":"46.0",
    "gn:asciiname":"Bolo",
    "gn:country_code":"ET",
    "gn:dem":3224,
    "gn:feature_class":"P",
    "gn:feature_code":"PPL",
    "gn:name":"Bolo",
    "gn:population":0,
    "gn:timezone":"Africa/Addis_Ababa",
    "iso:country":"ET",
    "name:ceb_x_preferred":[
        "Bolo"
    ],
    "name:deu_x_preferred":[
        "Bolo"
    ],
    "name:fra_x_preferred":[
        "Bolo"
    ],
    "name:glg_x_preferred":[
        "Bolo"
    ],
    "name:nld_x_preferred":[
        "Bolo"
    ],
    "name:pol_x_preferred":[
        "Bolo"
    ],
    "name:por_x_preferred":[
        "Bolo"
    ],
    "name:spa_x_preferred":[
        "Bolo"
    ],
    "name:swe_x_preferred":[
        "Bolo"
    ],
    "name:tgl_x_preferred":[
        "Bolo"
    ],
    "wof:name":"Bolo",
    "wof:placetype":"locality"
},
  "geometry": {"coordinates":[39.56762,10.9622],"type":"Point"}
}