{
  "type": "Feature",
  "properties": {
    "gn:admin1_code":"54.0",
    "gn:asciiname":"Burda",
    "gn:country_code":"ET",
    "gn:dem":1996,
    "gn:feature_class":"P",
    "gn:feature_code":"PPL",
    "gn:name":"Burda",
    "gn:population":0,
    "gn:timezone":"Africa/Addis_Ababa",
    "iso:country":"ET",
    "wof:name":"Burda",
    "wof:placetype":"locality"
},
  "geometry": {"coordinates":[36.81667,6.35],"type":"Point"}
}