{
  "type": "Feature",
  "properties": {
    "gn:admin1_code":"54.0",
    "gn:asciiname":"Burda",
    "gn:country_code":"ET",
    "gn:dem":1996,
    "gn:feature_class":"P",
    "gn:feature_code":"PPL",
    "gn:name":"Burda",
    "gn:population":0,
    "gn:timezone":"Africa/Addis_Ababa",
    "iso:country":"ET",
    "name:ces_x_preferred":[
        "Burda"
    ],
    "name:deu_x_preferred":[
        "Burda"
    ],
    "name:epo_x_preferred":[
        "Burda"
    ],
    "name:fra_x_preferred":[
        "Burda"
    ],
    "name:heb_x_preferred":[
        "\u05d1\u05d5\u05e8\u05d3\u05d4"
    ],
    "name:hun_x_preferred":[
        "Burda"
    ],
    "name:ron_x_preferred":[
        "Burda"
    ],
    "name:rus_x_preferred":[
        "\u0411\u0443\u0440\u0434\u0430"
    ],
    "name:slk_x_preferred":[
        "Burda"
    ],
    "name:swe_x_preferred":[
        "Burda"
    ],
    "name:ukr_x_preferred":[
        "\u0411\u0443\u0440\u0434\u0430"
    ],
    "wof:name":"Burda",
    "wof:placetype":"locality"
},
  "geometry": {"coordinates":[36.81667,6.35],"type":"Point"}
}