{
  "type": "Feature",
  "properties": {
    "gn:admin1_code":"51",
    "gn:asciiname":"Hambentu",
    "gn:country_code":"ET",
    "gn:dem":2338,
    "gn:feature_class":"P",
    "gn:feature_code":"PPL",
    "gn:name":"H\u0101mb\u0113ntu",
    "gn:population":0,
    "gn:timezone":"Africa/Addis_Ababa",
    "iso:country":"ET",
    "wof:name":"Hambentu",
    "wof:placetype":"locality"
},
  "geometry": {"coordinates":[39.95,7.36667],"type":"Point"}
}