{
  "type": "Feature",
  "properties": {
    "gn:admin1_code":"51.0",
    "gn:asciiname":"Hado",
    "gn:country_code":"ET",
    "gn:dem":1627,
    "gn:feature_class":"P",
    "gn:feature_code":"PPL",
    "gn:name":"Hado",
    "gn:population":0,
    "gn:timezone":"Africa/Addis_Ababa",
    "iso:country":"ET",
    "wof:name":"Hado",
    "wof:placetype":"locality"
},
  "geometry": {"coordinates":[42.50639,9.36611],"type":"Point"}
}