{
  "type": "Feature",
  "properties": {
    "gn:admin1_code":"53.0",
    "gn:asciiname":"Adi Herem",
    "gn:country_code":"ET",
    "gn:dem":1794,
    "gn:feature_class":"P",
    "gn:feature_code":"PPL",
    "gn:name":"\u0100d\u012b Herem",
    "gn:population":0,
    "gn:timezone":"Africa/Addis_Ababa",
    "iso:country":"ET",
    "name:und_x_variant":[
        "Addi Kherem",
        "\u0100d\u012b Herem"
    ],
    "wof:name":"Adi Herem",
    "wof:placetype":"locality"
},
  "geometry": {"coordinates":[39.25043,13.98079],"type":"Point"}
}