{
  "type": "Feature",
  "properties": {
    "gn:admin1_code":"52",
    "gn:asciiname":"Mule'ale",
    "gn:country_code":"ET",
    "gn:dem":1788,
    "gn:feature_class":"P",
    "gn:feature_code":"PPL",
    "gn:name":"Mule\u2019\u0101l\u0113",
    "gn:population":0,
    "gn:timezone":"Africa/Addis_Ababa",
    "iso:country":"ET",
    "wof:name":"Mule'ale",
    "wof:placetype":"locality"
},
  "geometry": {"coordinates":[43.02194,9.51444],"type":"Point"}
}