{
  "type": "Feature",
  "properties": {
    "gn:admin1_code":"54.0",
    "gn:asciiname":"Dimbira",
    "gn:country_code":"ET",
    "gn:dem":2006,
    "gn:feature_class":"P",
    "gn:feature_code":"PPL",
    "gn:name":"D\u012bmb\u012bra",
    "gn:population":0,
    "gn:timezone":"Africa/Addis_Ababa",
    "iso:country":"ET",
    "name:und_x_variant":[
        "Dembira",
        "D\u012bmb\u012bra"
    ],
    "wof:name":"Dimbira",
    "wof:placetype":"locality"
},
  "geometry": {"coordinates":[35.88333,7.25],"type":"Point"}
}