{
  "type": "Feature",
  "properties": {
    "gn:admin1_code":"49.0",
    "gn:asciiname":"Agac",
    "gn:country_code":"ET",
    "gn:dem":422,
    "gn:feature_class":"P",
    "gn:feature_code":"PPL",
    "gn:name":"Agac",
    "gn:population":0,
    "gn:timezone":"Africa/Addis_Ababa",
    "iso:country":"ET",
    "wof:name":"Agac",
    "wof:placetype":"locality"
},
  "geometry": {"coordinates":[33.85,7.61667],"type":"Point"}
}