{
  "type": "Feature",
  "properties": {
    "gn:admin1_code":"51",
    "gn:asciiname":"Illasa",
    "gn:country_code":"ET",
    "gn:dem":2424,
    "gn:feature_class":"P",
    "gn:feature_code":"PPL",
    "gn:name":"Illasa",
    "gn:population":0,
    "gn:timezone":"Africa/Addis_Ababa",
    "iso:country":"ET",
    "wof:name":"Illasa",
    "wof:placetype":"locality"
},
  "geometry": {"coordinates":[40.13333,7.08333],"type":"Point"}
}