{
  "type": "Feature",
  "properties": {
    "gn:admin1_code":"46",
    "gn:asciiname":"Yeduga",
    "gn:country_code":"ET",
    "gn:dem":2361,
    "gn:feature_class":"P",
    "gn:feature_code":"PPL",
    "gn:name":"Yeduga",
    "gn:population":0,
    "gn:timezone":"Africa/Addis_Ababa",
    "iso:country":"ET",
    "wof:name":"Yeduga",
    "wof:placetype":"locality"
},
  "geometry": {"coordinates":[37.76667,10.08333],"type":"Point"}
}