{
  "type": "Feature",
  "properties": {
    "gn:admin1_code":"54",
    "gn:asciiname":"Kegha",
    "gn:country_code":"ET",
    "gn:dem":2033,
    "gn:feature_class":"P",
    "gn:feature_code":"PPL",
    "gn:name":"Kegha",
    "gn:population":0,
    "gn:timezone":"Africa/Addis_Ababa",
    "iso:country":"ET",
    "name:und_x_variant":[
        "Checcia",
        "Kecha",
        "Kegha"
    ],
    "wof:name":"Kegha",
    "wof:placetype":"locality"
},
  "geometry": {"coordinates":[36.76667,5.13333],"type":"Point"}
}