{
  "type": "Feature",
  "properties": {
    "gn:admin1_code":"53.0",
    "gn:asciiname":"Akaza",
    "gn:country_code":"ET",
    "gn:dem":2445,
    "gn:feature_class":"P",
    "gn:feature_code":"PPL",
    "gn:name":"\u0100kaza",
    "gn:population":0,
    "gn:timezone":"Africa/Addis_Ababa",
    "iso:country":"ET",
    "wof:name":"Akaza",
    "wof:placetype":"locality"
},
  "geometry": {"coordinates":[39.67982,13.5117],"type":"Point"}
}