{
  "type": "Feature",
  "properties": {
    "gn:admin1_code":"53",
    "gn:asciiname":"Ki'en",
    "gn:country_code":"ET",
    "gn:dem":2356,
    "gn:feature_class":"P",
    "gn:feature_code":"PPL",
    "gn:name":"K\u012b\u2019\u0113n",
    "gn:population":0,
    "gn:timezone":"Africa/Addis_Ababa",
    "iso:country":"ET",
    "wof:name":"Ki'en",
    "wof:placetype":"locality"
},
  "geometry": {"coordinates":[39.62234,13.50276],"type":"Point"}
}