{
  "type": "Feature",
  "properties": {
    "gn:admin1_code":"46",
    "gn:asciiname":"Ker K'usk'wam",
    "gn:country_code":"ET",
    "gn:dem":1906,
    "gn:feature_class":"P",
    "gn:feature_code":"PPL",
    "gn:name":"K\u0113r K\u2019usk\u2019wam",
    "gn:population":0,
    "gn:timezone":"Africa/Addis_Ababa",
    "iso:country":"ET",
    "name:und_x_variant":[
        "Cercusquam",
        "K\u0113r K\u2019usk\u2019wam"
    ],
    "wof:name":"Ker K'usk'wam",
    "wof:placetype":"locality"
},
  "geometry": {"coordinates":[37.01667,11.41667],"type":"Point"}
}