{
  "type": "Feature",
  "properties": {
    "gn:admin1_code":"46.0",
    "gn:asciiname":"Chenefer",
    "gn:country_code":"ET",
    "gn:dem":2879,
    "gn:feature_class":"P",
    "gn:feature_code":"PPL",
    "gn:name":"Chenefer",
    "gn:population":0,
    "gn:timezone":"Africa/Addis_Ababa",
    "iso:country":"ET",
    "wof:name":"Chenefer",
    "wof:placetype":"locality"
},
  "geometry": {"coordinates":[39.06667,11.51667],"type":"Point"}
}