{
  "type": "Feature",
  "properties": {
    "gn:admin1_code":"46",
    "gn:asciiname":"Gotot",
    "gn:country_code":"ET",
    "gn:dem":2504,
    "gn:feature_class":"P",
    "gn:feature_code":"PPL",
    "gn:name":"Gotot",
    "gn:population":0,
    "gn:timezone":"Africa/Addis_Ababa",
    "iso:country":"ET",
    "wof:name":"Gotot",
    "wof:placetype":"locality"
},
  "geometry": {"coordinates":[39.36667,12.28333],"type":"Point"}
}