{
  "type": "Feature",
  "properties": {
    "gn:admin1_code":"52.0",
    "gn:asciiname":"Jirit",
    "gn:country_code":"ET",
    "gn:dem":509,
    "gn:feature_class":"P",
    "gn:feature_code":"PPL",
    "gn:name":"Jirit",
    "gn:population":0,
    "gn:timezone":"Africa/Addis_Ababa",
    "iso:country":"ET",
    "name:und_x_variant":[
        "Dzhirit",
        "Jirit"
    ],
    "wof:name":"Jirit",
    "wof:placetype":"locality"
},
  "geometry": {"coordinates":[43.36972,5.57056],"type":"Point"}
}