{
  "type": "Feature",
  "properties": {
    "gn:admin1_code":"51",
    "gn:asciiname":"Ibano",
    "gn:country_code":"ET",
    "gn:dem":2680,
    "gn:feature_class":"P",
    "gn:feature_code":"PPL",
    "gn:name":"\u012abano",
    "gn:population":0,
    "gn:timezone":"Africa/Addis_Ababa",
    "iso:country":"ET",
    "name:und_x_variant":[
        "Ebano",
        "Ieban\u00f2",
        "\u012abano"
    ],
    "wof:name":"Ibano",
    "wof:placetype":"locality"
},
  "geometry": {"coordinates":[38.75,6.86667],"type":"Point"}
}