{
  "type": "Feature",
  "properties": {
    "gn:admin1_code":"52.0",
    "gn:asciiname":"Dega Yiley",
    "gn:country_code":"ET",
    "gn:dem":338,
    "gn:feature_class":"P",
    "gn:feature_code":"PPL",
    "gn:name":"Dega Yil\u0113y",
    "gn:population":0,
    "gn:timezone":"Africa/Addis_Ababa",
    "iso:country":"ET",
    "name:und_x_variant":[
        "Dagaielei",
        "Dega Iiley",
        "Dega Yil\u0113y"
    ],
    "wof:name":"Dega Yiley",
    "wof:placetype":"locality"
},
  "geometry": {"coordinates":[42.765,6.2525],"type":"Point"}
}