{
  "type": "Feature",
  "properties": {
    "gn:admin1_code":"46.0",
    "gn:asciiname":"Gerbi",
    "gn:country_code":"ET",
    "gn:dem":1430,
    "gn:feature_class":"P",
    "gn:feature_code":"PPL",
    "gn:name":"Gerbi",
    "gn:population":0,
    "gn:timezone":"Africa/Addis_Ababa",
    "iso:country":"ET",
    "name:und_x_variant":[
        "Bab\u012bl\u0113",
        "Gerbi"
    ],
    "wof:name":"Gerbi",
    "wof:placetype":"locality"
},
  "geometry": {"coordinates":[39.82895,10.74759],"type":"Point"}
}