{
  "type": "Feature",
  "properties": {
    "gn:admin1_code":"51",
    "gn:asciiname":"Kotja",
    "gn:country_code":"ET",
    "gn:dem":1712,
    "gn:feature_class":"P",
    "gn:feature_code":"PPL",
    "gn:name":"Kotja",
    "gn:population":0,
    "gn:timezone":"Africa/Addis_Ababa",
    "iso:country":"ET",
    "wof:name":"Kotja",
    "wof:placetype":"locality"
},
  "geometry": {"coordinates":[36.86667,7.65],"type":"Point"}
}