{
  "type": "Feature",
  "properties": {
    "gn:admin1_code":"45.0",
    "gn:asciiname":"Asegela",
    "gn:country_code":"ET",
    "gn:dem":-85,
    "gn:feature_class":"P",
    "gn:feature_code":"PPL",
    "gn:name":"Asegela",
    "gn:population":0,
    "gn:timezone":"Africa/Addis_Ababa",
    "iso:country":"ET",
    "name:rus_x_preferred":[
        "\u0410\u0441\u044d\u043b\u043b\u0430"
    ],
    "name:und_x_variant":[
        "Asagal\u0101",
        "Assagella",
        "Assagalla",
        "Asegela"
    ],
    "wof:name":"Asegela",
    "wof:placetype":"locality"
},
  "geometry": {"coordinates":[40.73655,13.9135],"type":"Point"}
}