{
  "type": "Feature",
  "properties": {
    "gn:admin1_code":"54",
    "gn:asciiname":"Meyla",
    "gn:country_code":"ET",
    "gn:dem":1617,
    "gn:feature_class":"P",
    "gn:feature_code":"PPL",
    "gn:name":"Meyla",
    "gn:population":0,
    "gn:timezone":"Africa/Addis_Ababa",
    "iso:country":"ET",
    "wof:name":"Meyla",
    "wof:placetype":"locality"
},
  "geometry": {"coordinates":[37.11667,6.96667],"type":"Point"}
}