{
  "type": "Feature",
  "properties": {
    "gn:admin1_code":"53.0",
    "gn:asciiname":"Adi K'ajera",
    "gn:country_code":"ET",
    "gn:dem":1962,
    "gn:feature_class":"P",
    "gn:feature_code":"PPL",
    "gn:name":"\u0100d\u012b K\u2019ajera",
    "gn:population":0,
    "gn:timezone":"Africa/Addis_Ababa",
    "iso:country":"ET",
    "name:und_x_variant":[
        "Addi Kajera",
        "Addi Kadzhera",
        "\u0100d\u012b K\u2019ajera"
    ],
    "wof:name":"Adi K'ajera",
    "wof:placetype":"locality"
},
  "geometry": {"coordinates":[39.4311,13.37384],"type":"Point"}
}