{
  "type": "Feature",
  "properties": {
    "gn:admin1_code":"53.0",
    "gn:asciiname":"Adi Bula",
    "gn:country_code":"ET",
    "gn:dem":1574,
    "gn:feature_class":"P",
    "gn:feature_code":"PPL",
    "gn:name":"\u0100d\u012b Bula",
    "gn:population":0,
    "gn:timezone":"Africa/Addis_Ababa",
    "iso:country":"ET",
    "name:und_x_variant":[
        "\u0100l\u012b Bula",
        "\u0100d\u012b Bula"
    ],
    "wof:name":"Adi Bula",
    "wof:placetype":"locality"
},
  "geometry": {"coordinates":[38.96667,13.46667],"type":"Point"}
}