{
  "type": "Feature",
  "properties": {
    "gn:admin1_code":"54",
    "gn:asciiname":"Weyra",
    "gn:country_code":"ET",
    "gn:dem":2290,
    "gn:feature_class":"P",
    "gn:feature_code":"PPL",
    "gn:name":"Weyra",
    "gn:population":0,
    "gn:timezone":"Africa/Addis_Ababa",
    "iso:country":"ET",
    "wof:name":"Weyra",
    "wof:placetype":"locality"
},
  "geometry": {"coordinates":[37.48333,7.71667],"type":"Point"}
}