{
  "type": "Feature",
  "properties": {
    "gn:admin1_code":"54.0",
    "gn:asciiname":"Puya",
    "gn:country_code":"ET",
    "gn:dem":466,
    "gn:feature_class":"P",
    "gn:feature_code":"PPL",
    "gn:name":"Puya",
    "gn:population":0,
    "gn:timezone":"Africa/Addis_Ababa",
    "iso:country":"ET",
    "name:fra_x_preferred":[
        "Puya"
    ],
    "name:ita_x_preferred":[
        "Puya"
    ],
    "name:ron_x_preferred":[
        "Puya"
    ],
    "name:rus_x_preferred":[
        "\u041f\u0443\u0439\u044f"
    ],
    "name:spa_x_preferred":[
        "Puya"
    ],
    "name:vie_x_preferred":[
        "Puya"
    ],
    "wof:name":"Puya",
    "wof:placetype":"locality"
},
  "geometry": {"coordinates":[34.3198,6.94728],"type":"Point"}
}