{
  "type": "Feature",
  "properties": {
    "gn:admin1_code":"51",
    "gn:asciiname":"Gorey",
    "gn:country_code":"ET",
    "gn:dem":1648,
    "gn:feature_class":"P",
    "gn:feature_code":"PPL",
    "gn:name":"Gor\u0113y",
    "gn:population":0,
    "gn:timezone":"Africa/Addis_Ababa",
    "iso:country":"ET",
    "wof:name":"Gorey",
    "wof:placetype":"locality"
},
  "geometry": {"coordinates":[42.54583,9.23194],"type":"Point"}
}