{
  "type": "Feature",
  "properties": {
    "gn:admin1_code":"51.0",
    "gn:asciiname":"Abomsa",
    "gn:country_code":"ET",
    "gn:dem":1410,
    "gn:feature_class":"P",
    "gn:feature_code":"PPL",
    "gn:name":"\u0100bomsa",
    "gn:population":0,
    "gn:timezone":"Africa/Addis_Ababa",
    "iso:country":"ET",
    "name:azb_x_preferred":[
        "\u0627\u0628\u0648\u0645\u0633\u0627"
    ],
    "name:fas_x_preferred":[
        "\u0627\u0628\u0648\u0645\u0633\u0627"
    ],
    "name:fra_x_preferred":[
        "Abomsa"
    ],
    "name:und_x_variant":[
        "\u0100bomsa"
    ],
    "name:zho_x_preferred":[
        "\u963f\u535a\u59c6\u85a9"
    ],
    "wof:name":"Abomsa",
    "wof:placetype":"locality"
},
  "geometry": {"coordinates":[39.85,8.58333],"type":"Point"}
}