{
  "type": "Feature",
  "properties": {
    "gn:admin1_code":"51.0",
    "gn:asciiname":"Beriso",
    "gn:country_code":"ET",
    "gn:dem":2163,
    "gn:feature_class":"P",
    "gn:feature_code":"PPL",
    "gn:name":"Ber\u012bso",
    "gn:population":0,
    "gn:timezone":"Africa/Addis_Ababa",
    "iso:country":"ET",
    "wof:name":"Beriso",
    "wof:placetype":"locality"
},
  "geometry": {"coordinates":[36.21667,9.88333],"type":"Point"}
}