{
  "type": "Feature",
  "properties": {
    "gn:admin1_code":"45.0",
    "gn:asciiname":"Cartati",
    "gn:country_code":"ET",
    "gn:dem":629,
    "gn:feature_class":"P",
    "gn:feature_code":"PPL",
    "gn:name":"Cartati",
    "gn:population":0,
    "gn:timezone":"Africa/Addis_Ababa",
    "iso:country":"ET",
    "name:und_x_variant":[
        "Cartad",
        "Cartati"
    ],
    "wof:name":"Cartati",
    "wof:placetype":"locality"
},
  "geometry": {"coordinates":[41.57649,12.05814],"type":"Point"}
}