{
  "type": "Feature",
  "properties": {
    "gn:admin1_code":"53.0",
    "gn:asciiname":"Auza",
    "gn:country_code":"ET",
    "gn:dem":2049,
    "gn:feature_class":"P",
    "gn:feature_code":"PPL",
    "gn:name":"Auza",
    "gn:population":0,
    "gn:timezone":"Africa/Addis_Ababa",
    "iso:country":"ET",
    "wof:name":"Auza",
    "wof:placetype":"locality"
},
  "geometry": {"coordinates":[39.52751,13.79287],"type":"Point"}
}