{
  "type": "Feature",
  "properties": {
    "gn:admin1_code":"46",
    "gn:asciiname":"Tulu",
    "gn:country_code":"ET",
    "gn:dem":1455,
    "gn:feature_class":"P",
    "gn:feature_code":"PPL",
    "gn:name":"Tulu",
    "gn:population":0,
    "gn:timezone":"Africa/Addis_Ababa",
    "iso:country":"ET",
    "name:ceb_x_preferred":[
        "Tulu"
    ],
    "name:deu_x_preferred":[
        "Tulu"
    ],
    "name:rus_x_preferred":[
        "\u0422\u0443\u043b\u0443"
    ],
    "name:swe_x_preferred":[
        "Tulu"
    ],
    "wof:name":"Tulu",
    "wof:placetype":"locality"
},
  "geometry": {"coordinates":[39.80118,10.85848],"type":"Point"}
}