{
  "type": "Feature",
  "properties": {
    "gn:admin1_code":"46.0",
    "gn:asciiname":"Bambolina",
    "gn:country_code":"ET",
    "gn:dem":1160,
    "gn:feature_class":"P",
    "gn:feature_code":"PPL",
    "gn:name":"Bambolina",
    "gn:population":0,
    "gn:timezone":"Africa/Addis_Ababa",
    "iso:country":"ET",
    "name:und_x_variant":[
        "Bamboline",
        "Bambolina"
    ],
    "wof:name":"Bambolina",
    "wof:placetype":"locality"
},
  "geometry": {"coordinates":[38.51667,12.76667],"type":"Point"}
}