{
  "type": "Feature",
  "properties": {
    "gn:admin1_code":"51.0",
    "gn:asciiname":"Deri",
    "gn:country_code":"ET",
    "gn:dem":2188,
    "gn:feature_class":"P",
    "gn:feature_code":"PPL",
    "gn:name":"Der\u012b",
    "gn:population":0,
    "gn:timezone":"Africa/Addis_Ababa",
    "iso:country":"ET",
    "name:ceb_x_preferred":[
        "Deri"
    ],
    "name:deu_x_preferred":[
        "Deri"
    ],
    "name:fra_x_preferred":[
        "D\u00e9ri"
    ],
    "name:heb_x_preferred":[
        "\u05d3\u05e8\u05e2\u05d9"
    ],
    "name:swe_x_preferred":[
        "Deri"
    ],
    "wof:name":"Deri",
    "wof:placetype":"locality"
},
  "geometry": {"coordinates":[42.42,9.44778],"type":"Point"}
}