{
  "type": "Feature",
  "properties": {
    "gn:admin1_code":"51",
    "gn:asciiname":"Warsu",
    "gn:country_code":"ET",
    "gn:dem":2132,
    "gn:feature_class":"P",
    "gn:feature_code":"PPL",
    "gn:name":"Warsu",
    "gn:population":0,
    "gn:timezone":"Africa/Addis_Ababa",
    "iso:country":"ET",
    "wof:name":"Warsu",
    "wof:placetype":"locality"
},
  "geometry": {"coordinates":[36.43333,9.83333],"type":"Point"}
}