{
  "type": "Feature",
  "properties": {
    "gn:admin1_code":"46",
    "gn:asciiname":"Koreta",
    "gn:country_code":"ET",
    "gn:dem":1688,
    "gn:feature_class":"P",
    "gn:feature_code":"PPL",
    "gn:name":"Koreta",
    "gn:population":0,
    "gn:timezone":"Africa/Addis_Ababa",
    "iso:country":"ET",
    "wof:name":"Koreta",
    "wof:placetype":"locality"
},
  "geometry": {"coordinates":[37.53333,11.48333],"type":"Point"}
}