{
  "type": "Feature",
  "properties": {
    "gn:admin1_code":"52.0",
    "gn:asciiname":"Bogol Manyo",
    "gn:country_code":"ET",
    "gn:dem":393,
    "gn:feature_class":"P",
    "gn:feature_code":"PPL",
    "gn:name":"Bogol Manyo",
    "gn:population":0,
    "gn:timezone":"Africa/Addis_Ababa",
    "iso:country":"ET",
    "name:rus_x_preferred":[
        "Bogol\u2019-Man\u2019o"
    ],
    "name:und_x_variant":[
        "Magno",
        "Bokolmayu",
        "Bokol Mayo",
        "Bogol",
        "Bogol Magno",
        "Bogol Manyo"
    ],
    "wof:name":"Bogol Manyo",
    "wof:placetype":"locality"
},
  "geometry": {"coordinates":[41.53639,4.5175],"type":"Point"}
}