{
  "type": "Feature",
  "properties": {
    "gn:admin1_code":"49.0",
    "gn:asciiname":"Vuntu",
    "gn:country_code":"ET",
    "gn:dem":414,
    "gn:feature_class":"P",
    "gn:feature_code":"PPL",
    "gn:name":"Vuntu",
    "gn:population":0,
    "gn:timezone":"Africa/Addis_Ababa",
    "iso:country":"ET",
    "wof:name":"Vuntu",
    "wof:placetype":"locality"
},
  "geometry": {"coordinates":[33.65253,8.24563],"type":"Point"}
}