{
  "type": "Feature",
  "properties": {
    "gn:admin1_code":"53",
    "gn:asciiname":"Mengela",
    "gn:country_code":"ET",
    "gn:dem":2336,
    "gn:feature_class":"P",
    "gn:feature_code":"PPL",
    "gn:name":"Meng\u0113la",
    "gn:population":0,
    "gn:timezone":"Africa/Addis_Ababa",
    "iso:country":"ET",
    "wof:name":"Mengela",
    "wof:placetype":"locality"
},
  "geometry": {"coordinates":[39.72959,14.28319],"type":"Point"}
}