{
  "type": "Feature",
  "properties": {
    "gn:admin1_code":"51",
    "gn:asciiname":"Jagenfoy",
    "gn:country_code":"ET",
    "gn:dem":2088,
    "gn:feature_class":"P",
    "gn:feature_code":"PPL",
    "gn:name":"Jagenfoy",
    "gn:population":0,
    "gn:timezone":"Africa/Addis_Ababa",
    "iso:country":"ET",
    "wof:name":"Jagenfoy",
    "wof:placetype":"locality"
},
  "geometry": {"coordinates":[36.43333,9.81667],"type":"Point"}
}