{
  "type": "Feature",
  "properties": {
    "gn:admin1_code":"53",
    "gn:asciiname":"Furkwa",
    "gn:country_code":"ET",
    "gn:dem":2447,
    "gn:feature_class":"P",
    "gn:feature_code":"PPL",
    "gn:name":"Furkwa",
    "gn:population":0,
    "gn:timezone":"Africa/Addis_Ababa",
    "iso:country":"ET",
    "name:und_x_variant":[
        "Furkuo"
    ],
    "wof:name":"Furkwa",
    "wof:placetype":"locality"
},
  "geometry": {"coordinates":[39.63058,13.59205],"type":"Point"}
}