{
  "type": "Feature",
  "properties": {
    "gn:admin1_code":"49",
    "gn:asciiname":"Kwonyrek",
    "gn:country_code":"ET",
    "gn:dem":410,
    "gn:feature_class":"P",
    "gn:feature_code":"PPL",
    "gn:name":"Kwonyrek",
    "gn:population":0,
    "gn:timezone":"Africa/Addis_Ababa",
    "iso:country":"ET",
    "wof:name":"Kwonyrek",
    "wof:placetype":"locality"
},
  "geometry": {"coordinates":[33.08232,8.03692],"type":"Point"}
}