{
  "type": "Feature",
  "properties": {
    "gn:admin1_code":"51",
    "gn:asciiname":"Harbu Deko",
    "gn:country_code":"ET",
    "gn:dem":2530,
    "gn:feature_class":"P",
    "gn:feature_code":"PPL",
    "gn:name":"Harbu D\u0113ko",
    "gn:population":0,
    "gn:timezone":"Africa/Addis_Ababa",
    "iso:country":"ET",
    "wof:name":"Harbu Deko",
    "wof:placetype":"locality"
},
  "geometry": {"coordinates":[37.13333,9.81667],"type":"Point"}
}