{
  "type": "Feature",
  "properties": {
    "gn:admin1_code":"54",
    "gn:asciiname":"Segen",
    "gn:country_code":"ET",
    "gn:dem":971,
    "gn:feature_class":"P",
    "gn:feature_code":"PPL",
    "gn:name":"Segen",
    "gn:population":0,
    "gn:timezone":"Africa/Addis_Ababa",
    "iso:country":"ET",
    "wof:name":"Segen",
    "wof:placetype":"locality"
},
  "geometry": {"coordinates":[37.76667,5.58333],"type":"Point"}
}