{
  "type": "Feature",
  "properties": {
    "gn:admin1_code":"54.0",
    "gn:asciiname":"Beyo",
    "gn:country_code":"ET",
    "gn:dem":1108,
    "gn:feature_class":"P",
    "gn:feature_code":"PPL",
    "gn:name":"Beyo",
    "gn:population":0,
    "gn:timezone":"Africa/Addis_Ababa",
    "iso:country":"ET",
    "wof:name":"Beyo",
    "wof:placetype":"locality"
},
  "geometry": {"coordinates":[37.06667,6.01667],"type":"Point"}
}