{
  "type": "Feature",
  "properties": {
    "gn:admin1_code":"52.0",
    "gn:asciiname":"Burta En",
    "gn:country_code":"ET",
    "gn:dem":849,
    "gn:feature_class":"P",
    "gn:feature_code":"PPL",
    "gn:name":"Burta En",
    "gn:population":0,
    "gn:timezone":"Africa/Addis_Ababa",
    "iso:country":"ET",
    "name:und_x_variant":[
        "Burta Hen",
        "Burta En"
    ],
    "wof:name":"Burta En",
    "wof:placetype":"locality"
},
  "geometry": {"coordinates":[43.58333,7.66667],"type":"Point"}
}