{
  "type": "Feature",
  "properties": {
    "gn:admin1_code":"47",
    "gn:asciiname":"Mora",
    "gn:country_code":"ET",
    "gn:dem":1561,
    "gn:feature_class":"P",
    "gn:feature_code":"PPL",
    "gn:name":"Mora",
    "gn:population":0,
    "gn:timezone":"Africa/Addis_Ababa",
    "iso:country":"ET",
    "name:arg_x_preferred":[
        "Mora"
    ],
    "name:bul_x_preferred":[
        "\u041c\u043e\u0440\u0430"
    ],
    "name:cat_x_preferred":[
        "Mora"
    ],
    "name:ceb_x_preferred":[
        "Mora"
    ],
    "name:ces_x_preferred":[
        "Mora"
    ],
    "name:deu_x_preferred":[
        "Mora"
    ],
    "name:ell_x_preferred":[
        "\u039c\u03cc\u03c1\u03b1"
    ],
    "name:epo_x_preferred":[
        "Mora"
    ],
    "name:eus_x_preferred":[
        "Mora"
    ],
    "name:fas_x_preferred":[
        "\u0645\u0648\u0631\u0627"
    ],
    "name:fin_x_preferred":[
        "Mora"
    ],
    "name:fra_x_preferred":[
        "Mora"
    ],
    "name:heb_x_preferred":[
        "\u05de\u05d5\u05e8\u05d4"
    ],
    "name:hun_x_preferred":[
        "Mora"
    ],
    "name:ind_x_preferred":[
        "Mora"
    ],
    "name:ita_x_preferred":[
        "Mora"
    ],
    "name:jpn_x_preferred":[
        "\u30e2\u30fc\u30e9"
    ],
    "name:lav_x_preferred":[
        "Mora"
    ],
    "name:lit_x_preferred":[
        "Mora"
    ],
    "name:mzn_x_preferred":[
        "\u0645\u0648\u0631\u0627"
    ],
    "name:nld_x_preferred":[
        "Mora"
    ],
    "name:nor_x_preferred":[
        "Mora"
    ],
    "name:pol_x_preferred":[
        "Mora"
    ],
    "name:por_x_preferred":[
        "Mora"
    ],
    "name:rus_x_preferred":[
        "\u041c\u043e\u0440\u0430"
    ],
    "name:slk_x_preferred":[
        "Mora"
    ],
    "name:spa_x_preferred":[
        "Mora"
    ],
    "name:srp_x_preferred":[
        "\u041c\u043e\u0440\u0430"
    ],
    "name:swe_x_preferred":[
        "Mora"
    ],
    "name:tur_x_preferred":[
        "Mora"
    ],
    "name:ukr_x_preferred":[
        "\u041c\u043e\u0440\u0430"
    ],
    "name:vol_x_preferred":[
        "Mora"
    ],
    "name:zho_x_preferred":[
        "Mora"
    ],
    "wof:name":"Mora",
    "wof:placetype":"locality"
},
  "geometry": {"coordinates":[36.16667,10.55],"type":"Point"}
}