{
  "type": "Feature",
  "properties": {
    "gn:admin1_code":"49.0",
    "gn:asciiname":"Rek Ngor",
    "gn:country_code":"ET",
    "gn:dem":422,
    "gn:feature_class":"P",
    "gn:feature_code":"PPL",
    "gn:name":"Rek Ngor",
    "gn:population":0,
    "gn:timezone":"Africa/Addis_Ababa",
    "iso:country":"ET",
    "name:und_x_variant":[
        "Nikau"
    ],
    "wof:name":"Rek Ngor",
    "wof:placetype":"locality"
},
  "geometry": {"coordinates":[33.93307,8.26052],"type":"Point"}
}