{
  "type": "Feature",
  "properties": {
    "gn:admin1_code":"46",
    "gn:asciiname":"Jarota",
    "gn:country_code":"ET",
    "gn:dem":1706,
    "gn:feature_class":"P",
    "gn:feature_code":"PPL",
    "gn:name":"Jarota",
    "gn:population":0,
    "gn:timezone":"Africa/Addis_Ababa",
    "iso:country":"ET",
    "wof:name":"Jarota",
    "wof:placetype":"locality"
},
  "geometry": {"coordinates":[39.68333,11.75],"type":"Point"}
}