{
  "type": "Feature",
  "properties": {
    "gn:admin1_code":"51.0",
    "gn:asciiname":"Coromma",
    "gn:country_code":"ET",
    "gn:dem":1842,
    "gn:feature_class":"P",
    "gn:feature_code":"PPL",
    "gn:name":"Coromma",
    "gn:population":0,
    "gn:timezone":"Africa/Addis_Ababa",
    "iso:country":"ET",
    "wof:name":"Coromma",
    "wof:placetype":"locality"
},
  "geometry": {"coordinates":[38.08333,5.51667],"type":"Point"}
}