{
  "type": "Feature",
  "properties": {
    "gn:admin1_code":"52.0",
    "gn:asciiname":"Denan",
    "gn:country_code":"ET",
    "gn:dem":435,
    "gn:feature_class":"P",
    "gn:feature_code":"PPL",
    "gn:name":"Denan",
    "gn:population":0,
    "gn:timezone":"Africa/Addis_Ababa",
    "iso:country":"ET",
    "name:deu_x_preferred":[
        "Danan"
    ],
    "name:fra_x_preferred":[
        "Danan"
    ],
    "name:rus_x_preferred":[
        "\u0414\u0430\u043d\u0430\u043d"
    ],
    "name:und_x_variant":[
        "Badu Danan",
        "Danane",
        "Denan"
    ],
    "wof:name":"Denan",
    "wof:placetype":"locality"
},
  "geometry": {"coordinates":[43.49222,6.50611],"type":"Point"}
}