{
  "type": "Feature",
  "properties": {
    "gn:admin1_code":"46",
    "gn:asciiname":"K'ersa",
    "gn:country_code":"ET",
    "gn:dem":2655,
    "gn:feature_class":"P",
    "gn:feature_code":"PPL",
    "gn:name":"K\u2019ersa",
    "gn:population":0,
    "gn:timezone":"Africa/Addis_Ababa",
    "iso:country":"ET",
    "wof:name":"K'ersa",
    "wof:placetype":"locality"
},
  "geometry": {"coordinates":[39.23195,9.86141],"type":"Point"}
}