{
  "type": "Feature",
  "properties": {
    "gn:admin1_code":"46.0",
    "gn:asciiname":"Aba Libanos",
    "gn:country_code":"ET",
    "gn:dem":1796,
    "gn:feature_class":"P",
    "gn:feature_code":"PPL",
    "gn:name":"\u0100ba L\u012bbanos",
    "gn:population":0,
    "gn:timezone":"Africa/Addis_Ababa",
    "iso:country":"ET",
    "name:und_x_variant":[
        "\u0100ba L\u012bbanos (2)",
        "\u0100ba L\u012bbanos"
    ],
    "wof:name":"Aba Libanos",
    "wof:placetype":"locality"
},
  "geometry": {"coordinates":[37.35,12.35],"type":"Point"}
}