{
  "type": "Feature",
  "properties": {
    "gn:admin1_code":"53",
    "gn:asciiname":"Meswa'it",
    "gn:country_code":"ET",
    "gn:dem":2439,
    "gn:feature_class":"P",
    "gn:feature_code":"PPL",
    "gn:name":"Meswa\u2019it",
    "gn:population":0,
    "gn:timezone":"Africa/Addis_Ababa",
    "iso:country":"ET",
    "wof:name":"Meswa'it",
    "wof:placetype":"locality"
},
  "geometry": {"coordinates":[39.54333,12.69417],"type":"Point"}
}