{
  "type": "Feature",
  "properties": {
    "gn:admin1_code":"51.0",
    "gn:asciiname":"Buyo",
    "gn:country_code":"ET",
    "gn:dem":1793,
    "gn:feature_class":"P",
    "gn:feature_code":"PPL",
    "gn:name":"Buyo",
    "gn:population":0,
    "gn:timezone":"Africa/Addis_Ababa",
    "iso:country":"ET",
    "name:ceb_x_preferred":[
        "Buyo"
    ],
    "name:deu_x_preferred":[
        "Buyo"
    ],
    "name:fra_x_preferred":[
        "Buyo"
    ],
    "name:rus_x_preferred":[
        "\u0411\u0443\u0439\u043e"
    ],
    "name:tgl_x_preferred":[
        "Buyo"
    ],
    "wof:name":"Buyo",
    "wof:placetype":"locality"
},
  "geometry": {"coordinates":[38.05,9.48333],"type":"Point"}
}