{
  "type": "Feature",
  "properties": {
    "gn:admin1_code":"53.0",
    "gn:asciiname":"Addit'o",
    "gn:country_code":"ET",
    "gn:dem":2050,
    "gn:feature_class":"P",
    "gn:feature_code":"PPL",
    "gn:name":"Addit'o",
    "gn:population":0,
    "gn:timezone":"Africa/Addis_Ababa",
    "iso:country":"ET",
    "name:und_x_variant":[
        "\u0100d\u012b \u012ayo"
    ],
    "wof:name":"Addit'o",
    "wof:placetype":"locality"
},
  "geometry": {"coordinates":[38.65403,14.05872],"type":"Point"}
}