{
  "type": "Feature",
  "properties": {
    "gn:admin1_code":"52.0",
    "gn:asciiname":"Arrho",
    "gn:country_code":"ET",
    "gn:dem":1347,
    "gn:feature_class":"P",
    "gn:feature_code":"PPL",
    "gn:name":"Arrho",
    "gn:population":0,
    "gn:timezone":"Africa/Addis_Ababa",
    "iso:country":"ET",
    "wof:name":"Arrho",
    "wof:placetype":"locality"
},
  "geometry": {"coordinates":[42.96667,9.96667],"type":"Point"}
}