{
  "type": "Feature",
  "properties": {
    "gn:admin1_code":"53.0",
    "gn:asciiname":"Adi Gidey",
    "gn:country_code":"ET",
    "gn:dem":1853,
    "gn:feature_class":"P",
    "gn:feature_code":"PPL",
    "gn:name":"\u0100d\u012b Gidey",
    "gn:population":0,
    "gn:timezone":"Africa/Addis_Ababa",
    "iso:country":"ET",
    "name:und_x_variant":[
        "Addi Gidey",
        "\u0100d\u012b Gidey"
    ],
    "wof:name":"Adi Gidey",
    "wof:placetype":"locality"
},
  "geometry": {"coordinates":[39.03629,13.77016],"type":"Point"}
}