{
  "type": "Feature",
  "properties": {
    "gn:admin1_code":"51",
    "gn:asciiname":"Mendida",
    "gn:country_code":"ET",
    "gn:dem":2796,
    "gn:feature_class":"P",
    "gn:feature_code":"PPL",
    "gn:name":"Mend\u012bda",
    "gn:population":0,
    "gn:timezone":"Africa/Addis_Ababa",
    "iso:country":"ET",
    "name:und_x_variant":[
        "Medida",
        "Mend\u012bda"
    ],
    "wof:name":"Mendida",
    "wof:placetype":"locality"
},
  "geometry": {"coordinates":[39.31651,9.65699],"type":"Point"}
}