{
  "type": "Feature",
  "properties": {
    "gn:admin1_code":"46",
    "gn:asciiname":"Genda",
    "gn:country_code":"ET",
    "gn:dem":1906,
    "gn:feature_class":"P",
    "gn:feature_code":"PPL",
    "gn:name":"Genda",
    "gn:population":0,
    "gn:timezone":"Africa/Addis_Ababa",
    "iso:country":"ET",
    "name:ceb_x_preferred":[
        "Genda"
    ],
    "name:deu_x_preferred":[
        "Genda"
    ],
    "name:rus_x_preferred":[
        "\u0413\u044d\u043d\u0434\u0430"
    ],
    "name:swe_x_preferred":[
        "Genda"
    ],
    "wof:name":"Genda",
    "wof:placetype":"locality"
},
  "geometry": {"coordinates":[37.26667,12.36667],"type":"Point"}
}