{
  "type": "Feature",
  "properties": {
    "gn:admin1_code":"53.0",
    "gn:asciiname":"Alaur",
    "gn:country_code":"ET",
    "gn:dem":1934,
    "gn:feature_class":"P",
    "gn:feature_code":"PPL",
    "gn:name":"Alaur",
    "gn:population":0,
    "gn:timezone":"Africa/Addis_Ababa",
    "iso:country":"ET",
    "name:pan_x_preferred":[
        "\u0a05\u0a32\u0a4c\u0a5c"
    ],
    "wof:name":"Alaur",
    "wof:placetype":"locality"
},
  "geometry": {"coordinates":[39.45,13.56667],"type":"Point"}
}