{
  "type": "Feature",
  "properties": {
    "gn:admin1_code":"46.0",
    "gn:asciiname":"Chirchemesce",
    "gn:country_code":"ET",
    "gn:dem":1056,
    "gn:feature_class":"P",
    "gn:feature_code":"PPL",
    "gn:name":"Chirchemesce",
    "gn:population":0,
    "gn:timezone":"Africa/Addis_Ababa",
    "iso:country":"ET",
    "name:und_x_variant":[
        "Chirchemesc",
        "Chirchemesce"
    ],
    "wof:name":"Chirchemesce",
    "wof:placetype":"locality"
},
  "geometry": {"coordinates":[36.75,12.41667],"type":"Point"}
}