{
  "type": "Feature",
  "properties": {
    "gn:admin1_code":"51",
    "gn:asciiname":"Haro",
    "gn:country_code":"ET",
    "gn:dem":1814,
    "gn:feature_class":"P",
    "gn:feature_code":"PPL",
    "gn:name":"H\u0101ro",
    "gn:population":0,
    "gn:timezone":"Africa/Addis_Ababa",
    "iso:country":"ET",
    "name:cat_x_preferred":[
        "Haro"
    ],
    "name:ceb_x_preferred":[
        "Haro"
    ],
    "name:deu_x_preferred":[
        "Haro"
    ],
    "name:fra_x_preferred":[
        "Haro"
    ],
    "name:nld_x_preferred":[
        "Haro"
    ],
    "name:spa_x_preferred":[
        "Haro"
    ],
    "name:swe_x_preferred":[
        "Haro"
    ],
    "wof:name":"Haro",
    "wof:placetype":"locality"
},
  "geometry": {"coordinates":[38.65,9.45],"type":"Point"}
}