{
  "type": "Feature",
  "properties": {
    "gn:admin1_code":"51",
    "gn:asciiname":"Ila",
    "gn:country_code":"ET",
    "gn:dem":1734,
    "gn:feature_class":"P",
    "gn:feature_code":"PPL",
    "gn:name":"\u012ala",
    "gn:population":0,
    "gn:timezone":"Africa/Addis_Ababa",
    "iso:country":"ET",
    "name:ceb_x_preferred":[
        "Ila"
    ],
    "name:dan_x_preferred":[
        "Ila"
    ],
    "name:deu_x_preferred":[
        "Ila"
    ],
    "name:fra_x_preferred":[
        "Ila"
    ],
    "name:ind_x_preferred":[
        "Ila"
    ],
    "name:lit_x_preferred":[
        "Ila"
    ],
    "name:nld_x_preferred":[
        "Ila"
    ],
    "name:nor_x_preferred":[
        "Ila"
    ],
    "name:por_x_preferred":[
        "Ila"
    ],
    "name:rus_x_preferred":[
        "\u0418\u043b\u0430"
    ],
    "name:swe_x_preferred":[
        "Ila"
    ],
    "name:tam_x_preferred":[
        "\u0b87\u0bb2\u0bbe"
    ],
    "name:vol_x_preferred":[
        "Ila"
    ],
    "wof:name":"Ila",
    "wof:placetype":"locality"
},
  "geometry": {"coordinates":[38.75,8.31667],"type":"Point"}
}