{
  "type": "Feature",
  "properties": {
    "gn:admin1_code":"51",
    "gn:asciiname":"Ila",
    "gn:country_code":"ET",
    "gn:dem":1734,
    "gn:feature_class":"P",
    "gn:feature_code":"PPL",
    "gn:name":"\u012ala",
    "gn:population":0,
    "gn:timezone":"Africa/Addis_Ababa",
    "iso:country":"ET",
    "wof:name":"Ila",
    "wof:placetype":"locality"
},
  "geometry": {"coordinates":[38.75,8.31667],"type":"Point"}
}