{
  "type": "Feature",
  "properties": {
    "gn:admin1_code":"51.0",
    "gn:asciiname":"Derbas",
    "gn:country_code":"ET",
    "gn:dem":1918,
    "gn:feature_class":"P",
    "gn:feature_code":"PPL",
    "gn:name":"Derbas",
    "gn:population":0,
    "gn:timezone":"Africa/Addis_Ababa",
    "iso:country":"ET",
    "wof:name":"Derbas",
    "wof:placetype":"locality"
},
  "geometry": {"coordinates":[37.01667,9.26667],"type":"Point"}
}