{
  "type": "Feature",
  "properties": {
    "gn:admin1_code":"51.0",
    "gn:asciiname":"Bilingi",
    "gn:country_code":"ET",
    "gn:dem":1550,
    "gn:feature_class":"P",
    "gn:feature_code":"PPL",
    "gn:name":"B\u012bl\u012bng\u012b",
    "gn:population":0,
    "gn:timezone":"Africa/Addis_Ababa",
    "iso:country":"ET",
    "wof:name":"Bilingi",
    "wof:placetype":"locality"
},
  "geometry": {"coordinates":[40.58333,8.23333],"type":"Point"}
}