{
  "type": "Feature",
  "properties": {
    "gn:admin1_code":"51.0",
    "gn:asciiname":"Bebeli Kube",
    "gn:country_code":"ET",
    "gn:dem":2514,
    "gn:feature_class":"P",
    "gn:feature_code":"PPL",
    "gn:name":"Bebel\u012b Kub\u0113",
    "gn:population":0,
    "gn:timezone":"Africa/Addis_Ababa",
    "iso:country":"ET",
    "wof:name":"Bebeli Kube",
    "wof:placetype":"locality"
},
  "geometry": {"coordinates":[38.03333,8.66667],"type":"Point"}
}