{
  "type": "Feature",
  "properties": {
    "gn:admin1_code":"47",
    "gn:asciiname":"Iarda",
    "gn:country_code":"ET",
    "gn:dem":822,
    "gn:feature_class":"P",
    "gn:feature_code":"PPL",
    "gn:name":"Iarda",
    "gn:population":0,
    "gn:timezone":"Africa/Addis_Ababa",
    "iso:country":"ET",
    "wof:name":"Iarda",
    "wof:placetype":"locality"
},
  "geometry": {"coordinates":[35.88333,11.15],"type":"Point"}
}