{
  "type": "Feature",
  "properties": {
    "gn:admin1_code":"50",
    "gn:asciiname":"Fedis",
    "gn:country_code":"ET",
    "gn:dem":1947,
    "gn:feature_class":"P",
    "gn:feature_code":"PPL",
    "gn:name":"Fed\u012bs",
    "gn:population":0,
    "gn:timezone":"Africa/Addis_Ababa",
    "iso:country":"ET",
    "name:ceb_x_preferred":[
        "Fedis"
    ],
    "name:fra_x_preferred":[
        "Fedis"
    ],
    "name:swe_x_preferred":[
        "Fedis"
    ],
    "name:und_x_variant":[
        "Fed\u012bs"
    ],
    "wof:name":"Fedis",
    "wof:placetype":"locality"
},
  "geometry": {"coordinates":[42.09164000000001,9.25038],"type":"Point"}
}