{
  "type": "Feature",
  "properties": {
    "gn:admin1_code":"52",
    "gn:asciiname":"Godere",
    "gn:country_code":"ET",
    "gn:dem":351,
    "gn:feature_class":"P",
    "gn:feature_code":"PPL",
    "gn:name":"Godere",
    "gn:population":0,
    "gn:timezone":"Africa/Addis_Ababa",
    "iso:country":"ET",
    "name:und_x_variant":[
        "God Dere",
        "Godd\u0113r",
        "Godere"
    ],
    "wof:name":"Godere",
    "wof:placetype":"locality"
},
  "geometry": {"coordinates":[44.02639,5.21583],"type":"Point"}
}