{
  "type": "Feature",
  "properties": {
    "gn:admin1_code":"51.0",
    "gn:asciiname":"Diko",
    "gn:country_code":"ET",
    "gn:dem":2635,
    "gn:feature_class":"P",
    "gn:feature_code":"PPL",
    "gn:name":"D\u012bko",
    "gn:population":0,
    "gn:timezone":"Africa/Addis_Ababa",
    "iso:country":"ET",
    "wof:name":"Diko",
    "wof:placetype":"locality"
},
  "geometry": {"coordinates":[38.81667,9.53333],"type":"Point"}
}