{
  "type": "Feature",
  "properties": {
    "gn:admin1_code":"51",
    "gn:asciiname":"Duftu",
    "gn:country_code":"ET",
    "gn:dem":2725,
    "gn:feature_class":"P",
    "gn:feature_code":"PPL",
    "gn:name":"Duftu",
    "gn:population":0,
    "gn:timezone":"Africa/Addis_Ababa",
    "iso:country":"ET",
    "wof:name":"Duftu",
    "wof:placetype":"locality"
},
  "geometry": {"coordinates":[38.48333,8.51667],"type":"Point"}
}