{
  "type": "Feature",
  "properties": {
    "gn:admin1_code":"54",
    "gn:asciiname":"T'ora",
    "gn:country_code":"ET",
    "gn:dem":1967,
    "gn:feature_class":"P",
    "gn:feature_code":"PPL",
    "gn:name":"T\u2019ora",
    "gn:population":0,
    "gn:timezone":"Africa/Addis_Ababa",
    "iso:country":"ET",
    "wof:name":"T'ora",
    "wof:placetype":"locality"
},
  "geometry": {"coordinates":[38.41667,7.85],"type":"Point"}
}