{
  "type": "Feature",
  "properties": {
    "gn:admin1_code":"52",
    "gn:asciiname":"Segeg",
    "gn:country_code":"ET",
    "gn:dem":755,
    "gn:feature_class":"P",
    "gn:feature_code":"PPL",
    "gn:name":"Segeg",
    "gn:population":0,
    "gn:timezone":"Africa/Addis_Ababa",
    "iso:country":"ET",
    "name:fra_x_preferred":[
        "Segeg"
    ],
    "name:und_x_variant":[
        "Segug",
        "Segeg",
        "Segag"
    ],
    "wof:name":"Segeg",
    "wof:placetype":"locality"
},
  "geometry": {"coordinates":[42.8343,7.66102],"type":"Point"}
}