{
  "type": "Feature",
  "properties": {
    "gn:admin1_code":"52",
    "gn:asciiname":"Hen",
    "gn:country_code":"ET",
    "gn:dem":1010,
    "gn:feature_class":"P",
    "gn:feature_code":"PPL",
    "gn:name":"Hen",
    "gn:population":0,
    "gn:timezone":"Africa/Addis_Ababa",
    "iso:country":"ET",
    "name:bre_x_preferred":[
        "Hen"
    ],
    "name:cym_x_preferred":[
        "Hen"
    ],
    "name:deu_x_preferred":[
        "Hen"
    ],
    "name:fas_x_preferred":[
        "\u0645\u0631\u063a"
    ],
    "name:fra_x_preferred":[
        "Hen"
    ],
    "name:nld_x_preferred":[
        "Hen"
    ],
    "name:nor_x_preferred":[
        "Hen"
    ],
    "name:swe_x_preferred":[
        "Hen"
    ],
    "name:vie_x_preferred":[
        "Hen"
    ],
    "name:wln_x_preferred":[
        "Poye"
    ],
    "wof:name":"Hen",
    "wof:placetype":"locality"
},
  "geometry": {"coordinates":[43.76667,7.81667],"type":"Point"}
}