{
  "type": "Feature",
  "properties": {
    "gn:admin1_code":"49.0",
    "gn:asciiname":"Dumbirau",
    "gn:country_code":"ET",
    "gn:dem":408,
    "gn:feature_class":"P",
    "gn:feature_code":"PPL",
    "gn:name":"Dumbirau",
    "gn:population":0,
    "gn:timezone":"Africa/Addis_Ababa",
    "iso:country":"ET",
    "wof:name":"Dumbirau",
    "wof:placetype":"locality"
},
  "geometry": {"coordinates":[33.51534,8.46021],"type":"Point"}
}