{
  "type": "Feature",
  "properties": {
    "gn:admin1_code":"51.0",
    "gn:asciiname":"Biyo Karaba",
    "gn:country_code":"ET",
    "gn:dem":1566,
    "gn:feature_class":"P",
    "gn:feature_code":"PPL",
    "gn:name":"B\u012byo Karaba",
    "gn:population":0,
    "gn:timezone":"Africa/Addis_Ababa",
    "iso:country":"ET",
    "name:und_x_variant":[
        "Bio Carabba",
        "Bio Caraba",
        "B\u012byo Karaba"
    ],
    "wof:name":"Biyo Karaba",
    "wof:placetype":"locality"
},
  "geometry": {"coordinates":[41.16707,9.37169],"type":"Point"}
}