{
  "type": "Feature",
  "properties": {
    "gn:admin1_code":"51",
    "gn:asciiname":"Goro",
    "gn:country_code":"ET",
    "gn:dem":1595,
    "gn:feature_class":"P",
    "gn:feature_code":"PPL",
    "gn:name":"Goro",
    "gn:population":0,
    "gn:timezone":"Africa/Addis_Ababa",
    "iso:country":"ET",
    "wof:name":"Goro",
    "wof:placetype":"locality"
},
  "geometry": {"coordinates":[41.73806,9.14167],"type":"Point"}
}