{
  "type": "Feature",
  "properties": {
    "gn:country":"ET",
    "gn:fcode":"PPL",
    "gn:pop":65000,
    "iso:country":"ET",
    "name:amh_x_preferred":[
        "\u12a0\u12f2\u130d\u122b\u1275"
    ],
    "name:ara_x_preferred":[
        "\u0622\u062f\u064a\u063a\u0631\u0627\u062a"
    ],
    "name:ben_x_preferred":[
        "\u0986\u09a6\u09bf\u0997\u09cd\u09b0\u09c7\u099f"
    ],
    "name:chi_x_preferred":[
        "\u963f\u8fea\u683c\u62c9\u7279"
    ],
    "name:dan_x_preferred":[
        "Adigrat"
    ],
    "name:dut_x_preferred":[
        "Adigrat"
    ],
    "name:eng_x_preferred":[
        "Adigrat"
    ],
    "name:fin_x_preferred":[
        "Adigrat"
    ],
    "name:fre_x_preferred":[
        "Adigrat"
    ],
    "name:ger_x_preferred":[
        "Adigrat"
    ],
    "name:gre_x_preferred":[
        "\u0386\u03bd\u03c4\u03b9\u03b3\u03ba\u03c1\u03b1\u03c4"
    ],
    "name:guj_x_preferred":[
        "\u0a86\u0aa6\u0abf\u0a97\u0acd\u0ab0\u0abe\u0a9f"
    ],
    "name:heb_x_preferred":[
        "\u05d0\u05d3\u05d2\u05d9\u05e8\u05d0\u05d8"
    ],
    "name:hin_x_preferred":[
        "\u0905\u0926\u093f\u0917\u094d\u0930\u0924"
    ],
    "name:hrv_x_preferred":[
        "Adigrat"
    ],
    "name:ind_x_preferred":[
        "Adigrat"
    ],
    "name:ita_x_preferred":[
        "Adigrat"
    ],
    "name:jpn_x_preferred":[
        "\u30a2\u30c7\u30a3\u30b0\u30e9\u30c8"
    ],
    "name:kan_x_preferred":[
        "\u0c85\u0ca1\u0ccd\u0cb0\u0cbf\u0c97\u0ccd\u0cb0\u0cbe\u0c9f\u0ccd"
    ],
    "name:kor_x_preferred":[
        "\uc544\ub514\uadf8\ub78f"
    ],
    "name:lav_x_preferred":[
        "Adigrata"
    ],
    "name:lit_x_preferred":[
        "Adigratas"
    ],
    "name:mar_x_preferred":[
        "\u0905\u0926\u093f\u0917\u0930\u093e\u0924"
    ],
    "name:may_x_preferred":[
        "Adigrat"
    ],
    "name:nob_x_preferred":[
        "Adigrat"
    ],
    "name:per_x_preferred":[
        "\u0627\u062f\u06cc\u06af\u0631\u0627\u062a"
    ],
    "name:pol_x_preferred":[
        "Adigrat"
    ],
    "name:rum_x_preferred":[
        "Adigrat"
    ],
    "name:rus_x_preferred":[
        "\u0410\u0434\u0434\u0438-\u0413\u0440\u0430\u0442"
    ],
    "name:sin_x_preferred":[
        "\u0d85\u0daf\u0dd2\u0d9c\u0dca\u200d\u0dbb\u0da7\u0dca"
    ],
    "name:slv_x_preferred":[
        "Adigrat"
    ],
    "name:spa_x_preferred":[
        "Adigrat"
    ],
    "name:swe_x_preferred":[
        "Adigrat"
    ],
    "name:szl_x_preferred":[
        "Adigrat"
    ],
    "name:tam_x_preferred":[
        "\u0b85\u0b9f\u0bbf\u0b95\u0bcd\u0bb0\u0bbe\u0b9f\u0bcd"
    ],
    "name:tel_x_preferred":[
        "\u0c05\u0c26\u0c3f\u0c17\u0c4d\u0c30\u0c3e\u0c24\u0c4d"
    ],
    "name:tha_x_preferred":[
        "\u0e2d\u0e31\u0e14\u0e34\u0e01\u0e23\u0e32\u0e17"
    ],
    "name:tur_x_preferred":[
        "Adigrat"
    ],
    "name:ukr_x_preferred":[
        "\u0410\u0434\u0456\u0433\u0440\u0430\u0442"
    ],
    "name:urd_x_preferred":[
        "\u0627\u062f\u06cc\u062c\u0631\u0627\u062a"
    ],
    "name:vie_x_preferred":[
        "Adigrat"
    ],
    "qs:name":"\u0100d\u012bgrat",
    "qs:photos_9r":0,
    "qs:photos_sr":0,
    "qs:pop_sr":"9",
    "wof:name":"\u0100d\u012bgrat",
    "wof:placetype":"locality",
    "wof:population":65000
},
  "geometry": {"coordinates":[39.462,14.277],"type":"Point"}
}