{
  "type": "Feature",
  "properties": {
    "gn:admin1_code":"54.0",
    "gn:asciiname":"Ado",
    "gn:country_code":"ET",
    "gn:dem":1254,
    "gn:feature_class":"P",
    "gn:feature_code":"PPL",
    "gn:name":"\u0100do",
    "gn:population":0,
    "gn:timezone":"Africa/Addis_Ababa",
    "iso:country":"ET",
    "name:cat_x_preferred":[
        "Ado"
    ],
    "name:ceb_x_preferred":[
        "Ado"
    ],
    "name:dan_x_preferred":[
        "Ado"
    ],
    "name:deu_x_preferred":[
        "Ado"
    ],
    "name:fra_x_preferred":[
        "Ado"
    ],
    "name:hun_x_preferred":[
        "Ado"
    ],
    "name:por_x_preferred":[
        "Ado"
    ],
    "name:rus_x_preferred":[
        "\u0410\u0434\u043e"
    ],
    "name:ukr_x_preferred":[
        "\u0410\u0434\u043e"
    ],
    "wof:name":"Ado",
    "wof:placetype":"locality"
},
  "geometry": {"coordinates":[36.81667,7.01667],"type":"Point"}
}