{
  "type": "Feature",
  "properties": {
    "gn:admin1_code":"52",
    "gn:asciiname":"Hurso",
    "gn:country_code":"ET",
    "gn:dem":1130,
    "gn:feature_class":"P",
    "gn:feature_code":"PPL",
    "gn:name":"Hurso",
    "gn:population":0,
    "gn:timezone":"Africa/Addis_Ababa",
    "iso:country":"ET",
    "name:deu_x_preferred":[
        "Hurso"
    ],
    "name:und_x_variant":[
        "Urso",
        "Hurso"
    ],
    "wof:name":"Hurso",
    "wof:placetype":"locality"
},
  "geometry": {"coordinates":[41.64417,9.60194],"type":"Point"}
}