{
  "type": "Feature",
  "properties": {
    "gn:admin1_code":"46",
    "gn:asciiname":"K'ulk'wal Bado",
    "gn:country_code":"ET",
    "gn:dem":2698,
    "gn:feature_class":"P",
    "gn:feature_code":"PPL",
    "gn:name":"K\u2019ulk\u2019wal Bado",
    "gn:population":0,
    "gn:timezone":"Africa/Addis_Ababa",
    "iso:country":"ET",
    "wof:name":"K'ulk'wal Bado",
    "wof:placetype":"locality"
},
  "geometry": {"coordinates":[39.44457,10.08089],"type":"Point"}
}