{
  "type": "Feature",
  "properties": {
    "gn:admin1_code":"51.0",
    "gn:asciiname":"Ch'erch'er",
    "gn:country_code":"ET",
    "gn:dem":1992,
    "gn:feature_class":"P",
    "gn:feature_code":"PPL",
    "gn:name":"Ch\u2019erch\u2019er",
    "gn:population":0,
    "gn:timezone":"Africa/Addis_Ababa",
    "iso:country":"ET",
    "wof:name":"Ch'erch'er",
    "wof:placetype":"locality"
},
  "geometry": {"coordinates":[41.16058,9.22546],"type":"Point"}
}