{
  "type": "Feature",
  "properties": {
    "gn:admin1_code":"51",
    "gn:asciiname":"Gosu",
    "gn:country_code":"ET",
    "gn:dem":2664,
    "gn:feature_class":"P",
    "gn:feature_code":"PPL",
    "gn:name":"Gosu",
    "gn:population":0,
    "gn:timezone":"Africa/Addis_Ababa",
    "iso:country":"ET",
    "name:fra_x_preferred":[
        "Gosu"
    ],
    "name:kor_x_preferred":[
        "\uace0\uc218"
    ],
    "name:pol_x_preferred":[
        "Gosu"
    ],
    "name:spa_x_preferred":[
        "Gosu"
    ],
    "wof:name":"Gosu",
    "wof:placetype":"locality"
},
  "geometry": {"coordinates":[38.36667,9.18333],"type":"Point"}
}