{
  "type": "Feature",
  "properties": {
    "gn:admin1_code":"46",
    "gn:asciiname":"Geda Iyasu",
    "gn:country_code":"ET",
    "gn:dem":2336,
    "gn:feature_class":"P",
    "gn:feature_code":"PPL",
    "gn:name":"Geda \u012ayasu",
    "gn:population":0,
    "gn:timezone":"Africa/Addis_Ababa",
    "iso:country":"ET",
    "name:und_x_variant":[
        "Geda \u012ayasu (1)",
        "Geda \u012ayasu"
    ],
    "wof:name":"Geda Iyasu",
    "wof:placetype":"locality"
},
  "geometry": {"coordinates":[38.41667,10.51667],"type":"Point"}
}