{
  "type": "Feature",
  "properties": {
    "gn:admin1_code":"52",
    "gn:asciiname":"Harardighet",
    "gn:country_code":"ET",
    "gn:dem":964,
    "gn:feature_class":"P",
    "gn:feature_code":"PPL",
    "gn:name":"Harardighet",
    "gn:population":0,
    "gn:timezone":"Africa/Addis_Ababa",
    "iso:country":"ET",
    "wof:name":"Harardighet",
    "wof:placetype":"locality"
},
  "geometry": {"coordinates":[44.43333,7.73333],"type":"Point"}
}