{
  "type": "Feature",
  "properties": {
    "gn:admin1_code":"54.0",
    "gn:asciiname":"Nikuali",
    "gn:country_code":"ET",
    "gn:dem":463,
    "gn:feature_class":"P",
    "gn:feature_code":"PPL",
    "gn:name":"Nikuali",
    "gn:population":0,
    "gn:timezone":"Africa/Addis_Ababa",
    "iso:country":"ET",
    "wof:name":"Nikuali",
    "wof:placetype":"locality"
},
  "geometry": {"coordinates":[34.23535,7.00396],"type":"Point"}
}