{
  "type": "Feature",
  "properties": {
    "gn:admin1_code":"51.0",
    "gn:asciiname":"Abeyi",
    "gn:country_code":"ET",
    "gn:dem":1988,
    "gn:feature_class":"P",
    "gn:feature_code":"PPL",
    "gn:name":"\u0100bey\u012b",
    "gn:population":0,
    "gn:timezone":"Africa/Addis_Ababa",
    "iso:country":"ET",
    "wof:name":"Abeyi",
    "wof:placetype":"locality"
},
  "geometry": {"coordinates":[37.66667,9.01667],"type":"Point"}
}