{
  "type": "Feature",
  "properties": {
    "gn:admin1_code":"46",
    "gn:asciiname":"Mirach'",
    "gn:country_code":"ET",
    "gn:dem":1847,
    "gn:feature_class":"P",
    "gn:feature_code":"PPL",
    "gn:name":"Mirach\u2019",
    "gn:population":0,
    "gn:timezone":"Africa/Addis_Ababa",
    "iso:country":"ET",
    "wof:name":"Mirach'",
    "wof:placetype":"locality"
},
  "geometry": {"coordinates":[38.43333,10.48333],"type":"Point"}
}