{
  "type": "Feature",
  "properties": {
    "gn:admin1_code":"53.0",
    "gn:asciiname":"Adeseb",
    "gn:country_code":"ET",
    "gn:dem":1372,
    "gn:feature_class":"P",
    "gn:feature_code":"PPL",
    "gn:name":"Adeseb",
    "gn:population":0,
    "gn:timezone":"Africa/Addis_Ababa",
    "iso:country":"ET",
    "wof:name":"Adeseb",
    "wof:placetype":"locality"
},
  "geometry": {"coordinates":[38.81667,13.36667],"type":"Point"}
}