{
  "type": "Feature",
  "properties": {
    "gn:admin1_code":"51",
    "gn:asciiname":"Gumbichu",
    "gn:country_code":"ET",
    "gn:dem":2454,
    "gn:feature_class":"P",
    "gn:feature_code":"PPL",
    "gn:name":"Gumb\u012bchu",
    "gn:population":0,
    "gn:timezone":"Africa/Addis_Ababa",
    "iso:country":"ET",
    "name:und_x_variant":[
        "Aghembicciu",
        "Gumb\u012bchu"
    ],
    "wof:name":"Gumbichu",
    "wof:placetype":"locality"
},
  "geometry": {"coordinates":[38.73333,9.53333],"type":"Point"}
}