{
  "type": "Feature",
  "properties": {
    "gn:admin1_code":"54",
    "gn:asciiname":"Silt'e",
    "gn:country_code":"ET",
    "gn:dem":2079,
    "gn:feature_class":"P",
    "gn:feature_code":"PPL",
    "gn:name":"Silt\u2019\u0113",
    "gn:population":0,
    "gn:timezone":"Africa/Addis_Ababa",
    "iso:country":"ET",
    "name:und_x_variant":[
        "Uodesha",
        "Uodessa",
        "Silt\u2019\u0113"
    ],
    "wof:name":"Silt'e",
    "wof:placetype":"locality"
},
  "geometry": {"coordinates":[38.33333,8.01667],"type":"Point"}
}