{
  "type": "Feature",
  "properties": {
    "gn:admin1_code":"46.0",
    "gn:asciiname":"Abebaye",
    "gn:country_code":"ET",
    "gn:dem":2860,
    "gn:feature_class":"P",
    "gn:feature_code":"PPL",
    "gn:name":"\u0100bebay\u0113",
    "gn:population":0,
    "gn:timezone":"Africa/Addis_Ababa",
    "iso:country":"ET",
    "wof:name":"Abebaye",
    "wof:placetype":"locality"
},
  "geometry": {"coordinates":[39.50992,9.48151],"type":"Point"}
}