{
  "type": "Feature",
  "properties": {
    "gn:admin1_code":"51",
    "gn:asciiname":"Kefersa",
    "gn:country_code":"ET",
    "gn:dem":2030,
    "gn:feature_class":"P",
    "gn:feature_code":"PPL",
    "gn:name":"Kefersa",
    "gn:population":0,
    "gn:timezone":"Africa/Addis_Ababa",
    "iso:country":"ET",
    "name:und_x_variant":[
        "Cafifarsa",
        "Kafars\u0101",
        "Caffarsa",
        "Kaffarsa",
        "Kafifarsa",
        "Kefersa"
    ],
    "wof:name":"Kefersa",
    "wof:placetype":"locality"
},
  "geometry": {"coordinates":[37.33333,7.43333],"type":"Point"}
}