{
  "type": "Feature",
  "properties": {
    "gn:admin1_code":"45.0",
    "gn:asciiname":"Didigsala",
    "gn:country_code":"ET",
    "gn:dem":1342,
    "gn:feature_class":"P",
    "gn:feature_code":"PPL",
    "gn:name":"Didigsala",
    "gn:population":0,
    "gn:timezone":"Africa/Addis_Ababa",
    "iso:country":"ET",
    "wof:name":"Didigsala",
    "wof:placetype":"locality"
},
  "geometry": {"coordinates":[39.96667,12.88333],"type":"Point"}
}