{
  "type": "Feature",
  "properties": {
    "gn:admin1_code":"51",
    "gn:asciiname":"Tulu Geda",
    "gn:country_code":"ET",
    "gn:dem":2619,
    "gn:feature_class":"P",
    "gn:feature_code":"PPL",
    "gn:name":"Tulu Geda",
    "gn:population":0,
    "gn:timezone":"Africa/Addis_Ababa",
    "iso:country":"ET",
    "name:und_x_variant":[
        "Gidda",
        "Tulu Geda"
    ],
    "wof:name":"Tulu Geda",
    "wof:placetype":"locality"
},
  "geometry": {"coordinates":[38.88333,9.63333],"type":"Point"}
}