{
  "type": "Feature",
  "properties": {
    "gn:admin1_code":"51",
    "gn:asciiname":"Gurachu",
    "gn:country_code":"ET",
    "gn:dem":2009,
    "gn:feature_class":"P",
    "gn:feature_code":"PPL",
    "gn:name":"Gurachu",
    "gn:population":0,
    "gn:timezone":"Africa/Addis_Ababa",
    "iso:country":"ET",
    "wof:name":"Gurachu",
    "wof:placetype":"locality"
},
  "geometry": {"coordinates":[40.36667,7.11667],"type":"Point"}
}