{
  "type": "Feature",
  "properties": {
    "gn:admin1_code":"52.0",
    "gn:asciiname":"El Bio Addo",
    "gn:country_code":"ET",
    "gn:dem":289,
    "gn:feature_class":"P",
    "gn:feature_code":"PPL",
    "gn:name":"El Bio Addo",
    "gn:population":0,
    "gn:timezone":"Africa/Addis_Ababa",
    "iso:country":"ET",
    "wof:name":"El Bio Addo",
    "wof:placetype":"locality"
},
  "geometry": {"coordinates":[42.55802,4.60361],"type":"Point"}
}