{
  "type": "Feature",
  "properties": {
    "gn:admin1_code":"53.0",
    "gn:asciiname":"Adi Resene",
    "gn:country_code":"ET",
    "gn:dem":1317,
    "gn:feature_class":"P",
    "gn:feature_code":"PPL",
    "gn:name":"Adi Resene",
    "gn:population":0,
    "gn:timezone":"Africa/Addis_Ababa",
    "iso:country":"ET",
    "wof:name":"Adi Resene",
    "wof:placetype":"locality"
},
  "geometry": {"coordinates":[37.38333,13.76667],"type":"Point"}
}