{
  "type": "Feature",
  "properties": {
    "gn:admin1_code":"46",
    "gn:asciiname":"T'elezam",
    "gn:country_code":"ET",
    "gn:dem":2675,
    "gn:feature_class":"P",
    "gn:feature_code":"PPL",
    "gn:name":"T\u2019elezam",
    "gn:population":0,
    "gn:timezone":"Africa/Addis_Ababa",
    "iso:country":"ET",
    "wof:name":"T'elezam",
    "wof:placetype":"locality"
},
  "geometry": {"coordinates":[37.68333,10.66667],"type":"Point"}
}