{
  "type": "Feature",
  "properties": {
    "gn:admin1_code":"51",
    "gn:asciiname":"T'ifench'ir",
    "gn:country_code":"ET",
    "gn:dem":1836,
    "gn:feature_class":"P",
    "gn:feature_code":"PPL",
    "gn:name":"T\u2019if\u0113nch\u2019ir",
    "gn:population":0,
    "gn:timezone":"Africa/Addis_Ababa",
    "iso:country":"ET",
    "wof:name":"T'ifench'ir",
    "wof:placetype":"locality"
},
  "geometry": {"coordinates":[37.81667,8.36667],"type":"Point"}
}