{
  "type": "Feature",
  "properties": {
    "gn:admin1_code":"46",
    "gn:asciiname":"Sciumalaco",
    "gn:country_code":"ET",
    "gn:dem":2551,
    "gn:feature_class":"P",
    "gn:feature_code":"PPL",
    "gn:name":"Sciumalaco",
    "gn:population":0,
    "gn:timezone":"Africa/Addis_Ababa",
    "iso:country":"ET",
    "wof:name":"Sciumalaco",
    "wof:placetype":"locality"
},
  "geometry": {"coordinates":[37.78333,12.98333],"type":"Point"}
}