{
  "type": "Feature",
  "properties": {
    "gn:admin1_code":"46.0",
    "gn:asciiname":"Anghetam Abo",
    "gn:country_code":"ET",
    "gn:dem":2218,
    "gn:feature_class":"P",
    "gn:feature_code":"PPL",
    "gn:name":"Anghetam Abo",
    "gn:population":0,
    "gn:timezone":"Africa/Addis_Ababa",
    "iso:country":"ET",
    "name:und_x_variant":[
        "Anghetam",
        "Anghetam Abo"
    ],
    "wof:name":"Anghetam Abo",
    "wof:placetype":"locality"
},
  "geometry": {"coordinates":[37.61667,10.28333],"type":"Point"}
}