{
  "type": "Feature",
  "properties": {
    "gn:admin1_code":"51",
    "gn:asciiname":"Melka Guba",
    "gn:country_code":"ET",
    "gn:dem":747,
    "gn:feature_class":"P",
    "gn:feature_code":"PPL",
    "gn:name":"Melka Guba",
    "gn:population":0,
    "gn:timezone":"Africa/Addis_Ababa",
    "iso:country":"ET",
    "name:und_x_variant":[
        "Guba",
        "Malca Guba",
        "Melka Guba"
    ],
    "wof:name":"Melka Guba",
    "wof:placetype":"locality"
},
  "geometry": {"coordinates":[39.36667,4.78333],"type":"Point"}
}