{
  "type": "Feature",
  "properties": {
    "gn:admin1_code":"53.0",
    "gn:asciiname":"Abiy Addi",
    "gn:country_code":"ET",
    "gn:dem":1864,
    "gn:feature_class":"P",
    "gn:feature_code":"PPL",
    "gn:name":"Abiy Addi",
    "gn:population":0,
    "gn:timezone":"Africa/Addis_Ababa",
    "iso:country":"ET",
    "name:azb_x_preferred":[
        "\u0627\u0628\u06cc \u0627\u062f\u06cc"
    ],
    "name:fas_x_preferred":[
        "\u0627\u0628\u06cc \u0627\u062f\u06cc"
    ],
    "name:fra_x_preferred":[
        "Abiy Addi"
    ],
    "name:und_x_variant":[
        "\u0100biy \u0100d\u012b"
    ],
    "wof:name":"Abiy Addi",
    "wof:placetype":"locality"
},
  "geometry": {"coordinates":[39.07972,14.44194],"type":"Point"}
}