{
  "type": "Feature",
  "properties": {
    "gn:admin1_code":"27.0",
    "gn:asciiname":"Shifode Debar",
    "gn:country_code":"ET",
    "gn:dem":1799,
    "gn:feature_class":"P",
    "gn:feature_code":"PPL",
    "gn:name":"Shifode Debar",
    "gn:population":0,
    "gn:timezone":"Africa/Addis_Ababa",
    "iso:country":"ET",
    "wof:name":"Shifode Debar",
    "wof:placetype":"locality"
},
  "geometry": {"coordinates":[38.38583,7.7023],"type":"Point"}
}