{
  "type": "Feature",
  "properties": {
    "gn:admin1_code":"54.0",
    "gn:asciiname":"Cacia",
    "gn:country_code":"ET",
    "gn:dem":1503,
    "gn:feature_class":"P",
    "gn:feature_code":"PPL",
    "gn:name":"Cacia",
    "gn:population":0,
    "gn:timezone":"Africa/Addis_Ababa",
    "iso:country":"ET",
    "wof:name":"Cacia",
    "wof:placetype":"locality"
},
  "geometry": {"coordinates":[37.23333,7.11667],"type":"Point"}
}