{
  "type": "Feature",
  "properties": {
    "gn:admin1_code":"54.0",
    "gn:asciiname":"Cacia",
    "gn:country_code":"ET",
    "gn:dem":1503,
    "gn:feature_class":"P",
    "gn:feature_code":"PPL",
    "gn:name":"Cacia",
    "gn:population":0,
    "gn:timezone":"Africa/Addis_Ababa",
    "iso:country":"ET",
    "name:ceb_x_preferred":[
        "Cacia"
    ],
    "name:deu_x_preferred":[
        "Cacia"
    ],
    "name:kaz_x_preferred":[
        "\u041a\u0430\u0441\u0438\u044f"
    ],
    "name:msa_x_preferred":[
        "Cacia"
    ],
    "name:por_x_preferred":[
        "Cacia"
    ],
    "name:rus_x_preferred":[
        "\u041a\u0430\u0441\u0438\u044f"
    ],
    "name:spa_x_preferred":[
        "Cacia"
    ],
    "name:ukr_x_preferred":[
        "\u041a\u0430\u0441\u0456\u044f"
    ],
    "name:zho_x_preferred":[
        "\u5361\u897f\u4e9a"
    ],
    "wof:name":"Cacia",
    "wof:placetype":"locality"
},
  "geometry": {"coordinates":[37.23333,7.11667],"type":"Point"}
}