{
  "type": "Feature",
  "properties": {
    "gn:admin1_code":"51.0",
    "gn:asciiname":"Didimtu",
    "gn:country_code":"ET",
    "gn:dem":2233,
    "gn:feature_class":"P",
    "gn:feature_code":"PPL",
    "gn:name":"D\u012bd\u012bmtu",
    "gn:population":0,
    "gn:timezone":"Africa/Addis_Ababa",
    "iso:country":"ET",
    "wof:name":"Didimtu",
    "wof:placetype":"locality"
},
  "geometry": {"coordinates":[37.13333,9.46667],"type":"Point"}
}