{
  "type": "Feature",
  "properties": {
    "gn:admin1_code":"45.0",
    "gn:asciiname":"Daetali",
    "gn:country_code":"ET",
    "gn:dem":724,
    "gn:feature_class":"P",
    "gn:feature_code":"PPL",
    "gn:name":"Daetali",
    "gn:population":0,
    "gn:timezone":"Africa/Addis_Ababa",
    "iso:country":"ET",
    "name:und_x_variant":[
        "Additale",
        "Daetali"
    ],
    "wof:name":"Daetali",
    "wof:placetype":"locality"
},
  "geometry": {"coordinates":[40.26667,9.48333],"type":"Point"}
}