{
  "type": "Feature",
  "properties": {
    "gn:admin1_code":"45.0",
    "gn:asciiname":"Dalalian Maru",
    "gn:country_code":"ET",
    "gn:dem":-32,
    "gn:feature_class":"P",
    "gn:feature_code":"PPL",
    "gn:name":"Dalalian Maru",
    "gn:population":0,
    "gn:timezone":"Africa/Addis_Ababa",
    "iso:country":"ET",
    "wof:name":"Dalalian Maru",
    "wof:placetype":"locality"
},
  "geometry": {"coordinates":[41.05,13.51667],"type":"Point"}
}