{
  "type": "Feature",
  "properties": {
    "gn:admin1_code":"51",
    "gn:asciiname":"Tirtira",
    "gn:country_code":"ET",
    "gn:dem":2398,
    "gn:feature_class":"P",
    "gn:feature_code":"PPL",
    "gn:name":"T\u012brt\u012bra",
    "gn:population":0,
    "gn:timezone":"Africa/Addis_Ababa",
    "iso:country":"ET",
    "wof:name":"Tirtira",
    "wof:placetype":"locality"
},
  "geometry": {"coordinates":[37.73333,9.58333],"type":"Point"}
}