{
  "type": "Feature",
  "properties": {
    "gn:admin1_code":"51",
    "gn:asciiname":"K'ersa Deketa",
    "gn:country_code":"ET",
    "gn:dem":1929,
    "gn:feature_class":"P",
    "gn:feature_code":"PPL",
    "gn:name":"K\u2019ersa Deketa",
    "gn:population":0,
    "gn:timezone":"Africa/Addis_Ababa",
    "iso:country":"ET",
    "wof:name":"K'ersa Deketa",
    "wof:placetype":"locality"
},
  "geometry": {"coordinates":[41.91806,9.32056],"type":"Point"}
}