{
  "type": "Feature",
  "properties": {
    "gn:admin1_code":"45.0",
    "gn:asciiname":"Grukur",
    "gn:country_code":"ET",
    "gn:dem":-107,
    "gn:feature_class":"P",
    "gn:feature_code":"PPL",
    "gn:name":"Grukur",
    "gn:population":0,
    "gn:timezone":"Africa/Addis_Ababa",
    "iso:country":"ET",
    "wof:name":"Grukur",
    "wof:placetype":"locality"
},
  "geometry": {"coordinates":[40.9247,13.32606],"type":"Point"}
}