{
  "type": "Feature",
  "properties": {
    "gn:admin1_code":"54.0",
    "gn:asciiname":"Demza",
    "gn:country_code":"ET",
    "gn:dem":1229,
    "gn:feature_class":"P",
    "gn:feature_code":"PPL",
    "gn:name":"Demza",
    "gn:population":0,
    "gn:timezone":"Africa/Addis_Ababa",
    "iso:country":"ET",
    "wof:name":"Demza",
    "wof:placetype":"locality"
},
  "geometry": {"coordinates":[37.05,6.43333],"type":"Point"}
}