{
  "type": "Feature",
  "properties": {
    "gn:admin1_code":"46",
    "gn:asciiname":"Gedamayt Rebu`i Gebeya",
    "gn:country_code":"ET",
    "gn:dem":2971,
    "gn:feature_class":"P",
    "gn:feature_code":"PPL",
    "gn:name":"Gedamayt Rebu\u2018i Gebeya",
    "gn:population":0,
    "gn:timezone":"Africa/Addis_Ababa",
    "iso:country":"ET",
    "name:und_x_variant":[
        "Ruobgebaia",
        "Gedamayt Rebu\u2018i Gebeya"
    ],
    "wof:name":"Gedamayt Rebu`i Gebeya",
    "wof:placetype":"locality"
},
  "geometry": {"coordinates":[37.76667,10.55],"type":"Point"}
}