{
  "type": "Feature",
  "properties": {
    "gn:admin1_code":"51.0",
    "gn:asciiname":"Ariro",
    "gn:country_code":"ET",
    "gn:dem":1690,
    "gn:feature_class":"P",
    "gn:feature_code":"PPL",
    "gn:name":"\u0100r\u012bro",
    "gn:population":0,
    "gn:timezone":"Africa/Addis_Ababa",
    "iso:country":"ET",
    "wof:name":"Ariro",
    "wof:placetype":"locality"
},
  "geometry": {"coordinates":[38.03333,9.91667],"type":"Point"}
}