{
  "type": "Feature",
  "properties": {
    "gn:admin1_code":"51.0",
    "gn:asciiname":"Ch'eleysa",
    "gn:country_code":"ET",
    "gn:dem":2221,
    "gn:feature_class":"P",
    "gn:feature_code":"PPL",
    "gn:name":"Ch\u2019eleysa",
    "gn:population":0,
    "gn:timezone":"Africa/Addis_Ababa",
    "iso:country":"ET",
    "name:und_x_variant":[
        "Kheleysa",
        "Ch\u2019eleysa"
    ],
    "wof:name":"Ch'eleysa",
    "wof:placetype":"locality"
},
  "geometry": {"coordinates":[41.925,9.46722],"type":"Point"}
}