{
  "type": "Feature",
  "properties": {
    "gn:admin1_code":"51",
    "gn:asciiname":"Lugo",
    "gn:country_code":"ET",
    "gn:dem":2418,
    "gn:feature_class":"P",
    "gn:feature_code":"PPL",
    "gn:name":"Lugo",
    "gn:population":0,
    "gn:timezone":"Africa/Addis_Ababa",
    "iso:country":"ET",
    "wof:name":"Lugo",
    "wof:placetype":"locality"
},
  "geometry": {"coordinates":[39.05,8.95],"type":"Point"}
}