{
  "type": "Feature",
  "properties": {
    "gn:admin1_code":"46",
    "gn:asciiname":"Sirt'u Ager",
    "gn:country_code":"ET",
    "gn:dem":1638,
    "gn:feature_class":"P",
    "gn:feature_code":"PPL",
    "gn:name":"Sirt\u2019u \u0100ger",
    "gn:population":0,
    "gn:timezone":"Africa/Addis_Ababa",
    "iso:country":"ET",
    "wof:name":"Sirt'u Ager",
    "wof:placetype":"locality"
},
  "geometry": {"coordinates":[39.70855,9.19811],"type":"Point"}
}