{
  "type": "Feature",
  "properties": {
    "gn:admin1_code":"54",
    "gn:asciiname":"Sholtaka",
    "gn:country_code":"ET",
    "gn:dem":1351,
    "gn:feature_class":"P",
    "gn:feature_code":"PPL",
    "gn:name":"Sholtaka",
    "gn:population":0,
    "gn:timezone":"Africa/Addis_Ababa",
    "iso:country":"ET",
    "wof:name":"Sholtaka",
    "wof:placetype":"locality"
},
  "geometry": {"coordinates":[36.81667,5.71667],"type":"Point"}
}