{
  "type": "Feature",
  "properties": {
    "gn:admin1_code":"51",
    "gn:asciiname":"Medhane `Alem",
    "gn:country_code":"ET",
    "gn:dem":2673,
    "gn:feature_class":"P",
    "gn:feature_code":"PPL",
    "gn:name":"Medhan\u0113 \u2018Alem",
    "gn:population":0,
    "gn:timezone":"Africa/Addis_Ababa",
    "iso:country":"ET",
    "wof:name":"Medhane `Alem",
    "wof:placetype":"locality"
},
  "geometry": {"coordinates":[38.75,7.03333],"type":"Point"}
}