{
  "type": "Feature",
  "properties": {
    "gn:admin1_code":"53.0",
    "gn:asciiname":"Atfakarye",
    "gn:country_code":"ET",
    "gn:dem":1816,
    "gn:feature_class":"P",
    "gn:feature_code":"PPL",
    "gn:name":"Atfakarye",
    "gn:population":0,
    "gn:timezone":"Africa/Addis_Ababa",
    "iso:country":"ET",
    "name:rus_x_preferred":[
        "\u0410\u0442\u0444\u0430\u043a\u0430\u0440\u044c\u0435"
    ],
    "wof:name":"Atfakarye",
    "wof:placetype":"locality"
},
  "geometry": {"coordinates":[38.61556,14.20123],"type":"Point"}
}