{
  "type": "Feature",
  "properties": {
    "gn:admin1_code":"47",
    "gn:asciiname":"Horkelifa",
    "gn:country_code":"ET",
    "gn:dem":741,
    "gn:feature_class":"P",
    "gn:feature_code":"PPL",
    "gn:name":"Hork\u0113l\u012bfa",
    "gn:population":0,
    "gn:timezone":"Africa/Addis_Ababa",
    "iso:country":"ET",
    "name:und_x_variant":[
        "Karkalifa",
        "Hork\u0113l\u012bfa"
    ],
    "wof:name":"Horkelifa",
    "wof:placetype":"locality"
},
  "geometry": {"coordinates":[34.93333,10.63333],"type":"Point"}
}