{
  "type": "Feature",
  "properties": {
    "gn:admin1_code":"45",
    "gn:asciiname":"Gallifaghe",
    "gn:country_code":"ET",
    "gn:dem":444,
    "gn:feature_class":"P",
    "gn:feature_code":"PPL",
    "gn:name":"Gallifaghe",
    "gn:population":0,
    "gn:timezone":"Africa/Addis_Ababa",
    "iso:country":"ET",
    "name:und_x_variant":[
        "Gal\u012bfag\u0113"
    ],
    "wof:name":"Gallifaghe",
    "wof:placetype":"locality"
},
  "geometry": {"coordinates":[41.35,11.36667],"type":"Point"}
}