{
  "type": "Feature",
  "properties": {
    "gn:admin1_code":"51",
    "gn:asciiname":"Goba",
    "gn:country_code":"ET",
    "gn:dem":1315,
    "gn:feature_class":"P",
    "gn:feature_code":"PPL",
    "gn:name":"Goba",
    "gn:population":0,
    "gn:timezone":"Africa/Addis_Ababa",
    "iso:country":"ET",
    "name:ceb_x_preferred":[
        "Goba"
    ],
    "name:deu_x_preferred":[
        "Goba"
    ],
    "name:fra_x_preferred":[
        "Goba"
    ],
    "name:hrv_x_preferred":[
        "Goba"
    ],
    "name:ita_x_preferred":[
        "Goba"
    ],
    "name:nld_x_preferred":[
        "Goba"
    ],
    "name:pol_x_preferred":[
        "Goba"
    ],
    "name:por_x_preferred":[
        "Goba"
    ],
    "name:ron_x_preferred":[
        "Goba"
    ],
    "name:rus_x_preferred":[
        "\u0413\u043e\u0431\u0430"
    ],
    "name:spa_x_preferred":[
        "Goba"
    ],
    "name:swe_x_preferred":[
        "Goba"
    ],
    "wof:name":"Goba",
    "wof:placetype":"locality"
},
  "geometry": {"coordinates":[40.38333,8.01667],"type":"Point"}
}