{
  "type": "Feature",
  "properties": {
    "gn:admin1_code":"46.0",
    "gn:asciiname":"Ayer",
    "gn:country_code":"ET",
    "gn:dem":2788,
    "gn:feature_class":"P",
    "gn:feature_code":"PPL",
    "gn:name":"\u0100yer",
    "gn:population":0,
    "gn:timezone":"Africa/Addis_Ababa",
    "iso:country":"ET",
    "name:arg_x_preferred":[
        "Ayer"
    ],
    "name:cat_x_preferred":[
        "Ayer"
    ],
    "name:ceb_x_preferred":[
        "Ayer"
    ],
    "name:deu_x_preferred":[
        "Ayer"
    ],
    "name:fas_x_preferred":[
        "\u0622\u06cc\u0631"
    ],
    "name:fra_x_preferred":[
        "Ayer"
    ],
    "name:ita_x_preferred":[
        "Ayer"
    ],
    "name:nld_x_preferred":[
        "Ayer"
    ],
    "name:pol_x_preferred":[
        "Ayer"
    ],
    "name:rus_x_preferred":[
        "\u0410\u0439\u0435\u0440"
    ],
    "name:spa_x_preferred":[
        "Ayer"
    ],
    "name:swe_x_preferred":[
        "Ayer"
    ],
    "name:und_x_variant":[
        "\u0100yer (2)",
        "\u0100yer"
    ],
    "name:vol_x_preferred":[
        "Ayer"
    ],
    "wof:name":"Ayer",
    "wof:placetype":"locality"
},
  "geometry": {"coordinates":[39.11667,11.23333],"type":"Point"}
}