{
  "type": "Feature",
  "properties": {
    "gn:admin1_code":"51",
    "gn:asciiname":"Werebo",
    "gn:country_code":"ET",
    "gn:dem":1912,
    "gn:feature_class":"P",
    "gn:feature_code":"PPL",
    "gn:name":"Werebo",
    "gn:population":0,
    "gn:timezone":"Africa/Addis_Ababa",
    "iso:country":"ET",
    "wof:name":"Werebo",
    "wof:placetype":"locality"
},
  "geometry": {"coordinates":[37.91667,8.38333],"type":"Point"}
}