{
  "type": "Feature",
  "properties": {
    "gn:admin1_code":"46.0",
    "gn:asciiname":"Dame",
    "gn:country_code":"ET",
    "gn:dem":1801,
    "gn:feature_class":"P",
    "gn:feature_code":"PPL",
    "gn:name":"Dam\u0113",
    "gn:population":0,
    "gn:timezone":"Africa/Addis_Ababa",
    "iso:country":"ET",
    "wof:name":"Dame",
    "wof:placetype":"locality"
},
  "geometry": {"coordinates":[37.03333,12.18333],"type":"Point"}
}