{
  "type": "Feature",
  "properties": {
    "gn:admin1_code":"46",
    "gn:asciiname":"Yimod",
    "gn:country_code":"ET",
    "gn:dem":2879,
    "gn:feature_class":"P",
    "gn:feature_code":"PPL",
    "gn:name":"Yimod",
    "gn:population":0,
    "gn:timezone":"Africa/Addis_Ababa",
    "iso:country":"ET",
    "name:und_x_variant":[
        "Yimod (1)",
        "Yimod"
    ],
    "wof:name":"Yimod",
    "wof:placetype":"locality"
},
  "geometry": {"coordinates":[39.61661,10.05204],"type":"Point"}
}