{
  "type": "Feature",
  "properties": {
    "gn:admin1_code":"46",
    "gn:asciiname":"Yetnora",
    "gn:country_code":"ET",
    "gn:dem":2059,
    "gn:feature_class":"P",
    "gn:feature_code":"PPL",
    "gn:name":"Yetnora",
    "gn:population":0,
    "gn:timezone":"Africa/Addis_Ababa",
    "iso:country":"ET",
    "wof:name":"Yetnora",
    "wof:placetype":"locality"
},
  "geometry": {"coordinates":[39.02482,9.81579],"type":"Point"}
}