{
  "type": "Feature",
  "properties": {
    "iso:country":"ET",
    "name:amh_x_preferred":[
        "\u12a0\u134b\u121d\u1266"
    ],
    "name:cat_x_preferred":[
        "Afambo"
    ],
    "name:eng_x_preferred":[
        "Afambo"
    ],
    "name:fra_x_preferred":[
        "Afambo"
    ],
    "name:hrv_x_preferred":[
        "Afambo"
    ],
    "name:ita_x_preferred":[
        "Afambo"
    ],
    "name:nld_x_preferred":[
        "Afambo"
    ],
    "name:spa_x_preferred":[
        "Afambo"
    ],
    "name:und_x_variant":[
        "Afembo"
    ],
    "name:zul_x_preferred":[
        "Afambo"
    ],
    "qs:gn_country":"ET",
    "qs:gn_fcode":"PPL",
    "qs:gn_pop":0,
    "qs:name":"Afambo",
    "qs:name_adm0":"Ethiopia",
    "qs:name_adm1":"Afar",
    "qs:photos":16,
    "qs:photos_1k":3,
    "qs:photos_9k":1,
    "qs:photos_9r":1,
    "qs:photos_all":16,
    "qs:photos_sr":1,
    "qs:placetype":"Town",
    "qs:pop_sr":"3",
    "qs:woe_adm0":23424808,
    "wof:name":"Afambo",
    "wof:placetype":"locality"
},
  "geometry": {"coordinates":[41.68403,11.47704],"type":"Point"}
}