{
  "type": "Feature",
  "properties": {
    "gn:admin1_code":"53",
    "gn:asciiname":"Finarwa",
    "gn:country_code":"ET",
    "gn:dem":1529,
    "gn:feature_class":"P",
    "gn:feature_code":"PPL",
    "gn:name":"Finarwa",
    "gn:population":0,
    "gn:timezone":"Africa/Addis_Ababa",
    "iso:country":"ET",
    "name:und_x_variant":[
        "Fenaroa",
        "Finaruo",
        "Finarwa"
    ],
    "wof:name":"Finarwa",
    "wof:placetype":"locality"
},
  "geometry": {"coordinates":[39.02345,13.1005],"type":"Point"}
}