{
  "type": "Feature",
  "properties": {
    "gn:admin1_code":"39.0",
    "gn:asciiname":"Selamago",
    "gn:country_code":"ET",
    "gn:dem":509,
    "gn:feature_class":"P",
    "gn:feature_code":"PPL",
    "gn:name":"Selamago",
    "gn:population":0,
    "gn:timezone":"Africa/Addis_Ababa",
    "iso:country":"ET",
    "name:fra_x_preferred":[
        "Selamgo"
    ],
    "wof:name":"Selamago",
    "wof:placetype":"locality"
},
  "geometry": {"coordinates":[36.08333,5.91667],"type":"Point"}
}