{
  "type": "Feature",
  "properties": {
    "gn:admin1_code":"45.0",
    "gn:asciiname":"Saydo",
    "gn:country_code":"ET",
    "gn:dem":343,
    "gn:feature_class":"P",
    "gn:feature_code":"PPL",
    "gn:name":"Saydo",
    "gn:population":0,
    "gn:timezone":"Africa/Addis_Ababa",
    "iso:country":"ET",
    "wof:name":"Saydo",
    "wof:placetype":"locality"
},
  "geometry": {"coordinates":[41.63277,11.5094],"type":"Point"}
}