{
  "type": "Feature",
  "properties": {
    "gn:admin1_code":"53",
    "gn:asciiname":"May Senti",
    "gn:country_code":"ET",
    "gn:dem":2206,
    "gn:feature_class":"P",
    "gn:feature_code":"PPL",
    "gn:name":"May Sent\u012b",
    "gn:population":0,
    "gn:timezone":"Africa/Addis_Ababa",
    "iso:country":"ET",
    "wof:name":"May Senti",
    "wof:placetype":"locality"
},
  "geometry": {"coordinates":[39.24608,13.2749],"type":"Point"}
}