{
  "type": "Feature",
  "properties": {
    "gn:admin1_code":"51",
    "gn:asciiname":"K'int'ushule",
    "gn:country_code":"ET",
    "gn:dem":2322,
    "gn:feature_class":"P",
    "gn:feature_code":"PPL",
    "gn:name":"K\u2019int\u2019ushul\u0113",
    "gn:population":0,
    "gn:timezone":"Africa/Addis_Ababa",
    "iso:country":"ET",
    "wof:name":"K'int'ushule",
    "wof:placetype":"locality"
},
  "geometry": {"coordinates":[39.26667,8.85],"type":"Point"}
}