{
  "type": "Feature",
  "properties": {
    "gn:admin1_code":"46.0",
    "gn:asciiname":"Amerguya",
    "gn:country_code":"ET",
    "gn:dem":2824,
    "gn:feature_class":"P",
    "gn:feature_code":"PPL",
    "gn:name":"\u0100merguya",
    "gn:population":0,
    "gn:timezone":"Africa/Addis_Ababa",
    "iso:country":"ET",
    "wof:name":"Amerguya",
    "wof:placetype":"locality"
},
  "geometry": {"coordinates":[39.51925,10.38623],"type":"Point"}
}