{
  "type": "Feature",
  "properties": {
    "gn:admin1_code":"54",
    "gn:asciiname":"Ummuga",
    "gn:country_code":"ET",
    "gn:dem":1807,
    "gn:feature_class":"P",
    "gn:feature_code":"PPL",
    "gn:name":"Ummuga",
    "gn:population":0,
    "gn:timezone":"Africa/Addis_Ababa",
    "iso:country":"ET",
    "wof:name":"Ummuga",
    "wof:placetype":"locality"
},
  "geometry": {"coordinates":[37.76667,8.26667],"type":"Point"}
}