{
  "type": "Feature",
  "properties": {
    "gn:admin1_code":"51.0",
    "gn:asciiname":"Boru",
    "gn:country_code":"ET",
    "gn:dem":1856,
    "gn:feature_class":"P",
    "gn:feature_code":"PPL",
    "gn:name":"Boru",
    "gn:population":0,
    "gn:timezone":"Africa/Addis_Ababa",
    "iso:country":"ET",
    "name:ceb_x_preferred":[
        "Boru"
    ],
    "name:swe_x_preferred":[
        "Boru"
    ],
    "wof:name":"Boru",
    "wof:placetype":"locality"
},
  "geometry": {"coordinates":[36.43333,7.58333],"type":"Point"}
}