{
  "type": "Feature",
  "properties": {
    "gn:admin1_code":"51.0",
    "gn:asciiname":"Bilo",
    "gn:country_code":"ET",
    "gn:dem":1688,
    "gn:feature_class":"P",
    "gn:feature_code":"PPL",
    "gn:name":"B\u012blo",
    "gn:population":0,
    "gn:timezone":"Africa/Addis_Ababa",
    "iso:country":"ET",
    "wof:name":"Bilo",
    "wof:placetype":"locality"
},
  "geometry": {"coordinates":[36.98333,9.38333],"type":"Point"}
}