{
  "type": "Feature",
  "properties": {
    "gn:admin1_code":"52.0",
    "gn:asciiname":"Baadlei",
    "gn:country_code":"ET",
    "gn:dem":289,
    "gn:feature_class":"P",
    "gn:feature_code":"PPL",
    "gn:name":"Baadlei",
    "gn:population":0,
    "gn:timezone":"Africa/Addis_Ababa",
    "iso:country":"ET",
    "name:und_x_variant":[
        "Baadley",
        "Baadlei"
    ],
    "wof:name":"Baadlei",
    "wof:placetype":"locality"
},
  "geometry": {"coordinates":[43.28083,5.9075],"type":"Point"}
}