{
  "type": "Feature",
  "properties": {
    "gn:admin1_code":"51.0",
    "gn:asciiname":"Dulu",
    "gn:country_code":"ET",
    "gn:dem":2128,
    "gn:feature_class":"P",
    "gn:feature_code":"PPL",
    "gn:name":"Dulu",
    "gn:population":0,
    "gn:timezone":"Africa/Addis_Ababa",
    "iso:country":"ET",
    "name:und_x_variant":[
        "Dulu (2)",
        "Dulu"
    ],
    "wof:name":"Dulu",
    "wof:placetype":"locality"
},
  "geometry": {"coordinates":[41.85889,9.37278],"type":"Point"}
}