{
  "type": "Feature",
  "properties": {
    "gn:admin1_code":"46",
    "gn:asciiname":"Ginib Washa",
    "gn:country_code":"ET",
    "gn:dem":3108,
    "gn:feature_class":"P",
    "gn:feature_code":"PPL",
    "gn:name":"Ginib Washa",
    "gn:population":0,
    "gn:timezone":"Africa/Addis_Ababa",
    "iso:country":"ET",
    "name:und_x_variant":[
        "Ginb Washa",
        "Ginib Washa"
    ],
    "wof:name":"Ginib Washa",
    "wof:placetype":"locality"
},
  "geometry": {"coordinates":[39.71402,10.14871],"type":"Point"}
}