{
  "type": "Feature",
  "properties": {
    "gn:admin1_code":"52",
    "gn:asciiname":"Lafaleh",
    "gn:country_code":"ET",
    "gn:dem":2013,
    "gn:feature_class":"P",
    "gn:feature_code":"PPL",
    "gn:name":"Lafaleh",
    "gn:population":0,
    "gn:timezone":"Africa/Addis_Ababa",
    "iso:country":"ET",
    "wof:name":"Lafaleh",
    "wof:placetype":"locality"
},
  "geometry": {"coordinates":[42.48278,9.65417],"type":"Point"}
}