{
  "type": "Feature",
  "properties": {
    "gn:admin1_code":"51",
    "gn:asciiname":"Mut'e",
    "gn:country_code":"ET",
    "gn:dem":1669,
    "gn:feature_class":"P",
    "gn:feature_code":"PPL",
    "gn:name":"Mut\u2019\u0113",
    "gn:population":0,
    "gn:timezone":"Africa/Addis_Ababa",
    "iso:country":"ET",
    "wof:name":"Mut'e",
    "wof:placetype":"locality"
},
  "geometry": {"coordinates":[38.58333,9.46667],"type":"Point"}
}