{
  "type": "Feature",
  "properties": {
    "gn:admin1_code":"46.0",
    "gn:asciiname":"Bigunj",
    "gn:country_code":"ET",
    "gn:dem":3172,
    "gn:feature_class":"P",
    "gn:feature_code":"PPL",
    "gn:name":"Bigunj",
    "gn:population":0,
    "gn:timezone":"Africa/Addis_Ababa",
    "iso:country":"ET",
    "wof:name":"Bigunj",
    "wof:placetype":"locality"
},
  "geometry": {"coordinates":[39.15,11.06667],"type":"Point"}
}