{
  "type": "Feature",
  "properties": {
    "gn:admin1_code":"53.0",
    "gn:asciiname":"Abiy Imni",
    "gn:country_code":"ET",
    "gn:dem":2452,
    "gn:feature_class":"P",
    "gn:feature_code":"PPL",
    "gn:name":"\u0100b\u012by Imn\u012b",
    "gn:population":0,
    "gn:timezone":"Africa/Addis_Ababa",
    "iso:country":"ET",
    "wof:name":"Abiy Imni",
    "wof:placetype":"locality"
},
  "geometry": {"coordinates":[39.51667,12.53333],"type":"Point"}
}