{
  "type": "Feature",
  "properties": {
    "gn:admin1_code":"46",
    "gn:asciiname":"Melch'et",
    "gn:country_code":"ET",
    "gn:dem":3304,
    "gn:feature_class":"P",
    "gn:feature_code":"PPL",
    "gn:name":"Melch\u2019et",
    "gn:population":0,
    "gn:timezone":"Africa/Addis_Ababa",
    "iso:country":"ET",
    "wof:name":"Melch'et",
    "wof:placetype":"locality"
},
  "geometry": {"coordinates":[39.72951,10.40312],"type":"Point"}
}