{
  "type": "Feature",
  "properties": {
    "gn:admin1_code":"46.0",
    "gn:asciiname":"Askoye",
    "gn:country_code":"ET",
    "gn:dem":1880,
    "gn:feature_class":"P",
    "gn:feature_code":"PPL",
    "gn:name":"\u0100skoy\u0113",
    "gn:population":0,
    "gn:timezone":"Africa/Addis_Ababa",
    "iso:country":"ET",
    "wof:name":"Askoye",
    "wof:placetype":"locality"
},
  "geometry": {"coordinates":[37.18333,12.43333],"type":"Point"}
}