{
  "type": "Feature",
  "properties": {
    "gn:admin1_code":"45.0",
    "gn:asciiname":"Burka",
    "gn:country_code":"ET",
    "gn:dem":563,
    "gn:feature_class":"P",
    "gn:feature_code":"PPL",
    "gn:name":"Burka",
    "gn:population":0,
    "gn:timezone":"Africa/Addis_Ababa",
    "iso:country":"ET",
    "name:deu_x_preferred":[
        "Burka"
    ],
    "name:fra_x_preferred":[
        "Burka"
    ],
    "name:jpn_x_preferred":[
        "\u30d6\u30eb\u30ab"
    ],
    "name:nld_x_preferred":[
        "Boerka"
    ],
    "name:rus_x_preferred":[
        "\u0411\u0443\u0440\u043a\u0430"
    ],
    "name:ukr_x_preferred":[
        "\u0411\u0443\u0440\u043a\u0430"
    ],
    "name:und_x_variant":[
        "Malafaburi",
        "Burka"
    ],
    "wof:name":"Burka",
    "wof:placetype":"locality"
},
  "geometry": {"coordinates":[40.46922,10.61908],"type":"Point"}
}