{
  "type": "Feature",
  "properties": {
    "gn:admin1_code":"37.0",
    "gn:asciiname":"Irob",
    "gn:country_code":"ET",
    "gn:dem":2089,
    "gn:feature_class":"P",
    "gn:feature_code":"PPL",
    "gn:name":"Irob",
    "gn:population":0,
    "gn:timezone":"Africa/Addis_Ababa",
    "iso:country":"ET",
    "wof:name":"Irob",
    "wof:placetype":"locality"
},
  "geometry": {"coordinates":[39.62769,14.47723],"type":"Point"}
}