{
  "type": "Feature",
  "properties": {
    "gn:admin1_code":"51.0",
    "gn:asciiname":"Aweday",
    "gn:country_code":"ET",
    "gn:dem":2070,
    "gn:feature_class":"P",
    "gn:feature_code":"PPL",
    "gn:name":"\u0100weday",
    "gn:population":0,
    "gn:timezone":"Africa/Addis_Ababa",
    "iso:country":"ET",
    "name:und_x_variant":[
        "Auoday",
        "\u0100weday"
    ],
    "wof:name":"Aweday",
    "wof:placetype":"locality"
},
  "geometry": {"coordinates":[42.04343,9.36043],"type":"Point"}
}