{
  "type": "Feature",
  "properties": {
    "gn:admin1_code":"46",
    "gn:asciiname":"Mek'idela",
    "gn:country_code":"ET",
    "gn:dem":2497,
    "gn:feature_class":"P",
    "gn:feature_code":"PPL",
    "gn:name":"Mek\u2019idela",
    "gn:population":0,
    "gn:timezone":"Africa/Addis_Ababa",
    "iso:country":"ET",
    "wof:name":"Mek'idela",
    "wof:placetype":"locality"
},
  "geometry": {"coordinates":[39.26667,11.96667],"type":"Point"}
}