{
  "type": "Feature",
  "properties": {
    "gn:admin1_code":"51",
    "gn:asciiname":"Kusaye",
    "gn:country_code":"ET",
    "gn:dem":2085,
    "gn:feature_class":"P",
    "gn:feature_code":"PPL",
    "gn:name":"Kusay\u0113",
    "gn:population":0,
    "gn:timezone":"Africa/Addis_Ababa",
    "iso:country":"ET",
    "wof:name":"Kusaye",
    "wof:placetype":"locality"
},
  "geometry": {"coordinates":[38.43333,8.71667],"type":"Point"}
}