{
  "type": "Feature",
  "properties": {
    "gn:admin1_code":"26.0",
    "gn:asciiname":"Maaneed",
    "gn:country_code":"ET",
    "gn:dem":474,
    "gn:feature_class":"P",
    "gn:feature_code":"PPL",
    "gn:name":"Maaneed",
    "gn:population":0,
    "gn:timezone":"Africa/Addis_Ababa",
    "iso:country":"ET",
    "wof:name":"Maaneed",
    "wof:placetype":"locality"
},
  "geometry": {"coordinates":[46.79305,7.23916],"type":"Point"}
}