{
  "type": "Feature",
  "properties": {
    "gn:admin1_code":"52.0",
    "gn:asciiname":"Adad Dader",
    "gn:country_code":"ET",
    "gn:dem":563,
    "gn:feature_class":"P",
    "gn:feature_code":"PPL",
    "gn:name":"Adad Dader",
    "gn:population":0,
    "gn:timezone":"Africa/Addis_Ababa",
    "iso:country":"ET",
    "wof:name":"Adad Dader",
    "wof:placetype":"locality"
},
  "geometry": {"coordinates":[42.30611,6.68778],"type":"Point"}
}