{
  "type": "Feature",
  "properties": {
    "gn:admin1_code":"46.0",
    "gn:asciiname":"Tsekhay Guya",
    "gn:country_code":"ET",
    "gn:dem":2922,
    "gn:feature_class":"P",
    "gn:feature_code":"PPL",
    "gn:name":"Tsekhay Guya",
    "gn:population":0,
    "gn:timezone":"Africa/Addis_Ababa",
    "iso:country":"ET",
    "name:und_x_variant":[
        "Ts\u2019eh\u0101y Guya",
        "Tsekhay Guya"
    ],
    "wof:name":"Tsekhay Guya",
    "wof:placetype":"locality"
},
  "geometry": {"coordinates":[39.53787,10.3014],"type":"Point"}
}