{
  "type": "Feature",
  "properties": {
    "gn:admin1_code":"45",
    "gn:asciiname":"Lelegheddi",
    "gn:country_code":"ET",
    "gn:dem":465,
    "gn:feature_class":"P",
    "gn:feature_code":"PPL",
    "gn:name":"Lelegheddi",
    "gn:population":0,
    "gn:timezone":"Africa/Addis_Ababa",
    "iso:country":"ET",
    "wof:name":"Lelegheddi",
    "wof:placetype":"locality"
},
  "geometry": {"coordinates":[40.0238,14.2505],"type":"Point"}
}