{
  "type": "Feature",
  "properties": {
    "gn:admin1_code":"46.0",
    "gn:asciiname":"Buro Gabriet",
    "gn:country_code":"ET",
    "gn:dem":2347,
    "gn:feature_class":"P",
    "gn:feature_code":"PPL",
    "gn:name":"Buro Gabriet",
    "gn:population":0,
    "gn:timezone":"Africa/Addis_Ababa",
    "iso:country":"ET",
    "wof:name":"Buro Gabriet",
    "wof:placetype":"locality"
},
  "geometry": {"coordinates":[38.05,11.91667],"type":"Point"}
}