{
  "type": "Feature",
  "properties": {
    "gn:admin1_code":"46",
    "gn:asciiname":"Tehuledere",
    "gn:country_code":"ET",
    "gn:dem":2152,
    "gn:feature_class":"P",
    "gn:feature_code":"PPL",
    "gn:name":"Tehuleder\u0113",
    "gn:population":0,
    "gn:timezone":"Africa/Addis_Ababa",
    "iso:country":"ET",
    "name:amh_x_preferred":[
        "\u1270\u1201\u1208\u12f0\u122c"
    ],
    "name:fra_x_preferred":[
        "Tehuledere"
    ],
    "name:und_x_variant":[
        "Tehuleder\u0113"
    ],
    "wof:name":"Tehuledere",
    "wof:placetype":"locality"
},
  "geometry": {"coordinates":[39.75,11.31667],"type":"Point"}
}