{
  "type": "Feature",
  "properties": {
    "gn:admin1_code":"49.0",
    "gn:asciiname":"Madzhok",
    "gn:country_code":"ET",
    "gn:dem":419,
    "gn:feature_class":"P",
    "gn:feature_code":"PPL",
    "gn:name":"Madzhok",
    "gn:population":0,
    "gn:timezone":"Africa/Addis_Ababa",
    "iso:country":"ET",
    "wof:name":"Madzhok",
    "wof:placetype":"locality"
},
  "geometry": {"coordinates":[33.88926,8.25107],"type":"Point"}
}