{
  "type": "Feature",
  "properties": {
    "gn:admin1_code":"53.0",
    "gn:asciiname":"Adi Shahsheh",
    "gn:country_code":"ET",
    "gn:dem":2311,
    "gn:feature_class":"P",
    "gn:feature_code":"PPL",
    "gn:name":"\u0100d\u012b Shahsheh",
    "gn:population":0,
    "gn:timezone":"Africa/Addis_Ababa",
    "iso:country":"ET",
    "wof:name":"Adi Shahsheh",
    "wof:placetype":"locality"
},
  "geometry": {"coordinates":[39.46667,12.38333],"type":"Point"}
}