{
  "type": "Feature",
  "properties": {
    "gn:admin1_code":"49.0",
    "gn:asciiname":"Kamkere",
    "gn:country_code":"ET",
    "gn:dem":405,
    "gn:feature_class":"P",
    "gn:feature_code":"PPL",
    "gn:name":"Kamkere",
    "gn:population":0,
    "gn:timezone":"Africa/Addis_Ababa",
    "iso:country":"ET",
    "wof:name":"Kamkere",
    "wof:placetype":"locality"
},
  "geometry": {"coordinates":[33.22891,8.31448],"type":"Point"}
}