{
  "type": "Feature",
  "properties": {
    "gn:admin1_code":"52",
    "gn:asciiname":"Warder",
    "gn:country_code":"ET",
    "gn:dem":556,
    "gn:feature_class":"P",
    "gn:feature_code":"PPL",
    "gn:name":"Warder",
    "gn:population":0,
    "gn:timezone":"Africa/Addis_Ababa",
    "iso:country":"ET",
    "name:deu_x_preferred":[
        "Warder"
    ],
    "name:fra_x_preferred":[
        "Werder"
    ],
    "name:ita_x_preferred":[
        "Werder"
    ],
    "name:jpn_x_preferred":[
        "\u30ef\u30eb\u30c7\u30eb"
    ],
    "name:ron_x_preferred":[
        "Werder"
    ],
    "name:rus_x_preferred":[
        "\u0423\u043e\u0440\u0434\u0435\u0440"
    ],
    "name:som_x_preferred":[
        "Wardheer"
    ],
    "name:und_x_variant":[
        "Wardair",
        "Wadere",
        "Uardere",
        "Werd\u0113r",
        "Uorder",
        "Warder"
    ],
    "wof:name":"Warder",
    "wof:placetype":"locality"
},
  "geometry": {"coordinates":[45.34083,6.97444],"type":"Point"}
}