{
  "type": "Feature",
  "properties": {
    "gn:admin1_code":"52",
    "gn:asciiname":"Warder",
    "gn:country_code":"ET",
    "gn:dem":556,
    "gn:feature_class":"P",
    "gn:feature_code":"PPL",
    "gn:name":"Warder",
    "gn:population":0,
    "gn:timezone":"Africa/Addis_Ababa",
    "iso:country":"ET",
    "name:und_x_variant":[
        "Wardair",
        "Wadere",
        "Uardere",
        "Werd\u0113r",
        "Uorder",
        "Warder"
    ],
    "wof:name":"Warder",
    "wof:placetype":"locality"
},
  "geometry": {"coordinates":[45.34083,6.97444],"type":"Point"}
}