{
  "type": "Feature",
  "properties": {
    "gn:admin1_code":"51",
    "gn:asciiname":"Korji Gonda",
    "gn:country_code":"ET",
    "gn:dem":1873,
    "gn:feature_class":"P",
    "gn:feature_code":"PPL",
    "gn:name":"Korj\u012b Gonda",
    "gn:population":0,
    "gn:timezone":"Africa/Addis_Ababa",
    "iso:country":"ET",
    "wof:name":"Korji Gonda",
    "wof:placetype":"locality"
},
  "geometry": {"coordinates":[35.11667,9.05],"type":"Point"}
}