{
  "type": "Feature",
  "properties": {
    "gn:admin1_code":"46",
    "gn:asciiname":"Murjan",
    "gn:country_code":"ET",
    "gn:dem":1340,
    "gn:feature_class":"P",
    "gn:feature_code":"PPL",
    "gn:name":"Murjan",
    "gn:population":0,
    "gn:timezone":"Africa/Addis_Ababa",
    "iso:country":"ET",
    "wof:name":"Murjan",
    "wof:placetype":"locality"
},
  "geometry": {"coordinates":[40.07836,11.26748],"type":"Point"}
}