{
  "type": "Feature",
  "properties": {
    "gn:admin1_code":"51",
    "gn:asciiname":"K'ilt'u Gebeya",
    "gn:country_code":"ET",
    "gn:dem":2019,
    "gn:feature_class":"P",
    "gn:feature_code":"PPL",
    "gn:name":"K\u2019\u012blt\u2019u Gebeya",
    "gn:population":0,
    "gn:timezone":"Africa/Addis_Ababa",
    "iso:country":"ET",
    "wof:name":"K'ilt'u Gebeya",
    "wof:placetype":"locality"
},
  "geometry": {"coordinates":[36.23333,9.75],"type":"Point"}
}