{
  "type": "Feature",
  "properties": {
    "gn:admin1_code":"51",
    "gn:asciiname":"Sek'e",
    "gn:country_code":"ET",
    "gn:dem":1963,
    "gn:feature_class":"P",
    "gn:feature_code":"PPL",
    "gn:name":"Sek\u2019e",
    "gn:population":0,
    "gn:timezone":"Africa/Addis_Ababa",
    "iso:country":"ET",
    "wof:name":"Sek'e",
    "wof:placetype":"locality"
},
  "geometry": {"coordinates":[38.56667,9.55],"type":"Point"}
}