{
  "type": "Feature",
  "properties": {
    "gn:admin1_code":"51.0",
    "gn:asciiname":"Ch'ilelo",
    "gn:country_code":"ET",
    "gn:dem":2513,
    "gn:feature_class":"P",
    "gn:feature_code":"PPL",
    "gn:name":"Ch\u2019ilelo",
    "gn:population":0,
    "gn:timezone":"Africa/Addis_Ababa",
    "iso:country":"ET",
    "name:und_x_variant":[
        "Assa",
        "Ch\u2019ilelo"
    ],
    "wof:name":"Ch'ilelo",
    "wof:placetype":"locality"
},
  "geometry": {"coordinates":[38.28333,9.96667],"type":"Point"}
}