{
  "type": "Feature",
  "properties": {
    "gn:admin1_code":"40.0",
    "gn:asciiname":"Gewata",
    "gn:country_code":"ET",
    "gn:dem":1594,
    "gn:feature_class":"P",
    "gn:feature_code":"PPL",
    "gn:name":"Gewata",
    "gn:population":0,
    "gn:timezone":"Africa/Addis_Ababa",
    "iso:country":"ET",
    "wof:name":"Gewata",
    "wof:placetype":"locality"
},
  "geometry": {"coordinates":[35.93490999999999,7.56127],"type":"Point"}
}