{
  "type": "Feature",
  "properties": {
    "gn:admin1_code":"53.0",
    "gn:asciiname":"Adi Arba'a",
    "gn:country_code":"ET",
    "gn:dem":2044,
    "gn:feature_class":"P",
    "gn:feature_code":"PPL",
    "gn:name":"\u0100d\u012b \u0100rba\u2019\u0101",
    "gn:population":0,
    "gn:timezone":"Africa/Addis_Ababa",
    "iso:country":"ET",
    "wof:name":"Adi Arba'a",
    "wof:placetype":"locality"
},
  "geometry": {"coordinates":[39.57687,13.79488],"type":"Point"}
}