{
  "type": "Feature",
  "properties": {
    "gn:admin1_code":"51.0",
    "gn:asciiname":"Aggi",
    "gn:country_code":"ET",
    "gn:dem":1736,
    "gn:feature_class":"P",
    "gn:feature_code":"PPL",
    "gn:name":"Aggi",
    "gn:population":0,
    "gn:timezone":"Africa/Addis_Ababa",
    "iso:country":"ET",
    "name:und_x_variant":[
        "Aggai",
        "Agghi",
        "Aggi"
    ],
    "wof:name":"Aggi",
    "wof:placetype":"locality"
},
  "geometry": {"coordinates":[35.61667,7.88333],"type":"Point"}
}