{
  "type": "Feature",
  "properties": {
    "gn:admin1_code":"51",
    "gn:asciiname":"Jiren",
    "gn:country_code":"ET",
    "gn:dem":1685,
    "gn:feature_class":"P",
    "gn:feature_code":"PPL",
    "gn:name":"J\u012br\u0113n",
    "gn:population":0,
    "gn:timezone":"Africa/Addis_Ababa",
    "iso:country":"ET",
    "name:amh_x_preferred":[
        "\u1302\u122b\u1295"
    ],
    "name:und_x_variant":[
        "Giren",
        "Jiran",
        "J\u012br\u0113n"
    ],
    "wof:name":"Jiren",
    "wof:placetype":"locality"
},
  "geometry": {"coordinates":[36.68333,7.81667],"type":"Point"}
}