{
  "type": "Feature",
  "properties": {
    "gn:admin1_code":"54.0",
    "gn:asciiname":"Buscianne",
    "gn:country_code":"ET",
    "gn:dem":1738,
    "gn:feature_class":"P",
    "gn:feature_code":"PPL",
    "gn:name":"Buscianne",
    "gn:population":0,
    "gn:timezone":"Africa/Addis_Ababa",
    "iso:country":"ET",
    "wof:name":"Buscianne",
    "wof:placetype":"locality"
},
  "geometry": {"coordinates":[37.63333,7.76667],"type":"Point"}
}