{
  "type": "Feature",
  "properties": {
    "gn:admin1_code":"45",
    "gn:asciiname":"Jelale",
    "gn:country_code":"ET",
    "gn:dem":1181,
    "gn:feature_class":"P",
    "gn:feature_code":"PPLL",
    "gn:name":"Jelal\u0113",
    "gn:population":0,
    "gn:timezone":"Africa/Addis_Ababa",
    "iso:country":"ET",
    "wof:name":"Jelale",
    "wof:placetype":"locality"
},
  "geometry": {"coordinates":[39.90704,9.50951],"type":"Point"}
}