{
  "type": "Feature",
  "properties": {
    "gn:admin1_code":"38.0",
    "gn:asciiname":"Hakasha or Haqaasha",
    "gn:country_code":"ET",
    "gn:dem":2073,
    "gn:feature_class":"P",
    "gn:feature_code":"PPLF",
    "gn:name":"Hakasha or Haqaasha",
    "gn:population":0,
    "gn:timezone":"Africa/Addis_Ababa",
    "iso:country":"ET",
    "wof:name":"Hakasha or Haqaasha",
    "wof:placetype":"locality"
},
  "geometry": {"coordinates":[40.62032,7.19389],"type":"Point"}
}