{
  "type": "Feature",
  "properties": {
    "gn:admin1_code":"51",
    "gn:asciiname":"Humbe",
    "gn:country_code":"ET",
    "gn:dem":1997,
    "gn:feature_class":"P",
    "gn:feature_code":"PPL",
    "gn:name":"Humb\u0113",
    "gn:population":0,
    "gn:timezone":"Africa/Addis_Ababa",
    "iso:country":"ET",
    "name:und_x_variant":[
        "Bumbe",
        "Humb\u0113"
    ],
    "wof:name":"Humbe",
    "wof:placetype":"locality"
},
  "geometry": {"coordinates":[36.10433,8.46601],"type":"Point"}
}