{
  "type": "Feature",
  "properties": {
    "gn:admin1_code":"51",
    "gn:asciiname":"Kara Gada",
    "gn:country_code":"ET",
    "gn:dem":3268,
    "gn:feature_class":"P",
    "gn:feature_code":"PPL",
    "gn:name":"Kara Gada",
    "gn:population":0,
    "gn:timezone":"Africa/Addis_Ababa",
    "iso:country":"ET",
    "wof:name":"Kara Gada",
    "wof:placetype":"locality"
},
  "geometry": {"coordinates":[38.65,9.76667],"type":"Point"}
}