{
  "type": "Feature",
  "properties": {
    "gn:admin1_code":"51.0",
    "gn:asciiname":"Ch'ole",
    "gn:country_code":"ET",
    "gn:dem":2583,
    "gn:feature_class":"P",
    "gn:feature_code":"PPL",
    "gn:name":"Ch\u2019ol\u0113",
    "gn:population":0,
    "gn:timezone":"Africa/Addis_Ababa",
    "iso:country":"ET",
    "wof:name":"Ch'ole",
    "wof:placetype":"locality"
},
  "geometry": {"coordinates":[39.12031,9.15973],"type":"Point"}
}