{
  "type": "Feature",
  "properties": {
    "gn:admin1_code":"53.0",
    "gn:asciiname":"Adota",
    "gn:country_code":"ET",
    "gn:dem":2698,
    "gn:feature_class":"P",
    "gn:feature_code":"PPL",
    "gn:name":"\u0100dota",
    "gn:population":0,
    "gn:timezone":"Africa/Addis_Ababa",
    "iso:country":"ET",
    "wof:name":"Adota",
    "wof:placetype":"locality"
},
  "geometry": {"coordinates":[39.51667,12.65],"type":"Point"}
}