{
  "type": "Feature",
  "properties": {
    "gn:admin1_code":"54",
    "gn:asciiname":"Maji",
    "gn:country_code":"ET",
    "gn:dem":2377,
    "gn:feature_class":"P",
    "gn:feature_code":"PPL",
    "gn:name":"Maj\u012b",
    "gn:population":0,
    "gn:timezone":"Africa/Addis_Ababa",
    "iso:country":"ET",
    "name:fra_x_preferred":[
        "Maji"
    ],
    "name:jpn_x_preferred":[
        "\u30de\u30b8"
    ],
    "name:und_x_variant":[
        "Magi",
        "Maj\u012b"
    ],
    "wof:name":"Maji",
    "wof:placetype":"locality"
},
  "geometry": {"coordinates":[35.58241,6.17658],"type":"Point"}
}