{
  "type": "Feature",
  "properties": {
    "gn:admin1_code":"53",
    "gn:asciiname":"Re'ayle",
    "gn:country_code":"ET",
    "gn:dem":2877,
    "gn:feature_class":"P",
    "gn:feature_code":"PPL",
    "gn:name":"Re\u2019\u0101yle",
    "gn:population":0,
    "gn:timezone":"Africa/Addis_Ababa",
    "iso:country":"ET",
    "wof:name":"Re'ayle",
    "wof:placetype":"locality"
},
  "geometry": {"coordinates":[39.68139,14.10285],"type":"Point"}
}