{
  "type": "Feature",
  "properties": {
    "gn:admin1_code":"54",
    "gn:asciiname":"Sai",
    "gn:country_code":"ET",
    "gn:dem":571,
    "gn:feature_class":"P",
    "gn:feature_code":"PPL",
    "gn:name":"Sai",
    "gn:population":0,
    "gn:timezone":"Africa/Addis_Ababa",
    "iso:country":"ET",
    "name:ara_x_preferred":[
        "\u0633\u0627\u064a"
    ],
    "name:cat_x_preferred":[
        "Sai"
    ],
    "name:cdo_x_preferred":[
        "S\u0103i"
    ],
    "name:ceb_x_preferred":[
        "Sai"
    ],
    "name:est_x_preferred":[
        "Sai"
    ],
    "name:fra_x_preferred":[
        "Sai"
    ],
    "name:ind_x_preferred":[
        "Sai"
    ],
    "name:msa_x_preferred":[
        "Sai"
    ],
    "name:nld_x_preferred":[
        "Sai"
    ],
    "name:pol_x_preferred":[
        "Sai"
    ],
    "name:por_x_preferred":[
        "Sai"
    ],
    "name:spa_x_preferred":[
        "Sai"
    ],
    "name:swe_x_preferred":[
        "Sai"
    ],
    "name:und_x_variant":[
        "Seie",
        "Sai"
    ],
    "wof:name":"Sai",
    "wof:placetype":"locality"
},
  "geometry": {"coordinates":[35.8168,6.18924],"type":"Point"}
}