{
  "type": "Feature",
  "properties": {
    "iso:country":"ET",
    "qs:gn_pop":0,
    "qs:name":"Debra Sina",
    "qs:name_adm0":"Ethiopia",
    "qs:name_adm1":"Amhara",
    "qs:photos":32,
    "qs:photos_1k":6,
    "qs:photos_9k":1,
    "qs:photos_9r":2,
    "qs:photos_all":32,
    "qs:photos_sr":2,
    "qs:placetype":"Town",
    "qs:pop_sr":"0",
    "qs:woe_adm0":23424808,
    "wof:name":"Debra Sina",
    "wof:placetype":"locality"
},
  "geometry": {"coordinates":[39.739265,9.843546],"type":"Point"}
}