{
  "type": "Feature",
  "properties": {
    "gn:admin1_code":"46.0",
    "gn:asciiname":"Derek' Amba",
    "gn:country_code":"ET",
    "gn:dem":2733,
    "gn:feature_class":"P",
    "gn:feature_code":"PPL",
    "gn:name":"Derek\u2019 \u0100mba",
    "gn:population":0,
    "gn:timezone":"Africa/Addis_Ababa",
    "iso:country":"ET",
    "wof:name":"Derek' Amba",
    "wof:placetype":"locality"
},
  "geometry": {"coordinates":[39.27014000000001,10.70291],"type":"Point"}
}