{
  "type": "Feature",
  "properties": {
    "gn:admin1_code":"46",
    "gn:asciiname":"Wanza Ber",
    "gn:country_code":"ET",
    "gn:dem":1933,
    "gn:feature_class":"P",
    "gn:feature_code":"PPL",
    "gn:name":"Wanza Ber",
    "gn:population":0,
    "gn:timezone":"Africa/Addis_Ababa",
    "iso:country":"ET",
    "name:und_x_variant":[
        "Wanza Ben",
        "Wanza Ber"
    ],
    "wof:name":"Wanza Ber",
    "wof:placetype":"locality"
},
  "geometry": {"coordinates":[39.81117,9.7959],"type":"Point"}
}