{
  "type": "Feature",
  "properties": {
    "gn:admin1_code":"51.0",
    "gn:asciiname":"Cuni",
    "gn:country_code":"ET",
    "gn:dem":1967,
    "gn:feature_class":"P",
    "gn:feature_code":"PPL",
    "gn:name":"Cuni",
    "gn:population":0,
    "gn:timezone":"Africa/Addis_Ababa",
    "iso:country":"ET",
    "name:und_x_variant":[
        "Kuni",
        "Cuni"
    ],
    "wof:name":"Cuni",
    "wof:placetype":"locality"
},
  "geometry": {"coordinates":[39.21667,5.95],"type":"Point"}
}