{
  "type": "Feature",
  "properties": {
    "gn:admin1_code":"51",
    "gn:asciiname":"Horo",
    "gn:country_code":"ET",
    "gn:dem":2651,
    "gn:feature_class":"P",
    "gn:feature_code":"PPL",
    "gn:name":"Horo",
    "gn:population":0,
    "gn:timezone":"Africa/Addis_Ababa",
    "iso:country":"ET",
    "name:ceb_x_preferred":[
        "Horo"
    ],
    "name:deu_x_preferred":[
        "Horo"
    ],
    "name:fin_x_preferred":[
        "Horo"
    ],
    "name:fra_x_preferred":[
        "Horo"
    ],
    "name:ita_x_preferred":[
        "Horo"
    ],
    "name:pol_x_preferred":[
        "Horo"
    ],
    "name:swe_x_preferred":[
        "Horo"
    ],
    "wof:name":"Horo",
    "wof:placetype":"locality"
},
  "geometry": {"coordinates":[38.83333,9.36667],"type":"Point"}
}