{
  "type": "Feature",
  "properties": {
    "gn:admin1_code":"52.0",
    "gn:asciiname":"Bender Aman",
    "gn:country_code":"ET",
    "gn:dem":1412,
    "gn:feature_class":"P",
    "gn:feature_code":"PPL",
    "gn:name":"Bender Aman",
    "gn:population":0,
    "gn:timezone":"Africa/Addis_Ababa",
    "iso:country":"ET",
    "wof:name":"Bender Aman",
    "wof:placetype":"locality"
},
  "geometry": {"coordinates":[43.73333,9.25],"type":"Point"}
}