{
  "type": "Feature",
  "properties": {
    "gn:admin1_code":"53",
    "gn:asciiname":"Kube",
    "gn:country_code":"ET",
    "gn:dem":1955,
    "gn:feature_class":"P",
    "gn:feature_code":"PPL",
    "gn:name":"Kub\u0113",
    "gn:population":0,
    "gn:timezone":"Africa/Addis_Ababa",
    "iso:country":"ET",
    "wof:name":"Kube",
    "wof:placetype":"locality"
},
  "geometry": {"coordinates":[39.58333,12.63333],"type":"Point"}
}