{
  "type": "Feature",
  "properties": {
    "gn:admin1_code":"51",
    "gn:asciiname":"Wemetu",
    "gn:country_code":"ET",
    "gn:dem":2222,
    "gn:feature_class":"P",
    "gn:feature_code":"PPL",
    "gn:name":"Wemetu",
    "gn:population":0,
    "gn:timezone":"Africa/Addis_Ababa",
    "iso:country":"ET",
    "wof:name":"Wemetu",
    "wof:placetype":"locality"
},
  "geometry": {"coordinates":[37.71667,9.03333],"type":"Point"}
}