{
  "type": "Feature",
  "properties": {
    "gn:admin1_code":"53",
    "gn:asciiname":"Utza Guza",
    "gn:country_code":"ET",
    "gn:dem":1903,
    "gn:feature_class":"P",
    "gn:feature_code":"PPL",
    "gn:name":"Utza Guza",
    "gn:population":0,
    "gn:timezone":"Africa/Addis_Ababa",
    "iso:country":"ET",
    "wof:name":"Utza Guza",
    "wof:placetype":"locality"
},
  "geometry": {"coordinates":[39.16667,14.46667],"type":"Point"}
}