{
  "type": "Feature",
  "properties": {
    "gn:admin1_code":"51",
    "gn:asciiname":"Gurgura",
    "gn:country_code":"ET",
    "gn:dem":1340,
    "gn:feature_class":"P",
    "gn:feature_code":"PPL",
    "gn:name":"Gurgura",
    "gn:population":0,
    "gn:timezone":"Africa/Addis_Ababa",
    "iso:country":"ET",
    "wof:name":"Gurgura",
    "wof:placetype":"locality"
},
  "geometry": {"coordinates":[42.16109,8.67708],"type":"Point"}
}