{
  "type": "Feature",
  "properties": {
    "gn:admin1_code":"53",
    "gn:asciiname":"Mariam Setta",
    "gn:country_code":"ET",
    "gn:dem":2285,
    "gn:feature_class":"P",
    "gn:feature_code":"PPL",
    "gn:name":"Mariam Setta",
    "gn:population":0,
    "gn:timezone":"Africa/Addis_Ababa",
    "iso:country":"ET",
    "name:und_x_variant":[
        "Anda Mariam Sut\u00e0",
        "Sett\u00e0",
        "Mariam Setta"
    ],
    "wof:name":"Mariam Setta",
    "wof:placetype":"locality"
},
  "geometry": {"coordinates":[39.46667,14.05],"type":"Point"}
}