{
  "type": "Feature",
  "properties": {
    "gn:admin1_code":"51",
    "gn:asciiname":"Rob Gebeya",
    "gn:country_code":"ET",
    "gn:dem":1973,
    "gn:feature_class":"P",
    "gn:feature_code":"PPL",
    "gn:name":"Rob Gebeya",
    "gn:population":0,
    "gn:timezone":"Africa/Addis_Ababa",
    "iso:country":"ET",
    "wof:name":"Rob Gebeya",
    "wof:placetype":"locality"
},
  "geometry": {"coordinates":[36.91667,9.15],"type":"Point"}
}