{
  "type": "Feature",
  "properties": {
    "gn:admin1_code":"27.0",
    "gn:asciiname":"Kirkos",
    "gn:country_code":"ET",
    "gn:dem":2354,
    "gn:feature_class":"P",
    "gn:feature_code":"PPL",
    "gn:name":"Kirkos",
    "gn:population":0,
    "gn:timezone":"Africa/Addis_Ababa",
    "iso:country":"ET",
    "name:fra_x_preferred":[
        "Kirkos"
    ],
    "wof:name":"Kirkos",
    "wof:placetype":"locality"
},
  "geometry": {"coordinates":[38.76303,9.00221],"type":"Point"}
}