{
  "type": "Feature",
  "properties": {
    "gn:admin1_code":"51",
    "gn:asciiname":"K'ersalo",
    "gn:country_code":"ET",
    "gn:dem":2004,
    "gn:feature_class":"P",
    "gn:feature_code":"PPL",
    "gn:name":"K\u2019ersalo",
    "gn:population":0,
    "gn:timezone":"Africa/Addis_Ababa",
    "iso:country":"ET",
    "name:und_x_variant":[
        "Kersal\u2019",
        "K\u2019ersalo"
    ],
    "wof:name":"K'ersalo",
    "wof:placetype":"locality"
},
  "geometry": {"coordinates":[42.03222,9.34083],"type":"Point"}
}