{
  "type": "Feature",
  "properties": {
    "gn:admin1_code":"53",
    "gn:asciiname":"May Ch'a'a",
    "gn:country_code":"ET",
    "gn:dem":1888,
    "gn:feature_class":"P",
    "gn:feature_code":"PPL",
    "gn:name":"May Ch\u2019a\u2019\u0101",
    "gn:population":0,
    "gn:timezone":"Africa/Addis_Ababa",
    "iso:country":"ET",
    "name:und_x_variant":[
        "May Ch\u2019a\u2019a (1)",
        "May Ch\u2019a\u2019\u0101"
    ],
    "wof:name":"May Ch'a'a",
    "wof:placetype":"locality"
},
  "geometry": {"coordinates":[39.18667,14.45945],"type":"Point"}
}