{
  "type": "Feature",
  "properties": {
    "gn:admin1_code":"51",
    "gn:asciiname":"Negele",
    "gn:country_code":"ET",
    "gn:dem":1540,
    "gn:feature_class":"P",
    "gn:feature_code":"PPL",
    "gn:name":"Neg\u0113l\u0113",
    "gn:population":0,
    "gn:timezone":"Africa/Addis_Ababa",
    "iso:country":"ET",
    "name:fra_x_preferred":[
        "Negele Boran"
    ],
    "name:hrv_x_preferred":[
        "Negele Boran"
    ],
    "name:ita_x_preferred":[
        "Neghelli"
    ],
    "name:pol_x_preferred":[
        "Negele Boran"
    ],
    "name:ron_x_preferred":[
        "Negele Boran"
    ],
    "name:und_x_variant":[
        "Nag\u0113l\u0113",
        "Neghelle",
        "Negelie",
        "Negelle",
        "Negelli",
        "Neg\u0113l\u0113"
    ],
    "wof:name":"Negele",
    "wof:placetype":"locality"
},
  "geometry": {"coordinates":[39.58333,5.31667],"type":"Point"}
}