{
  "type": "Feature",
  "properties": {
    "gn:admin1_code":"46",
    "gn:asciiname":"Siringi",
    "gn:country_code":"ET",
    "gn:dem":2061,
    "gn:feature_class":"P",
    "gn:feature_code":"PPL",
    "gn:name":"Siringi",
    "gn:population":0,
    "gn:timezone":"Africa/Addis_Ababa",
    "iso:country":"ET",
    "name:und_x_variant":[
        "Sirighi Micael",
        "Sirigi",
        "Siringi"
    ],
    "wof:name":"Siringi",
    "wof:placetype":"locality"
},
  "geometry": {"coordinates":[36.71667,11.08333],"type":"Point"}
}