{
  "type": "Feature",
  "properties": {
    "gn:admin1_code":"51",
    "gn:asciiname":"Reribero",
    "gn:country_code":"ET",
    "gn:dem":2826,
    "gn:feature_class":"P",
    "gn:feature_code":"PPL",
    "gn:name":"Rer\u012bbero",
    "gn:population":0,
    "gn:timezone":"Africa/Addis_Ababa",
    "iso:country":"ET",
    "wof:name":"Reribero",
    "wof:placetype":"locality"
},
  "geometry": {"coordinates":[39.81667,8.28333],"type":"Point"}
}