{
  "type": "Feature",
  "properties": {
    "gn:admin1_code":"53",
    "gn:asciiname":"Midir Felasi",
    "gn:country_code":"ET",
    "gn:dem":1819,
    "gn:feature_class":"P",
    "gn:feature_code":"PPL",
    "gn:name":"Midir Felas\u012b",
    "gn:population":0,
    "gn:timezone":"Africa/Addis_Ababa",
    "iso:country":"ET",
    "wof:name":"Midir Felasi",
    "wof:placetype":"locality"
},
  "geometry": {"coordinates":[38.23388,14.37118],"type":"Point"}
}