{
  "type": "Feature",
  "properties": {
    "gn:admin1_code":"46",
    "gn:asciiname":"Sali",
    "gn:country_code":"ET",
    "gn:dem":2885,
    "gn:feature_class":"P",
    "gn:feature_code":"PPL",
    "gn:name":"Sal\u012b",
    "gn:population":0,
    "gn:timezone":"Africa/Addis_Ababa",
    "iso:country":"ET",
    "wof:name":"Sali",
    "wof:placetype":"locality"
},
  "geometry": {"coordinates":[38.51667,11.66667],"type":"Point"}
}