{
  "type": "Feature",
  "properties": {
    "gn:admin1_code":"46",
    "gn:asciiname":"Sali",
    "gn:country_code":"ET",
    "gn:dem":2885,
    "gn:feature_class":"P",
    "gn:feature_code":"PPL",
    "gn:name":"Sal\u012b",
    "gn:population":0,
    "gn:timezone":"Africa/Addis_Ababa",
    "iso:country":"ET",
    "name:bul_x_preferred":[
        "\u0421\u0430\u043b\u0438"
    ],
    "name:ceb_x_preferred":[
        "Sali"
    ],
    "name:ces_x_preferred":[
        "Sali"
    ],
    "name:deu_x_preferred":[
        "Sali"
    ],
    "name:fra_x_preferred":[
        "Sali"
    ],
    "name:hun_x_preferred":[
        "Sali"
    ],
    "name:ita_x_preferred":[
        "Sali"
    ],
    "name:por_x_preferred":[
        "Sali"
    ],
    "name:rus_x_preferred":[
        "\u0421\u0430\u043b\u0438"
    ],
    "name:swe_x_preferred":[
        "Sali"
    ],
    "name:ukr_x_preferred":[
        "\u0421\u0430\u043b\u0456"
    ],
    "wof:name":"Sali",
    "wof:placetype":"locality"
},
  "geometry": {"coordinates":[38.51667,11.66667],"type":"Point"}
}