{
  "type": "Feature",
  "properties": {
    "gn:admin1_code":"46",
    "gn:asciiname":"Zenalk'a",
    "gn:country_code":"ET",
    "gn:dem":2262,
    "gn:feature_class":"P",
    "gn:feature_code":"PPL",
    "gn:name":"Zenalk\u2019a",
    "gn:population":0,
    "gn:timezone":"Africa/Addis_Ababa",
    "iso:country":"ET",
    "name:und_x_variant":[
        "Zenalk\u2019a (2)",
        "Zenalk\u2019a"
    ],
    "wof:name":"Zenalk'a",
    "wof:placetype":"locality"
},
  "geometry": {"coordinates":[38.76667,12.56667],"type":"Point"}
}