{
  "type": "Feature",
  "properties": {
    "gn:admin1_code":"53.0",
    "gn:asciiname":"Bet Muha",
    "gn:country_code":"ET",
    "gn:dem":2255,
    "gn:feature_class":"P",
    "gn:feature_code":"PPL",
    "gn:name":"B\u0113t Muha",
    "gn:population":0,
    "gn:timezone":"Africa/Addis_Ababa",
    "iso:country":"ET",
    "name:und_x_variant":[
        "Bet Mykha",
        "B\u0113t Muha"
    ],
    "wof:name":"Bet Muha",
    "wof:placetype":"locality"
},
  "geometry": {"coordinates":[39.3063,13.74566],"type":"Point"}
}