{
  "type": "Feature",
  "properties": {
    "gn:admin1_code":"51",
    "gn:asciiname":"Mina",
    "gn:country_code":"ET",
    "gn:dem":2064,
    "gn:feature_class":"P",
    "gn:feature_code":"PPL",
    "gn:name":"M\u012bna",
    "gn:population":0,
    "gn:timezone":"Africa/Addis_Ababa",
    "iso:country":"ET",
    "name:ara_x_preferred":[
        "\u0645\u064a\u0646\u0627"
    ],
    "name:aze_x_preferred":[
        "Mina"
    ],
    "name:bos_x_preferred":[
        "Mina"
    ],
    "name:bul_x_preferred":[
        "\u041c\u0438\u043d\u0430"
    ],
    "name:cat_x_preferred":[
        "Mina"
    ],
    "name:ceb_x_preferred":[
        "Mina"
    ],
    "name:ces_x_preferred":[
        "Mina"
    ],
    "name:dan_x_preferred":[
        "Mina"
    ],
    "name:deu_x_preferred":[
        "Mina"
    ],
    "name:fas_x_preferred":[
        "\u0645\u06cc\u0646\u0627"
    ],
    "name:fin_x_preferred":[
        "Mina"
    ],
    "name:fra_x_preferred":[
        "Mina"
    ],
    "name:glg_x_preferred":[
        "Mina"
    ],
    "name:heb_x_preferred":[
        "\u05de\u05d9\u05e0\u05d4"
    ],
    "name:hrv_x_preferred":[
        "Mina"
    ],
    "name:hun_x_preferred":[
        "Mina"
    ],
    "name:ind_x_preferred":[
        "Mina"
    ],
    "name:ita_x_preferred":[
        "Mina"
    ],
    "name:jpn_x_preferred":[
        "Mina"
    ],
    "name:kir_x_preferred":[
        "\u041c\u0438\u043d\u0430"
    ],
    "name:lit_x_preferred":[
        "Mina"
    ],
    "name:nld_x_preferred":[
        "Mina"
    ],
    "name:nor_x_preferred":[
        "Mina"
    ],
    "name:pol_x_preferred":[
        "Mina"
    ],
    "name:por_x_preferred":[
        "Mina"
    ],
    "name:ron_x_preferred":[
        "Min\u0103"
    ],
    "name:rus_x_preferred":[
        "\u041c\u0438\u043d\u0430"
    ],
    "name:sco_x_preferred":[
        "Mina"
    ],
    "name:slk_x_preferred":[
        "M\u00edna"
    ],
    "name:spa_x_preferred":[
        "Mina"
    ],
    "name:srp_x_preferred":[
        "\u041c\u0438\u043d\u0430"
    ],
    "name:swe_x_preferred":[
        "Mina"
    ],
    "name:tur_x_preferred":[
        "Mina"
    ],
    "name:ukr_x_preferred":[
        "\u041c\u0456\u043d\u0430"
    ],
    "wof:name":"Mina",
    "wof:placetype":"locality"
},
  "geometry": {"coordinates":[38.53333,8.85],"type":"Point"}
}