{
  "type": "Feature",
  "properties": {
    "gn:admin1_code":"51",
    "gn:asciiname":"Mina",
    "gn:country_code":"ET",
    "gn:dem":2064,
    "gn:feature_class":"P",
    "gn:feature_code":"PPL",
    "gn:name":"M\u012bna",
    "gn:population":0,
    "gn:timezone":"Africa/Addis_Ababa",
    "iso:country":"ET",
    "wof:name":"Mina",
    "wof:placetype":"locality"
},
  "geometry": {"coordinates":[38.53333,8.85],"type":"Point"}
}