{
  "type": "Feature",
  "properties": {
    "gn:admin1_code":"54",
    "gn:asciiname":"Machi",
    "gn:country_code":"ET",
    "gn:dem":1962,
    "gn:feature_class":"P",
    "gn:feature_code":"PPLL",
    "gn:name":"Machi",
    "gn:population":0,
    "gn:timezone":"Africa/Addis_Ababa",
    "iso:country":"ET",
    "name:eng_x_preferred":[
        "Mashi"
    ],
    "name:und_x_variant":[
        "Masci",
        "Machi"
    ],
    "wof:name":"Machi",
    "wof:placetype":"locality"
},
  "geometry": {"coordinates":[35.56495,6.26757],"type":"Point"}
}