{
  "type": "Feature",
  "properties": {
    "gn:admin1_code":"51",
    "gn:asciiname":"Fulensa",
    "gn:country_code":"ET",
    "gn:dem":1398,
    "gn:feature_class":"P",
    "gn:feature_code":"PPL",
    "gn:name":"Ful\u0113nsa",
    "gn:population":0,
    "gn:timezone":"Africa/Addis_Ababa",
    "iso:country":"ET",
    "name:und_x_variant":[
        "Ful\u0113nsa 1",
        "Ful\u0113nsa"
    ],
    "wof:name":"Fulensa",
    "wof:placetype":"locality"
},
  "geometry": {"coordinates":[41.37113,8.20875],"type":"Point"}
}