{
  "type": "Feature",
  "properties": {
    "gn:admin1_code":"46",
    "gn:asciiname":"T'id Wiha",
    "gn:country_code":"ET",
    "gn:dem":2884,
    "gn:feature_class":"P",
    "gn:feature_code":"PPL",
    "gn:name":"T\u2019id Wiha",
    "gn:population":0,
    "gn:timezone":"Africa/Addis_Ababa",
    "iso:country":"ET",
    "wof:name":"T'id Wiha",
    "wof:placetype":"locality"
},
  "geometry": {"coordinates":[39.54131,10.24515],"type":"Point"}
}