{
  "type": "Feature",
  "properties": {
    "gn:admin1_code":"53.0",
    "gn:asciiname":"Adi Hak'eyti",
    "gn:country_code":"ET",
    "gn:dem":2141,
    "gn:feature_class":"P",
    "gn:feature_code":"PPL",
    "gn:name":"\u0100d\u012b Hak\u2019eyt\u012b",
    "gn:population":0,
    "gn:timezone":"Africa/Addis_Ababa",
    "iso:country":"ET",
    "name:und_x_variant":[
        "\u0100di Hak\u2019eyt\u012b (2)",
        "Addi Khakeyti",
        "\u0100d\u012b Hak\u2019eyt\u012b"
    ],
    "wof:name":"Adi Hak'eyti",
    "wof:placetype":"locality"
},
  "geometry": {"coordinates":[39.56798,13.29754],"type":"Point"}
}