{
  "type": "Feature",
  "properties": {
    "gn:admin1_code":"54.0",
    "gn:asciiname":"Cure",
    "gn:country_code":"ET",
    "gn:dem":477,
    "gn:feature_class":"P",
    "gn:feature_code":"PPL",
    "gn:name":"Cure",
    "gn:population":0,
    "gn:timezone":"Africa/Addis_Ababa",
    "iso:country":"ET",
    "name:ara_x_preferred":[
        "\u0647\u062f\u0623\u0629"
    ],
    "name:deu_x_preferred":[
        "Heilmittel"
    ],
    "name:scn_x_preferred":[
        "Rimediu"
    ],
    "name:spa_x_preferred":[
        "Remedio"
    ],
    "name:urd_x_preferred":[
        "\u0634\u0641\u0627"
    ],
    "wof:name":"Cure",
    "wof:placetype":"locality"
},
  "geometry": {"coordinates":[36.26667,5.75],"type":"Point"}
}