{
  "type": "Feature",
  "properties": {
    "gn:admin1_code":"46",
    "gn:asciiname":"Germame",
    "gn:country_code":"ET",
    "gn:dem":3279,
    "gn:feature_class":"P",
    "gn:feature_code":"PPL",
    "gn:name":"Germam\u0113",
    "gn:population":0,
    "gn:timezone":"Africa/Addis_Ababa",
    "iso:country":"ET",
    "wof:name":"Germame",
    "wof:placetype":"locality"
},
  "geometry": {"coordinates":[39.27564,10.99857],"type":"Point"}
}