{
  "type": "Feature",
  "properties": {
    "gn:admin1_code":"51",
    "gn:asciiname":"Unone",
    "gn:country_code":"ET",
    "gn:dem":2227,
    "gn:feature_class":"P",
    "gn:feature_code":"PPL",
    "gn:name":"Unon\u0113",
    "gn:population":0,
    "gn:timezone":"Africa/Addis_Ababa",
    "iso:country":"ET",
    "name:und_x_variant":[
        "Scirba",
        "Unon\u0113"
    ],
    "wof:name":"Unone",
    "wof:placetype":"locality"
},
  "geometry": {"coordinates":[37.26667,9.51667],"type":"Point"}
}