{
  "type": "Feature",
  "properties": {
    "gn:admin1_code":"51",
    "gn:asciiname":"Kurno",
    "gn:country_code":"ET",
    "gn:dem":2535,
    "gn:feature_class":"P",
    "gn:feature_code":"PPL",
    "gn:name":"Kurno",
    "gn:population":0,
    "gn:timezone":"Africa/Addis_Ababa",
    "iso:country":"ET",
    "wof:name":"Kurno",
    "wof:placetype":"locality"
},
  "geometry": {"coordinates":[38.31667,9.95],"type":"Point"}
}