{
  "type": "Feature",
  "properties": {
    "gn:admin1_code":"46",
    "gn:asciiname":"Muja",
    "gn:country_code":"ET",
    "gn:dem":2038,
    "gn:feature_class":"P",
    "gn:feature_code":"PPL",
    "gn:name":"Muja",
    "gn:population":0,
    "gn:timezone":"Africa/Addis_Ababa",
    "iso:country":"ET",
    "name:und_x_variant":[
        "Mugia",
        "Muja"
    ],
    "wof:name":"Muja",
    "wof:placetype":"locality"
},
  "geometry": {"coordinates":[38.48333,11.38333],"type":"Point"}
}