{
  "type": "Feature",
  "properties": {
    "gn:admin1_code":"46",
    "gn:asciiname":"Were T'ega",
    "gn:country_code":"ET",
    "gn:dem":2047,
    "gn:feature_class":"P",
    "gn:feature_code":"PPL",
    "gn:name":"Were T\u2019ega",
    "gn:population":0,
    "gn:timezone":"Africa/Addis_Ababa",
    "iso:country":"ET",
    "wof:name":"Were T'ega",
    "wof:placetype":"locality"
},
  "geometry": {"coordinates":[39.88333,11.25],"type":"Point"}
}