{
  "type": "Feature",
  "properties": {
    "gn:admin1_code":"53",
    "gn:asciiname":"Mereto",
    "gn:country_code":"ET",
    "gn:dem":2031,
    "gn:feature_class":"P",
    "gn:feature_code":"PPL",
    "gn:name":"Mer\u0113to",
    "gn:population":0,
    "gn:timezone":"Africa/Addis_Ababa",
    "iso:country":"ET",
    "wof:name":"Mereto",
    "wof:placetype":"locality"
},
  "geometry": {"coordinates":[39.32639,14.10889],"type":"Point"}
}