{
  "type": "Feature",
  "properties": {
    "gn:admin1_code":"51",
    "gn:asciiname":"Sombo",
    "gn:country_code":"ET",
    "gn:dem":1746,
    "gn:feature_class":"P",
    "gn:feature_code":"PPL",
    "gn:name":"Sombo",
    "gn:population":0,
    "gn:timezone":"Africa/Addis_Ababa",
    "iso:country":"ET",
    "name:und_x_variant":[
        "Sombo (5)",
        "Sombo"
    ],
    "wof:name":"Sombo",
    "wof:placetype":"locality"
},
  "geometry": {"coordinates":[36.86667,9.63333],"type":"Point"}
}