{
  "type": "Feature",
  "properties": {
    "gn:admin1_code":"46",
    "gn:asciiname":"Kube",
    "gn:country_code":"ET",
    "gn:dem":3539,
    "gn:feature_class":"P",
    "gn:feature_code":"PPL",
    "gn:name":"Kub\u0113",
    "gn:population":0,
    "gn:timezone":"Africa/Addis_Ababa",
    "iso:country":"ET",
    "name:ceb_x_preferred":[
        "Kube"
    ],
    "name:deu_x_preferred":[
        "Kube"
    ],
    "name:fra_x_preferred":[
        "Kube"
    ],
    "name:rus_x_preferred":[
        "\u041a\u0443\u0431\u0435"
    ],
    "name:swe_x_preferred":[
        "Kube"
    ],
    "wof:name":"Kube",
    "wof:placetype":"locality"
},
  "geometry": {"coordinates":[39.36667,11.81667],"type":"Point"}
}