{
  "type": "Feature",
  "properties": {
    "gn:country":"ET",
    "gn:fcode":"PPL",
    "gn:population":30633,
    "iso:country":"ET",
    "name:bul_x_preferred":[
        "\u041a\u043e\u0440\u0435\u043c"
    ],
    "name:ceb_x_preferred":[
        "Korem"
    ],
    "name:eng_x_preferred":[
        "Korem"
    ],
    "name:fra_x_preferred":[
        "Korem"
    ],
    "name:jpn_x_preferred":[
        "\u30b3\u30ec\u30e0"
    ],
    "name:nld_x_preferred":[
        "Korem"
    ],
    "name:swe_x_preferred":[
        "Korem"
    ],
    "name:und_x_variant":[
        "Koram"
    ],
    "qs_pg:aaroncc":"ET",
    "qs_pg:gn_country":"ET",
    "qs_pg:gn_fcode":"PPL",
    "qs_pg:gn_pop":30633,
    "qs_pg:name":"Korem",
    "qs_pg:photos_9r":0,
    "qs_pg:photos_sr":0,
    "qs_pg:pop_sr":7,
    "qs_pg:qs_pg_placetype":"locality",
    "wof:name":"Korem",
    "wof:placetype":"locality",
    "wof:population":30633
},
  "geometry": {"coordinates":[39.52278,12.50583],"type":"Point"}
}