{
  "type": "Feature",
  "properties": {
    "gn:admin1_code":"49",
    "gn:asciiname":"Fina",
    "gn:country_code":"ET",
    "gn:dem":428,
    "gn:feature_class":"P",
    "gn:feature_code":"PPL",
    "gn:name":"Fina",
    "gn:population":0,
    "gn:timezone":"Africa/Addis_Ababa",
    "iso:country":"ET",
    "name:und_x_variant":[
        "Faina",
        "Fina"
    ],
    "wof:name":"Fina",
    "wof:placetype":"locality"
},
  "geometry": {"coordinates":[34.23333,8.16667],"type":"Point"}
}