{
  "type": "Feature",
  "properties": {
    "gn:admin1_code":"52.0",
    "gn:asciiname":"Las Durkel",
    "gn:country_code":"ET",
    "gn:dem":591,
    "gn:feature_class":"P",
    "gn:feature_code":"PPL",
    "gn:name":"Las Durkel",
    "gn:population":0,
    "gn:timezone":"Africa/Addis_Ababa",
    "iso:country":"ET",
    "wof:name":"Las Durkel",
    "wof:placetype":"locality"
},
  "geometry": {"coordinates":[43.78583,6.65639],"type":"Point"}
}