{
  "type": "Feature",
  "properties": {
    "gn:admin1_code":"53.0",
    "gn:asciiname":"Ekda Gaber",
    "gn:country_code":"ET",
    "gn:dem":2721,
    "gn:feature_class":"P",
    "gn:feature_code":"PPL",
    "gn:name":"Ekda Gaber",
    "gn:population":0,
    "gn:timezone":"Africa/Addis_Ababa",
    "iso:country":"ET",
    "wof:name":"Ekda Gaber",
    "wof:placetype":"locality"
},
  "geometry": {"coordinates":[39.72962,13.8919],"type":"Point"}
}