{
  "type": "Feature",
  "properties": {
    "gn:admin1_code":"52",
    "gn:asciiname":"Gabagaba",
    "gn:country_code":"ET",
    "gn:dem":742,
    "gn:feature_class":"P",
    "gn:feature_code":"PPL",
    "gn:name":"Gabagaba",
    "gn:population":0,
    "gn:timezone":"Africa/Addis_Ababa",
    "iso:country":"ET",
    "name:und_x_variant":[
        "Vidtl\u2019",
        "Gabagaba"
    ],
    "wof:name":"Gabagaba",
    "wof:placetype":"locality"
},
  "geometry": {"coordinates":[43.65139,6.92417],"type":"Point"}
}