{
  "type": "Feature",
  "properties": {
    "gn:admin1_code":"51",
    "gn:asciiname":"Mukerma",
    "gn:country_code":"ET",
    "gn:dem":1614,
    "gn:feature_class":"P",
    "gn:feature_code":"PPL",
    "gn:name":"Mukerma",
    "gn:population":0,
    "gn:timezone":"Africa/Addis_Ababa",
    "iso:country":"ET",
    "wof:name":"Mukerma",
    "wof:placetype":"locality"
},
  "geometry": {"coordinates":[36.85,9.35],"type":"Point"}
}