{
  "type": "Feature",
  "properties": {
    "gn:admin1_code":"49",
    "gn:asciiname":"Pentin",
    "gn:country_code":"ET",
    "gn:dem":416,
    "gn:feature_class":"P",
    "gn:feature_code":"PPL",
    "gn:name":"Pentin",
    "gn:population":0,
    "gn:timezone":"Africa/Addis_Ababa",
    "iso:country":"ET",
    "wof:name":"Pentin",
    "wof:placetype":"locality"
},
  "geometry": {"coordinates":[33.65,7.86667],"type":"Point"}
}