{
  "type": "Feature",
  "properties": {
    "gn:admin1_code":"51",
    "gn:asciiname":"Gango",
    "gn:country_code":"ET",
    "gn:dem":2904,
    "gn:feature_class":"P",
    "gn:feature_code":"PPL",
    "gn:name":"Gango",
    "gn:population":0,
    "gn:timezone":"Africa/Addis_Ababa",
    "iso:country":"ET",
    "wof:name":"Gango",
    "wof:placetype":"locality"
},
  "geometry": {"coordinates":[38.91667,9.33333],"type":"Point"}
}