{
  "type": "Feature",
  "properties": {
    "gn:admin1_code":"46.0",
    "gn:asciiname":"Senguta",
    "gn:country_code":"ET",
    "gn:dem":1766,
    "gn:feature_class":"P",
    "gn:feature_code":"PPL",
    "gn:name":"Senguta",
    "gn:population":0,
    "gn:timezone":"Africa/Addis_Ababa",
    "iso:country":"ET",
    "wof:name":"Senguta",
    "wof:placetype":"locality"
},
  "geometry": {"coordinates":[39.87181,9.92509],"type":"Point"}
}