{
  "type": "Feature",
  "properties": {
    "gn:admin1_code":"46",
    "gn:asciiname":"Medina",
    "gn:country_code":"ET",
    "gn:dem":1368,
    "gn:feature_class":"P",
    "gn:feature_code":"PPL",
    "gn:name":"Med\u012bna",
    "gn:population":0,
    "gn:timezone":"Africa/Addis_Ababa",
    "iso:country":"ET",
    "wof:name":"Medina",
    "wof:placetype":"locality"
},
  "geometry": {"coordinates":[39.97537,9.91803],"type":"Point"}
}