{
  "type": "Feature",
  "properties": {
    "gn:admin1_code":"51",
    "gn:asciiname":"Shire",
    "gn:country_code":"ET",
    "gn:dem":2866,
    "gn:feature_class":"P",
    "gn:feature_code":"PPL",
    "gn:name":"Sh\u012br\u0113",
    "gn:population":0,
    "gn:timezone":"Africa/Addis_Ababa",
    "iso:country":"ET",
    "name:als_x_preferred":[
        "Shire"
    ],
    "name:ast_x_preferred":[
        "Shire"
    ],
    "name:ben_x_preferred":[
        "\u09b6\u09be\u09af\u09bc\u09be\u09b0"
    ],
    "name:dan_x_preferred":[
        "Shire"
    ],
    "name:deu_x_preferred":[
        "Shire"
    ],
    "name:ell_x_preferred":[
        "\u03a3\u03ac\u03b9\u03c1"
    ],
    "name:fas_x_preferred":[
        "\u0634\u0627\u06cc\u0631"
    ],
    "name:fra_x_preferred":[
        "Shire"
    ],
    "name:heb_x_preferred":[
        "\u05e9\u05d9\u05e8\u05d4"
    ],
    "name:hin_x_preferred":[
        "\u0936\u093e\u092f\u0930"
    ],
    "name:hun_x_preferred":[
        "Shire"
    ],
    "name:ind_x_preferred":[
        "Shire"
    ],
    "name:jpn_x_preferred":[
        "\u30b7\u30e3\u30a4\u30a2"
    ],
    "name:kor_x_preferred":[
        "\uc0e4\uc774\uc5b4"
    ],
    "name:lat_x_preferred":[
        "Scira"
    ],
    "name:nno_x_preferred":[
        "Shire"
    ],
    "name:por_x_preferred":[
        "Shire"
    ],
    "name:rus_x_preferred":[
        "\u0428\u0438\u0440"
    ],
    "name:spa_x_preferred":[
        "Shire"
    ],
    "name:tha_x_preferred":[
        "\u0e44\u0e0a\u0e23\u0e4c"
    ],
    "name:tur_x_preferred":[
        "Shire"
    ],
    "name:und_x_variant":[
        "S\u012br\u0113",
        "Sh\u012br\u0113"
    ],
    "name:urd_x_preferred":[
        "\u0634\u0627\u0626\u0631"
    ],
    "name:vie_x_preferred":[
        "S\u00f4ng Shire"
    ],
    "name:zho_x_preferred":[
        "\u90e1"
    ],
    "wof:name":"Shire",
    "wof:placetype":"locality"
},
  "geometry": {"coordinates":[38.98333,7.23333],"type":"Point"}
}