{
  "type": "Feature",
  "properties": {
    "gn:admin1_code":"51",
    "gn:asciiname":"Shire",
    "gn:country_code":"ET",
    "gn:dem":2866,
    "gn:feature_class":"P",
    "gn:feature_code":"PPL",
    "gn:name":"Sh\u012br\u0113",
    "gn:population":0,
    "gn:timezone":"Africa/Addis_Ababa",
    "iso:country":"ET",
    "name:als_x_preferred":[
        "Shire"
    ],
    "name:ast_x_preferred":[
        "Shire"
    ],
    "name:dan_x_preferred":[
        "Shire"
    ],
    "name:deu_x_preferred":[
        "Shire"
    ],
    "name:fas_x_preferred":[
        "\u0634\u0627\u06cc\u0631"
    ],
    "name:fra_x_preferred":[
        "Shire"
    ],
    "name:jpn_x_preferred":[
        "\u30b7\u30e3\u30a4\u30a2"
    ],
    "name:lat_x_preferred":[
        "Scira"
    ],
    "name:nno_x_preferred":[
        "Shire"
    ],
    "name:por_x_preferred":[
        "Shire"
    ],
    "name:rus_x_preferred":[
        "\u0428\u0438\u0440"
    ],
    "name:spa_x_preferred":[
        "Shire"
    ],
    "name:tha_x_preferred":[
        "\u0e44\u0e0a\u0e23\u0e4c"
    ],
    "name:tur_x_preferred":[
        "Shire"
    ],
    "name:und_x_variant":[
        "S\u012br\u0113",
        "Sh\u012br\u0113"
    ],
    "name:zho_x_preferred":[
        "\u90e1"
    ],
    "wof:name":"Shire",
    "wof:placetype":"locality"
},
  "geometry": {"coordinates":[38.98333,7.23333],"type":"Point"}
}