{
  "type": "Feature",
  "properties": {
    "gn:admin1_code":"51",
    "gn:asciiname":"Shire",
    "gn:country_code":"ET",
    "gn:dem":2866,
    "gn:feature_class":"P",
    "gn:feature_code":"PPL",
    "gn:name":"Sh\u012br\u0113",
    "gn:population":0,
    "gn:timezone":"Africa/Addis_Ababa",
    "iso:country":"ET",
    "name:und_x_variant":[
        "S\u012br\u0113",
        "Sh\u012br\u0113"
    ],
    "wof:name":"Shire",
    "wof:placetype":"locality"
},
  "geometry": {"coordinates":[38.98333,7.23333],"type":"Point"}
}