{
  "type": "Feature",
  "properties": {
    "gn:admin1_code":"52",
    "gn:asciiname":"Las Suban",
    "gn:country_code":"ET",
    "gn:dem":572,
    "gn:feature_class":"P",
    "gn:feature_code":"PPL",
    "gn:name":"Las Suban",
    "gn:population":0,
    "gn:timezone":"Africa/Addis_Ababa",
    "iso:country":"ET",
    "wof:name":"Las Suban",
    "wof:placetype":"locality"
},
  "geometry": {"coordinates":[46.88139,7.91889],"type":"Point"}
}