{
  "type": "Feature",
  "properties": {
    "gn:admin1_code":"47.0",
    "gn:asciiname":"Boo",
    "gn:country_code":"ET",
    "gn:dem":1679,
    "gn:feature_class":"P",
    "gn:feature_code":"PPL",
    "gn:name":"Boo",
    "gn:population":0,
    "gn:timezone":"Africa/Addis_Ababa",
    "iso:country":"ET",
    "name:ceb_x_preferred":[
        "Boo"
    ],
    "name:ces_x_preferred":[
        "Boo"
    ],
    "name:deu_x_preferred":[
        "Boo"
    ],
    "name:fra_x_preferred":[
        "Boo"
    ],
    "name:glg_x_preferred":[
        "Boo"
    ],
    "name:nld_x_preferred":[
        "Boo"
    ],
    "name:nor_x_preferred":[
        "Boo"
    ],
    "name:por_x_preferred":[
        "Boo"
    ],
    "name:spa_x_preferred":[
        "Boo"
    ],
    "name:swe_x_preferred":[
        "Boo"
    ],
    "name:zho_x_preferred":[
        "Boo"
    ],
    "wof:name":"Boo",
    "wof:placetype":"locality"
},
  "geometry": {"coordinates":[35.81667,9.36667],"type":"Point"}
}