{
  "type": "Feature",
  "properties": {
    "gn:admin1_code":"53",
    "gn:asciiname":"Hidmo",
    "gn:country_code":"ET",
    "gn:dem":2140,
    "gn:feature_class":"P",
    "gn:feature_code":"PPL",
    "gn:name":"Hidmo",
    "gn:population":0,
    "gn:timezone":"Africa/Addis_Ababa",
    "iso:country":"ET",
    "wof:name":"Hidmo",
    "wof:placetype":"locality"
},
  "geometry": {"coordinates":[39.54424,13.20761],"type":"Point"}
}