{
  "type": "Feature",
  "properties": {
    "gn:admin1_code":"51",
    "gn:asciiname":"Jewe",
    "gn:country_code":"ET",
    "gn:dem":1650,
    "gn:feature_class":"P",
    "gn:feature_code":"PPL",
    "gn:name":"Jew\u0113",
    "gn:population":0,
    "gn:timezone":"Africa/Addis_Ababa",
    "iso:country":"ET",
    "wof:name":"Jewe",
    "wof:placetype":"locality"
},
  "geometry": {"coordinates":[35.35,9.06667],"type":"Point"}
}