{
  "type": "Feature",
  "properties": {
    "gn:admin1_code":"53",
    "gn:asciiname":"Gijet",
    "gn:country_code":"ET",
    "gn:dem":2071,
    "gn:feature_class":"P",
    "gn:feature_code":"PPL",
    "gn:name":"Gijet",
    "gn:population":0,
    "gn:timezone":"Africa/Addis_Ababa",
    "iso:country":"ET",
    "name:und_x_variant":[
        "Gydzhet",
        "Gijet"
    ],
    "wof:name":"Gijet",
    "wof:placetype":"locality"
},
  "geometry": {"coordinates":[39.17043,13.32523],"type":"Point"}
}