{
  "type": "Feature",
  "properties": {
    "gn:admin1_code":"46.0",
    "gn:asciiname":"Dilala",
    "gn:country_code":"ET",
    "gn:dem":1830,
    "gn:feature_class":"P",
    "gn:feature_code":"PPL",
    "gn:name":"D\u012blala",
    "gn:population":0,
    "gn:timezone":"Africa/Addis_Ababa",
    "iso:country":"ET",
    "wof:name":"Dilala",
    "wof:placetype":"locality"
},
  "geometry": {"coordinates":[37.68333,11.83333],"type":"Point"}
}