{
  "type": "Feature",
  "properties": {
    "gn:admin1_code":"54",
    "gn:asciiname":"Gogi",
    "gn:country_code":"ET",
    "gn:dem":1796,
    "gn:feature_class":"P",
    "gn:feature_code":"PPL",
    "gn:name":"Gogi",
    "gn:population":0,
    "gn:timezone":"Africa/Addis_Ababa",
    "iso:country":"ET",
    "name:vie_x_preferred":[
        "Gogi"
    ],
    "wof:name":"Gogi",
    "wof:placetype":"locality"
},
  "geometry": {"coordinates":[38.56667,6.96667],"type":"Point"}
}