{
  "type": "Feature",
  "properties": {
    "gn:admin1_code":"51.0",
    "gn:asciiname":"Begejo",
    "gn:country_code":"ET",
    "gn:dem":2501,
    "gn:feature_class":"P",
    "gn:feature_code":"PPL",
    "gn:name":"Begejo",
    "gn:population":0,
    "gn:timezone":"Africa/Addis_Ababa",
    "iso:country":"ET",
    "wof:name":"Begejo",
    "wof:placetype":"locality"
},
  "geometry": {"coordinates":[39.96667,7.08333],"type":"Point"}
}