{
  "type": "Feature",
  "properties": {
    "gn:admin1_code":"51.0",
    "gn:asciiname":"Didimtu",
    "gn:country_code":"ET",
    "gn:dem":1590,
    "gn:feature_class":"P",
    "gn:feature_code":"PPL",
    "gn:name":"D\u012bd\u012bmtu",
    "gn:population":0,
    "gn:timezone":"Africa/Addis_Ababa",
    "iso:country":"ET",
    "name:und_x_variant":[
        "Bia Uoraba",
        "Bija",
        "Bio Uoraba",
        "D\u012bd\u012bmtu"
    ],
    "wof:name":"Didimtu",
    "wof:placetype":"locality"
},
  "geometry": {"coordinates":[42.17426,8.9229],"type":"Point"}
}