{
  "type": "Feature",
  "properties": {
    "gn:admin1_code":"46.0",
    "gn:asciiname":"Aman",
    "gn:country_code":"ET",
    "gn:dem":2222,
    "gn:feature_class":"P",
    "gn:feature_code":"PPL",
    "gn:name":"\u0100man",
    "gn:population":0,
    "gn:timezone":"Africa/Addis_Ababa",
    "iso:country":"ET",
    "wof:name":"Aman",
    "wof:placetype":"locality"
},
  "geometry": {"coordinates":[39.23911,10.25693],"type":"Point"}
}