{
  "type": "Feature",
  "properties": {
    "gn:admin1_code":"51",
    "gn:asciiname":"Egu",
    "gn:country_code":"ET",
    "gn:dem":2198,
    "gn:feature_class":"P",
    "gn:feature_code":"PPLL",
    "gn:name":"\u0112gu",
    "gn:population":0,
    "gn:timezone":"Africa/Addis_Ababa",
    "iso:country":"ET",
    "name:und_x_variant":[
        "\u0112gu",
        "\u0112gu Bota"
    ],
    "wof:name":"Egu",
    "wof:placetype":"locality"
},
  "geometry": {"coordinates":[42.10328,9.4891],"type":"Point"}
}