{
  "type": "Feature",
  "properties": {
    "gn:admin1_code":"51",
    "gn:asciiname":"Senk'el",
    "gn:country_code":"ET",
    "gn:dem":1993,
    "gn:feature_class":"P",
    "gn:feature_code":"PPL",
    "gn:name":"Senk\u2019el",
    "gn:population":0,
    "gn:timezone":"Africa/Addis_Ababa",
    "iso:country":"ET",
    "wof:name":"Senk'el",
    "wof:placetype":"locality"
},
  "geometry": {"coordinates":[39.28333,8.73333],"type":"Point"}
}