{
  "type": "Feature",
  "properties": {
    "gn:admin1_code":"51",
    "gn:asciiname":"El Niybo",
    "gn:country_code":"ET",
    "gn:dem":1184,
    "gn:feature_class":"P",
    "gn:feature_code":"PPL",
    "gn:name":"El Niybo",
    "gn:population":0,
    "gn:timezone":"Africa/Addis_Ababa",
    "iso:country":"ET",
    "name:und_x_variant":[
        "Niabo",
        "El Niabo",
        "El Niybo"
    ],
    "wof:name":"El Niybo",
    "wof:placetype":"locality"
},
  "geometry": {"coordinates":[39.96667,4.55],"type":"Point"}
}