{
  "type": "Feature",
  "properties": {
    "gn:admin1_code":"54",
    "gn:asciiname":"Dugda",
    "gn:country_code":"ET",
    "gn:dem":1926,
    "gn:feature_class":"P",
    "gn:feature_code":"PPL",
    "gn:name":"Dugda",
    "gn:population":0,
    "gn:timezone":"Africa/Addis_Ababa",
    "iso:country":"ET",
    "name:bih_x_preferred":[
        "\u0926\u0941\u0917\u094d\u0926\u093e"
    ],
    "name:bpy_x_preferred":[
        "\u09a6\u09c1\u0997\u09a6\u09be"
    ],
    "name:ceb_x_preferred":[
        "Dugda"
    ],
    "name:ita_x_preferred":[
        "Dugda"
    ],
    "name:mlg_x_preferred":[
        "Dugda"
    ],
    "name:msa_x_preferred":[
        "Dugda"
    ],
    "name:new_x_preferred":[
        "\u0926\u0941\u0917\u094d\u0926"
    ],
    "name:nld_x_preferred":[
        "Dugda"
    ],
    "name:por_x_preferred":[
        "Dugda"
    ],
    "name:spa_x_preferred":[
        "Dugda"
    ],
    "name:swe_x_preferred":[
        "Dugda"
    ],
    "name:vie_x_preferred":[
        "Dugda"
    ],
    "name:zho_x_preferred":[
        "\u675c\u683c\u8fbe"
    ],
    "wof:name":"Dugda",
    "wof:placetype":"locality"
},
  "geometry": {"coordinates":[38.63333,8.16667],"type":"Point"}
}