{
  "type": "Feature",
  "properties": {
    "gn:admin1_code":"53.0",
    "gn:asciiname":"Colqualuque",
    "gn:country_code":"ET",
    "gn:dem":1984,
    "gn:feature_class":"P",
    "gn:feature_code":"PPL",
    "gn:name":"Colqualuque",
    "gn:population":0,
    "gn:timezone":"Africa/Addis_Ababa",
    "iso:country":"ET",
    "wof:name":"Colqualuque",
    "wof:placetype":"locality"
},
  "geometry": {"coordinates":[38.78333,13.61667],"type":"Point"}
}