{
  "type": "Feature",
  "properties": {
    "gn:admin1_code":"52",
    "gn:asciiname":"Fideli",
    "gn:country_code":"ET",
    "gn:dem":749,
    "gn:feature_class":"P",
    "gn:feature_code":"PPL",
    "gn:name":"Fideli",
    "gn:population":0,
    "gn:timezone":"Africa/Addis_Ababa",
    "iso:country":"ET",
    "wof:name":"Fideli",
    "wof:placetype":"locality"
},
  "geometry": {"coordinates":[41.30559,9.98631],"type":"Point"}
}