{
  "type": "Feature",
  "properties": {
    "gn:admin1_code":"46.0",
    "gn:asciiname":"Debir",
    "gn:country_code":"ET",
    "gn:dem":2367,
    "gn:feature_class":"P",
    "gn:feature_code":"PPL",
    "gn:name":"Debir",
    "gn:population":0,
    "gn:timezone":"Africa/Addis_Ababa",
    "iso:country":"ET",
    "wof:name":"Debir",
    "wof:placetype":"locality"
},
  "geometry": {"coordinates":[37.93333,11.11667],"type":"Point"}
}