{
  "type": "Feature",
  "properties": {
    "gn:admin1_code":"51.0",
    "gn:asciiname":"Bore",
    "gn:country_code":"ET",
    "gn:dem":1026,
    "gn:feature_class":"P",
    "gn:feature_code":"PPL",
    "gn:name":"Bore",
    "gn:population":0,
    "gn:timezone":"Africa/Addis_Ababa",
    "iso:country":"ET",
    "wof:name":"Bore",
    "wof:placetype":"locality"
},
  "geometry": {"coordinates":[37.65,4.65],"type":"Point"}
}