{
  "type": "Feature",
  "properties": {
    "gn:admin1_code":"51",
    "gn:asciiname":"Hululo",
    "gn:country_code":"ET",
    "gn:dem":2128,
    "gn:feature_class":"P",
    "gn:feature_code":"PPL",
    "gn:name":"Hululo",
    "gn:population":0,
    "gn:timezone":"Africa/Addis_Ababa",
    "iso:country":"ET",
    "name:und_x_variant":[
        "Khululo",
        "Hululo"
    ],
    "wof:name":"Hululo",
    "wof:placetype":"locality"
},
  "geometry": {"coordinates":[41.93528,9.36583],"type":"Point"}
}