{
  "type": "Feature",
  "properties": {
    "gn:admin1_code":"51",
    "gn:asciiname":"Mulo",
    "gn:country_code":"ET",
    "gn:dem":2567,
    "gn:feature_class":"P",
    "gn:feature_code":"PPL",
    "gn:name":"Mulo",
    "gn:population":0,
    "gn:timezone":"Africa/Addis_Ababa",
    "iso:country":"ET",
    "name:ceb_x_preferred":[
        "Mulo"
    ],
    "name:deu_x_preferred":[
        "Mulo"
    ],
    "name:epo_x_preferred":[
        "Mulo"
    ],
    "name:ita_x_preferred":[
        "Mulo"
    ],
    "name:swe_x_preferred":[
        "Mulo"
    ],
    "wof:name":"Mulo",
    "wof:placetype":"locality"
},
  "geometry": {"coordinates":[38.68333,9.33333],"type":"Point"}
}