{
  "type": "Feature",
  "properties": {
    "gn:admin1_code":"54",
    "gn:asciiname":"Fire Hiywet",
    "gn:country_code":"ET",
    "gn:dem":2435,
    "gn:feature_class":"P",
    "gn:feature_code":"PPL",
    "gn:name":"Fir\u0113 Hiywet",
    "gn:population":0,
    "gn:timezone":"Africa/Addis_Ababa",
    "iso:country":"ET",
    "wof:name":"Fire Hiywet",
    "wof:placetype":"locality"
},
  "geometry": {"coordinates":[36.61667,6.05],"type":"Point"}
}