{
  "type": "Feature",
  "properties": {
    "gn:admin1_code":"46",
    "gn:asciiname":"Kubayo",
    "gn:country_code":"ET",
    "gn:dem":2902,
    "gn:feature_class":"P",
    "gn:feature_code":"PPL",
    "gn:name":"Kubayo",
    "gn:population":0,
    "gn:timezone":"Africa/Addis_Ababa",
    "iso:country":"ET",
    "wof:name":"Kubayo",
    "wof:placetype":"locality"
},
  "geometry": {"coordinates":[39.44347,10.83433],"type":"Point"}
}