{
  "type": "Feature",
  "properties": {
    "gn:admin1_code":"53.0",
    "gn:asciiname":"Adi Ts'egibna",
    "gn:country_code":"ET",
    "gn:dem":1746,
    "gn:feature_class":"P",
    "gn:feature_code":"PPL",
    "gn:name":"\u0100d\u012b Ts\u2019eg\u012bbna",
    "gn:population":0,
    "gn:timezone":"Africa/Addis_Ababa",
    "iso:country":"ET",
    "name:und_x_variant":[
        "Eila",
        "Addi Tsegibna",
        "\u0100d\u012b Ts\u2019eg\u012bbna"
    ],
    "wof:name":"Adi Ts'egibna",
    "wof:placetype":"locality"
},
  "geometry": {"coordinates":[39.12899,13.16598],"type":"Point"}
}