{
  "type": "Feature",
  "properties": {
    "gn:admin1_code":"51.0",
    "gn:asciiname":"Boreka",
    "gn:country_code":"ET",
    "gn:dem":1468,
    "gn:feature_class":"P",
    "gn:feature_code":"PPL",
    "gn:name":"Boreka",
    "gn:population":0,
    "gn:timezone":"Africa/Addis_Ababa",
    "iso:country":"ET",
    "wof:name":"Boreka",
    "wof:placetype":"locality"
},
  "geometry": {"coordinates":[36.56667,8.51667],"type":"Point"}
}