{
  "type": "Feature",
  "properties": {
    "gn:admin1_code":"53.0",
    "gn:asciiname":"Adi Hana",
    "gn:country_code":"ET",
    "gn:dem":2211,
    "gn:feature_class":"P",
    "gn:feature_code":"PPL",
    "gn:name":"\u0100d\u012b H\u0101na",
    "gn:population":0,
    "gn:timezone":"Africa/Addis_Ababa",
    "iso:country":"ET",
    "name:und_x_variant":[
        "Aderat",
        "Addi Khana",
        "\u0100d\u012b H\u0101na"
    ],
    "wof:name":"Adi Hana",
    "wof:placetype":"locality"
},
  "geometry": {"coordinates":[39.50948,13.18063],"type":"Point"}
}