{
  "type": "Feature",
  "properties": {
    "gn:admin1_code":"51.0",
    "gn:asciiname":"Abiley",
    "gn:country_code":"ET",
    "gn:dem":1672,
    "gn:feature_class":"P",
    "gn:feature_code":"PPL",
    "gn:name":"\u0100biley",
    "gn:population":0,
    "gn:timezone":"Africa/Addis_Ababa",
    "iso:country":"ET",
    "wof:name":"Abiley",
    "wof:placetype":"locality"
},
  "geometry": {"coordinates":[42.50472,9.31083],"type":"Point"}
}