{
  "type": "Feature",
  "properties": {
    "gn:admin1_code":"51",
    "gn:asciiname":"Hagelo",
    "gn:country_code":"ET",
    "gn:dem":1883,
    "gn:feature_class":"P",
    "gn:feature_code":"PPL",
    "gn:name":"Hagelo",
    "gn:population":0,
    "gn:timezone":"Africa/Addis_Ababa",
    "iso:country":"ET",
    "wof:name":"Hagelo",
    "wof:placetype":"locality"
},
  "geometry": {"coordinates":[37.03333,9.25],"type":"Point"}
}