{
  "type": "Feature",
  "properties": {
    "gn:admin1_code":"51",
    "gn:asciiname":"Fale",
    "gn:country_code":"ET",
    "gn:dem":2559,
    "gn:feature_class":"P",
    "gn:feature_code":"PPL",
    "gn:name":"Fal\u0113",
    "gn:population":0,
    "gn:timezone":"Africa/Addis_Ababa",
    "iso:country":"ET",
    "name:ceb_x_preferred":[
        "Fale"
    ],
    "name:deu_x_preferred":[
        "Fale"
    ],
    "name:nld_x_preferred":[
        "Fale"
    ],
    "name:pol_x_preferred":[
        "Fale"
    ],
    "name:por_x_preferred":[
        "Fale"
    ],
    "name:swe_x_preferred":[
        "Fale"
    ],
    "wof:name":"Fale",
    "wof:placetype":"locality"
},
  "geometry": {"coordinates":[38.28333,9.35],"type":"Point"}
}