{
  "type": "Feature",
  "properties": {
    "gn:admin1_code":"51",
    "gn:asciiname":"Ucha",
    "gn:country_code":"ET",
    "gn:dem":1917,
    "gn:feature_class":"P",
    "gn:feature_code":"PPL",
    "gn:name":"Ucha",
    "gn:population":0,
    "gn:timezone":"Africa/Addis_Ababa",
    "iso:country":"ET",
    "name:ceb_x_preferred":[
        "Ucha"
    ],
    "name:deu_x_preferred":[
        "Ucha"
    ],
    "name:nld_x_preferred":[
        "Ucha"
    ],
    "name:por_x_preferred":[
        "Ucha"
    ],
    "name:rus_x_preferred":[
        "\u0423\u0448\u0430"
    ],
    "name:spa_x_preferred":[
        "Ucha"
    ],
    "name:ukr_x_preferred":[
        "\u0423\u0448\u0430"
    ],
    "name:und_x_variant":[
        "Ucha (1)"
    ],
    "name:urd_x_preferred":[
        "\u0627\u0686\u0627"
    ],
    "wof:name":"Ucha",
    "wof:placetype":"locality"
},
  "geometry": {"coordinates":[36.18333,9.88333],"type":"Point"}
}