{
  "type": "Feature",
  "properties": {
    "gn:admin1_code":"46",
    "gn:asciiname":"Guftamlo",
    "gn:country_code":"ET",
    "gn:dem":1429,
    "gn:feature_class":"P",
    "gn:feature_code":"PPL",
    "gn:name":"Guftamlo",
    "gn:population":0,
    "gn:timezone":"Africa/Addis_Ababa",
    "iso:country":"ET",
    "wof:name":"Guftamlo",
    "wof:placetype":"locality"
},
  "geometry": {"coordinates":[38.83333,13.18333],"type":"Point"}
}