{
  "type": "Feature",
  "properties": {
    "gn:admin1_code":"45.0",
    "gn:asciiname":"Aculle",
    "gn:country_code":"ET",
    "gn:dem":596,
    "gn:feature_class":"P",
    "gn:feature_code":"PPL",
    "gn:name":"Aculle",
    "gn:population":0,
    "gn:timezone":"Africa/Addis_Ababa",
    "iso:country":"ET",
    "wof:name":"Aculle",
    "wof:placetype":"locality"
},
  "geometry": {"coordinates":[42.01667,12.51667],"type":"Point"}
}