{
  "type": "Feature",
  "properties": {
    "gn:admin1_code":"52",
    "gn:asciiname":"Gelhalali",
    "gn:country_code":"ET",
    "gn:dem":564,
    "gn:feature_class":"P",
    "gn:feature_code":"PPL",
    "gn:name":"Gelhalali",
    "gn:population":0,
    "gn:timezone":"Africa/Addis_Ababa",
    "iso:country":"ET",
    "wof:name":"Gelhalali",
    "wof:placetype":"locality"
},
  "geometry": {"coordinates":[43.89611,6.63],"type":"Point"}
}