{
  "type": "Feature",
  "properties": {
    "gn:admin1_code":"51",
    "gn:asciiname":"Mulu",
    "gn:country_code":"ET",
    "gn:dem":1255,
    "gn:feature_class":"P",
    "gn:feature_code":"PPL",
    "gn:name":"Mulu",
    "gn:population":0,
    "gn:timezone":"Africa/Addis_Ababa",
    "iso:country":"ET",
    "name:ceb_x_preferred":[
        "Mulu"
    ],
    "name:fas_x_preferred":[
        "\u0645\u0648\u0644\u0648"
    ],
    "name:swe_x_preferred":[
        "Mulu"
    ],
    "name:und_x_variant":[
        "Mullu"
    ],
    "wof:name":"Mulu",
    "wof:placetype":"locality"
},
  "geometry": {"coordinates":[40.83581,9.29337],"type":"Point"}
}