{
  "type": "Feature",
  "properties": {
    "gn:admin1_code":"54.0",
    "gn:asciiname":"Anik'a",
    "gn:country_code":"ET",
    "gn:dem":1472,
    "gn:feature_class":"P",
    "gn:feature_code":"PPL",
    "gn:name":"\u0100n\u012bk\u2019a",
    "gn:population":0,
    "gn:timezone":"Africa/Addis_Ababa",
    "iso:country":"ET",
    "wof:name":"Anik'a",
    "wof:placetype":"locality"
},
  "geometry": {"coordinates":[37.16667,6.16667],"type":"Point"}
}