{
  "type": "Feature",
  "properties": {
    "gn:admin1_code":"53",
    "gn:asciiname":"Kulu Ferha",
    "gn:country_code":"ET",
    "gn:dem":1958,
    "gn:feature_class":"P",
    "gn:feature_code":"PPL",
    "gn:name":"Kulu Ferha",
    "gn:population":0,
    "gn:timezone":"Africa/Addis_Ababa",
    "iso:country":"ET",
    "name:und_x_variant":[
        "Kulu Ferkha",
        "Kulu Ferha"
    ],
    "wof:name":"Kulu Ferha",
    "wof:placetype":"locality"
},
  "geometry": {"coordinates":[38.44582,14.15984],"type":"Point"}
}