{
  "type": "Feature",
  "properties": {
    "gn:admin1_code":"52",
    "gn:asciiname":"Megwin",
    "gn:country_code":"ET",
    "gn:dem":782,
    "gn:feature_class":"P",
    "gn:feature_code":"PPL",
    "gn:name":"Megw\u012bn",
    "gn:population":0,
    "gn:timezone":"Africa/Addis_Ababa",
    "iso:country":"ET",
    "name:pol_x_preferred":[
        "Megwin"
    ],
    "name:und_x_variant":[
        "Maleico",
        "Megw\u012bn"
    ],
    "name:zho_x_preferred":[
        "Megwin"
    ],
    "wof:name":"Megwin",
    "wof:placetype":"locality"
},
  "geometry": {"coordinates":[43.23237,7.22618],"type":"Point"}
}