{
  "type": "Feature",
  "properties": {
    "gn:admin1_code":"54",
    "gn:asciiname":"Dubisa",
    "gn:country_code":"ET",
    "gn:dem":2141,
    "gn:feature_class":"P",
    "gn:feature_code":"PPL",
    "gn:name":"Dub\u012bsa",
    "gn:population":0,
    "gn:timezone":"Africa/Addis_Ababa",
    "iso:country":"ET",
    "wof:name":"Dubisa",
    "wof:placetype":"locality"
},
  "geometry": {"coordinates":[38.65,8.35],"type":"Point"}
}