{
  "type": "Feature",
  "properties": {
    "gn:admin1_code":"52",
    "gn:asciiname":"Ellan",
    "gn:country_code":"ET",
    "gn:dem":360,
    "gn:feature_class":"P",
    "gn:feature_code":"PPL",
    "gn:name":"Ellan",
    "gn:population":0,
    "gn:timezone":"Africa/Addis_Ababa",
    "iso:country":"ET",
    "wof:name":"Ellan",
    "wof:placetype":"locality"
},
  "geometry": {"coordinates":[42.58333,6.33333],"type":"Point"}
}