{
  "type": "Feature",
  "properties": {
    "gn:admin1_code":"46",
    "gn:asciiname":"Gendwa",
    "gn:country_code":"ET",
    "gn:dem":2069,
    "gn:feature_class":"P",
    "gn:feature_code":"PPL",
    "gn:name":"Gendwa",
    "gn:population":0,
    "gn:timezone":"Africa/Addis_Ababa",
    "iso:country":"ET",
    "wof:name":"Gendwa",
    "wof:placetype":"locality"
},
  "geometry": {"coordinates":[37.36667,12.51667],"type":"Point"}
}