{
  "type": "Feature",
  "properties": {
    "gn:admin1_code":"51",
    "gn:asciiname":"Uomba",
    "gn:country_code":"ET",
    "gn:dem":2811,
    "gn:feature_class":"P",
    "gn:feature_code":"PPL",
    "gn:name":"Uomba",
    "gn:population":0,
    "gn:timezone":"Africa/Addis_Ababa",
    "iso:country":"ET",
    "name:und_x_variant":[
        "Oomba",
        "Uomba"
    ],
    "wof:name":"Uomba",
    "wof:placetype":"locality"
},
  "geometry": {"coordinates":[38.85,8.55],"type":"Point"}
}