{
  "type": "Feature",
  "properties": {
    "gn:admin1_code":"51.0",
    "gn:asciiname":"Aladi",
    "gn:country_code":"ET",
    "gn:dem":1897,
    "gn:feature_class":"P",
    "gn:feature_code":"PPL",
    "gn:name":"\u0100lad\u012b",
    "gn:population":0,
    "gn:timezone":"Africa/Addis_Ababa",
    "iso:country":"ET",
    "wof:name":"Aladi",
    "wof:placetype":"locality"
},
  "geometry": {"coordinates":[42.12833,9.17056],"type":"Point"}
}