{
  "type": "Feature",
  "properties": {
    "gn:admin1_code":"49.0",
    "gn:asciiname":"Nongol'kuet",
    "gn:country_code":"ET",
    "gn:dem":410,
    "gn:feature_class":"P",
    "gn:feature_code":"PPL",
    "gn:name":"Nongol\u2019kuet",
    "gn:population":0,
    "gn:timezone":"Africa/Addis_Ababa",
    "iso:country":"ET",
    "wof:name":"Nongol'kuet",
    "wof:placetype":"locality"
},
  "geometry": {"coordinates":[33.60148,8.40268],"type":"Point"}
}