{
  "type": "Feature",
  "properties": {
    "gn:admin1_code":"46",
    "gn:asciiname":"YeWeynit",
    "gn:country_code":"ET",
    "gn:dem":1687,
    "gn:feature_class":"P",
    "gn:feature_code":"PPL",
    "gn:name":"YeWeyn\u012bt",
    "gn:population":0,
    "gn:timezone":"Africa/Addis_Ababa",
    "iso:country":"ET",
    "wof:name":"YeWeynit",
    "wof:placetype":"locality"
},
  "geometry": {"coordinates":[37.81667,9.98333],"type":"Point"}
}