{
  "type": "Feature",
  "properties": {
    "gn:admin1_code":"46",
    "gn:asciiname":"Shime",
    "gn:country_code":"ET",
    "gn:dem":2357,
    "gn:feature_class":"P",
    "gn:feature_code":"PPL",
    "gn:name":"Shim\u0113",
    "gn:population":0,
    "gn:timezone":"Africa/Addis_Ababa",
    "iso:country":"ET",
    "name:und_x_variant":[
        "Semmie",
        "Shim\u0113"
    ],
    "wof:name":"Shime",
    "wof:placetype":"locality"
},
  "geometry": {"coordinates":[37.96667,11.41667],"type":"Point"}
}