{
  "type": "Feature",
  "properties": {
    "gn:admin1_code":"51.0",
    "gn:asciiname":"Debre Ts'ige",
    "gn:country_code":"ET",
    "gn:dem":2580,
    "gn:feature_class":"P",
    "gn:feature_code":"PPL",
    "gn:name":"Debre Ts\u2019ig\u0113",
    "gn:population":0,
    "gn:timezone":"Africa/Addis_Ababa",
    "iso:country":"ET",
    "wof:name":"Debre Ts'ige",
    "wof:placetype":"locality"
},
  "geometry": {"coordinates":[38.85,9.65],"type":"Point"}
}