{
  "type": "Feature",
  "properties": {
    "gn:admin1_code":"51",
    "gn:asciiname":"Jogola",
    "gn:country_code":"ET",
    "gn:dem":2262,
    "gn:feature_class":"P",
    "gn:feature_code":"PPL",
    "gn:name":"Jogola",
    "gn:population":0,
    "gn:timezone":"Africa/Addis_Ababa",
    "iso:country":"ET",
    "wof:name":"Jogola",
    "wof:placetype":"locality"
},
  "geometry": {"coordinates":[38.51667,9.65],"type":"Point"}
}