{
  "type": "Feature",
  "properties": {
    "gn:admin1_code":"51",
    "gn:asciiname":"Sebro",
    "gn:country_code":"ET",
    "gn:dem":2631,
    "gn:feature_class":"P",
    "gn:feature_code":"PPL",
    "gn:name":"Sebro",
    "gn:population":0,
    "gn:timezone":"Africa/Addis_Ababa",
    "iso:country":"ET",
    "wof:name":"Sebro",
    "wof:placetype":"locality"
},
  "geometry": {"coordinates":[38.91667,9.66667],"type":"Point"}
}