{
  "type": "Feature",
  "properties": {
    "gn:admin1_code":"46",
    "gn:asciiname":"Wendefada",
    "gn:country_code":"ET",
    "gn:dem":2031,
    "gn:feature_class":"P",
    "gn:feature_code":"PPL",
    "gn:name":"Wendefada",
    "gn:population":0,
    "gn:timezone":"Africa/Addis_Ababa",
    "iso:country":"ET",
    "wof:name":"Wendefada",
    "wof:placetype":"locality"
},
  "geometry": {"coordinates":[37.65,11.75],"type":"Point"}
}