{
  "type": "Feature",
  "properties": {
    "gn:admin1_code":"51",
    "gn:asciiname":"Shenen",
    "gn:country_code":"ET",
    "gn:dem":2511,
    "gn:feature_class":"P",
    "gn:feature_code":"PPL",
    "gn:name":"Shenen",
    "gn:population":0,
    "gn:timezone":"Africa/Addis_Ababa",
    "iso:country":"ET",
    "wof:name":"Shenen",
    "wof:placetype":"locality"
},
  "geometry": {"coordinates":[37.46667,8.73333],"type":"Point"}
}