{
  "type": "Feature",
  "properties": {
    "gn:admin1_code":"40.0",
    "gn:asciiname":"Pukumu",
    "gn:country_code":"ET",
    "gn:dem":441,
    "gn:feature_class":"P",
    "gn:feature_code":"PPL",
    "gn:name":"Pukumu",
    "gn:population":0,
    "gn:timezone":"Africa/Addis_Ababa",
    "iso:country":"ET",
    "wof:name":"Pukumu",
    "wof:placetype":"locality"
},
  "geometry": {"coordinates":[34.34612,8.24005],"type":"Point"}
}