{
  "type": "Feature",
  "properties": {
    "gn:admin1_code":"51",
    "gn:asciiname":"Wedesa Moto",
    "gn:country_code":"ET",
    "gn:dem":2139,
    "gn:feature_class":"P",
    "gn:feature_code":"PPL",
    "gn:name":"Wed\u0113sa Moto",
    "gn:population":0,
    "gn:timezone":"Africa/Addis_Ababa",
    "iso:country":"ET",
    "wof:name":"Wedesa Moto",
    "wof:placetype":"locality"
},
  "geometry": {"coordinates":[38.51667,9.98333],"type":"Point"}
}