{
  "type": "Feature",
  "properties": {
    "gn:admin1_code":"52.0",
    "gn:asciiname":"Argegle",
    "gn:country_code":"ET",
    "gn:dem":580,
    "gn:feature_class":"P",
    "gn:feature_code":"PPL",
    "gn:name":"Argegle",
    "gn:population":0,
    "gn:timezone":"Africa/Addis_Ababa",
    "iso:country":"ET",
    "wof:name":"Argegle",
    "wof:placetype":"locality"
},
  "geometry": {"coordinates":[43.40888,5.42571],"type":"Point"}
}