{
  "type": "Feature",
  "properties": {
    "gn:admin1_code":"53",
    "gn:asciiname":"Weteg",
    "gn:country_code":"ET",
    "gn:dem":2661,
    "gn:feature_class":"P",
    "gn:feature_code":"PPL",
    "gn:name":"Weteg",
    "gn:population":0,
    "gn:timezone":"Africa/Addis_Ababa",
    "iso:country":"ET",
    "wof:name":"Weteg",
    "wof:placetype":"locality"
},
  "geometry": {"coordinates":[39.58333,12.91667],"type":"Point"}
}