{
  "type": "Feature",
  "properties": {
    "gn:admin1_code":"46",
    "gn:asciiname":"Godana Mika'el",
    "gn:country_code":"ET",
    "gn:dem":2344,
    "gn:feature_class":"P",
    "gn:feature_code":"PPL",
    "gn:name":"Godana M\u012bka\u2019\u0113l",
    "gn:population":0,
    "gn:timezone":"Africa/Addis_Ababa",
    "iso:country":"ET",
    "name:und_x_variant":[
        "Yegodena Mikael",
        "Godena Michael",
        "Godena Mikael",
        "Goduna Michael",
        "Godana M\u012bka\u2019\u0113l"
    ],
    "wof:name":"Godana Mika'el",
    "wof:placetype":"locality"
},
  "geometry": {"coordinates":[37.83333,10.25],"type":"Point"}
}