{
  "type": "Feature",
  "properties": {
    "gn:admin1_code":"45.0",
    "gn:asciiname":"Dammata",
    "gn:country_code":"ET",
    "gn:dem":620,
    "gn:feature_class":"P",
    "gn:feature_code":"PPL",
    "gn:name":"Dammata",
    "gn:population":0,
    "gn:timezone":"Africa/Addis_Ababa",
    "iso:country":"ET",
    "wof:name":"Dammata",
    "wof:placetype":"locality"
},
  "geometry": {"coordinates":[41.78868,12.02872],"type":"Point"}
}