{
  "type": "Feature",
  "properties": {
    "gn:admin1_code":"51",
    "gn:asciiname":"Weleba",
    "gn:country_code":"ET",
    "gn:dem":2234,
    "gn:feature_class":"P",
    "gn:feature_code":"PPL",
    "gn:name":"Weleba",
    "gn:population":0,
    "gn:timezone":"Africa/Addis_Ababa",
    "iso:country":"ET",
    "wof:name":"Weleba",
    "wof:placetype":"locality"
},
  "geometry": {"coordinates":[37.31667,9.46667],"type":"Point"}
}