{
  "type": "Feature",
  "properties": {
    "gn:admin1_code":"51",
    "gn:asciiname":"Silo",
    "gn:country_code":"ET",
    "gn:dem":2549,
    "gn:feature_class":"P",
    "gn:feature_code":"PPL",
    "gn:name":"S\u012blo",
    "gn:population":0,
    "gn:timezone":"Africa/Addis_Ababa",
    "iso:country":"ET",
    "wof:name":"Silo",
    "wof:placetype":"locality"
},
  "geometry": {"coordinates":[38.63333,9.33333],"type":"Point"}
}