{
  "type": "Feature",
  "properties": {
    "gn:admin1_code":"46",
    "gn:asciiname":"Key Gedel",
    "gn:country_code":"ET",
    "gn:dem":2179,
    "gn:feature_class":"P",
    "gn:feature_code":"PPL",
    "gn:name":"Key Gedel",
    "gn:population":0,
    "gn:timezone":"Africa/Addis_Ababa",
    "iso:country":"ET",
    "wof:name":"Key Gedel",
    "wof:placetype":"locality"
},
  "geometry": {"coordinates":[39.80262000000001,9.7284],"type":"Point"}
}