{
  "type": "Feature",
  "properties": {
    "gn:admin1_code":"51",
    "gn:asciiname":"Gewil",
    "gn:country_code":"ET",
    "gn:dem":1789,
    "gn:feature_class":"P",
    "gn:feature_code":"PPL",
    "gn:name":"Gew\u012bl",
    "gn:population":0,
    "gn:timezone":"Africa/Addis_Ababa",
    "iso:country":"ET",
    "name:und_x_variant":[
        "Vato",
        "Gew\u012bl"
    ],
    "wof:name":"Gewil",
    "wof:placetype":"locality"
},
  "geometry": {"coordinates":[34.98333,9.05],"type":"Point"}
}