{
  "type": "Feature",
  "properties": {
    "gn:admin1_code":"51.0",
    "gn:asciiname":"Beda",
    "gn:country_code":"ET",
    "gn:dem":2222,
    "gn:feature_class":"P",
    "gn:feature_code":"PPL",
    "gn:name":"Beda",
    "gn:population":0,
    "gn:timezone":"Africa/Addis_Ababa",
    "iso:country":"ET",
    "name:und_x_variant":[
        "Beda 1",
        "Beda"
    ],
    "wof:name":"Beda",
    "wof:placetype":"locality"
},
  "geometry": {"coordinates":[42.05556,9.39417],"type":"Point"}
}