{
  "type": "Feature",
  "properties": {
    "gn:admin1_code":"53.0",
    "gn:asciiname":"Ayfelah",
    "gn:country_code":"ET",
    "gn:dem":2798,
    "gn:feature_class":"P",
    "gn:feature_code":"PPL",
    "gn:name":"\u0100yfelah",
    "gn:population":0,
    "gn:timezone":"Africa/Addis_Ababa",
    "iso:country":"ET",
    "wof:name":"Ayfelah",
    "wof:placetype":"locality"
},
  "geometry": {"coordinates":[39.63656,14.11935],"type":"Point"}
}