{
  "type": "Feature",
  "properties": {
    "gn:admin1_code":"53",
    "gn:asciiname":"Izban Hidaga",
    "gn:country_code":"ET",
    "gn:dem":2677,
    "gn:feature_class":"P",
    "gn:feature_code":"PPL",
    "gn:name":"Izban Hidaga",
    "gn:population":0,
    "gn:timezone":"Africa/Addis_Ababa",
    "iso:country":"ET",
    "name:und_x_variant":[
        "Izban Khidaga",
        "Izban Hidaga"
    ],
    "wof:name":"Izban Hidaga",
    "wof:placetype":"locality"
},
  "geometry": {"coordinates":[39.58374,13.00848],"type":"Point"}
}