{
  "type": "Feature",
  "properties": {
    "gn:admin1_code":"53.0",
    "gn:asciiname":"Adi Weyno",
    "gn:country_code":"ET",
    "gn:dem":1596,
    "gn:feature_class":"P",
    "gn:feature_code":"PPL",
    "gn:name":"\u0100d\u012b Weyno",
    "gn:population":0,
    "gn:timezone":"Africa/Addis_Ababa",
    "iso:country":"ET",
    "name:und_x_variant":[
        "Addi Uoyno",
        "\u0100d\u012b Weyno"
    ],
    "wof:name":"Adi Weyno",
    "wof:placetype":"locality"
},
  "geometry": {"coordinates":[38.08571,14.24398],"type":"Point"}
}