{
  "type": "Feature",
  "properties": {
    "gn:admin1_code":"52",
    "gn:asciiname":"Iya Hareda Ali Beyle",
    "gn:country_code":"ET",
    "gn:dem":1563,
    "gn:feature_class":"P",
    "gn:feature_code":"PPL",
    "gn:name":"\u012aya Hareda \u0100l\u012b B\u0113yl\u0113",
    "gn:population":0,
    "gn:timezone":"Africa/Addis_Ababa",
    "iso:country":"ET",
    "name:und_x_variant":[
        "Iya-Khareda-Ali-Beyle",
        "\u012aya Hareda \u0100l\u012b B\u0113yl\u0113"
    ],
    "wof:name":"Iya Hareda Ali Beyle",
    "wof:placetype":"locality"
},
  "geometry": {"coordinates":[43.37861,9.3725],"type":"Point"}
}