{
  "type": "Feature",
  "properties": {
    "gn:admin1_code":"51.0",
    "gn:asciiname":"Ch'ok'orsa",
    "gn:country_code":"ET",
    "gn:dem":1698,
    "gn:feature_class":"P",
    "gn:feature_code":"PPL",
    "gn:name":"Ch\u2019ok\u2019orsa",
    "gn:population":0,
    "gn:timezone":"Africa/Addis_Ababa",
    "iso:country":"ET",
    "wof:name":"Ch'ok'orsa",
    "wof:placetype":"locality"
},
  "geometry": {"coordinates":[36.88333,9.65],"type":"Point"}
}