{
  "type": "Feature",
  "properties": {
    "gn:admin1_code":"52.0",
    "gn:asciiname":"Awu Bere",
    "gn:country_code":"ET",
    "gn:dem":1616,
    "gn:feature_class":"P",
    "gn:feature_code":"PPL",
    "gn:name":"\u0100wu Ber\u0113",
    "gn:population":0,
    "gn:timezone":"Africa/Addis_Ababa",
    "iso:country":"ET",
    "name:und_x_variant":[
        "Avu-Bere",
        "\u0100wu Ber\u0113"
    ],
    "wof:name":"Awu Bere",
    "wof:placetype":"locality"
},
  "geometry": {"coordinates":[43.29361,9.44306],"type":"Point"}
}