{
  "type": "Feature",
  "properties": {
    "gn:admin1_code":"51",
    "gn:asciiname":"Kumando",
    "gn:country_code":"ET",
    "gn:dem":2845,
    "gn:feature_class":"P",
    "gn:feature_code":"PPL",
    "gn:name":"Kumando",
    "gn:population":0,
    "gn:timezone":"Africa/Addis_Ababa",
    "iso:country":"ET",
    "name:und_x_variant":[
        "Comanda Tabia",
        "Kumando"
    ],
    "wof:name":"Kumando",
    "wof:placetype":"locality"
},
  "geometry": {"coordinates":[38.73333,9.78333],"type":"Point"}
}