{
  "type": "Feature",
  "properties": {
    "gn:admin1_code":"51",
    "gn:asciiname":"Hulul",
    "gn:country_code":"ET",
    "gn:dem":1728,
    "gn:feature_class":"P",
    "gn:feature_code":"PPL",
    "gn:name":"Hulul",
    "gn:population":0,
    "gn:timezone":"Africa/Addis_Ababa",
    "iso:country":"ET",
    "name:und_x_variant":[
        "Ullul",
        "Khulul\u2019",
        "Hulul"
    ],
    "wof:name":"Hulul",
    "wof:placetype":"locality"
},
  "geometry": {"coordinates":[41.72056,9.48194],"type":"Point"}
}