{
  "type": "Feature",
  "properties": {
    "gn:admin1_code":"51",
    "gn:asciiname":"Gohey",
    "gn:country_code":"ET",
    "gn:dem":1798,
    "gn:feature_class":"P",
    "gn:feature_code":"PPL",
    "gn:name":"Goh\u0113y",
    "gn:population":0,
    "gn:timezone":"Africa/Addis_Ababa",
    "iso:country":"ET",
    "name:und_x_variant":[
        "Gokhey",
        "Goh\u0113y"
    ],
    "wof:name":"Gohey",
    "wof:placetype":"locality"
},
  "geometry": {"coordinates":[42.1175,9.11889],"type":"Point"}
}