{
  "type": "Feature",
  "properties": {
    "gn:admin1_code":"51",
    "gn:asciiname":"Yayu",
    "gn:country_code":"ET",
    "gn:dem":1558,
    "gn:feature_class":"P",
    "gn:feature_code":"PPL",
    "gn:name":"Yayu",
    "gn:population":0,
    "gn:timezone":"Africa/Addis_Ababa",
    "iso:country":"ET",
    "name:und_x_variant":[
        "Yayo",
        "Yayo (1)",
        "Yayu"
    ],
    "wof:name":"Yayu",
    "wof:placetype":"locality"
},
  "geometry": {"coordinates":[35.81667,8.33333],"type":"Point"}
}