{
  "type": "Feature",
  "properties": {
    "gn:admin1_code":"52",
    "gn:asciiname":"Gherou",
    "gn:country_code":"ET",
    "gn:dem":387,
    "gn:feature_class":"P",
    "gn:feature_code":"PPL",
    "gn:name":"Gherou",
    "gn:population":0,
    "gn:timezone":"Africa/Addis_Ababa",
    "iso:country":"ET",
    "name:und_x_variant":[
        "Gheron",
        "Gherou"
    ],
    "wof:name":"Gherou",
    "wof:placetype":"locality"
},
  "geometry": {"coordinates":[46.98333,7.03333],"type":"Point"}
}