{
  "type": "Feature",
  "properties": {
    "gn:admin1_code":"54",
    "gn:asciiname":"Kula",
    "gn:country_code":"ET",
    "gn:dem":2242,
    "gn:feature_class":"P",
    "gn:feature_code":"PPL",
    "gn:name":"Kula",
    "gn:population":0,
    "gn:timezone":"Africa/Addis_Ababa",
    "iso:country":"ET",
    "wof:name":"Kula",
    "wof:placetype":"locality"
},
  "geometry": {"coordinates":[35.81264,7.01573],"type":"Point"}
}