{
  "type": "Feature",
  "properties": {
    "gn:admin1_code":"52",
    "gn:asciiname":"Duri",
    "gn:country_code":"ET",
    "gn:dem":510,
    "gn:feature_class":"P",
    "gn:feature_code":"PPL",
    "gn:name":"Duri",
    "gn:population":0,
    "gn:timezone":"Africa/Addis_Ababa",
    "iso:country":"ET",
    "wof:name":"Duri",
    "wof:placetype":"locality"
},
  "geometry": {"coordinates":[43.46556,6.70361],"type":"Point"}
}