{
  "type": "Feature",
  "properties": {
    "gn:admin1_code":"53",
    "gn:asciiname":"Gobba",
    "gn:country_code":"ET",
    "gn:dem":1624,
    "gn:feature_class":"P",
    "gn:feature_code":"PPL",
    "gn:name":"Gobba",
    "gn:population":0,
    "gn:timezone":"Africa/Addis_Ababa",
    "iso:country":"ET",
    "wof:name":"Gobba",
    "wof:placetype":"locality"
},
  "geometry": {"coordinates":[39.81667,12.75],"type":"Point"}
}