{
  "type": "Feature",
  "properties": {
    "gn:admin1_code":"54",
    "gn:asciiname":"K'idame Gebeya",
    "gn:country_code":"ET",
    "gn:dem":2407,
    "gn:feature_class":"P",
    "gn:feature_code":"PPL",
    "gn:name":"K\u2019idam\u0113 Gebeya",
    "gn:population":0,
    "gn:timezone":"Africa/Addis_Ababa",
    "iso:country":"ET",
    "wof:name":"K'idame Gebeya",
    "wof:placetype":"locality"
},
  "geometry": {"coordinates":[37.51667,7.93333],"type":"Point"}
}