{
  "type": "Feature",
  "properties": {
    "gn:admin1_code":"53.0",
    "gn:asciiname":"Hamedila",
    "gn:country_code":"ET",
    "gn:dem":-91,
    "gn:feature_class":"P",
    "gn:feature_code":"PPL",
    "gn:name":"Hamedila",
    "gn:population":0,
    "gn:timezone":"Africa/Addis_Ababa",
    "iso:country":"ET",
    "wof:name":"Hamedila",
    "wof:placetype":"locality"
},
  "geometry": {"coordinates":[40.281,14.087],"type":"Point"}
}