{
  "type": "Feature",
  "properties": {
    "gn:admin1_code":"51",
    "gn:asciiname":"Gumbabi",
    "gn:country_code":"ET",
    "gn:dem":1649,
    "gn:feature_class":"P",
    "gn:feature_code":"PPL",
    "gn:name":"Gumbabi",
    "gn:population":0,
    "gn:timezone":"Africa/Addis_Ababa",
    "iso:country":"ET",
    "wof:name":"Gumbabi",
    "wof:placetype":"locality"
},
  "geometry": {"coordinates":[34.63333,9.03333],"type":"Point"}
}