{
  "type": "Feature",
  "properties": {
    "gn:admin1_code":"52",
    "gn:asciiname":"Gabba Galleccia",
    "gn:country_code":"ET",
    "gn:dem":490,
    "gn:feature_class":"P",
    "gn:feature_code":"PPL",
    "gn:name":"Gabba Galleccia",
    "gn:population":0,
    "gn:timezone":"Africa/Addis_Ababa",
    "iso:country":"ET",
    "wof:name":"Gabba Galleccia",
    "wof:placetype":"locality"
},
  "geometry": {"coordinates":[42.225,6.97444],"type":"Point"}
}