{
  "type": "Feature",
  "properties": {
    "gn:admin1_code":"53",
    "gn:asciiname":"Mahbere Daguea",
    "gn:country_code":"ET",
    "gn:dem":1611,
    "gn:feature_class":"P",
    "gn:feature_code":"PPL",
    "gn:name":"Mahbere Daguea",
    "gn:population":0,
    "gn:timezone":"Africa/Addis_Ababa",
    "iso:country":"ET",
    "name:und_x_variant":[
        "Mahber Degue",
        "Mahbere Tsion",
        "Mahbere Daguea"
    ],
    "wof:name":"Mahbere Daguea",
    "wof:placetype":"locality"
},
  "geometry": {"coordinates":[38.81667,13.81667],"type":"Point"}
}