{
  "type": "Feature",
  "properties": {
    "gn:admin1_code":"51",
    "gn:asciiname":"Dololo Jila",
    "gn:country_code":"ET",
    "gn:dem":1720,
    "gn:feature_class":"P",
    "gn:feature_code":"PPL",
    "gn:name":"Dololo J\u012bla",
    "gn:population":0,
    "gn:timezone":"Africa/Addis_Ababa",
    "iso:country":"ET",
    "wof:name":"Dololo Jila",
    "wof:placetype":"locality"
},
  "geometry": {"coordinates":[38.91667,8.56667],"type":"Point"}
}