{
  "type": "Feature",
  "properties": {
    "gn:admin1_code":"50.0",
    "gn:asciiname":"Awbeker Muti",
    "gn:country_code":"ET",
    "gn:dem":2025,
    "gn:feature_class":"P",
    "gn:feature_code":"PPLL",
    "gn:name":"Awbeker Muti",
    "gn:population":0,
    "gn:timezone":"Africa/Addis_Ababa",
    "iso:country":"ET",
    "wof:name":"Awbeker Muti",
    "wof:placetype":"locality"
},
  "geometry": {"coordinates":[42.10867,9.33729],"type":"Point"}
}