{
  "type": "Feature",
  "properties": {
    "gn:admin1_code":"53.0",
    "gn:asciiname":"Chelena",
    "gn:country_code":"ET",
    "gn:dem":1932,
    "gn:feature_class":"P",
    "gn:feature_code":"PPL",
    "gn:name":"Chelena",
    "gn:population":0,
    "gn:timezone":"Africa/Addis_Ababa",
    "iso:country":"ET",
    "wof:name":"Chelena",
    "wof:placetype":"locality"
},
  "geometry": {"coordinates":[39.33944,12.89556],"type":"Point"}
}