{
  "type": "Feature",
  "properties": {
    "gn:admin1_code":"51",
    "gn:asciiname":"Sewa",
    "gn:country_code":"ET",
    "gn:dem":1947,
    "gn:feature_class":"P",
    "gn:feature_code":"PPL",
    "gn:name":"Sewa",
    "gn:population":0,
    "gn:timezone":"Africa/Addis_Ababa",
    "iso:country":"ET",
    "wof:name":"Sewa",
    "wof:placetype":"locality"
},
  "geometry": {"coordinates":[36.96667,9.45],"type":"Point"}
}