{
  "type": "Feature",
  "properties": {
    "gn:admin1_code":"48",
    "gn:asciiname":"Jeldesa",
    "gn:country_code":"ET",
    "gn:dem":1099,
    "gn:feature_class":"P",
    "gn:feature_code":"PPL",
    "gn:name":"Jeld\u0113sa",
    "gn:population":0,
    "gn:timezone":"Africa/Addis_Ababa",
    "iso:country":"ET",
    "name:deu_x_preferred":[
        "Jaldessa"
    ],
    "name:ita_x_preferred":[
        "Jaldessa"
    ],
    "name:und_x_variant":[
        "Gildessa",
        "Jaldessa",
        "Dzhel\u2019dessa",
        "Jeld\u0113sa"
    ],
    "wof:name":"Jeldesa",
    "wof:placetype":"locality"
},
  "geometry": {"coordinates":[42.11972,9.71389],"type":"Point"}
}