{
  "type": "Feature",
  "properties": {
    "gn:admin1_code":"54.0",
    "gn:asciiname":"Darimo",
    "gn:country_code":"ET",
    "gn:dem":1941,
    "gn:feature_class":"P",
    "gn:feature_code":"PPL",
    "gn:name":"Darimo",
    "gn:population":0,
    "gn:timezone":"Africa/Addis_Ababa",
    "iso:country":"ET",
    "name:und_x_variant":[
        "Deraimo",
        "Darimo"
    ],
    "wof:name":"Darimo",
    "wof:placetype":"locality"
},
  "geometry": {"coordinates":[35.68333,7.86667],"type":"Point"}
}