{
  "type": "Feature",
  "properties": {
    "gn:admin1_code":"46",
    "gn:asciiname":"Jerjero",
    "gn:country_code":"ET",
    "gn:dem":2041,
    "gn:feature_class":"P",
    "gn:feature_code":"PPL",
    "gn:name":"Jerjero",
    "gn:population":0,
    "gn:timezone":"Africa/Addis_Ababa",
    "iso:country":"ET",
    "name:und_x_variant":[
        "Jerjero (2)",
        "Jerjero"
    ],
    "wof:name":"Jerjero",
    "wof:placetype":"locality"
},
  "geometry": {"coordinates":[39.35,11.23333],"type":"Point"}
}