{
  "type": "Feature",
  "properties": {
    "gn:admin1_code":"46",
    "gn:asciiname":"Girara",
    "gn:country_code":"ET",
    "gn:dem":2286,
    "gn:feature_class":"P",
    "gn:feature_code":"PPL",
    "gn:name":"Girara",
    "gn:population":0,
    "gn:timezone":"Africa/Addis_Ababa",
    "iso:country":"ET",
    "wof:name":"Girara",
    "wof:placetype":"locality"
},
  "geometry": {"coordinates":[39.28333,12.25],"type":"Point"}
}