{
  "type": "Feature",
  "properties": {
    "gn:admin1_code":"45",
    "gn:asciiname":"Thio Adoli",
    "gn:country_code":"ET",
    "gn:dem":-11,
    "gn:feature_class":"P",
    "gn:feature_code":"PPL",
    "gn:name":"Thio Adoli",
    "gn:population":0,
    "gn:timezone":"Africa/Addis_Ababa",
    "iso:country":"ET",
    "name:und_x_variant":[
        "Thio Adole",
        "T'o Adoli",
        "Thio Adoli"
    ],
    "wof:name":"Thio Adoli",
    "wof:placetype":"locality"
},
  "geometry": {"coordinates":[40.73495,13.71491],"type":"Point"}
}