{
  "type": "Feature",
  "properties": {
    "gn:admin1_code":"48",
    "gn:asciiname":"Sala Asaleh",
    "gn:country_code":"ET",
    "gn:dem":1055,
    "gn:feature_class":"P",
    "gn:feature_code":"PPL",
    "gn:name":"Sala Asaleh",
    "gn:population":0,
    "gn:timezone":"Africa/Addis_Ababa",
    "iso:country":"ET",
    "wof:name":"Sala Asaleh",
    "wof:placetype":"locality"
},
  "geometry": {"coordinates":[42.13194,9.73861],"type":"Point"}
}