{
  "type": "Feature",
  "properties": {
    "gn:admin1_code":"51",
    "gn:asciiname":"Nunu",
    "gn:country_code":"ET",
    "gn:dem":2314,
    "gn:feature_class":"P",
    "gn:feature_code":"PPL",
    "gn:name":"Nunu",
    "gn:population":0,
    "gn:timezone":"Africa/Addis_Ababa",
    "iso:country":"ET",
    "name:und_x_variant":[
        "Rob Gebaya",
        "Nunu"
    ],
    "wof:name":"Nunu",
    "wof:placetype":"locality"
},
  "geometry": {"coordinates":[36.65,8.78333],"type":"Point"}
}