{
  "type": "Feature",
  "properties": {
    "gn:admin1_code":"52",
    "gn:asciiname":"Erer",
    "gn:country_code":"ET",
    "gn:dem":1103,
    "gn:feature_class":"P",
    "gn:feature_code":"PPL",
    "gn:name":"\u0112rer",
    "gn:population":0,
    "gn:timezone":"Africa/Addis_Ababa",
    "iso:country":"ET",
    "name:deu_x_preferred":[
        "Erer"
    ],
    "name:und_x_variant":[
        "\u0112rer",
        "Errer"
    ],
    "wof:name":"Erer",
    "wof:placetype":"locality"
},
  "geometry": {"coordinates":[41.38551,9.55814],"type":"Point"}
}