{
  "type": "Feature",
  "properties": {
    "gn:admin1_code":"53",
    "gn:asciiname":"Yaha",
    "gn:country_code":"ET",
    "gn:dem":2196,
    "gn:feature_class":"P",
    "gn:feature_code":"PPL",
    "gn:name":"Yaha",
    "gn:population":0,
    "gn:timezone":"Africa/Addis_Ababa",
    "iso:country":"ET",
    "name:und_x_variant":[
        "Yaha (1)",
        "Yakha",
        "Yaha"
    ],
    "wof:name":"Yaha",
    "wof:placetype":"locality"
},
  "geometry": {"coordinates":[38.97413,14.25098],"type":"Point"}
}