{
  "type": "Feature",
  "properties": {
    "gn:admin1_code":"51",
    "gn:asciiname":"Gefra",
    "gn:country_code":"ET",
    "gn:dem":1439,
    "gn:feature_class":"P",
    "gn:feature_code":"PPL",
    "gn:name":"Gefra",
    "gn:population":0,
    "gn:timezone":"Africa/Addis_Ababa",
    "iso:country":"ET",
    "wof:name":"Gefra",
    "wof:placetype":"locality"
},
  "geometry": {"coordinates":[41.95778,9.15889],"type":"Point"}
}