{
  "type": "Feature",
  "properties": {
    "gn:admin1_code":"53.0",
    "gn:asciiname":"Zeban",
    "gn:country_code":"ET",
    "gn:dem":3036,
    "gn:feature_class":"P",
    "gn:feature_code":"PPL",
    "gn:name":"Zeban",
    "gn:population":0,
    "gn:timezone":"Africa/Addis_Ababa",
    "iso:country":"ET",
    "wof:name":"Zeban",
    "wof:placetype":"locality"
},
  "geometry": {"coordinates":[39.716,14.057],"type":"Point"}
}