{
  "type": "Feature",
  "properties": {
    "gn:admin1_code":"46",
    "gn:asciiname":"Met'erariya",
    "gn:country_code":"ET",
    "gn:dem":1778,
    "gn:feature_class":"P",
    "gn:feature_code":"PPL",
    "gn:name":"Met\u2019erar\u012bya",
    "gn:population":0,
    "gn:timezone":"Africa/Addis_Ababa",
    "iso:country":"ET",
    "wof:name":"Met'erariya",
    "wof:placetype":"locality"
},
  "geometry": {"coordinates":[39.05672,10.40483],"type":"Point"}
}