{
  "type": "Feature",
  "properties": {
    "gn:admin1_code":"46.0",
    "gn:asciiname":"Ch'ome",
    "gn:country_code":"ET",
    "gn:dem":3297,
    "gn:feature_class":"P",
    "gn:feature_code":"PPL",
    "gn:name":"Ch\u2019om\u0113",
    "gn:population":0,
    "gn:timezone":"Africa/Addis_Ababa",
    "iso:country":"ET",
    "wof:name":"Ch'ome",
    "wof:placetype":"locality"
},
  "geometry": {"coordinates":[39.37084,10.9734],"type":"Point"}
}