{
  "type": "Feature",
  "properties": {
    "gn:admin1_code":"46.0",
    "gn:asciiname":"Acam",
    "gn:country_code":"ET",
    "gn:dem":2002,
    "gn:feature_class":"P",
    "gn:feature_code":"PPL",
    "gn:name":"Acam",
    "gn:population":0,
    "gn:timezone":"Africa/Addis_Ababa",
    "iso:country":"ET",
    "wof:name":"Acam",
    "wof:placetype":"locality"
},
  "geometry": {"coordinates":[38.03333,12.31667],"type":"Point"}
}