{
  "type": "Feature",
  "properties": {
    "gn:admin1_code":"46",
    "gn:asciiname":"Gende Gora",
    "gn:country_code":"ET",
    "gn:dem":1342,
    "gn:feature_class":"P",
    "gn:feature_code":"PPL",
    "gn:name":"Gende Gora",
    "gn:population":0,
    "gn:timezone":"Africa/Addis_Ababa",
    "iso:country":"ET",
    "wof:name":"Gende Gora",
    "wof:placetype":"locality"
},
  "geometry": {"coordinates":[39.91667,11.45],"type":"Point"}
}