{
  "type": "Feature",
  "properties": {
    "gn:admin1_code":"51.0",
    "gn:asciiname":"Ayuweni",
    "gn:country_code":"ET",
    "gn:dem":2418,
    "gn:feature_class":"P",
    "gn:feature_code":"PPL",
    "gn:name":"\u0100yuw\u0113n\u012b",
    "gn:population":0,
    "gn:timezone":"Africa/Addis_Ababa",
    "iso:country":"ET",
    "wof:name":"Ayuweni",
    "wof:placetype":"locality"
},
  "geometry": {"coordinates":[37.18333,9.71667],"type":"Point"}
}