{
  "type": "Feature",
  "properties": {
    "gn:admin1_code":"51.0",
    "gn:asciiname":"Ch'irecha Bekeka",
    "gn:country_code":"ET",
    "gn:dem":2297,
    "gn:feature_class":"P",
    "gn:feature_code":"PPL",
    "gn:name":"Ch\u2019ir\u0113cha Bekeka",
    "gn:population":0,
    "gn:timezone":"Africa/Addis_Ababa",
    "iso:country":"ET",
    "wof:name":"Ch'irecha Bekeka",
    "wof:placetype":"locality"
},
  "geometry": {"coordinates":[37.13333,9.88333],"type":"Point"}
}