{
  "type": "Feature",
  "properties": {
    "gn:admin1_code":"53.0",
    "gn:asciiname":"Adi Abayo",
    "gn:country_code":"ET",
    "gn:dem":1874,
    "gn:feature_class":"P",
    "gn:feature_code":"PPL",
    "gn:name":"\u0100d\u012b \u0100bayo",
    "gn:population":0,
    "gn:timezone":"Africa/Addis_Ababa",
    "iso:country":"ET",
    "name:und_x_variant":[
        "Adi Abaio",
        "Addi Abayo",
        "Hamlo",
        "Khamlo",
        "\u0100d\u012b \u0100bayo"
    ],
    "wof:name":"Adi Abayo",
    "wof:placetype":"locality"
},
  "geometry": {"coordinates":[38.2942,14.2221],"type":"Point"}
}