{
  "type": "Feature",
  "properties": {
    "gn:admin1_code":"49",
    "gn:asciiname":"Ugudi",
    "gn:country_code":"ET",
    "gn:dem":432,
    "gn:feature_class":"P",
    "gn:feature_code":"PPL",
    "gn:name":"Ugudi",
    "gn:population":0,
    "gn:timezone":"Africa/Addis_Ababa",
    "iso:country":"ET",
    "wof:name":"Ugudi",
    "wof:placetype":"locality"
},
  "geometry": {"coordinates":[34.21667,7.96667],"type":"Point"}
}