{
  "type": "Feature",
  "properties": {
    "gn:admin1_code":"46",
    "gn:asciiname":"Shemzemo",
    "gn:country_code":"ET",
    "gn:dem":3189,
    "gn:feature_class":"P",
    "gn:feature_code":"PPL",
    "gn:name":"Shemzemo",
    "gn:population":0,
    "gn:timezone":"Africa/Addis_Ababa",
    "iso:country":"ET",
    "wof:name":"Shemzemo",
    "wof:placetype":"locality"
},
  "geometry": {"coordinates":[39.16667,12.21667],"type":"Point"}
}