{
  "type": "Feature",
  "properties": {
    "gn:admin1_code":"51",
    "gn:asciiname":"Gorba",
    "gn:country_code":"ET",
    "gn:dem":2381,
    "gn:feature_class":"P",
    "gn:feature_code":"PPL",
    "gn:name":"Gorba",
    "gn:population":0,
    "gn:timezone":"Africa/Addis_Ababa",
    "iso:country":"ET",
    "wof:name":"Gorba",
    "wof:placetype":"locality"
},
  "geometry": {"coordinates":[37.83333,9.08333],"type":"Point"}
}