{
  "type": "Feature",
  "properties": {
    "gn:admin1_code":"53",
    "gn:asciiname":"Hagula",
    "gn:country_code":"ET",
    "gn:dem":2299,
    "gn:feature_class":"P",
    "gn:feature_code":"PPL",
    "gn:name":"Hagula",
    "gn:population":0,
    "gn:timezone":"Africa/Addis_Ababa",
    "iso:country":"ET",
    "name:und_x_variant":[
        "Khagula"
    ],
    "wof:name":"Hagula",
    "wof:placetype":"locality"
},
  "geometry": {"coordinates":[39.58601,13.59286],"type":"Point"}
}