{
  "type": "Feature",
  "properties": {
    "gn:admin1_code":"54",
    "gn:asciiname":"Sciola",
    "gn:country_code":"ET",
    "gn:dem":1577,
    "gn:feature_class":"P",
    "gn:feature_code":"PPL",
    "gn:name":"Sciola",
    "gn:population":0,
    "gn:timezone":"Africa/Addis_Ababa",
    "iso:country":"ET",
    "wof:name":"Sciola",
    "wof:placetype":"locality"
},
  "geometry": {"coordinates":[37.51667,7.41667],"type":"Point"}
}