{
  "type": "Feature",
  "properties": {
    "gn:admin1_code":"54",
    "gn:asciiname":"Medalcho",
    "gn:country_code":"ET",
    "gn:dem":1714,
    "gn:feature_class":"P",
    "gn:feature_code":"PPL",
    "gn:name":"Medalcho",
    "gn:population":0,
    "gn:timezone":"Africa/Addis_Ababa",
    "iso:country":"ET",
    "name:und_x_variant":[
        "Medalcho (1)",
        "Medalcho"
    ],
    "wof:name":"Medalcho",
    "wof:placetype":"locality"
},
  "geometry": {"coordinates":[37.35,6.65],"type":"Point"}
}