{
  "type": "Feature",
  "properties": {
    "gn:admin1_code":"51.0",
    "gn:asciiname":"Daleti",
    "gn:country_code":"ET",
    "gn:dem":2612,
    "gn:feature_class":"P",
    "gn:feature_code":"PPL",
    "gn:name":"Dalet\u012b",
    "gn:population":0,
    "gn:timezone":"Africa/Addis_Ababa",
    "iso:country":"ET",
    "name:und_x_variant":[
        "Bocolo",
        "Dalet\u012b"
    ],
    "wof:name":"Daleti",
    "wof:placetype":"locality"
},
  "geometry": {"coordinates":[39.06839,9.69046],"type":"Point"}
}