{
  "type": "Feature",
  "properties": {
    "gn:admin1_code":"51",
    "gn:asciiname":"Mit'a",
    "gn:country_code":"ET",
    "gn:dem":2233,
    "gn:feature_class":"P",
    "gn:feature_code":"PPL",
    "gn:name":"M\u012bt\u2019a",
    "gn:population":0,
    "gn:timezone":"Africa/Addis_Ababa",
    "iso:country":"ET",
    "wof:name":"Mit'a",
    "wof:placetype":"locality"
},
  "geometry": {"coordinates":[37.16667,9.45],"type":"Point"}
}