{
  "type": "Feature",
  "properties": {
    "gn:admin1_code":"51",
    "gn:asciiname":"Mit'a",
    "gn:country_code":"ET",
    "gn:dem":2233,
    "gn:feature_class":"P",
    "gn:feature_code":"PPL",
    "gn:name":"M\u012bt\u2019a",
    "gn:population":0,
    "gn:timezone":"Africa/Addis_Ababa",
    "iso:country":"ET",
    "name:cat_x_preferred":[
        "Mita"
    ],
    "name:ces_x_preferred":[
        "Mita"
    ],
    "name:deu_x_preferred":[
        "Mita"
    ],
    "name:eus_x_preferred":[
        "Mita"
    ],
    "name:fra_x_preferred":[
        "Mita"
    ],
    "name:ita_x_preferred":[
        "Mita"
    ],
    "name:jpn_x_preferred":[
        "\u30df\u30bf\u5236"
    ],
    "name:lat_x_preferred":[
        "Mita"
    ],
    "name:mkd_x_preferred":[
        "\u041c\u0438\u0442\u0430"
    ],
    "name:pol_x_preferred":[
        "Mita"
    ],
    "name:por_x_preferred":[
        "Mita"
    ],
    "name:rus_x_preferred":[
        "\u041c\u0438\u0442\u0430"
    ],
    "name:spa_x_preferred":[
        "Mita"
    ],
    "name:ukr_x_preferred":[
        "\u041c\u0456\u0442\u0430"
    ],
    "wof:name":"Mit'a",
    "wof:placetype":"locality"
},
  "geometry": {"coordinates":[37.16667,9.45],"type":"Point"}
}