{
  "type": "Feature",
  "properties": {
    "gn:admin1_code":"51",
    "gn:asciiname":"Keltu Mescia",
    "gn:country_code":"ET",
    "gn:dem":1672,
    "gn:feature_class":"P",
    "gn:feature_code":"PPL",
    "gn:name":"Keltu Mescia",
    "gn:population":0,
    "gn:timezone":"Africa/Addis_Ababa",
    "iso:country":"ET",
    "wof:name":"Keltu Mescia",
    "wof:placetype":"locality"
},
  "geometry": {"coordinates":[40.36667,8.65],"type":"Point"}
}