{
  "type": "Feature",
  "properties": {
    "gn:admin1_code":"45",
    "gn:asciiname":"Meraile",
    "gn:country_code":"ET",
    "gn:dem":223,
    "gn:feature_class":"P",
    "gn:feature_code":"PPL",
    "gn:name":"Meraile",
    "gn:population":0,
    "gn:timezone":"Africa/Addis_Ababa",
    "iso:country":"ET",
    "wof:name":"Meraile",
    "wof:placetype":"locality"
},
  "geometry": {"coordinates":[41.98333,12.31667],"type":"Point"}
}