{
  "type": "Feature",
  "properties": {
    "gn:admin1_code":"46",
    "gn:asciiname":"Shiro",
    "gn:country_code":"ET",
    "gn:dem":2556,
    "gn:feature_class":"P",
    "gn:feature_code":"PPL",
    "gn:name":"Shiro",
    "gn:population":0,
    "gn:timezone":"Africa/Addis_Ababa",
    "iso:country":"ET",
    "wof:name":"Shiro",
    "wof:placetype":"locality"
},
  "geometry": {"coordinates":[37.88333,11.46667],"type":"Point"}
}