{
  "type": "Feature",
  "properties": {
    "gn:admin1_code":"46",
    "gn:asciiname":"Shiro",
    "gn:country_code":"ET",
    "gn:dem":2556,
    "gn:feature_class":"P",
    "gn:feature_code":"PPL",
    "gn:name":"Shiro",
    "gn:population":0,
    "gn:timezone":"Africa/Addis_Ababa",
    "iso:country":"ET",
    "name:fas_x_preferred":[
        "\u0634\u06cc\u0631\u0648"
    ],
    "name:ita_x_preferred":[
        "Shiro"
    ],
    "name:por_x_preferred":[
        "Shiro"
    ],
    "name:rus_x_preferred":[
        "\u0421\u0438\u0440\u043e"
    ],
    "name:spa_x_preferred":[
        "Shiro"
    ],
    "wof:name":"Shiro",
    "wof:placetype":"locality"
},
  "geometry": {"coordinates":[37.88333,11.46667],"type":"Point"}
}