{
  "type": "Feature",
  "properties": {
    "gn:admin1_code":"52",
    "gn:asciiname":"Tukayel",
    "gn:country_code":"ET",
    "gn:dem":798,
    "gn:feature_class":"P",
    "gn:feature_code":"PPL",
    "gn:name":"Tukayel",
    "gn:population":0,
    "gn:timezone":"Africa/Addis_Ababa",
    "iso:country":"ET",
    "name:rus_x_preferred":[
        "Tukael\u2019"
    ],
    "name:und_x_variant":[
        "Hagoga",
        "Turkayel",
        "Khagoga",
        "Tukayel"
    ],
    "wof:name":"Tukayel",
    "wof:placetype":"locality"
},
  "geometry": {"coordinates":[45.34583,8.12028],"type":"Point"}
}