{
  "type": "Feature",
  "properties": {
    "gn:admin1_code":"51",
    "gn:asciiname":"K'obo",
    "gn:country_code":"ET",
    "gn:dem":2084,
    "gn:feature_class":"P",
    "gn:feature_code":"PPL",
    "gn:name":"K\u2019obo",
    "gn:population":0,
    "gn:timezone":"Africa/Addis_Ababa",
    "iso:country":"ET",
    "wof:name":"K'obo",
    "wof:placetype":"locality"
},
  "geometry": {"coordinates":[41.46667,9.38333],"type":"Point"}
}