{
  "type": "Feature",
  "properties": {
    "gn:admin1_code":"53.0",
    "gn:asciiname":"Addi Kuere",
    "gn:country_code":"ET",
    "gn:dem":1994,
    "gn:feature_class":"P",
    "gn:feature_code":"PPL",
    "gn:name":"Addi Kuere",
    "gn:population":0,
    "gn:timezone":"Africa/Addis_Ababa",
    "iso:country":"ET",
    "name:und_x_variant":[
        "\u0100d\u012b Kwere"
    ],
    "wof:name":"Addi Kuere",
    "wof:placetype":"locality"
},
  "geometry": {"coordinates":[39.58708,13.28432],"type":"Point"}
}