{
  "type": "Feature",
  "properties": {
    "gn:admin1_code":"51.0",
    "gn:asciiname":"Ch'efe Hawiy",
    "gn:country_code":"ET",
    "gn:dem":2350,
    "gn:feature_class":"P",
    "gn:feature_code":"PPL",
    "gn:name":"Ch\u2019ef\u0113 Hawiy",
    "gn:population":0,
    "gn:timezone":"Africa/Addis_Ababa",
    "iso:country":"ET",
    "wof:name":"Ch'efe Hawiy",
    "wof:placetype":"locality"
},
  "geometry": {"coordinates":[38.45,9.53333],"type":"Point"}
}