{
  "type": "Feature",
  "properties": {
    "gn:admin1_code":"51",
    "gn:asciiname":"Goro Jerbo",
    "gn:country_code":"ET",
    "gn:dem":2400,
    "gn:feature_class":"P",
    "gn:feature_code":"PPL",
    "gn:name":"Goro Jerbo",
    "gn:population":0,
    "gn:timezone":"Africa/Addis_Ababa",
    "iso:country":"ET",
    "wof:name":"Goro Jerbo",
    "wof:placetype":"locality"
},
  "geometry": {"coordinates":[38.45,9.51667],"type":"Point"}
}