{
  "type": "Feature",
  "properties": {
    "gn:admin1_code":"53",
    "gn:asciiname":"Fe'u",
    "gn:country_code":"ET",
    "gn:dem":2302,
    "gn:feature_class":"P",
    "gn:feature_code":"PPL",
    "gn:name":"Fe\u2019u",
    "gn:population":0,
    "gn:timezone":"Africa/Addis_Ababa",
    "iso:country":"ET",
    "wof:name":"Fe'u",
    "wof:placetype":"locality"
},
  "geometry": {"coordinates":[39.33333,12.55],"type":"Point"}
}