{
  "type": "Feature",
  "properties": {
    "gn:admin1_code":"52.0",
    "gn:asciiname":"Deche",
    "gn:country_code":"ET",
    "gn:dem":473,
    "gn:feature_class":"P",
    "gn:feature_code":"PPL",
    "gn:name":"Deche",
    "gn:population":0,
    "gn:timezone":"Africa/Addis_Ababa",
    "iso:country":"ET",
    "wof:name":"Deche",
    "wof:placetype":"locality"
},
  "geometry": {"coordinates":[41.95,6.48333],"type":"Point"}
}