{
  "type": "Feature",
  "properties": {
    "gn:admin1_code":"51",
    "gn:asciiname":"Gugufi",
    "gn:country_code":"ET",
    "gn:dem":1590,
    "gn:feature_class":"P",
    "gn:feature_code":"PPL",
    "gn:name":"Guguf\u012b",
    "gn:population":0,
    "gn:timezone":"Africa/Addis_Ababa",
    "iso:country":"ET",
    "wof:name":"Gugufi",
    "wof:placetype":"locality"
},
  "geometry": {"coordinates":[41.9075,8.78972],"type":"Point"}
}