{
  "type": "Feature",
  "properties": {
    "gn:admin1_code":"51",
    "gn:asciiname":"Hunt'e",
    "gn:country_code":"ET",
    "gn:dem":2424,
    "gn:feature_class":"P",
    "gn:feature_code":"PPL",
    "gn:name":"Hunt\u2019\u0113",
    "gn:population":0,
    "gn:timezone":"Africa/Addis_Ababa",
    "iso:country":"ET",
    "wof:name":"Hunt'e",
    "wof:placetype":"locality"
},
  "geometry": {"coordinates":[39.41667,7.01667],"type":"Point"}
}