{
  "type": "Feature",
  "properties": {
    "gn:admin1_code":"46",
    "gn:asciiname":"Yidino",
    "gn:country_code":"ET",
    "gn:dem":1885,
    "gn:feature_class":"P",
    "gn:feature_code":"PPL",
    "gn:name":"Yidino",
    "gn:population":0,
    "gn:timezone":"Africa/Addis_Ababa",
    "iso:country":"ET",
    "wof:name":"Yidino",
    "wof:placetype":"locality"
},
  "geometry": {"coordinates":[38.83333,9.86667],"type":"Point"}
}