{
  "type": "Feature",
  "properties": {
    "gn:admin1_code":"46.0",
    "gn:asciiname":"Boled",
    "gn:country_code":"ET",
    "gn:dem":2121,
    "gn:feature_class":"P",
    "gn:feature_code":"PPL",
    "gn:name":"Boled",
    "gn:population":0,
    "gn:timezone":"Africa/Addis_Ababa",
    "iso:country":"ET",
    "name:und_x_variant":[
        "Boulle",
        "Boled"
    ],
    "wof:name":"Boled",
    "wof:placetype":"locality"
},
  "geometry": {"coordinates":[39.02792,9.79957],"type":"Point"}
}