{
  "type": "Feature",
  "properties": {
    "gn:admin1_code":"53",
    "gn:asciiname":"Genti",
    "gn:country_code":"ET",
    "gn:dem":2431,
    "gn:feature_class":"P",
    "gn:feature_code":"PPL",
    "gn:name":"Gent\u012b",
    "gn:population":0,
    "gn:timezone":"Africa/Addis_Ababa",
    "iso:country":"ET",
    "wof:name":"Genti",
    "wof:placetype":"locality"
},
  "geometry": {"coordinates":[39.71234000000001,13.05092],"type":"Point"}
}