{
  "type": "Feature",
  "properties": {
    "gn:admin1_code":"52.0",
    "gn:asciiname":"Cabahot",
    "gn:country_code":"ET",
    "gn:dem":844,
    "gn:feature_class":"P",
    "gn:feature_code":"PPL",
    "gn:name":"Cabahot",
    "gn:population":0,
    "gn:timezone":"Africa/Addis_Ababa",
    "iso:country":"ET",
    "name:und_x_variant":[
        "Kabakhot",
        "Cabahot"
    ],
    "wof:name":"Cabahot",
    "wof:placetype":"locality"
},
  "geometry": {"coordinates":[43.94417,7.80472],"type":"Point"}
}