{
  "type": "Feature",
  "properties": {
    "gn:admin1_code":"53",
    "gn:asciiname":"Sibahile",
    "gn:country_code":"ET",
    "gn:dem":2720,
    "gn:feature_class":"P",
    "gn:feature_code":"PPL",
    "gn:name":"S\u012bbahil\u0113",
    "gn:population":0,
    "gn:timezone":"Africa/Addis_Ababa",
    "iso:country":"ET",
    "wof:name":"Sibahile",
    "wof:placetype":"locality"
},
  "geometry": {"coordinates":[39.48333,12.51667],"type":"Point"}
}