{
  "type": "Feature",
  "properties": {
    "gn:admin1_code":"51",
    "gn:asciiname":"Goragussa",
    "gn:country_code":"ET",
    "gn:dem":1026,
    "gn:feature_class":"P",
    "gn:feature_code":"PPL",
    "gn:name":"Goragussa",
    "gn:population":0,
    "gn:timezone":"Africa/Addis_Ababa",
    "iso:country":"ET",
    "name:und_x_variant":[
        "Korogassa",
        "Goragussa"
    ],
    "wof:name":"Goragussa",
    "wof:placetype":"locality"
},
  "geometry": {"coordinates":[39.85,8.75],"type":"Point"}
}