{
  "type": "Feature",
  "properties": {
    "gn:admin1_code":"51",
    "gn:asciiname":"Gogola",
    "gn:country_code":"ET",
    "gn:dem":2832,
    "gn:feature_class":"P",
    "gn:feature_code":"PPL",
    "gn:name":"Gogola",
    "gn:population":0,
    "gn:timezone":"Africa/Addis_Ababa",
    "iso:country":"ET",
    "wof:name":"Gogola",
    "wof:placetype":"locality"
},
  "geometry": {"coordinates":[38.03333,9.18333],"type":"Point"}
}