{
  "type": "Feature",
  "properties": {
    "gn:admin1_code":"46",
    "gn:asciiname":"Golima",
    "gn:country_code":"ET",
    "gn:dem":1344,
    "gn:feature_class":"P",
    "gn:feature_code":"PPL",
    "gn:name":"Gol\u012bma",
    "gn:population":0,
    "gn:timezone":"Africa/Addis_Ababa",
    "iso:country":"ET",
    "wof:name":"Golima",
    "wof:placetype":"locality"
},
  "geometry": {"coordinates":[37.96667,13.43333],"type":"Point"}
}