{
  "type": "Feature",
  "properties": {
    "gn:admin1_code":"54",
    "gn:asciiname":"Fachi",
    "gn:country_code":"ET",
    "gn:dem":1865,
    "gn:feature_class":"P",
    "gn:feature_code":"PPL",
    "gn:name":"Fachi",
    "gn:population":0,
    "gn:timezone":"Africa/Addis_Ababa",
    "iso:country":"ET",
    "name:eng_x_preferred":[
        "Faki"
    ],
    "name:und_x_variant":[
        "Feki",
        "Fachi"
    ],
    "wof:name":"Fachi",
    "wof:placetype":"locality"
},
  "geometry": {"coordinates":[35.65138,6.8622],"type":"Point"}
}