{
  "type": "Feature",
  "properties": {
    "gn:admin1_code":"54",
    "gn:asciiname":"Fachi",
    "gn:country_code":"ET",
    "gn:dem":1865,
    "gn:feature_class":"P",
    "gn:feature_code":"PPL",
    "gn:name":"Fachi",
    "gn:population":0,
    "gn:timezone":"Africa/Addis_Ababa",
    "iso:country":"ET",
    "name:deu_x_preferred":[
        "Fachi"
    ],
    "name:eng_x_preferred":[
        "Faki"
    ],
    "name:epo_x_preferred":[
        "Fachi"
    ],
    "name:fin_x_preferred":[
        "Fachi"
    ],
    "name:fra_x_preferred":[
        "Fachi"
    ],
    "name:ita_x_preferred":[
        "Fachi"
    ],
    "name:msa_x_preferred":[
        "Fachi"
    ],
    "name:por_x_preferred":[
        "Fachi"
    ],
    "name:ron_x_preferred":[
        "Fachi"
    ],
    "name:spa_x_preferred":[
        "Fachi"
    ],
    "name:und_x_variant":[
        "Feki"
    ],
    "name:urd_x_preferred":[
        "\u0641\u0627\u0686\u06cc"
    ],
    "wof:name":"Fachi",
    "wof:placetype":"locality"
},
  "geometry": {"coordinates":[35.65138,6.8622],"type":"Point"}
}