{
  "type": "Feature",
  "properties": {
    "gn:admin1_code":"51",
    "gn:asciiname":"Shashole",
    "gn:country_code":"ET",
    "gn:dem":2950,
    "gn:feature_class":"P",
    "gn:feature_code":"PPL",
    "gn:name":"Shashol\u0113",
    "gn:population":0,
    "gn:timezone":"Africa/Addis_Ababa",
    "iso:country":"ET",
    "wof:name":"Shashole",
    "wof:placetype":"locality"
},
  "geometry": {"coordinates":[39.33504,9.47074],"type":"Point"}
}