{
  "type": "Feature",
  "properties": {
    "gn:admin1_code":"52",
    "gn:asciiname":"Turr",
    "gn:country_code":"ET",
    "gn:dem":381,
    "gn:feature_class":"P",
    "gn:feature_code":"PPL",
    "gn:name":"Turr",
    "gn:population":0,
    "gn:timezone":"Africa/Addis_Ababa",
    "iso:country":"ET",
    "wof:name":"Turr",
    "wof:placetype":"locality"
},
  "geometry": {"coordinates":[43.41583,6.34417],"type":"Point"}
}