{
  "type": "Feature",
  "properties": {
    "gn:admin1_code":"51",
    "gn:asciiname":"Wila",
    "gn:country_code":"ET",
    "gn:dem":2981,
    "gn:feature_class":"P",
    "gn:feature_code":"PPL",
    "gn:name":"Wila",
    "gn:population":0,
    "gn:timezone":"Africa/Addis_Ababa",
    "iso:country":"ET",
    "wof:name":"Wila",
    "wof:placetype":"locality"
},
  "geometry": {"coordinates":[38.36667,8.35],"type":"Point"}
}