{
  "type": "Feature",
  "properties": {
    "gn:admin1_code":"51",
    "gn:asciiname":"Lafto",
    "gn:country_code":"ET",
    "gn:dem":1884,
    "gn:feature_class":"P",
    "gn:feature_code":"PPL",
    "gn:name":"Lafto",
    "gn:population":0,
    "gn:timezone":"Africa/Addis_Ababa",
    "iso:country":"ET",
    "name:und_x_variant":[
        "Lafto (2)",
        "Lafto"
    ],
    "wof:name":"Lafto",
    "wof:placetype":"locality"
},
  "geometry": {"coordinates":[41.78056,8.97778],"type":"Point"}
}