{
  "type": "Feature",
  "properties": {
    "gn:admin1_code":"51.0",
    "gn:asciiname":"Bijit",
    "gn:country_code":"ET",
    "gn:dem":1798,
    "gn:feature_class":"P",
    "gn:feature_code":"PPL",
    "gn:name":"B\u012bj\u012bt",
    "gn:population":0,
    "gn:timezone":"Africa/Addis_Ababa",
    "iso:country":"ET",
    "wof:name":"Bijit",
    "wof:placetype":"locality"
},
  "geometry": {"coordinates":[36.73333,9.65],"type":"Point"}
}