{
  "type": "Feature",
  "properties": {
    "gn:admin1_code":"51",
    "gn:asciiname":"Ejersa Lefo",
    "gn:country_code":"ET",
    "gn:dem":2298,
    "gn:feature_class":"P",
    "gn:feature_code":"PPL",
    "gn:name":"\u0112jersa Lefo",
    "gn:population":0,
    "gn:timezone":"Africa/Addis_Ababa",
    "iso:country":"ET",
    "name:und_x_variant":[
        "Agarsa Lafu",
        "\u0112jersa Lefo"
    ],
    "wof:name":"Ejersa Lefo",
    "wof:placetype":"locality"
},
  "geometry": {"coordinates":[38.31667,9.03333],"type":"Point"}
}