{
  "type": "Feature",
  "properties": {
    "gn:admin1_code":"52",
    "gn:asciiname":"Jare",
    "gn:country_code":"ET",
    "gn:dem":1778,
    "gn:feature_class":"P",
    "gn:feature_code":"PPL",
    "gn:name":"Jar\u0113",
    "gn:population":0,
    "gn:timezone":"Africa/Addis_Ababa",
    "iso:country":"ET",
    "name:ceb_x_preferred":[
        "Jare"
    ],
    "name:swe_x_preferred":[
        "Jare"
    ],
    "name:und_x_variant":[
        "Dzhare",
        "Jar\u0113"
    ],
    "wof:name":"Jare",
    "wof:placetype":"locality"
},
  "geometry": {"coordinates":[42.92333,9.6725],"type":"Point"}
}