{
  "type": "Feature",
  "properties": {
    "gn:admin1_code":"46.0",
    "gn:asciiname":"Bit'a",
    "gn:country_code":"ET",
    "gn:dem":2207,
    "gn:feature_class":"P",
    "gn:feature_code":"PPL",
    "gn:name":"B\u012bt\u2019a",
    "gn:population":0,
    "gn:timezone":"Africa/Addis_Ababa",
    "iso:country":"ET",
    "wof:name":"Bit'a",
    "wof:placetype":"locality"
},
  "geometry": {"coordinates":[39.13496,10.38302],"type":"Point"}
}