{
  "type": "Feature",
  "properties": {
    "gn:admin1_code":"46.0",
    "gn:asciiname":"Agit'a",
    "gn:country_code":"ET",
    "gn:dem":2316,
    "gn:feature_class":"P",
    "gn:feature_code":"PPL",
    "gn:name":"\u0100git\u2019a",
    "gn:population":0,
    "gn:timezone":"Africa/Addis_Ababa",
    "iso:country":"ET",
    "wof:name":"Agit'a",
    "wof:placetype":"locality"
},
  "geometry": {"coordinates":[38.96667,12.43333],"type":"Point"}
}