{
  "type": "Feature",
  "properties": {
    "gn:admin1_code":"51.0",
    "gn:asciiname":"Derge",
    "gn:country_code":"ET",
    "gn:dem":1751,
    "gn:feature_class":"P",
    "gn:feature_code":"PPL",
    "gn:name":"Derg\u0113",
    "gn:population":0,
    "gn:timezone":"Africa/Addis_Ababa",
    "iso:country":"ET",
    "wof:name":"Derge",
    "wof:placetype":"locality"
},
  "geometry": {"coordinates":[37.68333,9.51667],"type":"Point"}
}