{
  "type": "Feature",
  "properties": {
    "gn:admin1_code":"51.0",
    "gn:asciiname":"Derge",
    "gn:country_code":"ET",
    "gn:dem":1751,
    "gn:feature_class":"P",
    "gn:feature_code":"PPL",
    "gn:name":"Derg\u0113",
    "gn:population":0,
    "gn:timezone":"Africa/Addis_Ababa",
    "iso:country":"ET",
    "name:fra_x_preferred":[
        "Dergu\u00e9"
    ],
    "name:ita_x_preferred":[
        "Derge"
    ],
    "name:nld_x_preferred":[
        "Derge"
    ],
    "name:nor_x_preferred":[
        "Derge"
    ],
    "name:rus_x_preferred":[
        "\u0413\u044d\u043d\u0446\u0438\u043d"
    ],
    "name:spa_x_preferred":[
        "Derge"
    ],
    "name:zho_x_preferred":[
        "\u66f4\u5e86\u9547"
    ],
    "wof:name":"Derge",
    "wof:placetype":"locality"
},
  "geometry": {"coordinates":[37.68333,9.51667],"type":"Point"}
}