{
  "type": "Feature",
  "properties": {
    "gn:admin1_code":"48",
    "gn:asciiname":"Urgo",
    "gn:country_code":"ET",
    "gn:dem":1688,
    "gn:feature_class":"P",
    "gn:feature_code":"PPL",
    "gn:name":"Urgo",
    "gn:population":0,
    "gn:timezone":"Africa/Addis_Ababa",
    "iso:country":"ET",
    "name:und_x_variant":[
        "Balaua",
        "Urgo"
    ],
    "wof:name":"Urgo",
    "wof:placetype":"locality"
},
  "geometry": {"coordinates":[41.98361,9.55583],"type":"Point"}
}