{
  "type": "Feature",
  "properties": {
    "gn:admin1_code":"51.0",
    "gn:asciiname":"Bishan Jebi",
    "gn:country_code":"ET",
    "gn:dem":1629,
    "gn:feature_class":"P",
    "gn:feature_code":"PPL",
    "gn:name":"B\u012bshan Jeb\u012b",
    "gn:population":0,
    "gn:timezone":"Africa/Addis_Ababa",
    "iso:country":"ET",
    "wof:name":"Bishan Jebi",
    "wof:placetype":"locality"
},
  "geometry": {"coordinates":[38.11667,9.78333],"type":"Point"}
}