{
  "type": "Feature",
  "properties": {
    "gn:admin1_code":"54",
    "gn:asciiname":"Tarch'a Sodo",
    "gn:country_code":"ET",
    "gn:dem":1277,
    "gn:feature_class":"P",
    "gn:feature_code":"PPL",
    "gn:name":"Tarch\u2019a Sodo",
    "gn:population":0,
    "gn:timezone":"Africa/Addis_Ababa",
    "iso:country":"ET",
    "wof:name":"Tarch'a Sodo",
    "wof:placetype":"locality"
},
  "geometry": {"coordinates":[37.15,7.15],"type":"Point"}
}