{
  "type": "Feature",
  "properties": {
    "gn:admin1_code":"52",
    "gn:asciiname":"Gos",
    "gn:country_code":"ET",
    "gn:dem":1089,
    "gn:feature_class":"P",
    "gn:feature_code":"PPL",
    "gn:name":"Gos",
    "gn:population":0,
    "gn:timezone":"Africa/Addis_Ababa",
    "iso:country":"ET",
    "wof:name":"Gos",
    "wof:placetype":"locality"
},
  "geometry": {"coordinates":[44.41083,8.48056],"type":"Point"}
}