{
  "type": "Feature",
  "properties": {
    "gn:admin1_code":"51.0",
    "gn:asciiname":"Boneya",
    "gn:country_code":"ET",
    "gn:dem":1750,
    "gn:feature_class":"P",
    "gn:feature_code":"PPL",
    "gn:name":"Boneya",
    "gn:population":0,
    "gn:timezone":"Africa/Addis_Ababa",
    "iso:country":"ET",
    "wof:name":"Boneya",
    "wof:placetype":"locality"
},
  "geometry": {"coordinates":[38.76667,10.15],"type":"Point"}
}