{
  "type": "Feature",
  "properties": {
    "gn:admin1_code":"53",
    "gn:asciiname":"Tembien",
    "gn:country_code":"ET",
    "gn:dem":1856,
    "gn:feature_class":"P",
    "gn:feature_code":"PPL",
    "gn:name":"Tembien",
    "gn:population":0,
    "gn:timezone":"Africa/Addis_Ababa",
    "iso:country":"ET",
    "name:heb_x_preferred":[
        "\u05ea\u05de\u05d1\u05d9\u05d9\u05df"
    ],
    "name:ron_x_preferred":[
        "Tembien"
    ],
    "name:und_x_variant":[
        "Temb\u0113n",
        "\u0100b\u012by \u0100d\u012b"
    ],
    "wof:name":"Tembien",
    "wof:placetype":"locality"
},
  "geometry": {"coordinates":[39.00234,13.62448],"type":"Point"}
}