{
  "type": "Feature",
  "properties": {
    "gn:admin1_code":"51",
    "gn:asciiname":"Umer Roba",
    "gn:country_code":"ET",
    "gn:dem":2174,
    "gn:feature_class":"P",
    "gn:feature_code":"PPL",
    "gn:name":"Umer Roba",
    "gn:population":0,
    "gn:timezone":"Africa/Addis_Ababa",
    "iso:country":"ET",
    "wof:name":"Umer Roba",
    "wof:placetype":"locality"
},
  "geometry": {"coordinates":[42.11694,9.46222],"type":"Point"}
}