{
  "type": "Feature",
  "properties": {
    "gn:admin1_code":"51.0",
    "gn:asciiname":"Demi",
    "gn:country_code":"ET",
    "gn:dem":2175,
    "gn:feature_class":"P",
    "gn:feature_code":"PPL",
    "gn:name":"Dem\u012b",
    "gn:population":0,
    "gn:timezone":"Africa/Addis_Ababa",
    "iso:country":"ET",
    "name:und_x_variant":[
        "Dem\u012b (1)",
        "Dem\u012b"
    ],
    "wof:name":"Demi",
    "wof:placetype":"locality"
},
  "geometry": {"coordinates":[36.21667,9.81667],"type":"Point"}
}