{
  "type": "Feature",
  "properties": {
    "gn:admin1_code":"51",
    "gn:asciiname":"T'eko Uno",
    "gn:country_code":"ET",
    "gn:dem":1414,
    "gn:feature_class":"P",
    "gn:feature_code":"PPL",
    "gn:name":"T\u2019\u0113ko Uno",
    "gn:population":0,
    "gn:timezone":"Africa/Addis_Ababa",
    "iso:country":"ET",
    "wof:name":"T'eko Uno",
    "wof:placetype":"locality"
},
  "geometry": {"coordinates":[41.22055,8.57401],"type":"Point"}
}