{
  "type": "Feature",
  "properties": {
    "gn:admin1_code":"51",
    "gn:asciiname":"Loloha",
    "gn:country_code":"ET",
    "gn:dem":1434,
    "gn:feature_class":"P",
    "gn:feature_code":"PPL",
    "gn:name":"Loloha",
    "gn:population":0,
    "gn:timezone":"Africa/Addis_Ababa",
    "iso:country":"ET",
    "name:und_x_variant":[
        "Lola",
        "Loloha"
    ],
    "wof:name":"Loloha",
    "wof:placetype":"locality"
},
  "geometry": {"coordinates":[41.32966,8.73816],"type":"Point"}
}