{
  "type": "Feature",
  "properties": {
    "gn:admin1_code":"53",
    "gn:asciiname":"Weldayo",
    "gn:country_code":"ET",
    "gn:dem":1649,
    "gn:feature_class":"P",
    "gn:feature_code":"PPL",
    "gn:name":"Weldayo",
    "gn:population":0,
    "gn:timezone":"Africa/Addis_Ababa",
    "iso:country":"ET",
    "wof:name":"Weldayo",
    "wof:placetype":"locality"
},
  "geometry": {"coordinates":[39.75,12.83333],"type":"Point"}
}