{
  "type": "Feature",
  "properties": {
    "gn:admin1_code":"46.0",
    "gn:asciiname":"Amba Ras",
    "gn:country_code":"ET",
    "gn:dem":2794,
    "gn:feature_class":"P",
    "gn:feature_code":"PPL",
    "gn:name":"\u0100mba Ras",
    "gn:population":0,
    "gn:timezone":"Africa/Addis_Ababa",
    "iso:country":"ET",
    "wof:name":"Amba Ras",
    "wof:placetype":"locality"
},
  "geometry": {"coordinates":[37.71667,12.76667],"type":"Point"}
}