{
  "type": "Feature",
  "properties": {
    "gn:admin1_code":"51.0",
    "gn:asciiname":"Abelt",
    "gn:country_code":"ET",
    "gn:dem":1591,
    "gn:feature_class":"P",
    "gn:feature_code":"PPL",
    "gn:name":"\u0100belt",
    "gn:population":0,
    "gn:timezone":"Africa/Addis_Ababa",
    "iso:country":"ET",
    "name:und_x_variant":[
        "Sciarsciama",
        "\u0100belt"
    ],
    "wof:name":"Abelt",
    "wof:placetype":"locality"
},
  "geometry": {"coordinates":[37.53333,8.18333],"type":"Point"}
}