{
  "type": "Feature",
  "properties": {
    "gn:admin1_code":"54",
    "gn:asciiname":"T'at'esa",
    "gn:country_code":"ET",
    "gn:dem":1893,
    "gn:feature_class":"P",
    "gn:feature_code":"PPL",
    "gn:name":"T\u2019at\u2019\u0113sa",
    "gn:population":0,
    "gn:timezone":"Africa/Addis_Ababa",
    "iso:country":"ET",
    "wof:name":"T'at'esa",
    "wof:placetype":"locality"
},
  "geometry": {"coordinates":[37.95,8.25],"type":"Point"}
}