{
  "type": "Feature",
  "properties": {
    "gn:admin1_code":"46",
    "gn:asciiname":"Gelemo Ager",
    "gn:country_code":"ET",
    "gn:dem":2614,
    "gn:feature_class":"P",
    "gn:feature_code":"PPL",
    "gn:name":"Gelemo \u0100ger",
    "gn:population":0,
    "gn:timezone":"Africa/Addis_Ababa",
    "iso:country":"ET",
    "name:und_x_variant":[
        "Gelemo \u0100ger",
        "Gelmo \u0100ger"
    ],
    "wof:name":"Gelemo Ager",
    "wof:placetype":"locality"
},
  "geometry": {"coordinates":[39.6337,10.93997],"type":"Point"}
}